Workbook

Sheet legacy_hidden_sheet_1

Sheet vaccines
A1: id | B1: code_name | C1: product_characteristics_link_primary_field_for_version_1 | D1: short_name | E1: long_name | F1: manufacturer | G1: in_use_in_Russia | H1: comment_to_show | I1: comment_to_show_wo_html | J1: dosage | K1: creation_date | L1: update_date | M1: OKhLP_specialists_link | N1: laypeople_leaflet_GRLS_link | O1: laypeople_leaflet_OKhLP_link | P1: GRLS_instruction_link | Q1: legacy_links
A2: 1 | B2: BCG_Microgen | C2: https://grls.rosminzdrav.ru/Grls_View_v2.aspx?routingGuid=9f91626d-1063-4ea5-9346-800cc6ef9b44 | D2: БЦЖ (Микроген) | E2: Вакцина туберкулезная (БЦЖ) | F2: Микроген | G2: in use | H2: <p>Используется в двух случаях: <ol><li>на тех территориях, где показатель заболеваемости туберкулеза превышает 80&nbsp;случаев на 100&nbsp;000&nbsp;населения;</li> <li>если в окружении новорожденного есть больной туберкулезом.</li></ol></p> | I2: Используется в двух случаях: 1. на тех территориях, где показатель заболеваемости туберкулеза превышает 80 случаев на 100 000 населения; 2. если в окружении новорожденного есть больной туберкулезом. | J2: =0.05 -> 0.05 | K2: 44712 | L2: 45689 | M2: есть | N2: https://grls.rosminzdrav.ru/Grls_View_v2.aspx?routingGuid=9f91626d-1063-4ea5-9346-800cc6ef9b44 | O2: есть | P2: https://grls.rosminzdrav.ru/Grls_View_v2.aspx?routingGuid=e175064d-f010-42d9-bfca-0b186e7cb1d7 | Q2: http://grls.rosminzdrav.ru/Grls_View_v2.aspx?routingGuid=f4d664a2-1579-4fe1-a208-c61795ed1ce9&t= https://grls.rosminzdrav.ru/Grls_View_v2.aspx?routingGuid=580694c3-d27d-4aa9-900d-0437dc6119ca https://grls.rosminzdrav.ru/Grls_View_v2.aspx?routingGuid=e175064d-f010-42d9-bfca-0b186e7cb1d7 https://lk.regmed.ru/Register/GetPDFfromDA?ID=1597322951 https://lk.regmed.ru/Register/GetPDFfromDA?ID=1597323001
A3: 2 | B3: BCG_M_Microgen | C3: https://grls.rosminzdrav.ru/Grls_View_v2.aspx?routingGuid=115ba81b-7cb9-4737-9e63-163458ef9d0b | D3: БЦЖ-М (Микроген) | E3: Вакцина туберкулезная для щадящей первичной иммунизации (БЦЖ-М) | F3: Микроген | G3: in use | H3: <p>Используется по умолчанию для вакцинации детей против туберкулеза. Однако на территориях с повышенной заболеваемостью туберкулезом, а также если в окружении новорожденного есть больной туберкулезом, используется другая вакцина — "БЦЖ".</p> | I3: Используется по умолчанию для вакцинации детей против туберкулеза. Однако на территориях с повышенной заболеваемостью туберкулезом, а также если в окружении новорожденного есть больной туберкулезом, используется другая вакцина — "БЦЖ". | J3: =0.025 -> 0.025 | K3: 44712 | L3: 45689 | M3: есть | N3: https://grls.rosminzdrav.ru/Grls_View_v2.aspx?routingGuid=115ba81b-7cb9-4737-9e63-163458ef9d0b | O3: есть | P3: https://grls.rosminzdrav.ru/Grls_View_v2.aspx?routingGuid=84b15383-df1c-4cb1-a2bb-287483fe9800 | Q3: http://grls.rosminzdrav.ru/Grls_View_v2.aspx?routingGuid=c4592056-f001-476c-9fcf-8f64bc5ec53b&t= https://grls.rosminzdrav.ru/Grls_View_v2.aspx?routingGuid=42231e5b-155e-451f-9f13-d2990507b30c https://grls.rosminzdrav.ru/Grls_View_v2.aspx?routingGuid=84b15383-df1c-4cb1-a2bb-287483fe9800 https://lk.regmed.ru/Register/GetPDFfromDA?ID=1597318981 https://lk.regmed.ru/Register/GetPDFfromDA?ID=1597319151
A4: 3 | B4: BCG_Gamaleya | C4: https://grls.rosminzdrav.ru/Grls_View_v2.aspx?routingGuid=4215760f-875d-476b-a9b6-af2e398c3025 | D4: БЦЖ (Гамалеи) | E4: Вакцина туберкулезная (БЦЖ) | F4: НИЦЭМ им. Н.Ф. Гамалеи | G4: in use | H4: <p>Используется в двух случаях: <ol><li>на тех территориях, где показатель заболеваемости туберкулеза превышает 80&nbsp;случаев на 100&nbsp;000&nbsp;населения;</li> <li>если в окружении новорожденного есть больной туберкулезом.</li></ol></p> | I4: Используется в двух случаях: 1. на тех территориях, где показатель заболеваемости туберкулеза превышает 80 случаев на 100 000 населения; 2. если в окружении новорожденного есть больной туберкулезом. | J4: =0.05 -> 0.05 | K4: 44712 | L4: 45801 | M4: есть | N4: https://grls.rosminzdrav.ru/Grls_View_v2.aspx?routingGuid=4215760f-875d-476b-a9b6-af2e398c3025 | O4: есть | P4: https://grls.rosminzdrav.ru/Grls_View_v2.aspx?routingGuid=9197ac42-596c-4696-829a-f39b4433e1ba | Q4: http://grls.rosminzdrav.ru/Grls_View_v2.aspx?routingGuid=43b8e297-04e6-46a8-9d65-f7f656dfcafc&t= https://grls.rosminzdrav.ru/Grls_View_v2.aspx?routingGuid=9197ac42-596c-4696-829a-f39b4433e1ba
A5: 4 | B5: BCG_M_Gamaleya | C5: https://grls.rosminzdrav.ru/Grls_View_v2.aspx?routingGuid=30fc01db-b288-495f-9e55-e1dd798d18a9 | D5: БЦЖ-М (Гамалеи) | E5: Вакцина туберкулезная для щадящей первичной иммунизации (БЦЖ-М) | F5: НИЦЭМ им. Н.Ф. Гамалеи | G5: in use | H5: <p>Используется по умолчанию для вакцинации детей против туберкулеза. Однако на территориях с повышенной заболеваемостью туберкулезом, а также если в окружении новорожденного есть больной туберкулезом, используется другая вакцина — "БЦЖ".</p> | I5: Используется по умолчанию для вакцинации детей против туберкулеза. Однако на территориях с повышенной заболеваемостью туберкулезом, а также если в окружении новорожденного есть больной туберкулезом, используется другая вакцина — "БЦЖ". | J5: =0.025 -> 0.025 | K5: 44712 | L5: 45818 | M5: есть | N5: https://grls.rosminzdrav.ru/Grls_View_v2.aspx?routingGuid=30fc01db-b288-495f-9e55-e1dd798d18a9 | O5: есть | P5: https://grls.rosminzdrav.ru/Grls_View_v2.aspx?routingGuid=221f440c-110f-4587-8edb-bc7559e9b891 | Q5: http://grls.rosminzdrav.ru/Grls_View_v2.aspx?routingGuid=d9b7a224-4ea9-4e72-9147-51b294e89dc3&t= https://grls.rosminzdrav.ru/Grls_View_v2.aspx?routingGuid=221f440c-110f-4587-8edb-bc7559e9b891
A6: 5 | B6: Infanrix | C6: https://grls.rosminzdrav.ru/Grls_View_v2.aspx?routingGuid=60b8bad6-1fec-492d-a07c-25eee3daa0b5 | D6: Инфанрикс | E6: Инфанрикс® (Вакцина для профилактики дифтерии, столбняка, коклюша (бесклеточная) трехкомпонентная адсорбированная жидкая) | F6: GSK | G6: not in use | H6: <p>DTaP, бесклеточный коклюшный компонент</p> | I6: DTaP, бесклеточный коклюшный компонент | J6: =0.5 -> 0.5 | K6: 44712 | L6: 45689 | M6: есть | N6: нет | O6: есть | P6: https://grls.rosminzdrav.ru/Grls_View_v2.aspx?routingGuid=60b8bad6-1fec-492d-a07c-25eee3daa0b5 | Q6: http://grls.rosminzdrav.ru/Grls_View_v2.aspx?routingGuid=5d56b9eb-b9a5-4bd5-b6cc-ff7f975b513b&t= https://grls.rosminzdrav.ru/Grls_View_v2.aspx?routingGuid=58af8725-f1f7-4c7e-8b50-f3f15e82f83f https://grls.rosminzdrav.ru/Grls_View_v2.aspx?routingGuid=415bcf4b-21de-45a5-b2b4-60dc3b1dce77
A7: 6 | B7: AKDS_Microgen | C7: https://grls.rosminzdrav.ru/Grls_View_v2.aspx?routingGuid=73faea00-ddd0-427e-9f40-49dfea9a2470 | D7: АКДС (Микроген) | E7: Вакцина коклюшно-дифтерийно-столбнячная адсорбированная (АКДС-вакцина) | F7: Микроген | G7: in use | H7: <p>DTaP, цельноклеточный коклюшный компонент</p> | I7: DTaP, цельноклеточный коклюшный компонент | J7: =0.5 -> 0.5 | K7: 44712 | L7: 45689 | M7: есть | N7: https://grls.rosminzdrav.ru/Grls_View_v2.aspx?routingGuid=73faea00-ddd0-427e-9f40-49dfea9a2470 | O7: есть | P7: https://grls.rosminzdrav.ru/Grls_View_v2.aspx?routingGuid=e6156693-4103-4342-8849-ac022e006944 | Q7: http://grls.rosminzdrav.ru/Grls_View_v2.aspx?routingGuid=a670767c-43c3 – 4823-8c12-311809975160&t= https://grls.rosminzdrav.ru/Grls_View_v2.aspx?routingGuid=eaf85871-f010-44dc-9405-8624e77e3499 https://grls.rosminzdrav.ru/Grls_View_v2.aspx?routingGuid=e6156693-4103-4342-8849-ac022e006944 https://lk.regmed.ru/Register/GetPDFfromDA?ID=1587927891 https://lk.regmed.ru/Register/GetPDFfromDA?ID=1587927901
A8: 7 | B8: AKDS_Biomed | C8: https://grls.rosminzdrav.ru/Grls_View_v2.aspx?routingGuid=aba4f9bd-407e-42a8-a32c-1105beece2f6 | D8: АКДС (Биомед) | E8: Вакцина коклюшно-дифтерийно-столбнячная адсорбированная (АКДС-вакцина) | F8: Биомед | G8: in use | H8: <p>DTaP, цельноклеточный коклюшный компонент</p> | I8: DTaP, цельноклеточный коклюшный компонент | J8: =0.5 -> 0.5 | K8: 44712 | L8: 45079 | M8: нет | N8: нет | O8: нет | P8: https://grls.rosminzdrav.ru/Grls_View_v2.aspx?routingGuid=aba4f9bd-407e-42a8-a32c-1105beece2f6
A9: 8 | B9: Bubo_kok | C9: https://grls.rosminzdrav.ru/Grls_View_v2.aspx?routingGuid=81b39c46-e795-4993-b85b-0cf51e164f6b | D9: Бубо-Кок | E9: Бубо®-Кок | F9: Комбиотех | G9: not in use | J9: =0.5 -> 0.5 | K9: 44712 | L9: 44712 | M9: нет | N9: нет | O9: нет | P9: https://grls.rosminzdrav.ru/Grls_View_v2.aspx?routingGuid=81b39c46-e795-4993-b85b-0cf51e164f6b
A10: 9 | B10: Pentaxim | C10: https://grls.rosminzdrav.ru/Grls_View_v2.aspx?routingGuid=04b887e5-95d7-44df-beaa-a539fe956444 | D10: Пентаксим | E10: Пентаксим® (вакцина для профилактики дифтерии и столбняка адсорбированная, коклюша ацеллюлярная, полиомиелита инактивированная и инфекций, вызываемых Haemophilus influenzae тип b, конъюгированная) | F10: Sanofi Pasteur | G10: in use | H10: <p>DTaP-IPV-Hib, бесклеточный коклюшный компонент</p> | I10: DTaP-IPV-Hib, бесклеточный коклюшный компонент | J10: =0.5 -> 0.5 | K10: 44712 | L10: 46204 | M10: есть | N10: https://grls.rosminzdrav.ru/Grls_View_v2.aspx?routingGuid=04b887e5-95d7-44df-beaa-a539fe956444 | O10: есть | P10: https://grls.rosminzdrav.ru/Grls_View_v2.aspx?routingGuid=fa23fbae-fb1a-45b2-8191-2db254575e44 | Q10: http://grls.rosminzdrav.ru/Grls_View_v2.aspx?routingGuid=f43b3011-7633 – 434e-a703-3e18238e9b83&t= https://grls.rosminzdrav.ru/Grls_View_v2.aspx?routingGuid=4d5a75ea-7318-4f8a-8614-2188f4327bdb&t= https://grls.rosminzdrav.ru/Grls_View_v2.aspx?routingGuid=8289a09f-0328-4db3-9276-2022b87fed33 https://grls.rosminzdrav.ru/Grls_View_v2.aspx?routingGuid=fa23fbae-fb1a-45b2-8191-2db254575e44 https://lk.regmed.ru/Register/GetPDFfromDA?ID=1513980681 https://grls.rosminzdrav.ru/Grls_View_v2.aspx?routingGuid=b2790880-bd07-4709-bcc8-484689f1439b https://lk.regmed.ru/Register/GetPDFfromDA?ID=1574041341 https://lk.regmed.ru/Register/GetPDFfromDA?ID=1582784751 https://lk.regmed.ru/Register/GetPDFfromDA?ID=1582784721 https://grls.rosminzdrav.ru/Grls_View_v2.aspx?routingGuid=023a461f-a6cb-488f-8489-6afbcdaac988 https://grls.rosminzdrav.ru/Grls_View_v2.aspx?routingGuid=c5882f45-fe9f-4981-9d00-2a4c650d1d69
A11: 10 | B11: Infanrix_Hexa | C11: https://grls.rosminzdrav.ru/Grls_View_v2.aspx?routingGuid=f9454b06-083d-4c13-8eda-e54a19450d13 | D11: Инфанрикс Гекса | E11: Инфанрикс® Гекса (Вакцина для профилактики дифтерии, столбняка, коклюша (бесклеточная), полиомиелита (инактивированная), гепатита B комбинированная, адсорбированная в комплекте с вакциной для профилактики инфекции, вызываемой Haemophilus influenzae тип b конъюгированной, адсорбированной) | F11: GSK | G11: in use | H11: <p>DTaP-IPV-Hib-HepB, бесклеточный коклюшный компонент</p> | I11: DTaP-IPV-Hib-HepB, бесклеточный коклюшный компонент | J11: =0.5 -> 0.5 | K11: 44712 | L11: 46000 | M11: есть | N11: https://grls.rosminzdrav.ru/Grls_View_v2.aspx?routingGuid=f9454b06-083d-4c13-8eda-e54a19450d13 | O11: есть | P11: https://grls.rosminzdrav.ru/Grls_View_v2.aspx?routingGuid=4b6927fa-e480-44a7-b945-557299500fe8 | Q11: http://grls.rosminzdrav.ru/Grls_View_v2.aspx?routingGuid=5aba1c6d-00b7-484e-b79c-ad45273f4575&t= https://grls.rosminzdrav.ru/Grls_View_v2.aspx?routingGuid=1a3ae12c-6484-4823-a535-8a689832cc91&t= https://grls.rosminzdrav.ru/Grls_View_v2.aspx?routingGuid=d9b8e111-d7b5-4d26-bfb7-cabd995d0470 https://grls.rosminzdrav.ru/Grls_View_v2.aspx?routingGuid=8e26d23e-07b5-4826-b6e2-686cce4141a8 https://grls.rosminzdrav.ru/Grls_View_v2.aspx?routingGuid=3a8d0e82-1e71-4ef0-b0c4-10350ec87f9a
A12: 11 | B12: Bubo_M | C12: https://grls.rosminzdrav.ru/Grls_View_v2.aspx?routingGuid=0b7d30f1-b40f-453c-9c7b-800a072aa409 | D12: Бубо-М | E12: Бубо®-М (Вакцина комбинированная гепатита B и анатоксина дифтерийно-столбнячного с уменьшенным содержанием антигенов адсорбированная жидкая) | F12: Комбиотех | G12: not in use | J12: =0.5 -> 0.5 | K12: 44712 | L12: 46188 | M12: есть | N12: нет | O12: есть | P12: https://grls.rosminzdrav.ru/Grls_View_v2.aspx?routingGuid=0b7d30f1-b40f-453c-9c7b-800a072aa409 | Q12: https://grls.rosminzdrav.ru/Grls_View_v2.aspx?routingGuid=d4d36459-a495-4769-bf77-558ba99330b1
A13: 12 | B13: AD_M_Microgen | C13: https://grls.rosminzdrav.ru/Grls_View_v2.aspx?routingGuid=fa42329f-9433-4dc6-af8a-f811be13fb87 | D13: АД-М (Микроген) | E13: Анатоксин дифтерийный очищенный адсорбированный с уменьшенным содержанием антигена жидкий (АД-М-анатоксин) | F13: Микроген | G13: in use | J13: =0.5 -> 0.5 | K13: 44712 | L13: 45689 | M13: https://lk.regmed.ru/Register/GetPDFfromDAToken?Token=9916a334-02fd-4f23-ad64-c996916ac2d6 | N13: https://grls.rosminzdrav.ru/Grls_View_v2.aspx?routingGuid=fa42329f-9433-4dc6-af8a-f811be13fb87 | O13: https://lk.regmed.ru/Register/GetPDFfromDAToken?Token=22df29cf-dc92-4628-a24c-edf2e8b2b256 | P13: https://grls.rosminzdrav.ru/Grls_View_v2.aspx?routingGuid=6e48dbe9-c71e-4694-b7ac-47a70cf6b097 | Q13: http://grls.rosminzdrav.ru/Grls_View_v2.aspx?routingGuid=2a2e60b9-cc49-4bc2-9f7f-5766163a5610&t= https://grls.rosminzdrav.ru/Grls_View_v2.aspx?routingGuid=be7e45b4-ee7c-4ffc-b4fd-6b8e48edfbe3 https://grls.rosminzdrav.ru/Grls_View_v2.aspx?routingGuid=6e48dbe9-c71e-4694-b7ac-47a70cf6b097 https://lk.regmed.ru/Register/GetPDFfromDA?ID=1601683231 https://lk.regmed.ru/Register/GetPDFfromDA?ID=1601683241
A14: 13 | B14: ADS_Microgen | C14: https://grls.rosminzdrav.ru/Grls_View_v2.aspx?routingGuid=82af2230-6ada-4cb2-a263-0a2c1f841be2 | D14: АДС (Микроген) | E14: Анатоксин дифтерийно-столбнячный очищенный адсорбированный жидкий (АДС-анатоксин) | F14: Микроген | G14: in use | J14: =0.5 -> 0.5 | K14: 44712 | L14: 45689 | M14: https://lk.regmed.ru/Register/GetPDFfromDAToken?Token=ff0cddac-c2c3-4fac-84e2-d026f4f71869 | N14: https://grls.rosminzdrav.ru/Grls_View_v2.aspx?routingGuid=82af2230-6ada-4cb2-a263-0a2c1f841be2 | O14: https://lk.regmed.ru/Register/GetPDFfromDAToken?Token=9a6142ea-2a03-4b1a-9dbb-31db8de71e87 | P14: https://grls.rosminzdrav.ru/Grls_View_v2.aspx?routingGuid=263b30af-486c-42e0-911a-2a5ed131f20b | Q14: http://grls.rosminzdrav.ru/Grls_View_v2.aspx?routingGuid=56e77eb8-534a-44be-afd0-061fb8ec4621&t= https://grls.rosminzdrav.ru/Grls_View_v2.aspx?routingGuid=2a7cde6e-0f3e-447e-9619-585de96a0f74 https://grls.rosminzdrav.ru/Grls_View_v2.aspx?routingGuid=263b30af-486c-42e0-911a-2a5ed131f20b https://lk.regmed.ru/Register/GetPDFfromDA?ID=1605321651 https://lk.regmed.ru/Register/GetPDFfromDA?ID=1605321641
A15: 14 | B15: ADS_M_Microgen | C15: https://grls.rosminzdrav.ru/Grls_View_v2.aspx?routingGuid=7901c857-1397-49d2-9a93-f8c171091efa | D15: АДС-М (Микроген) | E15: Анатоксин дифтерийно-столбнячный очищенный адсорбированный с уменьшенным содержанием антигенов жидкий (АДС-М-анатоксин) | F15: Микроген | G15: in use | J15: =0.5 -> 0.5 | K15: 44712 | L15: 45861 | M15: https://lk.regmed.ru/Register/GetPDFfromDAToken?Token=67df064e-3139-49b6-917f-a5131fbd35d6 | N15: https://grls.rosminzdrav.ru/Grls_View_v2.aspx?routingGuid=7901c857-1397-49d2-9a93-f8c171091efa | O15: https://lk.regmed.ru/Register/GetPDFfromDAToken?Token=8e7de8c8-45c1-4c8d-8449-0c0d2af1e327 | P15: https://grls.rosminzdrav.ru/Grls_View_v2.aspx?routingGuid=6aefbaea-b7c4-49fe-b6a2-0d376c18f14a | Q15: http://grls.rosminzdrav.ru/Grls_View_v2.aspx?routingGuid=f7b0a096-adc5-4d00-9845-688629c81df0&t= https://grls.rosminzdrav.ru/Grls_View_v2.aspx?routingGuid=25f82e77-7060-400f-9bbb-141130ec982a&t= https://grls.rosminzdrav.ru/Grls_View_v2.aspx?routingGuid=6aefbaea-b7c4-49fe-b6a2-0d376c18f14a https://lk.regmed.ru/Register/GetPDFfromDA?ID=1600526521 https://lk.regmed.ru/Register/GetPDFfromDA?ID=1600526511 https://grls.rosminzdrav.ru/Grls_View_v2.aspx?routingGuid=95537b39-97ee-4255-9697-68976985653e
A16: 15 | B16: ADS_M_Biomed | C16: https://grls.rosminzdrav.ru/Grls_View_v2.aspx?routingGuid=795940d7 – 9c11-423c-98fe-44a1d739a593 | D16: АДС-М (Биомед) | E16: Анатоксин дифтерийно-столбнячный очищенный адсорбированный с уменьшенным содержанием антигенов жидкий (АДС-М анатоксин) | F16: Биомед | G16: in use | J16: =0.5 -> 0.5 | K16: 44712 | L16: 44712 | M16: нет | N16: нет | O16: нет | P16: https://grls.rosminzdrav.ru/Grls_View_v2.aspx?routingGuid=795940d7-9c11-423c-98fe-44a1d739a593
A17: 16 | B17: Adacel | C17: https://grls.rosminzdrav.ru/Grls_View_v2.aspx?routingGuid=d8627a3c-16a5-46d0-b31f-e60eb2448d80 | D17: Адасель | E17: АДАСЕЛЬ® [Вакцина для профилактики дифтерии (с уменьшенным содержанием антигена), коклюша (с уменьшенным содержанием антигена, бесклеточная) и столбняка, комбинированная, адсорбированная] | F17: Санофи Пастер Лимитед | G17: in use | H17: <p>Tdap, сниженное содержание дифтерийного и коклюшного компонента, бесклеточный коклюшный компонент</p> | I17: Tdap, сниженное содержание дифтерийного и коклюшного компонента, бесклеточный коклюшный компонент | J17: =0.5 -> 0.5 | K17: 44712 | L17: 45689 | M17: https://lk.regmed.ru/Register/GetPDFfromDAToken?Token=7fabfdf2-4fe8-448e-859f-9a4b20cc3213 | N17: https://grls.rosminzdrav.ru/Grls_View_v2.aspx?routingGuid=d8627a3c-16a5-46d0-b31f-e60eb2448d80 | O17: https://lk.regmed.ru/Register/GetPDFfromDAToken?Token=64e50f3b-676a-4ffd-a308-008f4019c7c0 | P17: https://grls.rosminzdrav.ru/Grls_View_v2.aspx?routingGuid=375ef2f9-abab-464c-b1b3-b993bc8f42ec | Q17: http://grls.rosminzdrav.ru/Grls_View_v2.aspx?routingGuid=6e2aecff-8338-4266-8505-8b8c9b01801a&t= https://grls.rosminzdrav.ru/Grls_View_v2.aspx?routingGuid=7eeca2fc-ee22-43f1-a33e-01b127cb9cce&t= https://grls.rosminzdrav.ru/Grls_View_v2.aspx?routingGuid=95654753-d6d2-4485-8c56-7f29dbeace86 https://grls.rosminzdrav.ru/Grls_View_v2.aspx?routingGuid=375ef2f9-abab-464c-b1b3-b993bc8f42ec https://lk.regmed.ru/Register/GetPDFfromDA?ID=1555257271 https://lk.regmed.ru/Register/GetPDFfromDA?ID=1592320751 https://lk.regmed.ru/Register/GetPDFfromDA?ID=1592320761
A18: 17 | B18: Algavac_M | C18: https://grls.rosminzdrav.ru/Grls_View_v2.aspx?routingGuid=2bf12380-3a71-4642-a9a3-ef0e4ca9b815 | D18: Альгавак М | E18: АЛЬГАВАК® М | G18: in use | K18: 44712 | L18: 45715 | M18: нет | N18: нет | O18: нет | P18: https://grls.rosminzdrav.ru/Grls_View_v2.aspx?routingGuid=2bf12380-3a71-4642-a9a3-ef0e4ca9b815 | Q18: http://grls.rosminzdrav.ru/Grls_View_v2.aspx?routingGuid=19f151f4-39f1-4518-bdad-6c70489cb7db&t= https://grls.rosminzdrav.ru/Grls_View_v2.aspx?routingGuid=d5b58794-3b91-45d1-84ee-df1f0ee83ea6
A19: 18 | B19: Algavac | C19: https://grls.rosminzdrav.ru/Grls_View_v2.aspx?routingGuid=4f6d874c-7745-4c6b-8c90-228a1f2f3484 | D19: Альгавак | E19: АЛЬГАВАК® | G19: not in use | H19: <p>Вакцину АЛЬГАВАК можно использовать для ревакцинации в тех случаях, когда предыдущая вакцинация осуществлялась другими инактивированными вакцинами для профилактики гепатита А.</p> | I19: Вакцину АЛЬГАВАК можно использовать для ревакцинации в тех случаях, когда предыдущая вакцинация осуществлялась другими инактивированными вакцинами для профилактики гепатита А. | K19: 44712 | L19: 46188 | M19: есть | N19: нет | O19: есть | P19: https://grls.rosminzdrav.ru/Grls_View_v2.aspx?routingGuid=4f6d874c-7745-4c6b-8c90-228a1f2f3484 | Q19: https://grls.rosminzdrav.ru/Grls_View_v2.aspx?routingGuid=a282addd-c0aa-4540-a495-2a96a71e6fbe https://grls.rosminzdrav.ru/Grls_View_v2.aspx?routingGuid=f7a52b5d-5517-4495-b65c-80dd8f948f0c
A20: 19 | B20: Havrix_720 | C20: https://grls.rosminzdrav.ru/Grls_View_v2.aspx?routingGuid=b8dfef4d-a4cf-4d18-9599-1a3fb42864c7 | D20: Хаврикс 720 | E20: Хаврикс® (вакцина против гепатита А инактивированная) | F20: GSK | G20: in use | K20: 44712 | L20: 45689 | M20: https://lk.regmed.ru/Register/GetPDFfromDAToken?Token=6d0a7c06-3859-4f01-8d37-bf8887046a88 | N20: https://grls.rosminzdrav.ru/Grls_View_v2.aspx?routingGuid=b8dfef4d-a4cf-4d18-9599-1a3fb42864c7 | O20: https://lk.regmed.ru/Register/GetPDFfromDAToken?Token=88854c2c-329e-40d6-9464-84468572891b | P20: https://grls.rosminzdrav.ru/Grls_View_v2.aspx?routingGuid=8c19af66-4fb0-474c-a1bf-d60e191504cd | Q20: http://grls.rosminzdrav.ru/Grls_View_v2.aspx?routingGuid=8ecd1f23-ce36-4316-8f63 – 4aa28a61a7e4&t= https://grls.rosminzdrav.ru/Grls_View_v2.aspx?routingGuid=7f9925e4-9dd3 – 46b4-9a72-c4306af33e14&t= https://grls.rosminzdrav.ru/Grls_View_v2.aspx?routingGuid=6cee7e81-acb9-4ae0-8da8-13bc218f9f43 https://grls.rosminzdrav.ru/Grls_View_v2.aspx?routingGuid=8ffa4f17-cffc-4a79-b721-833a058ae522 https://lk.regmed.ru/Register/GetPDFfromDA?ID=1607490831 https://lk.regmed.ru/Register/GetPDFfromDA?ID=1607490821
A21: 20 | B21: Havrix_1440 | C21: https://grls.rosminzdrav.ru/Grls_View_v2.aspx?routingGuid=b8dfef4d-a4cf-4d18-9599-1a3fb42864c7 | D21: Хаврикс 1440 | E21: Хаврикс® (вакцина против гепатита А инактивированная) | F21: GSK | G21: not in use | K21: 44712 | L21: 45689 | M21: https://lk.regmed.ru/Register/GetPDFfromDAToken?Token=6d0a7c06-3859-4f01-8d37-bf8887046a88 | N21: https://grls.rosminzdrav.ru/Grls_View_v2.aspx?routingGuid=b8dfef4d-a4cf-4d18-9599-1a3fb42864c7 | O21: https://lk.regmed.ru/Register/GetPDFfromDAToken?Token=88854c2c-329e-40d6-9464-84468572891b | P21: https://grls.rosminzdrav.ru/Grls_View_v2.aspx?routingGuid=8c19af66-4fb0-474c-a1bf-d60e191504cd | Q21: http://grls.rosminzdrav.ru/Grls_View_v2.aspx?routingGuid=8ecd1f23-ce36-4316-8f63 – 4aa28a61a7e4&t= https://grls.rosminzdrav.ru/Grls_View_v2.aspx?routingGuid=7f9925e4-9dd3 – 46b4-9a72-c4306af33e14&t= https://grls.rosminzdrav.ru/Grls_View_v2.aspx?routingGuid=6cee7e81-acb9-4ae0-8da8-13bc218f9f43 https://grls.rosminzdrav.ru/Grls_View_v2.aspx?routingGuid=8ffa4f17-cffc-4a79-b721-833a058ae522 https://lk.regmed.ru/Register/GetPDFfromDA?ID=1607490831 https://lk.regmed.ru/Register/GetPDFfromDA?ID=1607490821 https://lk.regmed.ru/Register/GetPDFfromDA?ID=1607490821
A22: 21 | B22: Avaxim_80 | C22: https://grls.rosminzdrav.ru/Grls_View_v2.aspx?routingGuid=0814c0aa-66c2-4566-a774-02de4c45b6ac | D22: Аваксим 80 | E22: Аваксим 80 (вакцина для профилактики гепатита A инактивированная, адсорбированная) | G22: not in use | K22: 44712 | L22: 44916 | M22: нет | N22: нет | O22: нет | P22: https://grls.rosminzdrav.ru/Grls_View_v2.aspx?routingGuid=0814c0aa-66c2-4566-a774-02de4c45b6ac | Q22: http://grls.rosminzdrav.ru/Grls_View_v2.aspx?routingGuid=3a8088d9-7d7f-445f-a8e4-a1bab7a809ad&t= https://grls.rosminzdrav.ru/Grls_View_v2.aspx?routingGuid=78ff9266-b5f3 – 490a-a1b8-27301443480a&t=
A23: 22 | B23: Avaxim_160 | C23: https://grls.rosminzdrav.ru/Grls_View_v2.aspx?routingGuid=658e07cb-fcb9-412f-9392-b9e9e21a6343 | D23: Аваксим 160 | E23: Аваксим 160 (вакцина для профилактики гепатита A инактивированная, адсорбированная) | G23: not in use | K23: 44712 | L23: 44916 | M23: нет | N23: нет | O23: нет | P23: https://grls.rosminzdrav.ru/Grls_View_v2.aspx?routingGuid=658e07cb-fcb9-412f-9392-b9e9e21a6343 | Q23: http://grls.rosminzdrav.ru/Grls_View_v2.aspx?routingGuid=0e797243-3326-40c5-91d4-3790146525e4&t= https://grls.rosminzdrav.ru/Grls_View_v2.aspx?routingGuid=5209bb3a-760a-415a-8697-652ac260fca5&t=
A24: 23 | B24: Regevac_0_5 | C24: https://grls.rosminzdrav.ru/Grls_View_v2.aspx?routingGuid=ec6e3b51-e76b-4abf-99cf-7c02bab06091 | D24: Регевак детский | E24: Регевак® В (Вакцина против гепатита В, рекомбинантная дрожжевая жидкая) | G24: in use | K24: 44712 | L24: 45988 | M24: есть | N24: нет | O24: есть | P24: https://grls.rosminzdrav.ru/Grls_View_v2.aspx?routingGuid=ec6e3b51-e76b-4abf-99cf-7c02bab06091 | Q24: http://grls.rosminzdrav.ru/Grls_View_v2.aspx?routingGuid=accc9e6e-21d3 – 4b43-8eb4-65d0bf807a6a&t= https://grls.rosminzdrav.ru/Grls_View_v2.aspx?routingGuid=7bf6a88b-0ee8-48d7-afe3-7585739a9aaf https://grls.rosminzdrav.ru/Grls_View_v2.aspx?routingGuid=7b2a598f-1146-475f-9678-bf4c14e2523a
A25: 24 | B25: HepB_Combiotech_0_5 | C25: https://grls.rosminzdrav.ru/Grls_View_v2.aspx?routingGuid=0cc60fe9-635e-4134-80d2-59a7787e33fb | D25: гепатита B (Комбиотех) детская | E25: Вакцина гепатита В рекомбинантная дрожжевая | F25: Комбиотех | G25: in use | H25: <p>Препарат выпускается в виде «взрослой» и «детской» вакцины с консервантом и без консерванта.</p> | I25: Препарат выпускается в виде «взрослой» и «детской» вакцины с консервантом и без консерванта. | K25: 44712 | L25: 46130 | M25: есть | N25: нет | O25: нет | P25: https://grls.rosminzdrav.ru/Grls_View_v2.aspx?routingGuid=0cc60fe9-635e-4134-80d2-59a7787e33fb | Q25: https://grls.rosminzdrav.ru/Grls_View_v2.aspx?routingGuid=3059b036-5e60-42ed-b26c-7eb6d5d06406
A26: 25 | B26: Euvax_B_0_5 | C26: https://grls.rosminzdrav.ru/Grls_View_v2.aspx?routingGuid=0d28b2ad-18b2-4e7a-8c27-436c0feea6d4 | D26: Эувакс В детский | E26: Эувакс В (вакцина для профилактики гепатита B рекомбинантная) | G26: not in use | K26: 44712 | L26: 44712 | M26: нет | N26: нет | O26: нет | P26: https://grls.rosminzdrav.ru/Grls_View_v2.aspx?routingGuid=0d28b2ad-18b2-4e7a-8c27-436c0feea6d4 | Q26: https://grls.rosminzdrav.ru/Grls_View_v2.aspx?routingGuid=0c704154-cba0-4019-ad47-535acfcd840c
A27: 26 | B27: Euvax_B_1_0 | C27: https://grls.rosminzdrav.ru/Grls_View_v2.aspx?routingGuid=0d28b2ad-18b2-4e7a-8c27-436c0feea6d4 | D27: Эувакс В взрослый | E27: Эувакс В (вакцина для профилактики гепатита B рекомбинантная) | G27: not in use | K27: 44712 | L27: 44712 | M27: нет | N27: нет | O27: нет | P27: https://grls.rosminzdrav.ru/Grls_View_v2.aspx?routingGuid=0d28b2ad-18b2-4e7a-8c27-436c0feea6d4 | Q27: https://grls.rosminzdrav.ru/Grls_View_v2.aspx?routingGuid=0c704154-cba0-4019-ad47-535acfcd840c
A28: 27 | B28: Cervarix | C28: https://grls.rosminzdrav.ru/Grls_View_v2.aspx?routingGuid=eb109c11-f04c-4753-b278-73a5bd064e47 | D28: Церварикс | E28: Церварикс® | G28: in use | K28: 44712 | L28: 45689 | M28: https://lk.regmed.ru/Register/GetPDFfromDAToken?Token=f88d9e07-3794-4fde-9c2d-fd91c377cc95 | N28: https://grls.rosminzdrav.ru/Grls_View_v2.aspx?routingGuid=eb109c11-f04c-4753-b278-73a5bd064e47 | O28: https://lk.regmed.ru/Register/GetPDFfromDAToken?Token=a5276048-6e32-4f08-9d02-266d9f69b4db | P28: https://grls.rosminzdrav.ru/Grls_View_v2.aspx?routingGuid=74a77c48-c131-41c4-ab9d-88f8daa7fa64 | Q28: http://grls.rosminzdrav.ru/Grls_View_v2.aspx?routingGuid=f1674482-805b-467b-896f-f78e3c14cba4&t= https://grls.rosminzdrav.ru/Grls_View_v2.aspx?routingGuid=ad735aab-e490-4da0-a3d9-0cec0766c5ca&t= https://grls.rosminzdrav.ru/Grls_View_v2.aspx?routingGuid=2978c96b-a743 – 462b-8c08-0a3d26589799 https://lk.regmed.ru/Register/GetPDFfromDA?ID=1611660161 https://lk.regmed.ru/Register/GetPDFfromDA?ID=1611660121
A29: 28 | B29: Gardasil_4 | C29: https://grls.rosminzdrav.ru/Grls_View_v2.aspx?routingGuid=2ae3187f-3553-4a0f-953d-db66a9c16d23 | D29: Гардасил 4 | E29: Гардасил® | F29: MSD | G29: in use | H29: <p>4-валентная</p> | I29: 4-валентная | J29: =0.5 -> 0.5 | K29: 44712 | L29: 45689 | M29: https://lk.regmed.ru/Register/GetPDFfromDAToken?Token=ba26e648-28b3-4eac-b578-0748c8e03c4e | N29: нет | O29: https://lk.regmed.ru/Register/GetPDFfromDAToken?Token=0b4492da-8526-4af7-a136-8dc82478f429 | P29: https://grls.rosminzdrav.ru/Grls_View_v2.aspx?routingGuid=2ae3187f-3553-4a0f-953d-db66a9c16d23 | Q29: https://grls.rosminzdrav.ru/Grls_View_v2.aspx?routingGuid=aa002533-365b-40c6-b369-8384878dcd93&t= https://grls.rosminzdrav.ru/Grls_View_v2.aspx?routingGuid=2bec1ede-4863 – 4d77-abb6-4e68d781b2e4&t= https://grls.rosminzdrav.ru/Grls_View_v2.aspx?routingGuid=4d6605d8-b4e5-43b2-8c81-ef86901d93fd https://grls.rosminzdrav.ru/Grls_View_v2.aspx?routingGuid=764b9dc3-6936-4f27-b568-bf9afd87abfc https://lk.regmed.ru/Register/GetPDFfromDA?ID=1575625191 https://lk.regmed.ru/Register/GetPDFfromDA?ID=1575625171 https://grls.rosminzdrav.ru/Grls_View_v2.aspx?routingGuid=764b9dc3-6936-4f27-b568-bf9afd87abfc
A30: 29 | B30: Sputnik | C30: https://grls.rosminzdrav.ru/Grls_View_v2.aspx?routingGuid=579be5e3-09cf-46b4-8238-f3087cd4e808 | D30: Спутник V | E30: Гам-КОВИД-Вак Комбинированная векторная вакцина для профилактики коронавирусной инфекции, вызываемой вирусом SARS-CoV-2 | F30: НИЦЭМ им. Н.Ф. Гамалеи | G30: in use | J30: =0.5 -> 0.5 | K30: 44712 | L30: 45923 | M30: https://lk.regmed.ru/Register/GetPDFfromDAToken?Token=dc4e4486-14e8-430b-b506-5364c1e11fe7 | N30: https://grls.rosminzdrav.ru/Grls_View_v2.aspx?routingGuid=579be5e3-09cf-46b4-8238-f3087cd4e808 | O30: https://lk.regmed.ru/Register/GetPDFfromDAToken?Token=3453097f-e598-4860-bd54-aa72f063f2ef | P30: https://grls.rosminzdrav.ru/Grls_View_v2.aspx?routingGuid=85127f3b-11cb-47df-95aa-325127c74955 | Q30: https://grls.rosminzdrav.ru/Grls_View_v2.aspx?routingGuid=d494c688-0bc6-4c30-9e81-23f043ceb43e&t= https://grls.rosminzdrav.ru/Grls_View_v2.aspx?routingGuid=5d7a9ba1-f4ec-4557-ba99-dcab4740067d&t= https://grls.rosminzdrav.ru/Grls_View_v2.aspx?routingGuid=1c3ac13e-0c68-4319-b618-e203985fa74a https://grls.rosminzdrav.ru/Grls_View_v2.aspx?routingGuid=b0900ae9-5b06-4cb2-bdb4-e8a3bec5f6d6
A31: 30 | B31: Sputnik_Lyo | C31: https://grls.rosminzdrav.ru/Grls_View_v2.aspx?routingGuid=ff05de13-f90b-475b-a47c-609c8a0539a7 | D31: Спутник V (лиофилизат) | E31: Гам-КОВИД-Вак-Лио Комбинированная векторная вакцина для профилактики коронавирусной инфекции, вызываемой вирусом SARS-CoV-2 | G31: not in use | K31: 44712 | L31: 44712 | M31: нет | N31: нет | O31: нет | P31: https://grls.rosminzdrav.ru/Grls_View_v2.aspx?routingGuid=ff05de13-f90b-475b-a47c-609c8a0539a7
A32: 31 | B32: EpiVacCorona | C32: https://grls.rosminzdrav.ru/Grls_View_v2.aspx?routingGuid=fd7355d2-abfa-4846-99da-a1c5c6e8991a | D32: ЭпиВакКорона | E32: ЭпиВакКорона Вакцина на основе пептидных антигенов для профилактики COVID-19 | F32: Вектор | G32: not in use | J32: =0.5 -> 0.5 | K32: 44712 | L32: 45078 | M32: нет | N32: нет | O32: нет | P32: https://grls.rosminzdrav.ru/Grls_View_v2.aspx?routingGuid=fd7355d2-abfa-4846-99da-a1c5c6e8991a | Q32: http://grls.rosminzdrav.ru/Grls_View_v2.aspx?routingGuid=d8f07c35 – 7edc-49ab-8647-6b6865449167&t= https://grls.rosminzdrav.ru/Grls_View_v2.aspx?routingGuid=6248c7e9-198f-44e0-9682-5794b677fec3&t= https://grls.rosminzdrav.ru/Grls_View_v2.aspx?routingGuid=34ca6cb0-7450-4f53-8bec-17d2bdf92c2b
A33: 32 | B33: Grippol_Microgen | C33: https://grls.rosminzdrav.ru/Grls_View_v2.aspx?routingGuid=70f8f0f0-7bac-41ec-a36d-51dcd6ebce84 | D33: Гриппол (Микроген) | E33: Гриппол® Вакцина гриппозная тривалентная полимер-субъединичная жидкая | F33: Микроген | G33: not in use | K33: 44712 | L33: 44712 | M33: нет | N33: нет | O33: нет | P33: нет | Q33: https://grls.rosminzdrav.ru/Grls_View_v2.aspx?routingGuid=0ae550bc-37b4-4f2e-bbff-b1a71c00c505
A34: 33 | B34: Grippol_Petrovax | C34: https://grls.rosminzdrav.ru/Grls_View_v2.aspx?routingGuid=ce700a9a-2b35-47e5-a73b-3cf65afee43b | D34: Гриппол (Петровакс) | E34: Гриппол® [Вакцина гриппозная тривалентная полимер-субъединичная жидкая] | F34: Петровакс | G34: not in use | K34: 44712 | L34: 44712 | M34: нет | N34: нет | O34: нет | P34: https://grls.rosminzdrav.ru/Grls_View_v2.aspx?routingGuid=ce700a9a-2b35-47e5-a73b-3cf65afee43b
A35: 34 | B35: Grippol_plus_0_5 | C35: https://grls.rosminzdrav.ru/Grls_View_v2.aspx?routingGuid=907b510e-7f7f-46df-b43a-f6541b9871fc | D35: Гриппол плюс 0,5 мл | E35: Гриппол® плюс [Вакцина гриппозная тривалентная инактивированная полимер-субъединичная] | F35: Петровакс | G35: in use | K35: 44712 | L35: 45689 | M35: https://lk.regmed.ru/Register/GetPDFfromDAToken?Token=8cc54647-279e-4b2f-82d7-b1ed3161d86a | N35: https://grls.rosminzdrav.ru/Grls_View_v2.aspx?routingGuid=907b510e-7f7f-46df-b43a-f6541b9871fc | O35: https://lk.regmed.ru/Register/GetPDFfromDAToken?Token=333cbca5-2931-4145-ba0e-d5b9ee3e74f7 | P35: https://grls.rosminzdrav.ru/Grls_View_v2.aspx?routingGuid=6cb99bc7-105a-4075-a791-8895b32ca394 | Q35: http://grls.rosminzdrav.ru/Grls_View_v2.aspx?routingGuid=e5e46dca-6622-4d3a-a0cd-349a012a5fc0&t= https://grls.rosminzdrav.ru/Grls_View_v2.aspx?routingGuid=85b9ac25-4fe7-4433-8cd8-f0b342dd9cf7&t= https://grls.rosminzdrav.ru/Grls_View_v2.aspx?routingGuid=4427eb1b-4f6c-42f5-9639-cb5f3a09cba2 https://grls.rosminzdrav.ru/Grls_View_v2.aspx?routingGuid=3b219e04-d778-4884-b683-c531afd10243 https://grls.rosminzdrav.ru/InstrImg/2023/09/26/1497492/e385d3ef-3918-4b5f-911b-fd418c787580.pdf https://lk.regmed.ru/Register/GetPDFfromDA?ID=1512826451 https://lk.regmed.ru/Register/GetPDFfromDA?ID=1599002471 https://lk.regmed.ru/Register/GetPDFfromDA?ID=1599002501 https://grls.rosminzdrav.ru/Grls_View_v2.aspx?routingGuid=9f01a261-d030-46db-82a0-3ab09a958a2e https://grls.rosminzdrav.ru/Grls_View_v2.aspx?routingGuid=3b219e04-d778-4884-b683-c531afd10243
A36: 35 | B36: Sovigripp | C36: https://grls.rosminzdrav.ru/Grls_View_v2.aspx?routingGuid=b287b682-550a-418f-8189-05dac16da4ae | D36: Совигрипп | E36: СОВИГРИПП® Вакцина гриппозная инактивированная субъединичная | F36: Микроген | G36: in use | K36: 44712 | L36: 45689 | M36: https://lk.regmed.ru/Register/GetPDFfromDAToken?Token=4d1562e5-05e7-405f-9673-b89a20ffd447 | N36: https://grls.rosminzdrav.ru/Grls_View_v2.aspx?routingGuid=b287b682-550a-418f-8189-05dac16da4ae | O36: https://lk.regmed.ru/Register/GetPDFfromDAToken?Token=068c5473-106f-49bc-a5f7-7ba1b7f020c3 | P36: https://grls.rosminzdrav.ru/Grls_View_v2.aspx?routingGuid=80286849-4848-4b66-a986-a99c8a476964 | Q36: http://grls.rosminzdrav.ru/Grls_View_v2.aspx?routingGuid=52ba41b8-9298-4f53-a5c0-8dedc52494a6&t= https://grls.rosminzdrav.ru/Grls_View_v2.aspx?routingGuid=072a45dd-9eac-44a1-b14d-fa7fffdf4885&t= https://grls.rosminzdrav.ru/Grls_View_v2.aspx?routingGuid=6ed700c7-271c-40a1-814a-0d3f717a24de https://grls.rosminzdrav.ru/Grls_View_v2.aspx?routingGuid=80286849-4848-4b66-a986-a99c8a476964 https://lk.regmed.ru/Register/GetPDFfromDA?ID=1633580161 https://lk.regmed.ru/Register/GetPDFfromDA?ID=1633580151
A37: 36 | B37: Ultrix | C37: https://grls.rosminzdrav.ru/Grls_View_v2.aspx?routingGuid=b90698f2-e111-4450-b82c-5c3ca26a25f5 | D37: Ультрикс | E37: Ультрикс® Вакцина гриппозная инактивированная расщепленная | F37: ФОРТ | G37: not in use | K37: 44712 | L37: 45689 | M37: https://lk.regmed.ru/Register/GetPDFfromDAToken?Token=ebfed185-d787-4d31-8be8-d3cbc95b7794 | N37: https://grls.rosminzdrav.ru/Grls_View_v2.aspx?routingGuid=b90698f2-e111-4450-b82c-5c3ca26a25f5 | O37: https://lk.regmed.ru/Register/GetPDFfromDAToken?Token=030e4140-af45-48dd-b213-76aeb3a23c36 | P37: https://grls.rosminzdrav.ru/Grls_View_v2.aspx?routingGuid=fe89d09a-8d9b-45fa-bb82-740a81904a6d | Q37: http://grls.rosminzdrav.ru/Grls_View_v2.aspx?routingGuid=fb9c24c2-c33a-4920-8361-9997d94b4e68&t= https://grls.rosminzdrav.ru/Grls_View_v2.aspx?routingGuid=fe89d09a-8d9b-45fa-bb82-740a81904a6d https://lk.regmed.ru/Register/GetPDFfromDA?ID=1523760571 https://lk.regmed.ru/Register/GetPDFfromDA?ID=1523760581
A38: 37 | B38: Flu_M | C38: https://grls.rosminzdrav.ru/Grls_View_v2.aspx?routingGuid=e7496b1f-1be9-46a3-b43f-e1c83a5b6cc8 | D38: Флю-М | E38: Флю-М [Вакцина гриппозная инактивированная расщепленная] | F38: СПбНИИВС | G38: in use | K38: 44712 | L38: 46130 | M38: нет | N38: https://grls.rosminzdrav.ru/Grls_View_v2.aspx?routingGuid=e7496b1f-1be9-46a3-b43f-e1c83a5b6cc8 | O38: нет | P38: https://grls.rosminzdrav.ru/Grls_View_v2.aspx?routingGuid=c6301213-2c71-499d-bf27-8fd593484674 | Q38: http://grls.rosminzdrav.ru/Grls_View_v2.aspx?routingGuid=24b95e82-2958-40e4-a4a2-4771c644d37a&t= https://grls.rosminzdrav.ru/Grls_View_v2.aspx?routingGuid=48a4c1e2-75b8-4e93-9354-db9c0f57205c&t= https://grls.rosminzdrav.ru/Grls_View_v2.aspx?routingGuid=6feebd54-4999-44d5-bd49-445441202847 https://grls.rosminzdrav.ru/Grls_View_v2.aspx?routingGuid=dfddbade-1401-4b6d-903d-74fe3c1a2821
A39: 38 | B39: Vaxigrip | C39: https://grls.rosminzdrav.ru/Grls_View_v2.aspx?routingGuid=34537f7c-cc43 – 45ef-bc9a-9820641bf718 | D39: Ваксигрип | E39: Ваксигрип® (инактивированная сплит-вакцина для профилактики гриппа) | G39: not in use | K39: 44712 | L39: 45078 | M39: нет | N39: нет | O39: нет | P39: https://grls.rosminzdrav.ru/Grls_View_v2.aspx?routingGuid=34537f7c-cc43-45ef-bc9a-9820641bf718 | Q39: http://grls.rosminzdrav.ru/Grls_View_v2.aspx?routingGuid=dbe0bb34-ff56-47e4-9873-0133b28f09c9&t=
A40: 39 | B40: Influvac | C40: https://grls.rosminzdrav.ru/Grls_View_v2.aspx?routingGuid=f0e5ea62-1cea-4427-923d-201a87349492 | D40: Инфлювак | E40: Инфлювак® (вакцина гриппозная субъединичная инактивированная) | G40: in use | K40: 44712 | L40: 46130 | M40: есть | N40: https://grls.rosminzdrav.ru/Grls_View_v2.aspx?routingGuid=f0e5ea62-1cea-4427-923d-201a87349492 | O40: есть | P40: https://grls.rosminzdrav.ru/Grls_View_v2.aspx?routingGuid=d1eda2da-96d0-46b8-883a-7358a06372b2 | Q40: http://grls.rosminzdrav.ru/Grls_View_v2.aspx?routingGuid=fec37fbb-555f-4f09-832e-e55c4adf9598&t= https://grls.rosminzdrav.ru/Grls_View_v2.aspx?routingGuid=bbe4964e-190b-475d-bc21-5df56876bcc3&t= https://grls.rosminzdrav.ru/Grls_View_v2.aspx?routingGuid=904ea0a9-2557-42e6-b1fe-cf2e3d5a2a5f
A41: 40 | B41: Ultrix_quadri | C41: https://grls.rosminzdrav.ru/Grls_View_v2.aspx?routingGuid=39b44822-0ca7-409d-bc25-db49ef3d5471 | D41: Ультрикс Квадри | E41: Ультрикс® Квадри Вакцина гриппозная четырехвалентная инактивированная расщепленная | G41: in use | K41: 44712 | L41: 45689 | M41: https://lk.regmed.ru/Register/GetPDFfromDAToken?Token=6b6de448-9da8-4025-8b7a-e10951e7ff00 | N41: https://grls.rosminzdrav.ru/Grls_View_v2.aspx?routingGuid=39b44822-0ca7-409d-bc25-db49ef3d5471 | O41: https://lk.regmed.ru/Register/GetPDFfromDAToken?Token=b2eb25a3-b0e8-4ec0-a061-84b5525ed27c | P41: https://grls.rosminzdrav.ru/Grls_View_v2.aspx?routingGuid=d8000e0b-8c92-4c5f-97ca-007605503798 | Q41: http://grls.rosminzdrav.ru/Grls_View_v2.aspx?routingGuid=124a42d3-7fac-48c0-aaaf-cfe4d199894b&t= https://grls.rosminzdrav.ru/Grls_View_v2.aspx?routingGuid=45037bd5-8037-42bf-9ee0-98d83f94c5c1&t= https://grls.rosminzdrav.ru/Grls_View_v2.aspx?routingGuid=7d222a39-9ad4-46f7-9bdb-89acbc8d2d6f https://grls.rosminzdrav.ru/Grls_View_v2.aspx?routingGuid=5b2d02e2-366c-4fda-9c5c-c8682c64f4ab https://grls.rosminzdrav.ru/Grls_View_v2.aspx?routingGuid=d8000e0b-8c92-4c5f-97ca-007605503798 https://lk.regmed.ru/Register/GetPDFfromDA?ID=1612604181 https://lk.regmed.ru/Register/GetPDFfromDA?ID=1612604221
A42: 41 | B42: Grippol_quadrivalent | C42: https://grls.rosminzdrav.ru/Grls_View_v2.aspx?routingGuid=9d163668-04c5-490d-81ed-287f1cc6ac47 | D42: Гриппол Квадривалент | E42: Гриппол® Квадривалент Вакцина гриппозная четырехвалентная инактивированная субъединичная адъювантная | G42: in use | K42: 44712 | L42: 45818 | M42: https://lk.regmed.ru/Register/GetPDFfromDAToken?Token=21d09ab4-e8b0-4241-88e6-6f4a8868109c | N42: https://grls.rosminzdrav.ru/Grls_View_v2.aspx?routingGuid=9d163668-04c5-490d-81ed-287f1cc6ac47 | O42: https://lk.regmed.ru/Register/GetPDFfromDAToken?Token=b432b611-0158-4b27-8d05-73c60d69171c | P42: https://grls.rosminzdrav.ru/Grls_View_v2.aspx?routingGuid=2227b96d-2e61-48bd-9cca-17ce427fdc48 | Q42: http://grls.rosminzdrav.ru/Grls_View_v2.aspx?routingGuid=df187e16-c6c8-4e25-996d-d24609d80ffe&t= https://grls.rosminzdrav.ru/Grls_View_v2.aspx?routingGuid=795bca3c-a1a9-4b1f-b746-0543118bba89&t= https://grls.rosminzdrav.ru/Grls_View_v2.aspx?routingGuid=aaad7988-7890-4311-aff9-8bea62268f88 https://grls.rosminzdrav.ru/Grls_View_v2.aspx?routingGuid=246d6b61-cf90-437b-9ff2-8fd5f105a763 https://lk.regmed.ru/Register/GetPDFfromDA?ID=1597541001 https://lk.regmed.ru/Register/GetPDFfromDA?ID=1597541011 https://grls.rosminzdrav.ru/Grls_View_v2.aspx?routingGuid=a3561d12-68bd-4cc8-a1b3-aa2502077435
A43: 42 | B43: measles_Microgen | C43: https://grls.rosminzdrav.ru/Grls_View_v2.aspx?routingGuid=21ef9e10-0802-4099-9f29-815fab9bf24f | D43: коревая (Микроген) | E43: Вакцина коревая культуральная живая | F43: Микроген | G43: in use | K43: 44712 | L43: 45689 | M43: https://lk.regmed.ru/Register/GetPDFfromDAToken?Token=7542b90d-b67b-4205-9d82-117e106aba6c | N43: нет | O43: https://lk.regmed.ru/Register/GetPDFfromDAToken?Token=49eb0c51-5786-40d6-aa23-a6ca97631b43 | P43: https://grls.rosminzdrav.ru/Grls_View_v2.aspx?routingGuid=21ef9e10-0802-4099-9f29-815fab9bf24f | Q43: http://grls.rosminzdrav.ru/Grls_View_v2.aspx?routingGuid=61237c83-f5c4-43db-aad1-879afb2576dc&t= https://grls.rosminzdrav.ru/Grls_View_v2.aspx?routingGuid=50f4ddc8-d32e-4bc9-a7e8-ef3b725bdcf4 https://grls.rosminzdrav.ru/Grls_View_v2.aspx?routingGuid=01e97889-adda-4d87-b2f3-d4b8afcbbc5a https://lk.regmed.ru/Register/GetPDFfromDA?ID=1581220991 https://lk.regmed.ru/Register/GetPDFfromDA?ID=1581220981
A44: 43 | B44: measles_Serum_India | C44: https://grls.rosminzdrav.ru/Grls_View_v2.aspx?routingGuid=af4dd5ba-8e11-450c-83f0-3c6db2b13cf6 | D44: коревая (Серум Инститьют) | E44: Вакцина против кори живая аттенуированная | F44: Серум Инститьют | G44: not in use | K44: 44712 | L44: 46053 | M44: есть | N44: нет | O44: есть | P44: https://grls.rosminzdrav.ru/Grls_View_v2.aspx?routingGuid=af4dd5ba-8e11-450c-83f0-3c6db2b13cf6 | Q44: http://grls.rosminzdrav.ru/Grls_View_v2.aspx?routingGuid=3a8b491f-08bf-49aa-80ac-02b9a3c91a1f&t= https://grls.rosminzdrav.ru/Grls_View_v2.aspx?routingGuid=231607bd-b4c9-4eec-b6e1-5f28de2c5eb3 https://grls.rosminzdrav.ru/Grls_View_v2.aspx?routingGuid=d0960ca7-bae5-4ef6-a711-929de9abc901 https://grls.rosminzdrav.ru/Grls_View_v2.aspx?routingGuid=0fb5a06d-2df7-4647-98fa-055df85c6963
A45: 44 | B45: measles_Vector | C45: https://grls.rosminzdrav.ru/Grls_View_v2.aspx?routingGuid=1c26875c-896c-488d-b713-142d18c1310f | D45: коревая (Вектор) | E45: Вакцина коревая культуральная живая | F45: Вектор | G45: in use | K45: 44712 | L45: 44750 | M45: нет | N45: нет | O45: нет | P45: https://grls.rosminzdrav.ru/Grls_View_v2.aspx?routingGuid=1c26875c-896c-488d-b713-142d18c1310f | Q45: https://grls.rosminzdrav.ru/Grls_View_v2.aspx?routingGuid=1c26875c-896c-488d-b713-142d18c1310f
A46: 45 | B46: measles_mumps_Microgen | C46: https://grls.rosminzdrav.ru/Grls_View_v2.aspx?routingGuid=bbcf7276-a503-4968-abd0-286f29aa80a7 | D46: паротитно-коревая (Микроген) | E46: Вакцина паротитно-коревая культуральная живая | F46: Микроген | G46: in use | K46: 44712 | L46: 45689 | M46: https://lk.regmed.ru/Register/GetPDFfromDAToken?Token=871cc235-deab-47cc-ac2f-13a865cc2b7f | N46: нет | O46: https://lk.regmed.ru/Register/GetPDFfromDAToken?Token=60f59013-3af8-438a-b5ec-739308a69e96 | P46: https://grls.rosminzdrav.ru/Grls_View_v2.aspx?routingGuid=bbcf7276-a503-4968-abd0-286f29aa80a7 | Q46: http://grls.rosminzdrav.ru/Grls_View_v2.aspx?routingGuid=ca43f50c-f676-44b2-86ad-853f677b4498&t= https://grls.rosminzdrav.ru/Grls_View_v2.aspx?routingGuid=791e81d9-294b-4baf-8a70-168c7f7f86f2 https://grls.rosminzdrav.ru/Grls_View_v2.aspx?routingGuid=d16807c0-3ae7-4dcf-9b27 – 98da382d2a0b https://lk.regmed.ru/Register/GetPDFfromDA?ID=1537524921 https://lk.regmed.ru/Register/GetPDFfromDA?ID=1597558391 https://lk.regmed.ru/Register/GetPDFfromDA?ID=1597558401
A47: 46 | B47: Vactrivir | C47: https://grls.rosminzdrav.ru/Grls_View_v2.aspx?routingGuid=a4090b86-5da6-4481-8230-dd9e607b60af | D47: Вактривир | E47: ВАКТРИВИР Комбинированная вакцина против кори, краснухи и паротита культуральная живая | G47: in use | H47: <p>При необходимости вакцинации детей в возрасте младше 12&nbsp;месяцев, если это предусмотрено Национальными рекомендациями, вакцину следует вводить в возрасте не ранее 9&nbsp;месяцев.</p> | I47: При необходимости вакцинации детей в возрасте младше 12 месяцев, если это предусмотрено Национальными рекомендациями, вакцину следует вводить в возрасте не ранее 9 месяцев. | K47: 44712 | L47: 45830 | M47: https://lk.regmed.ru/Register/GetPDFfromDAToken?Token=8415d4f4-69df-4249-bc87-8ca7cad24c51 | N47: https://grls.rosminzdrav.ru/Grls_View_v2.aspx?routingGuid=a4090b86-5da6-4481-8230-dd9e607b60af | O47: https://lk.regmed.ru/Register/GetPDFfromDAToken?Token=fd485da8-7368-4961-a19c-06323bb3bcc0 | P47: https://grls.rosminzdrav.ru/Grls_View_v2.aspx?routingGuid=5b6518f1-1b39-4e40-8390-4b9a01bf80dd | Q47: http://grls.rosminzdrav.ru/Grls_View_v2.aspx?routingGuid=81101529-b9fa-42c8-b76c-a700ade3d59c&t= https://grls.rosminzdrav.ru/Grls_View_v2.aspx?routingGuid=8697837e-9a5b-40ee-a9cf-889ae74a67df https://grls.rosminzdrav.ru/Grls_View_v2.aspx?routingGuid=227d901e-8846-4d42-b5d6-b13f1432ed6f https://grls.rosminzdrav.ru/Grls_View_v2.aspx?routingGuid=de5e2075-b10e-4d53-a550-05da38523f20 https://lk.regmed.ru/Register/GetPDFfromDA?ID=1574035031 https://grls.rosminzdrav.ru/Grls_View_v2.aspx?routingGuid=52ee92d0-9f04-49b0-837d-e4075fbf0b34 https://lk.regmed.ru/Register/GetPDFfromDA?ID=1615125021 https://lk.regmed.ru/Register/GetPDFfromDA?ID=1615125031
A48: 47 | B48: MMR_II | C48: https://grls.rosminzdrav.ru/Grls_View_v2.aspx?routingGuid=aa975a20-f44a-451e-bf3e-3dcc80435b61 | D48: М-М-Р II | E48: М-М-Р II® (Вакцина против кори, паротита и краснухи, живая) | G48: not in use | K48: 44712 | L48: 45715 | M48: нет | N48: нет | O48: нет | P48: https://grls.rosminzdrav.ru/Grls_View_v2.aspx?routingGuid=aa975a20-f44a-451e-bf3e-3dcc80435b61 | Q48: http://grls.rosminzdrav.ru/Grls_View_v2.aspx?routingGuid=0d17eb38-2f27-41b3-ae00-df4048d683a8&t= https://grls.rosminzdrav.ru/Grls_View_v2.aspx?routingGuid=20933871-b349-4a9f-b8ed-0bdd37633ce8 https://grls.rosminzdrav.ru/Grls_View_v2.aspx?routingGuid=79070156-b013 – 49b6-b02e-67816d8e0b88
A49: 48 | B49: MenA_Microgen | C49: https://grls.rosminzdrav.ru/Grls_View_v2.aspx?routingGuid=573dc2fd-b104-4a0c-a56a-486f57764912 | D49: Менингококковая гр. A | E49: Вакцина менингококковая группы А полисахаридная | F49: Микроген | G49: in use | H49: <p>менингококки группы&nbsp;A</p> | I49: менингококки группы A | K49: 44712 | L49: 45689 | M49: https://lk.regmed.ru/Register/GetPDFfromDAToken?Token=22a07d8d-d541-45f6-8093-29d650df9705 | N49: нет | O49: https://lk.regmed.ru/Register/GetPDFfromDAToken?Token=3d5332a3-fefe-4a5b-acda-977c16b3d967 | P49: https://grls.rosminzdrav.ru/Grls_View_v2.aspx?routingGuid=573dc2fd-b104-4a0c-a56a-486f57764912 | Q49: http://grls.rosminzdrav.ru/Grls_View_v2.aspx?routingGuid=539093dd-5019-4c91-982a-7b0108bbce0e&t= https://grls.rosminzdrav.ru/Grls_View_v2.aspx?routingGuid=c70e230d-b8c5-4764-b82d-fe3e658e3dcf https://grls.rosminzdrav.ru/Grls_View_v2.aspx?routingGuid=0120e001-9957-4ac6-9c90-e3953b7e1e18 https://lk.regmed.ru/Register/GetPDFfromDA?ID=1583272671 https://lk.regmed.ru/Register/GetPDFfromDA?ID=1583272641
A50: 49 | B50: MeningoVac_A_C | C50: https://grls.rosminzdrav.ru/Grls_View_v2.aspx?routingGuid=162087a7-8c2e-4c1c-ada9-b2d41a7fc06d | D50: Менингококковая гр. А+С | E50: Вакцина менингококковая групп А и С полисахаридная | F50: Микроген | G50: not in use | H50: <p>менингококки группы&nbsp;A, C</p> | I50: менингококки группы A, C | J50: =0.5 -> 0.5 | K50: 44712 | L50: 45689 | M50: https://lk.regmed.ru/Register/GetPDFfromDAToken?Token=023326ba-2394-4cee-8436-d2d7251635d0 | N50: нет | O50: https://lk.regmed.ru/Register/GetPDFfromDAToken?Token=ee03c4ca-717d-4833-b701-e198134f2d9e | P50: https://grls.rosminzdrav.ru/Grls_View_v2.aspx?routingGuid=162087a7-8c2e-4c1c-ada9-b2d41a7fc06d | Q50: http://grls.rosminzdrav.ru/Grls_View_v2.aspx?routingGuid=f5818301-d1f3 – 41f0-8756-aae5c73114a3&t= https://grls.rosminzdrav.ru/Grls_View_v2.aspx?routingGuid=347acbcf-2d55-4d52-b4e7-d02d0bcc8066 https://lk.regmed.ru/Register/GetPDFfromDA?ID=1581523381 https://lk.regmed.ru/Register/GetPDFfromDA?ID=1581523391
A51: 50 | B51: Menactra | C51: https://grls.rosminzdrav.ru/Grls_View_v2.aspx?routingGuid=f79c63df-14fc-4066-a985-f34555bed179 | D51: Менактра | E51: МЕНАКТРА® [вакцина менингококковая полисахаридная (серогрупп A, C, Y и W-135), конъюгированная с дифтерийным анатоксином] | F51: Санофи Пастер Лимитед | G51: in use | H51: <p>менингококки группы&nbsp;A, C, W, Y</p> | I51: менингококки группы A, C, W, Y | K51: 44712 | L51: 45689 | M51: https://lk.regmed.ru/Register/GetPDFfromDAToken?Token=daa21352-7464-4e37-a24b-31888db79e80 | N51: https://grls.rosminzdrav.ru/Grls_View_v2.aspx?routingGuid=f79c63df-14fc-4066-a985-f34555bed179 | O51: https://lk.regmed.ru/Register/GetPDFfromDAToken?Token=0725a6ff-6dab-4a0b-bf38-21b81e568dfb | P51: https://grls.rosminzdrav.ru/Grls_View_v2.aspx?routingGuid=ad209ac6-713c-44f3-a988-34b85866cd93 | Q51: http://grls.rosminzdrav.ru/Grls_View_v2.aspx?routingGuid=8b65507f-1d6e-4318-b54e-d1d9632dd46c&t= https://grls.rosminzdrav.ru/Grls_View_v2.aspx?routingGuid=0061bcf7-8c2f-4f33-8766 – 7cc2a63e0b45 https://grls.rosminzdrav.ru/Grls_View_v2.aspx?routingGuid=ad209ac6 – 713c-44f3-a988-34b85866cd93 https://grls.rosminzdrav.ru/Grls_View_v2.aspx?routingGuid=f84cd187-dbcf-4c4d-9040-4b41beb42fc7 https://lk.regmed.ru/Register/GetPDFfromDA?ID=1574028031 https://lk.regmed.ru/Register/GetPDFfromDA?ID=1574028041
A52: 51 | B52: mumps_Microgen | C52: https://grls.rosminzdrav.ru/Grls_View_v2.aspx?routingGuid=4f505e78-1d02-4b8f-aaf9-618368787be0 | D52: паротитная (Микроген) | E52: Вакцина паротитная культуральная живая | F52: Микроген | G52: in use | K52: 44712 | L52: 45689 | M52: https://lk.regmed.ru/Register/GetPDFfromDAToken?Token=a03421c1-d658-4466-a600-c80d1005976d | N52: нет | O52: https://lk.regmed.ru/Register/GetPDFfromDAToken?Token=7069eb11-87e9-4098-956f-d6a04dcc1ff5 | P52: https://grls.rosminzdrav.ru/Grls_View_v2.aspx?routingGuid=4f505e78-1d02-4b8f-aaf9-618368787be0 | Q52: http://grls.rosminzdrav.ru/Grls_View_v2.aspx?routingGuid=5357746a-154a-43d6-8079-181497073d49&t= https://grls.rosminzdrav.ru/Grls_View_v2.aspx?routingGuid=d43c44b3 – 4860-410e-949e-394ac27f51da https://grls.rosminzdrav.ru/Grls_View_v2.aspx?routingGuid=63e40ea5-953e-4097-bba6-8a294540ae29 https://lk.regmed.ru/Register/GetPDFfromDA?ID=1537525101 https://lk.regmed.ru/Register/GetPDFfromDA?ID=1594767771 https://lk.regmed.ru/Register/GetPDFfromDA?ID=1594767781
A53: 52 | B53: Prevenar_13 | C53: https://grls.rosminzdrav.ru/Grls_View_v2.aspx?routingGuid=c88b7ed6-2791-496d-95ac-2bf2453e540b | D53: Превенар 13 | E53: Превенар® 13 (вакцина пневмококковая полисахаридная конъюгированная адсорбированная, тринадцативалентная) | F53: Пфайзер | G53: in use | K53: 44712 | L53: 45689 | M53: https://lk.regmed.ru/Register/GetPDFfromDAToken?Token=3553002d-a459-42b4-8d3c-382ab7278081 | N53: https://grls.rosminzdrav.ru/Grls_View_v2.aspx?routingGuid=c88b7ed6-2791-496d-95ac-2bf2453e540b | O53: https://lk.regmed.ru/Register/GetPDFfromDAToken?Token=2582b5a2-7a42-49c7-ab2d-7f067592996f | P53: https://grls.rosminzdrav.ru/Grls_View_v2.aspx?routingGuid=fa171426-1eca-44bc-81f4-6031a67504f1 | Q53: http://grls.rosminzdrav.ru/Grls_View_v2.aspx?routingGuid=17eeb85f-062a-4f03-b4ba-7053cbca6a2e&t= https://grls.rosminzdrav.ru/Grls_View_v2.aspx?routingGuid=fa171426-1eca-44bc-81f4-6031a67504f1 https://grls.rosminzdrav.ru/Grls_View_v2.aspx?routingGuid=ec38a615-5756-4de3-8136-56f2af639760 https://lk.regmed.ru/Register/GetPDFfromDA?ID=1544529771 https://lk.regmed.ru/Register/GetPDFfromDA?ID=1544529781
A54: 53 | B54: Synflorix | C54: https://grls.rosminzdrav.ru/Grls_View_v2.aspx?routingGuid=98f6f75c-4d06-4e15-8e8e-52e513e2c4c1 | D54: Синфлорикс | E54: Синфлорикс (Вакцина 10-валентная пневмококковая полисахаридная, конъюгированная с D-протеином нетипируемой Haemophilus influenzae, столбнячным и дифтерийным анатоксинами, адсорбированная) | G54: not in use | K54: 44712 | L54: 45715 | M54: нет | N54: нет | O54: нет | P54: https://grls.rosminzdrav.ru/Grls_View_v2.aspx?routingGuid=98f6f75c-4d06-4e15-8e8e-52e513e2c4c1 | Q54: http://grls.rosminzdrav.ru/Grls_View_v2.aspx?routingGuid=bc69c871-334e-49d1-9c5e-34547e17b015&t= https://grls.rosminzdrav.ru/Grls_View_v2.aspx?routingGuid=150b2fd7-dd3c-4227-aa69-61c4de6db279
A55: 54 | B55: Pneumovax_23 | C55: https://grls.rosminzdrav.ru/Grls_View_v2.aspx?routingGuid=7ded6546-8feb-4afd-9a4d-1fce9414a552 | D55: Пневмовакс 23 | E55: Пневмовакс® 23 (Вакцина пневмококковая, поливалентная) | F55: Мерк Шарп и Доум Б.В. | G55: in use | K55: 44712 | L55: 45689 | M55: https://lk.regmed.ru/Register/GetPDFfromDAToken?Token=10e497be-3d4a-43a2-aa31-092ce691668e | N55: нет | O55: https://lk.regmed.ru/Register/GetPDFfromDAToken?Token=712b88e8-5bd2-4955-b963-d496b4e78858 | P55: https://grls.rosminzdrav.ru/Grls_View_v2.aspx?routingGuid=7ded6546-8feb-4afd-9a4d-1fce9414a552 | Q55: http://grls.rosminzdrav.ru/Grls_View_v2.aspx?routingGuid=e3696973-e636-4bc1-8a9d-42508ea757a1&t= https://grls.rosminzdrav.ru/Grls_View_v2.aspx?routingGuid=522fd231-380e-4abc-a562-f38eb2a801db https://grls.rosminzdrav.ru/Grls_View_v2.aspx?routingGuid=32e86091-0622-4dce-aa51-9247900477f9 https://grls.rosminzdrav.ru/Grls_View_v2.aspx?routingGuid=29d4d7af-97b9-4f6d-9b2d-73b52e5c06f6 https://lk.regmed.ru/Register/GetPDFfromDA?ID=1509638211 https://lk.regmed.ru/Register/GetPDFfromDA?ID=1509638231
A56: 55 | B56: MonoVac_Polio | C56: https://grls.rosminzdrav.ru/Grls_View_v2.aspx?routingGuid=94cb6422-2bae-41b1-b881-7019bc1e6c88 | D56: МоноВак полио | E56: МоноВак полио тип 2 (Вакцина полиомиелитная пероральная, моновалентная, живая аттенуированная 2 типа) | G56: in use | K56: 44712 | L56: 44944 | M56: нет | N56: нет | O56: нет | P56: https://grls.rosminzdrav.ru/Grls_View_v2.aspx?routingGuid=94cb6422-2bae-41b1-b881-7019bc1e6c88 | Q56: http://grls.rosminzdrav.ru/Grls_View_v2.aspx?routingGuid=e3ab4daa-0aca-47e9-8b48-96b99c77096e&t= https://grls.rosminzdrav.ru/Grls_View_v2.aspx?routingGuid=400205c6-33cc-46fd-92c6-8ab850bc639d
A57: 56 | B57: BiVac_Polio | C57: https://grls.rosminzdrav.ru/Grls_View_v2.aspx?routingGuid=35f3aeab-53d0-4aa3-b370-016ed06e2330 | D57: БиВак полио | E57: БиВак полио (Вакцина полиомиелитная пероральная, двухвалентная, живая аттенуированная 1, 3 типов) | G57: in use | K57: 44712 | L57: 45988 | M57: нет | N57: нет | O57: нет | P57: https://grls.rosminzdrav.ru/Grls_View_v2.aspx?routingGuid=35f3aeab-53d0-4aa3-b370-016ed06e2330 | Q57: http://grls.rosminzdrav.ru/Grls_View_v2.aspx?routingGuid=aef7142f-ecd9-454b-b8cb-58f9ca7f752f&t= https://grls.rosminzdrav.ru/Grls_View_v2.aspx?routingGuid=5cb1f1e4-9c80-4be1-b816-427d028c9f95 https://grls.rosminzdrav.ru/Grls_View_v2.aspx?routingGuid=dc8f7579-e089-4ac2-9211-3b2670e33c76
A58: 57 | B58: Polymilex | C58: https://grls.rosminzdrav.ru/Grls_View_v2.aspx?routingGuid=f91918fb-09b8-4766-8e48-6606a0541073 | D58: Полимилекс | E58: ПОЛИМИЛЕКС® вакцина для профилактики полиомиелита инактивированная | G58: in use | K58: 44712 | L58: 45715 | M58: нет | N58: нет | O58: нет | P58: https://grls.rosminzdrav.ru/Grls_View_v2.aspx?routingGuid=f91918fb-09b8-4766-8e48-6606a0541073 | Q58: http://grls.rosminzdrav.ru/Grls_View_v2.aspx?routingGuid=368521c3-ffe0-427c-9e7e-b3e0530b260b&t= https://grls.rosminzdrav.ru/Grls_View_v2.aspx?routingGuid=4e478c56 – 77e4-49ba-a746-209737ab662f
A59: 58 | B59: COCAV | C59: https://grls.rosminzdrav.ru/Grls_View_v2.aspx?routingGuid=7da83465-3e51-4a42-99a7-7aff7e64f9e4 | D59: Кокав | E59: КОКАВ Вакцина антирабическая культуральная концентрированная очищенная инактивированная | G59: in use | H59: <p>Для постэкспозиционной профилактики, то есть в случае укуса потенциально бешеным животным, противопоказания отсутствуют. В том числе прививка может проводиться беременным, если беременная была укушена животным, которое может быть инфицировано вирусом бешенства.<br> <br> Указанные ниже противопоказания относятся к плановой вакцинации лиц, имеющих высокий профессиональный риск заражения бешенством, — ветеринарных работников, егерей, охотников, лесников, лиц, работающих с уличным вирусом бешенства или выполняющих работы по отлову и содержанию животных.</p> | I59: Для постэкспозиционной профилактики, то есть в случае укуса потенциально бешеным животным, противопоказания отсутствуют. В том числе прививка может проводиться беременным, если беременная была укушена животным, которое может быть инфицировано вирусом бешенства. Указанные ниже противопоказания относятся к плановой вакцинации лиц, имеющих высокий профессиональный риск заражения бешенством, — ветеринарных работников, егерей, охотников, лесников, лиц, работающих с уличным вирусом бешенства или выполняющих работы по отлову и содержанию животных. | K59: 44712 | L59: 45689 | M59: https://lk.regmed.ru/Register/GetPDFfromDAToken?Token=92b647e6-6e46-4d97-b5db-055d884d1048 | N59: https://grls.rosminzdrav.ru/Grls_View_v2.aspx?routingGuid=7da83465-3e51-4a42-99a7-7aff7e64f9e4 | O59: https://lk.regmed.ru/Register/GetPDFfromDAToken?Token=d3a2ba4c-0ab7-4f72-bada-cdbf545e9964 | P59: https://grls.rosminzdrav.ru/Grls_View_v2.aspx?routingGuid=3fbed720-7541-47c6-ba18-678e6f65efe9 | Q59: http://grls.rosminzdrav.ru/Grls_View_v2.aspx?routingGuid=de917eb7 – 9b46-453b-bb49-a588ee683192&t= https://grls.rosminzdrav.ru/Grls_View_v2.aspx?routingGuid=8744c2e9-96ff-4d34-b547-c43d40f6645c https://grls.rosminzdrav.ru/Grls_View_v2.aspx?routingGuid=3fbed720-7541-47c6-ba18-678e6f65efe9 https://lk.regmed.ru/Register/GetPDFfromDA?ID=1649843881 https://lk.regmed.ru/Register/GetPDFfromDA?ID=1649843891
A60: 59 | B60: rabies_Chumakov | C60: https://grls.rosminzdrav.ru/Grls_View_v2.aspx?routingGuid=91d987ae-568f-4c6b-8623-8abf1ea0cbdc | D60: антирабическая (Чумакова) | E60: Вакцина антирабическая культуральная концентрированная очищенная инактивированная сухая | G60: in use | K60: 44712 | L60: 46188 | M60: нет | N60: нет | O60: нет | P60: https://grls.rosminzdrav.ru/Grls_View_v2.aspx?routingGuid=91d987ae-568f-4c6b-8623-8abf1ea0cbdc | Q60: http://grls.rosminzdrav.ru/Grls_View_v2.aspx?routingGuid=fa3953b4-a836-46cb-84fa-04af871c773f&t= https://grls.rosminzdrav.ru/Grls_View_v2.aspx?routingGuid=d4c5684e-c17e-4ff7-b95c-cefe70d65da5 https://grls.rosminzdrav.ru/Grls_View_v2.aspx?routingGuid=485c049d-1b8b-4626-9945-f7a0177807db https://grls.rosminzdrav.ru/Grls_View_v2.aspx?routingGuid=1bbff108-9884-4a0e-9bed-8f37a0ec4e99
A61: 60 | B61: Rabivac_Vnukovo_32 | C61: https://grls.rosminzdrav.ru/Grls_View_v2.aspx?routingGuid=e4ffdd5e-89db-479f-b9a3-4aee83beeb8a | D61: Рабивак-Внуково-32 | E61: Рабивак-Внуково-32 Вакцина антирабическая культуральная инактивированная для иммунизации человека | G61: not in use | K61: 44712 | L61: 44748 | M61: нет | N61: нет | O61: нет | P61: https://grls.rosminzdrav.ru/Grls_View_v2.aspx?routingGuid=e4ffdd5e-89db-479f-b9a3-4aee83beeb8a | Q61: https://grls.rosminzdrav.ru/Grls_View_v2.aspx?routingGuid=fdc0478a-afd9-4fb4-b9fd-51277ddd1027
A62: 61 | B62: RotaTeq | C62: https://grls.rosminzdrav.ru/Grls_View_v2.aspx?routingGuid=5a312c4c-479c-463e-85d1-fa7e8990168d | D62: РотаТек | E62: РотаТек® | G62: not in use | K62: 44712 | L62: 44787 | M62: нет | N62: нет | O62: нет | P62: https://grls.rosminzdrav.ru/Grls_View_v2.aspx?routingGuid=5a312c4c-479c-463e-85d1-fa7e8990168d | Q62: http://grls.rosminzdrav.ru/Grls_View_v2.aspx?routingGuid=6b6eb6ab-e08f-451b-83af-6529917525e0&t= https://grls.rosminzdrav.ru/Grls_View_v2.aspx?routingGuid=bdde7917-0e6b-44f1-86ee-6d3838d08a32 https://grls.rosminzdrav.ru/Grls_View_v2.aspx?routingGuid=20c71417-2e14-4301-8f0d-86adf899e2c5
A63: 62 | B63: rubella_Microgen | C63: https://grls.rosminzdrav.ru/Grls_View_v2.aspx?routingGuid=0482f816-63ad-49b9-9b56-808b708f6dab | D63: краснушная (Микроген) | E63: Вакцина против краснухи культуральная живая | F63: Микроген | G63: in use | K63: 44712 | L63: 45689 | M63: https://lk.regmed.ru/Register/GetPDFfromDAToken?Token=861ea14c-5408-419d-bd47-031af580ecf7 | N63: нет | O63: https://lk.regmed.ru/Register/GetPDFfromDAToken?Token=adbfd269-10a4-4e66-843d-b02b4eb3546f | P63: https://grls.rosminzdrav.ru/Grls_View_v2.aspx?routingGuid=0482f816-63ad-49b9-9b56-808b708f6dab | Q63: https://grls.rosminzdrav.ru/Grls_View_v2.aspx?routingGuid=e7d9a488-4838-4519-b9b2-7a7c83cac570 https://lk.regmed.ru/Register/GetPDFfromDA?ID=1574035311 https://lk.regmed.ru/Register/GetPDFfromDA?ID=1621077341 https://lk.regmed.ru/Register/GetPDFfromDA?ID=1621077331 https://grls.rosminzdrav.ru/Grls_View_v2.aspx?routingGuid=e7d9a488-4838-4519-b9b2-7a7c83cac570
A64: 63 | B64: rubella_Serum | C64: https://grls.rosminzdrav.ru/Grls_View_v2.aspx?routingGuid=dee8c37b-28f6-45f1-9773-d691d9fb54ae | D64: краснушная (Серум Инститьют) | E64: Вакцина против краснухи живая аттенуированная | F64: Серум Инститьют | G64: not in use | K64: 44712 | L64: 44750 | M64: нет | N64: нет | O64: нет | P64: https://grls.rosminzdrav.ru/Grls_View_v2.aspx?routingGuid=dee8c37b-28f6-45f1-9773-d691d9fb54ae
A65: 64 | B65: AS_Microgen | C65: https://grls.rosminzdrav.ru/Grls_View_v2.aspx?routingGuid=640af3c6-436c-47e2-a2cb-8cfff245452f | D65: Анатоксин столбнячный (Микроген) | E65: Анатоксин столбнячный очищенный адсорбированный жидкий (АС-анатоксин) | G65: in use | H65: <p>Анатоксин противопоказан только в первую половину беременности. Во вторую половину беременности введение анатоксина возможно.</p> | I65: Анатоксин противопоказан только в первую половину беременности. Во вторую половину беременности введение анатоксина возможно. | K65: 44712 | L65: 45689 | M65: есть | N65: https://grls.rosminzdrav.ru/Grls_View_v2.aspx?routingGuid=640af3c6-436c-47e2-a2cb-8cfff245452f | O65: есть | P65: https://grls.rosminzdrav.ru/Grls_View_v2.aspx?routingGuid=f3397dc1-d0e3-472a-975a-f988a9b4b549 | Q65: http://grls.rosminzdrav.ru/Grls_View_v2.aspx?routingGuid=c8239b79-bc3e-435f-a7e7-3fdc63171bd6&t= https://grls.rosminzdrav.ru/Grls_View_v2.aspx?routingGuid=33a12605-0c27-4bd0-938c-de686230b880 https://grls.rosminzdrav.ru/Grls_View_v2.aspx?routingGuid=f3397dc1-d0e3-472a-975a-f988a9b4b549 https://lk.regmed.ru/Register/GetPDFfromDA?ID=1597558331 https://lk.regmed.ru/Register/GetPDFfromDA?ID=1597558341 https://grls.rosminzdrav.ru/Grls_View_v2.aspx?routingGuid=f3397dc1-d0e3-472a-975a-f988a9b4b549
A66: 65 | B66: AS_Biomed | C66: https://grls.rosminzdrav.ru/Grls_View_v2.aspx?routingGuid=e46d0e09-a66e-402e-8777-b446fa489d1c | D66: Анатоксин столбнячный (Биомед) | E66: Анатоксин столбнячный очищенный адсорбированный жидкий (АС-анатоксин) | G66: in use | K66: 44712 | L66: 44750 | M66: нет | N66: нет | O66: нет | P66: https://grls.rosminzdrav.ru/Grls_View_v2.aspx?routingGuid=e46d0e09-a66e-402e-8777-b446fa489d1c | Q66: https://grls.rosminzdrav.ru/Grls_View_v2.aspx?routingGuid=efdeae15-37e3-4ec2-bdef-9e98fdbd8846
A67: 66 | B67: Vaqta_25 | C67: https://grls.rosminzdrav.ru/Grls_View_v2.aspx?routingGuid=2d805292-2bee-4665-b4ef-a466b3e3bc8f | D67: Вакта 25 | E67: Вакта® | G67: not in use | K67: 44712 | L67: 45079 | M67: нет | N67: нет | O67: нет | P67: https://grls.rosminzdrav.ru/Grls_View_v2.aspx?routingGuid=2d805292-2bee-4665-b4ef-a466b3e3bc8f | Q67: http://grls.rosminzdrav.ru/Grls_View_v2.aspx?routingGuid=e2729daf-b6bd-46e1-9860-a1e798ffdb95&t=
A68: 67 | B68: Vaqta_50 | C68: https://grls.rosminzdrav.ru/Grls_View_v2.aspx?routingGuid=2d805292-2bee-4665-b4ef-a466b3e3bc8f | D68: Вакта 50 | E68: Вакта® | G68: not in use | K68: 44712 | L68: 45079 | M68: нет | N68: нет | O68: нет | P68: https://grls.rosminzdrav.ru/Grls_View_v2.aspx?routingGuid=2d805292-2bee-4665-b4ef-a466b3e3bc8f | Q68: http://grls.rosminzdrav.ru/Grls_View_v2.aspx?routingGuid=e2729daf-b6bd-46e1-9860-a1e798ffdb95&t=
A69: 68 | B69: Klesh_E_Vac_0_5 | C69: https://grls.rosminzdrav.ru/Grls_View_v2.aspx?routingGuid=708a5616-61d3-4695-a4cb-2e78bcfca33b | D69: Клещ-Э-Вак 0,5 | E69: Клещ-Э-Вак (Вакцина клещевого энцефалита культуральная очищенная концентрированная инактивированная сорбированная) | G69: in use | K69: 44712 | L69: 45988 | M69: есть | N69: https://grls.rosminzdrav.ru/Grls_View_v2.aspx?routingGuid=708a5616-61d3-4695-a4cb-2e78bcfca33b | O69: есть | P69: https://grls.rosminzdrav.ru/Grls_View_v2.aspx?routingGuid=245ee300-7d64-4000-ab8b-ded51091a060 | Q69: http://grls.rosminzdrav.ru/Grls_View_v2.aspx?routingGuid=fba2bb4d-f934-460c-b318-dad8525f8cd6&t= https://grls.rosminzdrav.ru/Grls_View_v2.aspx?routingGuid=80b33204-fa6e-445b-95d7-e8679b50536d https://grls.rosminzdrav.ru/Grls_View_v2.aspx?routingGuid=245ee300-7d64-4000-ab8b-ded51091a060 https://grls.rosminzdrav.ru/Grls_View_v2.aspx?routingGuid=4d82f537-a6f0-4a51-a9d5-4a215a7bf663
A70: 69 | B70: Klesh_E_Vac_0_25 | C70: https://grls.rosminzdrav.ru/Grls_View_v2.aspx?routingGuid=708a5616-61d3-4695-a4cb-2e78bcfca33b | D70: Клещ-Э-Вак 0,25 | E70: Клещ-Э-Вак (Вакцина клещевого энцефалита культуральная очищенная концентрированная инактивированная сорбированная) | G70: in use | K70: 44712 | L70: 45988 | M70: есть | N70: https://grls.rosminzdrav.ru/Grls_View_v2.aspx?routingGuid=708a5616-61d3-4695-a4cb-2e78bcfca33b | O70: есть | P70: https://grls.rosminzdrav.ru/Grls_View_v2.aspx?routingGuid=245ee300-7d64-4000-ab8b-ded51091a060 | Q70: http://grls.rosminzdrav.ru/Grls_View_v2.aspx?routingGuid=fba2bb4d-f934-460c-b318-dad8525f8cd6&t= https://grls.rosminzdrav.ru/Grls_View_v2.aspx?routingGuid=80b33204-fa6e-445b-95d7-e8679b50536d https://grls.rosminzdrav.ru/Grls_View_v2.aspx?routingGuid=245ee300-7d64-4000-ab8b-ded51091a060 https://grls.rosminzdrav.ru/Grls_View_v2.aspx?routingGuid=4d82f537-a6f0-4a51-a9d5-4a215a7bf663
A71: 70 | B71: EnceVir_0_5 | C71: https://grls.rosminzdrav.ru/Grls_View_v2.aspx?routingGuid=9ea2867c-ced6-45dd-bf78-db44e14fd708 | D71: ЭнцеВир | E71: ЭнцеВир® Вакцина клещевого энцефалита культуральная очищенная концентрированная инактивированная сорбированная | G71: in use | K71: 44712 | L71: 45689 | M71: https://lk.regmed.ru/Register/GetPDFfromDAToken?Token=1f268f03-9b1c-4d7b-9599-88099428d00f | N71: https://grls.rosminzdrav.ru/Grls_View_v2.aspx?routingGuid=9ea2867c-ced6-45dd-bf78-db44e14fd708 | O71: https://lk.regmed.ru/Register/GetPDFfromDAToken?Token=e9c994dc-e4ae-4196-9018-5e51b545e040 | P71: https://grls.rosminzdrav.ru/Grls_View_v2.aspx?routingGuid=9702f069-1e9e-45d6-b8c9-dfa602227867 | Q71: http://grls.rosminzdrav.ru/Grls_View_v2.aspx?routingGuid=b015b822-3621-47b5-a28b-f3fcb1be3e29&t= https://grls.rosminzdrav.ru/Grls_View_v2.aspx?routingGuid=9702f069-1e9e-45d6-b8c9-dfa602227867 https://lk.regmed.ru/Register/GetPDFfromDA?ID=1498623391 https://lk.regmed.ru/Register/GetPDFfromDA?ID=1607784571 https://lk.regmed.ru/Register/GetPDFfromDA?ID=1607784561 https://grls.rosminzdrav.ru/Grls_View_v2.aspx?routingGuid=6d6ef607-d867-4bfe-bed0-e407bbed6085
A72: 71 | B72: EnceVir_Neo_kids | C72: https://grls.rosminzdrav.ru/Grls_View_v2.aspx?routingGuid=c2615365-07f8-416b-be71-d3e983cb1eb3 | D72: ЭнцеВир Нео детский | E72: ЭнцеВир® Нео детский (Вакцина клещевого энцефалита культуральная очищенная концентрированная инактивированная сорбированная) | G72: in use | K72: 44712 | L72: 45689 | M72: https://lk.regmed.ru/Register/GetPDFfromDAToken?Token=5a727ed4-b3cb-4f35-8c47-cdc269e90fed | N72: https://grls.rosminzdrav.ru/Grls_View_v2.aspx?routingGuid=c2615365-07f8-416b-be71-d3e983cb1eb3 | O72: https://lk.regmed.ru/Register/GetPDFfromDAToken?Token=14eebaad-2e05-4a98-9cb4-66fbe0d85f28 | P72: https://grls.rosminzdrav.ru/Grls_View_v2.aspx?routingGuid=69534cbd-1ff0-4210-8fa1-3ed6ab7564ac | Q72: http://grls.rosminzdrav.ru/Grls_View_v2.aspx?routingGuid=dfd84eba-8612-49fd-a32e-b83d21643d56&t= https://grls.rosminzdrav.ru/Grls_View_v2.aspx?routingGuid=69534cbd-1ff0-4210-8fa1-3ed6ab7564ac https://grls.rosminzdrav.ru/Grls_View_v2.aspx?routingGuid=0d453064-33d0-4577-bee5-ce36095de060 https://lk.regmed.ru/Register/GetPDFfromDA?ID=1448810831 https://lk.regmed.ru/Register/GetPDFfromDA?ID=1609919901 https://lk.regmed.ru/Register/GetPDFfromDA?ID=1609919911 https://grls.rosminzdrav.ru/Grls_View_v2.aspx?routingGuid=0d453064-33d0-4577-bee5-ce36095de060
A73: 72 | B73: TBE_Chumakov_lyo | C73: https://grls.rosminzdrav.ru/Grls_View_v2.aspx?routingGuid=69bf2722-aa8e-4374-a63b-c2e0fd5da7cd | D73: клещевого энцефалита (Чумакова) | E73: Вакцина клещевого энцефалита культуральная очищенная концентрированная инактивированная сухая | G73: in use | K73: 44712 | L73: 45750 | M73: https://lk.regmed.ru/Register/GetPDFfromDAToken?Token=2516e721-6e26-4b63-bc37-7163e862ca17 | N73: нет | O73: https://lk.regmed.ru/Register/GetPDFfromDAToken?Token=295e328d-3b30-4202-920f-eb247e014d71 | P73: https://grls.rosminzdrav.ru/Grls_View_v2.aspx?routingGuid=69bf2722-aa8e-4374-a63b-c2e0fd5da7cd | Q73: http://grls.rosminzdrav.ru/Grls_View_v2.aspx?routingGuid=0760d6c3 – 49ad-4187 – 9036-5a690d19e861&t= https://grls.rosminzdrav.ru/Grls_View_v2.aspx?routingGuid=eb87c775-0842-4be2-bfed-f822cdd39a3b https://grls.rosminzdrav.ru/Grls_View_v2.aspx?routingGuid=eb87c775-0842-4be2-bfed-f822cdd39a3b https://grls.rosminzdrav.ru/Grls_View_v2.aspx?routingGuid=48aa0e31-2ad9-4072-8261-154769e437ef
A74: 73 | B74: Varilrix | C74: https://grls.rosminzdrav.ru/Grls_View_v2.aspx?routingGuid=cf5179f1-d6f7-4a8b-9251-28065290b167 | D74: Варилрикс | E74: Варилрикс® (Вакцина против ветряной оспы живая аттенуированная) | G74: in use | H74: <p><ul><li>Плановая профилактика ветряной оспы, в том числе у лиц с повышенным риском тяжелого и осложненного течения ветряной оспы;</li> <li>плановая профилактика ветряной оспы у здорового окружения лиц, отнесенных к группам риска;</li> <li>экстренная профилактика ветряной оспы в течение 72&nbsp;часов с момента контакта с больным ветряной оспой.</li></ul></p> | I74: • Плановая профилактика ветряной оспы, в том числе у лиц с повышенным риском тяжелого и осложненного течения ветряной оспы; • плановая профилактика ветряной оспы у здорового окружения лиц, отнесенных к группам риска; • экстренная профилактика ветряной оспы в течение 72 часов с момента контакта с больным ветряной оспой. | K74: 44712 | L74: 45830 | M74: https://lk.regmed.ru/Register/GetPDFfromDAToken?Token=0cff0d2a-3085-4425-a8d9-40621446b45c | N74: https://grls.rosminzdrav.ru/Grls_View_v2.aspx?routingGuid=cf5179f1-d6f7-4a8b-9251-28065290b167 | O74: https://lk.regmed.ru/Register/GetPDFfromDAToken?Token=60bf52c4-1cf3-491f-95c7-1443f70310fe | P74: https://grls.rosminzdrav.ru/Grls_View_v2.aspx?routingGuid=a4eb2ebc-3815-42d3-b335-960b32db498b | Q74: http://grls.rosminzdrav.ru/Grls_View_v2.aspx?routingGuid=00437fd1-ba5c-4f78-8b06-e8e57dc373f6&t= https://grls.rosminzdrav.ru/Grls_View_v2.aspx?routingGuid=b8eef4c9-1095-483d-9adf-8986d099a434&t= https://grls.rosminzdrav.ru/Grls_View_v2.aspx?routingGuid=75f8e7c0-e43a-499b-8353-d460ba2db123 https://grls.rosminzdrav.ru/Grls_View_v2.aspx?routingGuid=d45dfeef-25f0-48a2-8913-bd6f2593fc47 https://grls.rosminzdrav.ru/Grls_View_v2.aspx?routingGuid=5fa2f190-cb0c-4092-828c-b1ecb66ac0c9 https://lk.regmed.ru/Register/GetPDFfromDA?ID=1590558311 https://lk.regmed.ru/Register/GetPDFfromDA?ID=1590558321 https://grls.rosminzdrav.ru/Grls_View_v2.aspx?routingGuid=009bdf5c-019d-4756-b09a-8f33d379a82c https://grls.rosminzdrav.ru/Grls_View_v2.aspx?routingGuid=a301ef1c-ce81-4f58-8f58-15c069f1bbdc
A75: 74 | B75: YF_Chumakov_lyo | C75: https://grls.rosminzdrav.ru/Grls_View_v2.aspx?routingGuid=a0eece39-1af9-4420-be24-7ff034677feb | D75: желтой лихорадки | E75: Вакцина желтой лихорадки живая сухая | G75: in use | H75: <p>Профилактика желтой лихорадки у детей с 9-месячного возраста и взрослых, направляющихся, проезжающих, или проживающих в регионах, в которых регистрируется заболеваемость желтой лихорадкой; у лиц, направляющихся в страну, въезд в которую требует наличия международного свидетельства о вакцинации; а также у лиц, работающих с живыми культурами возбудителя желтой лихорадки.</p> | I75: Профилактика желтой лихорадки у детей с 9-месячного возраста и взрослых, направляющихся, проезжающих, или проживающих в регионах, в которых регистрируется заболеваемость желтой лихорадкой; у лиц, направляющихся в страну, въезд в которую требует наличия международного свидетельства о вакцинации; а также у лиц, работающих с живыми культурами возбудителя желтой лихорадки. | K75: 44712 | L75: 44807 | M75: нет | N75: нет | O75: нет | P75: https://grls.rosminzdrav.ru/Grls_View_v2.aspx?routingGuid=a0eece39-1af9-4420-be24-7ff034677feb | Q75: http://grls.rosminzdrav.ru/Grls_View_v2.aspx?routingGuid=6f07494f-792b-4a67-a25b-2c4b1c6afbe0&t= https://grls.rosminzdrav.ru/Grls_View_v2.aspx?routingGuid=e67ca0ff-f237-4f88-98a3-1baf9ecd4cef https://grls.rosminzdrav.ru/Grls_View_v2.aspx?routingGuid=01ebf2bb-9158-470c-b8b8-d141a757ec46
A76: 75 | B76: tularemia_Microgen | C76: https://grls.rosminzdrav.ru/Grls_View_v2.aspx?routingGuid=1f496df2-7c22-4ddc-8980-da1023a88a35 | D76: туляремийная | E76: Вакцина туляремийная живая | F76: Микроген | G76: in use | H76: <p>Прививкам подлежит население, проживающее на энзоотичных по туляремии территориях, а также прибывшие на эти территории лица, выполняющие следующие работы: сельскохозяйственные, гидромелиоративные, строительные, другие работы по выемке и перемещению грунта, заготовительные, промысловые, геологические, изыскательные, экспедиционные, дератизационные и дезинсекционные, по лесозаготовке, расчистке и благоустройству леса, зон оздоровления и отдыха населения.</p> | I76: Прививкам подлежит население, проживающее на энзоотичных по туляремии территориях, а также прибывшие на эти территории лица, выполняющие следующие работы: сельскохозяйственные, гидромелиоративные, строительные, другие работы по выемке и перемещению грунта, заготовительные, промысловые, геологические, изыскательные, экспедиционные, дератизационные и дезинсекционные, по лесозаготовке, расчистке и благоустройству леса, зон оздоровления и отдыха населения. | K76: 44712 | L76: 45689 | M76: https://lk.regmed.ru/Register/GetPDFfromDAToken?Token=ec8dbc07-4048-4803-b294-939328173382 | N76: https://grls.rosminzdrav.ru/Grls_View_v2.aspx?routingGuid=1f496df2-7c22-4ddc-8980-da1023a88a35 | O76: https://lk.regmed.ru/Register/GetPDFfromDAToken?Token=57130d1c-3dc2-4727-bfc6-85009a2c893a | P76: https://grls.rosminzdrav.ru/Grls_View_v2.aspx?routingGuid=91324daa-ff4a-4519-8513-0f5d89103116 | Q76: http://grls.rosminzdrav.ru/Grls_View_v2.aspx?routingGuid=36bc288f-5bfc-4c4c-a748-b68aefafeba1&t= https://grls.rosminzdrav.ru/Grls_View_v2.aspx?routingGuid=087c5f71-676f-4a3d-8dbd-c6c98cd0f0a5 https://lk.regmed.ru/Register/GetPDFfromDA?ID=1626767261 https://lk.regmed.ru/Register/GetPDFfromDA?ID=1626767251
A77: 76 | B77: plague_molecular_lyo_RPN | C77: https://grls.rosminzdrav.ru/Grls_View_v2.aspx?routingGuid=d4e26cea-321e-489e-90b0-10674ba3eaf9 | D77: чумная микроинкапсулированная | E77: Вакцина чумная молекулярная микроинкапсулированная (ВЧММ) | G77: in use | K77: 44712 | L77: 44803 | M77: нет | N77: нет | O77: нет | P77: https://grls.rosminzdrav.ru/Grls_View_v2.aspx?routingGuid=d4e26cea-321e-489e-90b0-10674ba3eaf9 | Q77: http://grls.rosminzdrav.ru/Grls_View_v2.aspx?routingGuid=0358c243-78a1-4df6-8df2-bcef660d17f3&t= https://grls.rosminzdrav.ru/Grls_View_v2.aspx?routingGuid=2bfc32c6-d422-4615-a249-925c37c9bba7
A78: 77 | B78: plague_live_lyo_48_NII_Minoborony | C78: https://grls.rosminzdrav.ru/Grls_View_v2.aspx?routingGuid=0962362a-d8cb-4c53-b4f2-43cc75eea35f | D78: чумная (лиофилизат, 48 НИИ) | E78: Вакцина чумная живая | G78: in use | K78: 44712 | L78: 44803 | M78: нет | N78: нет | O78: нет | P78: https://grls.rosminzdrav.ru/Grls_View_v2.aspx?routingGuid=0962362a-d8cb-4c53-b4f2-43cc75eea35f
A79: 78 | B79: plague_live_tablets_48_NII_Minoborony | C79: https://grls.rosminzdrav.ru/Grls_View_v2.aspx?routingGuid=37890f2a-f963 – 4c4a-a9fc-d7738025bf49 | D79: чумная (таблетки, 48 НИИ) | E79: Вакцина чумная живая | G79: in use | K79: 44712 | L79: 44803 | M79: нет | N79: нет | O79: нет | P79: https://grls.rosminzdrav.ru/Grls_View_v2.aspx?routingGuid=37890f2a-f963-4c4a-a9fc-d7738025bf49
A80: 79 | B80: plague_live_lyo_RPN | C80: https://grls.rosminzdrav.ru/Grls_View_v2.aspx?routingGuid=a55e6d43-fef5-4c3d-af16-a15f6b065685 | D80: чумная (лиофилизат, НИИ РПН) | E80: Вакцина чумная живая | G80: in use | K80: 44712 | L80: 44803 | M80: нет | N80: нет | O80: нет | P80: https://grls.rosminzdrav.ru/Grls_View_v2.aspx?routingGuid=a55e6d43-fef5-4c3d-af16-a15f6b065685 | Q80: http://grls.rosminzdrav.ru/Grls_View_v2.aspx?routingGuid=37474124-8d9f-4196-99ab-6a0bd063d777&t=
A81: 80 | B81: brucellosis_therapeutic_48_NII_Minoborony | C81: https://grls.rosminzdrav.ru/Grls_View_v2.aspx?routingGuid=7da2f9f3 – 53a6-4cbe-9eae-65a3d0bed21b | D81: бруцеллезная (лечебная) | E81: Вакцина бруцеллезная инактивированная лечебная | G81: in use | K81: 44712 | L81: 44803 | M81: нет | N81: нет | O81: нет | P81: https://grls.rosminzdrav.ru/Grls_View_v2.aspx?routingGuid=7da2f9f3-53a6-4cbe-9eae-65a3d0bed21b
A82: 81 | B82: brucellosis_prophylactic_Microgen | C82: https://grls.rosminzdrav.ru/Grls_View_v2.aspx?routingGuid=41231e71-613c-4a24-ab98-462b5d95f938 | D82: бруцеллезная (профилактическая) | E82: Вакцина бруцеллезная живая | G82: in use | K82: 44712 | L82: 45798 | M82: https://lk.regmed.ru/Register/GetPDFfromDAToken?Token=bbb42574-93e7-4e33-91ef-666773d1f867 | N82: нет | O82: https://lk.regmed.ru/Register/GetPDFfromDAToken?Token=2ee8485e-7a43-4e4b-89e5-47703a28d58a | P82: https://grls.rosminzdrav.ru/Grls_View_v2.aspx?routingGuid=41231e71-613c-4a24-ab98-462b5d95f938 | Q82: http://grls.rosminzdrav.ru/Grls_View_v2.aspx?routingGuid=2116d9c4-05b6-4d24-80cf-d438d2ed4e0e&t= https://grls.rosminzdrav.ru/Grls_View_v2.aspx?routingGuid=af63196a-a228-460c-8e32-0a3e6e1838ad https://grls.rosminzdrav.ru/Grls_View_v2.aspx?routingGuid=b5609cfe-f7fd-455b-b30e-6f795aa4a55f
A83: 82 | B83: anthrax_live_48_NII_Minoborony | C83: https://grls.rosminzdrav.ru/Grls_View_v2.aspx?routingGuid=d7622abd-8b68-42cc-aeb2-08d107689bbc | D83: сибиреязвенная | E83: Вакцина сибиреязвенная живая | G83: in use | H83: <p>Подлежат обязательной вакцинации: <ul><li>Лица, работающие с живыми культурами возбудителя сибирской язвы, с зараженными лабораторными животными или производящие исследования материалов, зараженных или подозрительным на инфицирование возбудителем сибирской язвы.</li> <li>Лица, профессионально занятые содержанием скота, а также производящие убой скота, занятые заготовкой, сбором, хранением, транспортировкой, переработкой и реализацией сырья животного происхождения.</li> <li>Лица, выполняющие сельскохозяйственные, гидромелиоративные, строительные, по выемке и перемещению грунта, заготовительные, промысловые, геологические, изыскательские, экспедиционные на энзоотичных по сибирской язве территориях.</ul></p> | I83: Подлежат обязательной вакцинации: • Лица, работающие с живыми культурами возбудителя сибирской язвы, с зараженными лабораторными животными или производящие исследования материалов, зараженных или подозрительным на инфицирование возбудителем сибирской язвы. • Лица, профессионально занятые содержанием скота, а также производящие убой скота, занятые заготовкой, сбором, хранением, транспортировкой, переработкой и реализацией сырья животного происхождения. • Лица, выполняющие сельскохозяйственные, гидромелиоративные, строительные, по выемке и перемещению грунта, заготовительные, промысловые, геологические, изыскательские, экспедиционные на энзоотичных по сибирской язве территориях. | K83: 44712 | L83: 44807 | M83: нет | N83: нет | O83: нет | P83: https://grls.rosminzdrav.ru/Grls_View_v2.aspx?routingGuid=d7622abd-8b68-42cc-aeb2-08d107689bbc
A84: 83 | B84: anthrax_combined_48_NII_Minoborony | C84: https://grls.rosminzdrav.ru/Grls_View_v2.aspx?routingGuid=45ea6a47-5e12-4580-b8ed-b03d229557e4 | D84: сибиреязвенная комбинированная | E84: Вакцина сибиреязвенная комбинированная | G84: in use | H84: <p>Плановым прививкам подлежат: <ol><li>Лица, работающие с живыми культурами возбудителя сибирской язвы, с зараженными лабораторными животными или производящие исследования материалов, зараженных возбудителем сибирской язвы.</li> <li>Лица, производящие убой скота, занятые заготовкой, сбором, хранением, транспортировкой, переработкой и реализацией сырья животного происхождения.</li> <li>Лица, выполняющие следующие работы на энзоотичных по сибирской язве территориях: <ul><li>Обслуживание общественного скота.</li> <li>Сельскохозяйственные, агро- и гидромелиоративные, строительные и другие работы, связанные с выемкой и перемещением грунта.</li> <li>Заготовительные, промысловые, геологические, изыскательные, экспедиционные.</li></ul></li></ol></p> | I84: Плановым прививкам подлежат: 1. Лица, работающие с живыми культурами возбудителя сибирской язвы, с зараженными лабораторными животными или производящие исследования материалов, зараженных возбудителем сибирской язвы. 2. Лица, производящие убой скота, занятые заготовкой, сбором, хранением, транспортировкой, переработкой и реализацией сырья животного происхождения. 3. Лица, выполняющие следующие работы на энзоотичных по сибирской язве территориях: • Обслуживание общественного скота. • Сельскохозяйственные, агро- и гидромелиоративные, строительные и другие работы, связанные с выемкой и перемещением грунта. • Заготовительные, промысловые, геологические, изыскательные, экспедиционные. | K84: 44712 | L84: 44807 | M84: нет | N84: нет | O84: нет | P84: https://grls.rosminzdrav.ru/Grls_View_v2.aspx?routingGuid=45ea6a47-5e12-4580-b8ed-b03d229557e4
A85: 84 | B85: Rabipur | C85: https://grls.rosminzdrav.ru/Grls_View_v2.aspx?routingGuid=b5f5bf28-a50c-46a3-8777-66ad5b7b6870 | D85: Рабипур | E85: Рабипур® (Вакцина антирабическая культуральная очищенная инактивированная) | F85: Кайрон Беринг Вакцинс | G85: not in use | H85: <p>Иммунизация, проводимая в плановом порядке, рекомендована лицам из групп риска инфицирования вирусом бешенства: лицам, работающим с «уличным» вирусом бешенства, ветеринарным работникам, егерям, охотникам, лесникам, лицам, выполняющим работы по отлову и содержанию животных, работникам скотобоен и лабораторий, а также при планировании поездок в эндемичные по бешенству регионы.</p> | I85: Иммунизация, проводимая в плановом порядке, рекомендована лицам из групп риска инфицирования вирусом бешенства: лицам, работающим с «уличным» вирусом бешенства, ветеринарным работникам, егерям, охотникам, лесникам, лицам, выполняющим работы по отлову и содержанию животных, работникам скотобоен и лабораторий, а также при планировании поездок в эндемичные по бешенству регионы. | K85: 44712 | L85: 44807 | M85: нет | N85: нет | O85: нет | P85: https://grls.rosminzdrav.ru/Grls_View_v2.aspx?routingGuid=b5f5bf28-a50c-46a3-8777-66ad5b7b6870 | Q85: http://grls.rosminzdrav.ru/Grls_View_v2.aspx?routingGuid=0f830a1f-1669-498e-9461-97b3b29333bd&t=
A86: 85 | B86: leptospirosis_Rostov_NII | C86: https://grls.rosminzdrav.ru/Grls_View_v2.aspx?routingGuid=5ef363e0-7cee-48c5-ad35-c352b3fb519e | D86: лептоспирозная | E86: Вакцина лептоспирозная концентрированная инактивированная жидкая | G86: in use | H86: <p>Прививкам подлежат лица, выполняющие следующие работы: <ul><li>По заготовке, хранению, обработке сырья и продуктов животноводства, полученных из хозяйств, расположенных на энзоотических по лептоспирозу территориях.</li> <li>По убою скота, больного лептоспирозом, заготовке и переработке мяса и мясопродуктов, полученных от больных лептоспирозом животных.</li> <li>По отлову и содержанию безнадзорных животных.</li> <li>Работающие с живыми культурами возбудителей лептоспироза.</li></ul></p> | I86: Прививкам подлежат лица, выполняющие следующие работы: • По заготовке, хранению, обработке сырья и продуктов животноводства, полученных из хозяйств, расположенных на энзоотических по лептоспирозу территориях. • По убою скота, больного лептоспирозом, заготовке и переработке мяса и мясопродуктов, полученных от больных лептоспирозом животных. • По отлову и содержанию безнадзорных животных. • Работающие с живыми культурами возбудителей лептоспироза. | K86: 44712 | L86: 44808 | M86: нет | N86: нет | O86: нет | P86: https://grls.rosminzdrav.ru/Grls_View_v2.aspx?routingGuid=5ef363e0-7cee-48c5-ad35-c352b3fb519e | Q86: https://grls.rosminzdrav.ru/Grls_View_v2.aspx?routingGuid=8ac9b405-1c58-4a70-bda8-033c7966fd4d
A87: 86 | B87: Q_fever_M_44_Microgen | C87: https://grls.rosminzdrav.ru/Grls_View_v2.aspx?routingGuid=62187342-c256-42fb-8419-8f916294db89 | D87: Ку-лихорадки | E87: Вакцина Ку-лихорадки М-44 живая (Вакцина Ку-лихорадки М-44) | F87: Микроген | G87: in use | K87: 44712 | L87: 45716 | M87: https://lk.regmed.ru/Register/GetPDFfromDAToken?Token=6d636ac5-7688-499c-b16b-bff4c5285c1a | N87: нет | O87: https://lk.regmed.ru/Register/GetPDFfromDAToken?Token=c2b7dbca-7236-4aa8-be60-8c042331a880 | P87: https://grls.rosminzdrav.ru/Grls_View_v2.aspx?routingGuid=62187342-c256-42fb-8419-8f916294db89 | Q87: http://grls.rosminzdrav.ru/Grls_View_v2.aspx?routingGuid=b8526b31-c6bb-4bc1-966f-5c85550cee41&t= https://grls.rosminzdrav.ru/Grls_View_v2.aspx?routingGuid=a8444b14-22c7-466e-90e0-d8ab9e9942b9 http://grls.rosminzdrav.ru/Grls_View_v2.aspx?routingGuid=b8526b31-c6bb-4bc1-966f-5c85550cee41&t= https://grls.rosminzdrav.ru/Grls_View_v2.aspx?routingGuid=9d6bca2e-ec70-4ccb-bc18-aae81abfc820 https://lk.regmed.ru/Register/GetPDFfromDA?ID=1448785121 https://lk.regmed.ru/Register/GetPDFfromDA?ID=1448785111
A88: 87 | B88: cholera_NII_Microb | C88: https://grls.rosminzdrav.ru/Grls_View_v2.aspx?routingGuid=c27afa22-136b-4a31-96c0-fa7b3d7357f4 | D88: холерная | E88: Вакцина холерная бивалентная химическая | G88: in use | K88: 44712 | L88: 44903 | M88: нет | N88: нет | O88: нет | P88: https://grls.rosminzdrav.ru/Grls_View_v2.aspx?routingGuid=c27afa22-136b-4a31-96c0-fa7b3d7357f4 | Q88: http://grls.rosminzdrav.ru/Grls_View_v2.aspx?routingGuid=2bad86b1-6c60-4df8-9f0b-e3bbc2d0aed4&t= https://grls.rosminzdrav.ru/Grls_View_v2.aspx?routingGuid=c27afa22-136b-4a31-96c0-fa7b3d7357f4 https://grls.rosminzdrav.ru/Grls_View_v2.aspx?routingGuid=23a4f1ff-bfe0-46fb-b9cc-800092325aaf
A89: 88 | B89: Vianvac | C89: https://grls.rosminzdrav.ru/Grls_View_v2.aspx?routingGuid=fdfbbbec-8dee-4615-b7eb-26968c926dbf | D89: Вианвак | E89: ВИАНВАК® (Вакцина брюшнотифозная Ви-полисахаридная) | G89: in use | K89: 44712 | L89: 46130 | M89: есть | N89: нет | O89: нет | P89: https://grls.rosminzdrav.ru/Grls_View_v2.aspx?routingGuid=fdfbbbec-8dee-4615-b7eb-26968c926dbf | Q89: http://grls.rosminzdrav.ru/Grls_View_v2.aspx?routingGuid=3e6672e6-b148-4ea7-a3ec-d95072a55562&t= https://grls.rosminzdrav.ru/Grls_View_v2.aspx?routingGuid=51ab849d-8edb-4ef3-819a-2a9807b63a14 https://grls.rosminzdrav.ru/Grls_View_v2.aspx?routingGuid=76c87b45-b6ce-477c-97ea-019809d8e9e4
A90: 89 | B90: Typhivac | C90: https://grls.rosminzdrav.ru/Grls_View_v2.aspx?routingGuid=0544ac02-95bc-4db8-8c03-e56ad7882e51 | D90: Тифивак | E90: Тифивак (Вакцина брюшнотифозная спиртовая) | G90: not in use | K90: 44712 | L90: 45139 | M90: нет | N90: нет | O90: нет | P90: https://grls.rosminzdrav.ru/Grls_View_v2.aspx?routingGuid=0544ac02-95bc-4db8-8c03-e56ad7882e51 | Q90: https://grls.rosminzdrav.ru/Grls_View_v2.aspx?routingGuid=e9aa0be8-7a01-4d82-9e8d-6cce064a2b65&t=
A91: 90 | B91: Shigellvac | C91: https://grls.rosminzdrav.ru/Grls_View_v2.aspx?routingGuid=45faa55d-d1ab-4179-9b8d-7b152e30bfec | D91: Шигеллвак | E91: Шигеллвак (Вакцина дизентерийная против шигелл Зонне полисахаридная) | G91: in use | K91: 44712 | L91: 46130 | M91: есть | N91: нет | O91: нет | P91: https://grls.rosminzdrav.ru/Grls_View_v2.aspx?routingGuid=45faa55d-d1ab-4179-9b8d-7b152e30bfec | Q91: https://grls.rosminzdrav.ru/Grls_View_v2.aspx?routingGuid=daa1567c-260a-4baf-bc15-9532637374d6&t= https://grls.rosminzdrav.ru/Grls_View_v2.aspx?routingGuid=a4171a20-3e03-47a3-ab1f-36c63fe1187c https://grls.rosminzdrav.ru/Grls_View_v2.aspx?routingGuid=320c5d6b-28a9-4d00-953d-d31a51ca500e https://grls.rosminzdrav.ru/Grls_View_v2.aspx?routingGuid=9e871f71-9cba-4dd8-a32e-7bb5635a876e
A92: 91 | B92: CoviVac | C92: https://grls.rosminzdrav.ru/Grls_View_v2.aspx?routingGuid=dd8bb917-0073-4bc0-809b-587e89c9a8b0 | D92: КовиВак | E92: КовиВак (Вакцина коронавирусная инактивированная цельновирионная концентрированная очищенная) | G92: in use | K92: 44712 | L92: 44903 | M92: нет | N92: нет | O92: нет | P92: нет | Q92: http://grls.rosminzdrav.ru/Grls_View_v2.aspx?routingGuid=71035dbe-6178-42c0-8d36-aa54e546a65b&t= https://grls.rosminzdrav.ru/Grls_View_v2.aspx?routingGuid=ea3395fe-7012-45d7 – 94c6-ef826206f61f https://grls.rosminzdrav.ru/Grls_View_v2.aspx?routingGuid=956ad8ef-fb1c-4652-bec5-137afe7169fa https://grls.rosminzdrav.ru/Grls_View_v2.aspx?routingGuid=b8dfa2a8-c740-4d19-aeba-a686a18348a3
A93: 92 | B93: Sputnik_light | C93: https://grls.rosminzdrav.ru/Grls_View_v2.aspx?routingGuid=e231ed27-8f9b-48e2-9c90-6d4b5edb2693 | D93: Спутник Лайт | E93: Спутник Лайт Векторная вакцина для профилактики коронавирусной инфекции, вызываемой вирусом SARS-CoV-2 | G93: in use | K93: 44712 | L93: 45830 | M93: https://lk.regmed.ru/Register/GetPDFfromDAToken?Token=50f49d83-55c5-4c3f-95fd-eb87ceb7bbc1 | N93: нет | O93: https://lk.regmed.ru/Register/GetPDFfromDAToken?Token=ce9023ae-8f18-40b4-87c3-b37e8c580d72 | P93: https://grls.rosminzdrav.ru/Grls_View_v2.aspx?routingGuid=e231ed27-8f9b-48e2-9c90-6d4b5edb2693 | Q93: https://grls.rosminzdrav.ru/Grls_View_v2.aspx?routingGuid=f8533219-aa8e-4abf-85af-03f5cf67b7de&t= https://grls.rosminzdrav.ru/Grls_View_v2.aspx?routingGuid=b1a6c581-3c52-4bcd-89e5-9ff444a560ef https://grls.rosminzdrav.ru/Grls_View_v2.aspx?routingGuid=6ec3a403-0ce9-49f9-a55b-fffb93a25310 https://grls.rosminzdrav.ru/Grls_View_v2.aspx?routingGuid=bed61280-103d-4953-bd62-a42f498f24f0
A94: 93 | B94: Sputnik_M | C94: https://grls.rosminzdrav.ru/Grls_View_v2.aspx?routingGuid=3f429426-417a-42af-8212-54d0f9b4f48a | D94: Спутник М | E94: Гам-КОВИД-Вак-М Комбинированная векторная вакцина для профилактики коронавирусной инфекции, вызываемой вирусом SARS-CoV-2 | G94: in use | K94: 44712 | L94: 45715 | M94: нет | N94: нет | O94: нет | P94: https://grls.rosminzdrav.ru/Grls_View_v2.aspx?routingGuid=3f429426-417a-42af-8212-54d0f9b4f48a | Q94: https://grls.rosminzdrav.ru/Grls_View_v2.aspx?routingGuid=8c0994ff-cbcc-429d-b150-e0cf4404a1ac&t= https://grls.rosminzdrav.ru/Grls_View_v2.aspx?routingGuid=18926338-7c38-4ccf-b394-4d556b40c602 https://grls.rosminzdrav.ru/Grls_View_v2.aspx?routingGuid=16ad293f-7b40-4643-b107-f5c64026a321
A95: 94 | B95: Convacel | C95: https://grls.rosminzdrav.ru/Grls_View_v2.aspx?routingGuid=f6747520-46db-401c-ac99-b006cfc89abf | D95: Конвасэл | E95: Конвасэл® Вакцина субъединичная рекомбинантная для профилактики коронавирусной инфекции, вызываемой вирусом SARS-CoV-2 | G95: in use | K95: 44712 | L95: 46053 | M95: есть | N95: https://grls.rosminzdrav.ru/Grls_View_v2.aspx?routingGuid=f6747520-46db-401c-ac99-b006cfc89abf | O95: есть | P95: https://grls.rosminzdrav.ru/Grls_View_v2.aspx?routingGuid=78dc381a-ed0b-4ebc-a939-78b672f706f0 | Q95: https://grls.rosminzdrav.ru/Grls_View_v2.aspx?routingGuid=6bd9d7fe-4357-44a0-b8c4-f2d9cbaf6176&t= https://grls.rosminzdrav.ru/Grls_View_v2.aspx?routingGuid=11d8e5d1-2320-46ec-a4aa-c2e63ff45751 https://grls.rosminzdrav.ru/Grls_View_v2.aspx?routingGuid=5d707d03-dc3f-4f67-8060-ed8d0c71bd7a https://grls.rosminzdrav.ru/Grls_View_v2.aspx?routingGuid=8cd3c3b7-1285-4dfb-abc0-2ec53d022381 https://grls.rosminzdrav.ru/Grls_View_v2.aspx?routingGuid=78dc381a-ed0b-4ebc-a939-78b672f706f0
A96: 95 | B96: Aurora | C96: https://grls.rosminzdrav.ru/Grls_View_v2.aspx?routingGuid=e674fd41-ea9d-4a0b-9f4b-7f728da76cf0 | D96: АВРОРА-КоВ | E96: АВРОРА-КоВ Вакцина на основе пептидных антигенов для профилактики COVID-19 | G96: in use | K96: 44712 | L96: 44904 | M96: нет | N96: нет | O96: нет | P96: https://grls.rosminzdrav.ru/Grls_View_v2.aspx?routingGuid=def42703-fcd2-477f-98fe-ced5a9ac0ccf | Q96: https://grls.rosminzdrav.ru/Grls_View_v2.aspx?routingGuid=c80b2c6f-35a1-4d85-91e9-e6c699e85ddc&t= https://grls.rosminzdrav.ru/Grls_View_v2.aspx?routingGuid=73f9bb84-4526-443a-89d1-c2a821aab4b7 https://grls.rosminzdrav.ru/Grls_View_v2.aspx?routingGuid=b7a2c8d7-8717-4e34-b251-8162b605cbeb
A97: 96 | B97: Rota_V_Aid | C97: https://grls.rosminzdrav.ru/Grls_View_v2.aspx?routingGuid=3e6a77c5-d2ae-4f34-b737-7803e65abe65 | D97: Рота-V-Эйд | E97: Рота-V-Эйд® | F97: Серум Инститьют | G97: in use | K97: 44712 | L97: 45689 | M97: https://lk.regmed.ru/Register/GetPDFfromDAToken?Token=0f30d250-b996-4595-b47d-8966e076423c | N97: https://grls.rosminzdrav.ru/Grls_View_v2.aspx?routingGuid=3e6a77c5-d2ae-4f34-b737-7803e65abe65 | O97: https://lk.regmed.ru/Register/GetPDFfromDAToken?Token=527e32cb-7614-4bf0-9239-1a2231d3c4c5 | P97: https://grls.rosminzdrav.ru/Grls_View_v2.aspx?routingGuid=bd0099be-c683-4345-a633-3de57fe08bab | Q97: https://grls.rosminzdrav.ru/Grls_View_v2.aspx?routingGuid=e0e0ca2f-5129-4f15-8c99-b6e061a95537&t= https://grls.rosminzdrav.ru/Grls_View_v2.aspx?routingGuid=1fb95f51-b428-42f2-99da-ea96433f3370 https://grls.rosminzdrav.ru/Grls_View_v2.aspx?routingGuid=50003822-e06b-471c-8291-86a8f5287124 https://grls.rosminzdrav.ru/Grls_View_v2.aspx?routingGuid=bd0099be-c683-4345-a633-3de57fe08bab https://grls.rosminzdrav.ru/Grls_View_v2.aspx?routingGuid=24229572-2447-4089-8215-5b93b8e4c976 https://lk.regmed.ru/Register/GetPDFfromDA?ID=1641359721 https://lk.regmed.ru/Register/GetPDFfromDA?ID=1641359711
A98: 97 | B98: Hib_Rostov | C98: https://grls.rosminzdrav.ru/Grls_View_v2.aspx?routingGuid=8790c6b6-9ab5-4df0-8084-075d18ec2595 | D98: гемофильная (ростовский НИИ) | E98: Вакцина гемофильная тип b конъюгированная | F98: ФБУН "Ростовский научно-исследовательский институт микробиологии и паразитологии" | G98: in use | K98: 44712 | L98: 44904 | M98: нет | N98: нет | O98: нет | P98: https://grls.rosminzdrav.ru/Grls_View_v2.aspx?routingGuid=8790c6b6-9ab5-4df0-8084-075d18ec2595
A99: 98 | B99: HepB_Combiotech_1_0 | C99: https://grls.rosminzdrav.ru/Grls_View_v2.aspx?routingGuid=0cc60fe9-635e-4134-80d2-59a7787e33fb | D99: гепатита B (Комбиотех) взрослая | E99: Вакцина гепатита В рекомбинантная дрожжевая | F99: Комбиотех | G99: in use | H99: <p>Препарат выпускается в виде «взрослой» и «детской» вакцины с консервантом и без консерванта.</p> | I99: Препарат выпускается в виде «взрослой» и «детской» вакцины с консервантом и без консерванта. | K99: 44712 | L99: 46130 | M99: есть | N99: нет | O99: нет | P99: https://grls.rosminzdrav.ru/Grls_View_v2.aspx?routingGuid=0cc60fe9-635e-4134-80d2-59a7787e33fb | Q99: https://grls.rosminzdrav.ru/Grls_View_v2.aspx?routingGuid=3059b036-5e60-42ed-b26c-7eb6d5d06406
A100: 99 | B100: Regevac_1_0 | C100: https://grls.rosminzdrav.ru/Grls_View_v2.aspx?routingGuid=ec6e3b51-e76b-4abf-99cf-7c02bab06091 | D100: Регевак взрослый | E100: Регевак® В (Вакцина против гепатита В, рекомбинантная дрожжевая жидкая) | G100: in use | K100: 44712 | L100: 45988 | M100: есть | N100: нет | O100: есть | P100: https://grls.rosminzdrav.ru/Grls_View_v2.aspx?routingGuid=ec6e3b51-e76b-4abf-99cf-7c02bab06091 | Q100: http://grls.rosminzdrav.ru/Grls_View_v2.aspx?routingGuid=accc9e6e-21d3 – 4b43-8eb4-65d0bf807a6a&t= https://grls.rosminzdrav.ru/Grls_View_v2.aspx?routingGuid=7bf6a88b-0ee8-48d7-afe3-7585739a9aaf https://lk.regmed.ru/Register/GetPDFfromDA?ID=1520916731 https://lk.regmed.ru/Register/GetPDFfromDA?ID=1520916701 https://grls.rosminzdrav.ru/Grls_View_v2.aspx?routingGuid=14a2c7d0-b44c-4e6b-b921-dde554eca629 https://grls.rosminzdrav.ru/Grls_View_v2.aspx?routingGuid=7b2a598f-1146-475f-9678-bf4c14e2523a
...

Sheet ingredients_text
A1: vaccine_id | B1: code_name | C1: ingredients_text_w/o_html | D1: ingredients_text_html | E1: ingredients_date | F1: ingredients_view_number | G1: ingredients_version | H1: ingredients_version_link | I1: creation_date | J1: update_date | K1: comment
A2: 1 | B2: =VLOOKUP(A2,[1]vaccines!A:B,2) -> BCG_Microgen | C2: 1 доза (0,1 мл) содержит: Действующее вещество: микробные клетки Mycobacterium bovis BCG-I — 0,05 мг*. Полный перечень вспомогательных веществ приведен в разделе 6.1. Препарат не содержит консервантов и антибиотиков. Выпускается в комплекте с растворителем — натрия хлорид растворитель для приготовления лекарственных форм для инъекций 0,9 %. * расчетное содержание в 1 дозе. 6.1. Перечень вспомогательных веществ Лиофилизат: • Натрия глутамата моногидрат. | D2: <p>1&nbsp;доза (0,1&nbsp;мл) содержит:<br><br> Действующее вещество: микробные клетки <i>Mycobacterium bovis BCG-I</i> — 0,05&nbsp;мг*.<br> Полный перечень вспомогательных веществ приведен в разделе&nbsp;6.1.<br> Препарат не содержит консервантов и антибиотиков.<br> Выпускается в комплекте с растворителем — натрия хлорид растворитель для приготовления лекарственных форм для инъекций 0,9&nbsp;%.<br><br> *&nbsp;расчетное содержание в 1&nbsp;дозе.<br><br> <b>6.1.&nbsp;Перечень вспомогательных веществ</b><br><br> <i>Лиофилизат:</i> <ul><li>Натрия глутамата моногидрат.</li></ul></p> | E2: 45461 | H2: https://lk.regmed.ru/Register/GetPDFfromDA?ID=1597322951 | I2: 45105 | J2: 45517 | K2: добавлено Елена Савинова
A3: 2 | B3: =VLOOKUP(A3,[1]vaccines!A:B,2) -> BCG_M_Microgen | C3: 1 доза (0,1 мл) содержит: Действующее вещество: микробные клетки Mycobacterium bovis BCG-I — 0,025 мг*. Полный перечень вспомогательных веществ приведен в разделе 6.1. Препарат не содержит консервантов и антибиотиков. Выпускается в комплекте с растворителем — натрия хлорид растворитель для приготовления лекарственных форм для инъекций 0,9 %. * расчетное содержание в 1 дозе. 6.1. Перечень вспомогательных веществ • Натрия глутамата моногидрат. | D3: <p>1&nbsp;доза (0,1&nbsp;мл) содержит:<br><br> Действующее вещество: микробные клетки <i>Mycobacterium bovis BCG-I</i> — 0,025&nbsp;мг*.<br> Полный перечень вспомогательных веществ приведен в разделе&nbsp;6.1.<br> Препарат не содержит консервантов и антибиотиков.<br> Выпускается в комплекте с растворителем — натрия хлорид растворитель для приготовления лекарственных форм для инъекций 0,9&nbsp;%.<br><br> *&nbsp;расчетное содержание в 1&nbsp;дозе.<br><br> <b>6.1.&nbsp;Перечень вспомогательных веществ</b> <ul><li>Натрия глутамата моногидрат.</li></ul></p> | E3: 45461 | H3: https://lk.regmed.ru/Register/GetPDFfromDA?ID=1597318981 | I3: 45107 | J3: 45517 | K3: проверено Елена Савинова
A4: 3 | B4: =VLOOKUP(A4,[1]vaccines!A:B,2) -> BCG_Gamaleya | C4: В одной дозе содержится: • 0,05 мг Микобактерий вакцинного штамма Mycobacterium bovis, субштамм BCG-1 (Russia). Перечень вспомогательных веществ: • Стабилизатор — натрия глутамат моногидрат — не более 0,3 мг; • Раствор натрия хлорида 0,9 % для инъекций — до 0,1 мл. | D4: <p>В одной дозе содержится: <ul><li>0,05&nbsp;мг Микобактерий вакцинного штамма <i>Mycobacterium bovis</i>, субштамм BCG-1 (Russia).</li></ul> Перечень вспомогательных веществ: <ul><li>Стабилизатор — натрия глутамат моногидрат — не более 0,3&nbsp;мг;</li> <li>Раствор натрия хлорида 0,9&nbsp;% для инъекций — до 0,1&nbsp;мл.</li></ul></p> | E4: 45769 | F4: 1 | G4: 0 | H4: https://grls.rosminzdrav.ru/InstrImg/2025/05/19/1517351/3bec22d2-65bc-4a94-9482-413901e57760.pdf | I4: 45108 | J4: 45801
A5: 4 | B5: =VLOOKUP(A5,[1]vaccines!A:B,2) -> BCG_M_Gamaleya | C5: В одной дозе содержится: • 0,025 мг Микобактерий вакцинного штамма Mycobacterium bovis, субштамм BCG-1 (Russia). Перечень вспомогательных веществ: • Стабилизатор — натрия глутамат моногидрат — не более 0,15 мг; • Раствор натрия хлорида 0,9 % для инъекций — до 0,1 мл. | D5: <p>В одной дозе содержится: <ul><li>0,025&nbsp;мг Микобактерий вакцинного штамма Mycobacterium bovis, субштамм BCG-1 (Russia).</li></ul> Перечень вспомогательных веществ: <ul><li>Стабилизатор — натрия глутамат моногидрат — не более 0,15&nbsp;мг;</li> <li>Раствор натрия хлорида 0,9&nbsp;% для инъекций — до 0,1&nbsp;мл.</li></ul></p> | E5: 45771 | F5: 1 | G5: 0 | H5: https://grls.rosminzdrav.ru/InstrImg/2025/06/02/1517794/d7367d9e-e745-46a7-b297-5a093bf3738a.pdf | I5: =I4 -> 45108 | J5: 45818
A6: 5 | B6: =VLOOKUP(A6,[1]vaccines!A:B,2) -> Infanrix | C6: 1 доза (0,5 мл) вакцины содержит: Действующие вещества: • анатоксин дифтерийный¹·³ — не менее 30 МЕ; • анатоксин столбнячный²·³ — не менее 40 МЕ; • анатоксин коклюшный (АК)³ — 25 мкг; • гемагглютинин филаментозный (ФГА)³ — 25 мкг; • пертактин (ПРН)³ (белок наружной мембраны 69 кДа) — 8 мкг. ¹ Содержание дифтерийного анатоксина 25 Lf (флоккулирующих единиц). ² Содержание столбнячного анатоксина 10 Lf (флоккулирующих единиц). ³ Адсорбированный на алюминия гидроксиде (0,5 мг в пересчете на алюминий). Перечень вспомогательных веществ: • Натрия хлорид. • Вода для инъекций. | D6: <p>1&nbsp;доза (0,5&nbsp;мл) вакцины содержит:<br><br> <i>Действующие вещества:</i> <ul><li>анатоксин дифтерийный¹<sup>,</sup>³ — не менее 30&nbsp;МЕ;</li> <li>анатоксин столбнячный²<sup>,</sup>³ — не менее 40&nbsp;МЕ;</li> <li>анатоксин коклюшный (АК)³ — 25&nbsp;мкг;</li> <li>гемагглютинин филаментозный (ФГА)³ — 25&nbsp;мкг;</li> <li>пертактин (ПРН)³ (белок наружной мембраны 69&nbsp;кДа) — 8&nbsp;мкг.</li></ul> ¹&nbsp;Содержание дифтерийного анатоксина 25&nbsp;Lf (флоккулирующих единиц).<br> ²&nbsp;Содержание столбнячного анатоксина 10&nbsp;Lf (флоккулирующих единиц).<br> ³&nbsp;Адсорбированный на алюминия гидроксиде (0,5&nbsp;мг в пересчете на алюминий).<br><br> <i>Перечень вспомогательных веществ:</i> <ul><li>Натрия хлорид.</li> <li>Вода для инъекций.</li></ul></p> | E6: 44211 | H6: https://lk.regmed.ru/Register/GetPDFfromDA?ID=1484709711 | I6: 45105 | J6: 45481 | K6: добавлено Елена Савинова
A7: 6 | B7: =VLOOKUP(A7,[1]vaccines!A:B,2) -> AKDS_Microgen | C7: В 1 дозе (0,5 мл) содержится: Препарат с консервантом. Действующие вещества: • анатоксин дифтерийный¹ — 15 флокулирующих единиц (Lf); • анатоксин столбнячный¹ — 5 единиц связывания (EC); • коклюшная суспензия инактивированная — 10 млрд коклюшных микробных клеток. ¹ - Адсорбированный на алюминия гидроксиде (в пересчете на Al³⁺) — не более 0,55 мг; Препарат без консерванта. Действующие вещества: • анатоксин дифтерийный¹ — 15 флокулирующих единиц (Lf); • анатоксин столбнячный¹ — 5 единиц связывания (EC); • коклюшная суспензия инактивированная без тиомерсала — 10 млрд коклюшных микробных клеток. ¹ - Адсорбированный на алюминия гидроксиде (в пересчете на Al³⁺) — не более 0,55 мг; Перечень вспомогательных веществ: Препарат с консервантом. • Алюминия гидроксид; • Формальдегид; • Консервант — тиомерсал. Препарат без консерванта. • Алюминия гидроксид; • Формальдегид. | D7: <p>В 1&nbsp;дозе (0,5&nbsp;мл) содержится:<br><br> <i>Препарат с консервантом.</i><br><br> Действующие вещества: <ul><li>анатоксин дифтерийный¹ — 15&nbsp;флокулирующих единиц (Lf);</li> <li>анатоксин столбнячный¹ — 5&nbsp;единиц связывания (EC);</li> <li>коклюшная суспензия инактивированная — 10&nbsp;млрд коклюшных микробных клеток.</li></ul> ¹&nbsp;- Адсорбированный на алюминия гидроксиде (в пересчете на Al³⁺) — не более 0,55&nbsp;мг;<br><br> <i>Препарат без консерванта.</i><br><br> Действующие вещества: <ul><li>анатоксин дифтерийный¹ — 15&nbsp;флокулирующих единиц (Lf);</li> <li>анатоксин столбнячный¹ — 5&nbsp;единиц связывания (EC);</li> <li>коклюшная суспензия инактивированная без тиомерсала — 10&nbsp;млрд коклюшных микробных клеток.</li></ul> ¹&nbsp;- Адсорбированный на алюминия гидроксиде (в пересчете на Al³⁺) — не более 0,55&nbsp;мг;<br><br> Перечень вспомогательных веществ:<br><br> <i>Препарат с консервантом.</i> <ul><li>Алюминия гидроксид;</li> <li>Формальдегид;</li> <li>Консервант — тиомерсал.</li></ul> <i>Препарат без консерванта.</i> <ul><li>Алюминия гидроксид;</li> <li>Формальдегид.</li></ul></p> | E7: 45415 | H7: https://lk.regmed.ru/Register/GetPDFfromDA?ID=1587927891 | I7: 45115 | J7: 45461
A8: 7 | B8: =VLOOKUP(A8,[1]vaccines!A:B,2) -> AKDS_Biomed | C8: АКДС-вакцина состоит из взвеси убитых коклюшных микробов и очищенных дифтерийного и столбнячного анатоксинов, сорбированных на алюминия гидроксиде. В одной дозе препарата (0,5 мл) содержится 10 международных единиц (МЕ) инактивированных коклюшных микробов, 15 флокулирующих единиц (Lf) дифтерийного, 5 единиц связывания (EC) столбнячного анатоксинов, от 0,25 до 0,55 мг алюминия гидроксида в пересчете на алюминий (сорбент), от 42,5 до 57,5 мкг тиомерсала (консервант). | D8: <p>В одной дозе препарата (0,5&nbsp;мл) содержится 10&nbsp;международных единиц (МЕ) инактивированных коклюшных микробов, 15&nbsp;флокулирующих единиц (Lf) дифтерийного, 5&nbsp;единиц связывания (EC) столбнячного анатоксинов, от 0,25 до 0,55&nbsp;мг алюминия гидроксида в пересчете на алюминий (сорбент), от 42,5 до 57,5&nbsp;мкг тиомерсала (консервант).</p> | E8: 41388 | F8: 1 | G8: 0 | H8: https://grls.rosminzdrav.ru/InstrImg/2017/4/26/1416322/%D0%A0_N002666_01[2013]_0.pdf | I8: 45115
A9: 8 | B9: =VLOOKUP(A9,[1]vaccines!A:B,2) -> Bubo_kok | C9: Препарат содержит в одной дозе (0,5 мл): 15 флокулирующих единиц (Lf) дифтерийного, 5 единиц связывания (EC) столбнячного анатоксинов, 10 млрд коклюшных бактерий, 5 мкг HBsAg, 0,4 мг алюминия гидроксида (Al³⁺), 50 мкг мертиолята (консервант). | D9: <p>Препарат содержит в одной дозе (0,5&nbsp;мл): 15&nbsp;флокулирующих единиц (Lf) дифтерийного, 5&nbsp;единиц связывания (EC) столбнячного анатоксинов, 10&nbsp;млрд коклюшных бактерий, 5&nbsp;мкг HBsAg, 0,4&nbsp;мг алюминия гидроксида (Al³⁺), 50&nbsp;мкг мертиолята (консервант).</p> | E9: 40395 | F9: 1 | G9: 0 | H9: https://grls.rosminzdrav.ru/InstrImg/2020/05/28/10700/9d141b34-47e7-48c8-9480-616cbbc792fc.pdf | I9: 45115
A10: 9 | B10: =VLOOKUP(A10,[1]vaccines!A:B,2) -> Pentaxim | C10: Действующими веществами являются: После восстановления 1 доза (0,5 мл) содержит: Изначально в виде суспензии: • Анатоксин дифтерийный¹ — 30 Lf (≥ 30 МЕ²)³; • Анатоксин столбнячный¹ — 10 LF (≥ 40 МЕ⁴)³; • Анатоксин коклюшный¹ — 25 мкг; • Гемагглютинин филаментозный¹ — 25 мкг; • Вирус полиомиелита 1-го типа инактивированный (Mahoney)⁵ — 40 единиц D антигена⁶; • Вирус полиомиелита 2-го типа инактивированный (MEF-1)⁵ — 8 единиц D антигена⁶; • Вирус полиомиелита 3-го типа инактивированный (Saukett)⁵ — 32 единицы D антигена⁶. Изначально в виде лиофилизата для приготовления суспензии: • Полисахарид Haemophilus influenzae тип b (полирибозилрибитол фосфат) — 10 мкг, конъюгированный со столбнячным анатоксином — 18-30 мкг. ¹ — адсорбирован на алюминия гидроксида гидрате (0,3 мг в пересчете на алюминий); ² — в качестве среднего значения, нижний предел доверительного интервала (р = 0,95) не менее 20 МЕ/доза; ³ — или эквивалентная активность, определенная при оценке иммуногенности; ⁴ — нижний предел доверительного интервала (р = 0,95); ⁵ — культивированный на клетках VERO; ⁶ — или эквивалентное содержание антигена, определенное подходящим иммунохимическим методом. Антибиотики (стрептомицин, неомицин и полимиксин В) и глутаральдегид используются при производстве вакцины, но не присутствуют в определяемых количествах в конечном продукте. Вспомогательные вещества, наличие которых надо учитывать в составе вакцины: фенилаланин Перечень вспомогательных веществ: Суспензия для внутримышечного введения: • Алюминия гидроксида гидрат; • Раствор формальдегида; • Феноксиэтанол; • Этанол безводный; • Среда Хенкса 199 (10×) без фенолового красного (представляет собой сложную смесь аминокислот (включая фенилаланин), минералов, витаминов и других компонентов (таких как глюкоза), разведенную в воде для инъекций); • Натрия гидроксид или ледяная уксусная кислота используются для корректировки рН; • Вода для инъекций. Лиофилизат для приготовления суспензии для внутримышечного введения: • Трометамол; • Сахароза; • Концентрированная хлористоводородная кислота для корректировки рН (до 7,2 ± 0,1). | D10: <p>Действующими веществами являются:<br> После восстановления 1&nbsp;доза (0,5&nbsp;мл) содержит:<br><br> <i>Изначально в виде суспензии:</i> <ul><li>Анатоксин дифтерийный¹ — 30&nbsp;Lf (≥&nbsp;30&nbsp;МЕ²)³;</li> <li>Анатоксин столбнячный¹ — 10&nbsp;LF (≥&nbsp;40&nbsp;МЕ⁴)³;</li> <li>Анатоксин коклюшный¹ — 25&nbsp;мкг;</li> <li>Гемагглютинин филаментозный¹ — 25&nbsp;мкг;</li> <li>Вирус полиомиелита 1-го&nbsp;типа инактивированный (Mahoney)⁵ — 40&nbsp;единиц D&nbsp;антигена⁶;</li> <li>Вирус полиомиелита 2-го&nbsp;типа инактивированный (MEF-1)⁵ — 8&nbsp;единиц D&nbsp;антигена⁶;</li> <li>Вирус полиомиелита 3-го&nbsp;типа инактивированный (Saukett)⁵ — 32&nbsp;единицы D&nbsp;антигена⁶.</li></ul> <i>Изначально в виде лиофилизата для приготовления суспензии:</i> <ul><li>Полисахарид Haemophilus influenzae тип b (полирибозилрибитол фосфат) — 10&nbsp;мкг,<br> конъюгированный со столбнячным анатоксином — 18-30&nbsp;мкг.</li></ul> ¹ — адсорбирован на алюминия гидроксида гидрате (0,3&nbsp;мг в пересчете на алюминий);<br> ² — в качестве среднего значения, нижний предел доверительного интервала (р&nbsp;=&nbsp;0,95) не менее 20&nbsp;МЕ/доза;<br> ³ — или эквивалентная активность, определенная при оценке иммуногенности;<br> ⁴ — нижний предел доверительного интервала (р&nbsp;=&nbsp;0,95);<br> ⁵ — культивированный на клетках VERO;<br> ⁶ — или эквивалентное содержание антигена, определенное подходящим иммунохимическим методом.<br><br> Антибиотики (стрептомицин, неомицин и полимиксин В) и глутаральдегид используются при производстве вакцины, но не присутствуют в определяемых количествах в конечном продукте.<br> Вспомогательные вещества, наличие которых надо учитывать в составе вакцины: фенилаланин<br><br> Перечень вспомогательных веществ:<br> <i>Суспензия для внутримышечного введения:</i> <ul><li>Алюминия гидроксида гидрат;</li> <li>Раствор формальдегида;</li> <li>Феноксиэтанол;</li> <li>Этанол безводный;</li> <li>Среда Хенкса&nbsp;199 (10×) без фенолового красного (представляет собой сложную смесь аминокислот (включая фенилаланин), минералов, витаминов и других компонентов (таких как глюкоза), разведенную в воде для инъекций);</li> <li>Натрия гидроксид или ледяная уксусная кислота используются для корректировки рН;</li> <li>Вода для инъекций.</li></ul> <i>Лиофилизат для приготовления суспензии для внутримышечного введения:</i> <ul><li>Трометамол;</li> <li>Сахароза;</li> <li>Концентрированная хлористоводородная кислота для корректировки рН (до 7,2&nbsp;±&nbsp;0,1).</li></ul></p> | E10: 45980 | F10: 1 | G10: 0 | H10: https://grls.rosminzdrav.ru/InstrImg/2026/05/27/1530421/6bdc8421-6c08-4bf7-be7f-0ae5d96a478d.pdf | I10: =I9 -> 45115 | J10: 46204 | K10: zaytseva@vaccina.info не нашла символ запятой в верхнем индексе, который бы нормально копировался сюда, поэтому здесь и далее в столбце "ingredients_text_w/o_html" вместо него символ "·". В столбце "ingredients_text_html" запятая в верхнем индексе поставлена с помощью тэга <sup>.
A11: 10 | B11: =VLOOKUP(A11,[1]vaccines!A:B,2) -> Infanrix_Hexa | C11: 1 доза (0,5 мл) вакцины содержит: Вакцина для профилактики дифтерии, столбняка, коклюша (бесклеточная), полиомиелита (инактивированная), гепатита В комбинированная, адсорбированная Действующие вещества: • Анатоксин дифтерийный¹·³ — Не менее 30 МЕ; • Анатоксин столбнячный²·³ — Не менее 40 МЕ; • Анатоксин коклюшный (АК)³ — 25 мкг; • Гемагглютинин филаментозный (ФГА)³ — 25 мкг; • Пертактин (белок наружной мембраны 69 кДа)³ — 8 мкг; • Антиген поверхностный рекомбинантный вируса гепатита B (HBsAg)⁴ — 10 мкг; • Вирус полиомиелита тип 1 инактивированный — 40 ЕД D-антигена; • Вирус полиомиелита тип 2 инактивированный — 8 ЕД D-антигена; • Вирус полиомиелита тип 3 инактивированный — 32 ЕД D-антигена. Вакцина для профилактики инфекции, вызываемой Haemophilus influenzae тип b конъюгированная, адсорбированная Действующее вещество: • Капсульный полисахарид Haemophilus influenzae тип b⁴ — 10 мкг; конъюгированный со столбнячным анатоксином — ≈25 мкг. ¹ Содержание дифтерийного анатоксина 25 Lf (флоккулирующих единиц). ² Содержание столбнячного анатоксина 10 Lf (флоккулирующих единиц). ³ Адсорбированный на алюминия гидроксиде (0,5 мг в пересчете на алюминий). ⁴ Адсорбированный на алюминия фосфате (0,32 мг в пересчете на алюминий). Перечень вспомогательных веществ: Вакцина для профилактики дифтерии, столбняка, коклюша (бесклеточная), полиомиелита (инактивированная), гепатита В комбинированная, адсорбированная: • Натрия хлорид. • Среда 199 (М 199)¹ (включая аминокислоты). • Вода для инъекций. ¹ Состав среды 199 (М 199): кальция хлорида дигидрат, железа нитрата нонагидрат, калия хлорид, калия дигидрофосфат, магния сульфата гептагидрат, натрия хлорид, натрия гидрокарбонат, натрия гидрофосфат, L-аланин, L-аргинина гидрохлорид, L-аспарагиновая кислота, L-цистеина гидрохлорид, L-цистин, L-глутаминовая кислота, L-глутамин, глицин, L-гистидина гидрохлорида моногидрат, L-гидроксипролин, L-изолейцин, L-лейцин, L-лизина гидрохлорид, L-метионин, L-фенилаланин, L-пролин, L-серин, L-треонин, L-триптофан, L-тирозин, L-валин, аскорбиновая кислота, альфа-токоферол, биотин, кальциферол, кальция пантотенат, холина хлорид, фолиевая кислота, инозитол, менадион, никотиновая кислота, никотинамид, пара-аминобензойная кислота, пиридоксаль гидрохлорид, пиридоксина гидрохлорид, рибофлавин, тиамина гидрохлорид, ретинола ацетат, аденин, аденозина фосфат, аденозина трифосфат натрия, холестерол, дезоксирибоза, глюкоза, глутатион, гуанина гидрохлорид, гипоксантин, рибоза, натрия ацетат, тимин, твин-80, урацил, ксантин. Вакцина для профилактики инфекции, вызываемой Haemophilus influenzae тип b, конъюгированная, адсорбированная: • Лактоза. Данный препарат содержит менее 1 ммоль (23 мг) натрия на 1 дозу, то есть по сути не содержит натрия. | D11: <p>1&nbsp;доза (0,5&nbsp;мл) вакцины содержит:<br><br> Вакцина для профилактики дифтерии, столбняка, коклюша (бесклеточная), полиомиелита (инактивированная), гепатита В комбинированная, адсорбированная <ul><i>Действующие вещества:</i> <li>Анатоксин дифтерийный¹<sup>,</sup>³ — Не менее 30&nbsp;МЕ;</li> <li>Анатоксин столбнячный²<sup>,</sup>³ — Не менее 40&nbsp;МЕ;</li> <li>Анатоксин коклюшный (АК)³ — 25&nbsp;мкг;</li> <li>Гемагглютинин филаментозный (ФГА)³ — 25&nbsp;мкг;</li> <li>Пертактин (белок наружной мембраны 69&nbsp;кДа)³ — 8&nbsp;мкг;</li> <li>Антиген поверхностный рекомбинантный вируса гепатита B (HBsAg)⁴ — 10&nbsp;мкг;</li> <li>Вирус полиомиелита тип&nbsp;1 инактивированный — 40&nbsp;ЕД D-антигена;</li> <li>Вирус полиомиелита тип&nbsp;2 инактивированный — 8&nbsp;ЕД D-антигена;</li> <li>Вирус полиомиелита тип&nbsp;3 инактивированный — 32&nbsp;ЕД D-антигена.</li></ul> Вакцина для профилактики инфекции, вызываемой <i>Haemophilus influenzae</i> тип <i>b</i> конъюгированная, адсорбированная <ul><i>Действующее вещество:</i> <li>Капсульный полисахарид Haemophilus influenzae тип b⁴ — 10&nbsp;мкг;<br> конъюгированный со столбнячным анатоксином — ≈25&nbsp;мкг.</li></ul> ¹ Содержание дифтерийного анатоксина 25&nbsp;Lf (флоккулирующих единиц).<br> ² Содержание столбнячного анатоксина 10&nbsp;Lf (флоккулирующих единиц).<br> ³ Адсорбированный на алюминия гидроксиде (0,5&nbsp;мг в пересчете на алюминий).<br> ⁴ Адсорбированный на алюминия фосфате (0,32&nbsp;мг в пересчете на алюминий).</p> <p><i>Перечень вспомогательных веществ:</i><br><br> Вакцина для профилактики дифтерии, столбняка, коклюша (бесклеточная), полиомиелита (инактивированная), гепатита В комбинированная, адсорбированная: <ul><li>Натрия хлорид.</li> <li>Среда&nbsp;199 (М&nbsp;199)¹ (включая аминокислоты).</li> <li>Вода для инъекций.</li></ul> ¹ Состав среды&nbsp;199 (М&nbsp;199):<br> кальция хлорида дигидрат, железа нитрата нонагидрат, калия хлорид, калия дигидрофосфат, магния сульфата гептагидрат, натрия хлорид, натрия гидрокарбонат, натрия гидрофосфат, L-аланин, L-аргинина гидрохлорид, L-аспарагиновая кислота, L-цистеина гидрохлорид, L-цистин, L-глутаминовая кислота, L-глутамин, глицин, L-гистидина гидрохлорида моногидрат, L-гидроксипролин, L-изолейцин, L-лейцин, L-лизина гидрохлорид, L-метионин, L-фенилаланин, L-пролин, L-серин, L-треонин, L-триптофан, L-тирозин, L-валин, аскорбиновая кислота, альфа-токоферол, биотин, кальциферол, кальция пантотенат, холина хлорид, фолиевая кислота, инозитол, менадион, никотиновая кислота, никотинамид, пара-аминобензойная кислота, пиридоксаль гидрохлорид, пиридоксина гидрохлорид, рибофлавин, тиамина гидрохлорид, ретинола ацетат, аденин, аденозина фосфат, аденозина трифосфат натрия, холестерол, дезоксирибоза, глюкоза, глутатион, гуанина гидрохлорид, гипоксантин, рибоза, натрия ацетат, тимин, твин-80, урацил, ксантин.<br><br> Вакцина для профилактики инфекции, вызываемой <i>Haemophilus influenzae</i> тип <i>b</i>, конъюгированная, адсорбированная: <ul><li>Лактоза.</li></ul> Данный препарат содержит менее 1&nbsp;ммоль (23&nbsp;мг) натрия на 1&nbsp;дозу, то есть по сути не содержит натрия.</p> | E11: 45953 | F11: 1 | G11: 0 | H11: https://grls.rosminzdrav.ru/InstrImg/2025/12/04/1523945/374687b9-516b-4eb9-9e34-640e88c2e1e2.pdf | I11: =I10 -> 45115 | J11: 46000
A12: 11 | B12: =VLOOKUP(A12,[1]vaccines!A:B,2) -> Bubo_M | C12: 1 доза (0,5 мл) содержит действующие вещества: • Антиген вируса гепатита В поверхностный рекомбинантный (HBsAg) (серотип ay и/или ad)¹ — 10 мкг; • дифтерийный анатоксин очищенный концентрированный жидкий (ОКДА)¹ — 5 Lf (флокулирующих единиц); • столбнячный анатоксин очищенный концентрированный жидкий (ОКСА)¹ — 5 ЕС (антитоксинсвязывающих единиц). ¹ — адсорбированный на алюминия гидроксиде (Al³⁺) — 0,45 мг. Перечень вспомогательных веществ: • Тиомерсал (консервант). | D12: <p>1&nbsp;доза (0,5&nbsp;мл) содержит действующие вещества: <ul><li>Антиген вируса гепатита&nbsp;В поверхностный рекомбинантный (HBsAg) (серотип ay и/или ad)¹ — 10&nbsp;мкг;</li> <li>дифтерийный анатоксин очищенный концентрированный жидкий (ОКДА)¹ — 5&nbsp;Lf (флокулирующих единиц);</li> <li>столбнячный анатоксин очищенный концентрированный жидкий (ОКСА)¹ — 5&nbsp;ЕС (антитоксинсвязывающих единиц).</li></ul> ¹&nbsp;—&nbsp;адсорбированный на алюминия гидроксиде (Al³⁺) — 0,45&nbsp;мг.<br><br> <i>Перечень вспомогательных веществ:</i> <ul><li>Тиомерсал (консервант).</li></ul></p> | E12: 46136 | F12: 1 | G12: 0 | H12: https://grls.rosminzdrav.ru/InstrImg/2026/06/02/1530636/e301156c-c7d5-45d7-bf58-5346c270c493.pdf | I12: 45116 | J12: 46188
A13: 12 | B13: =VLOOKUP(A13,[1]vaccines!A:B,2) -> AD_M_Microgen | C13: В 1 дозе (0,5 мл) содержится: Препарат с консервантом и без консерванта Действующее вещество: • Анатоксин дифтерийный¹ — 5 Lf. Вспомогательные вещества, наличие которых надо учитывать в составе лекарственного препарата: • Содержит формальдегид — не более 50 мкг. ¹ Адсорбированный на алюминия гидроксиде (в пересчете на Al³⁺) — не более 0,55 мг. Полный перечень вспомогательных веществ приведен в разделе 6.1. 6.1. Перечень вспомогательных веществ Препарат с консервантом: • Алюминия гидроксид • Тиомерсал (консервант) Препарат без консерванта: • Алюминия гидроксид | D13: <p>В 1&nbsp;дозе (0,5&nbsp;мл) содержится:<br><br> <i>Препарат с консервантом и без консерванта</i><br><br> Действующее вещество: <ul><li>Анатоксин дифтерийный¹ — 5&nbsp;Lf.</li></ul> Вспомогательные вещества, наличие которых надо учитывать в составе лекарственного препарата: <ul><li>Содержит формальдегид — не более 50&nbsp;мкг.</li></ul> ¹&nbsp;Адсорбированный на алюминия гидроксиде (в пересчете на Al³⁺) — не более 0,55&nbsp;мг.<br><br> Полный перечень вспомогательных веществ приведен в разделе&nbsp;6.1.</p> <p><b>6.1.&nbsp;Перечень вспомогательных веществ</b><br><br> <i>Препарат с консервантом:</i> <ul><li>Алюминия гидроксид</li> <li>Тиомерсал (консервант)</li></ul> <i>Препарат без консерванта:</i> <ul><li>Алюминия гидроксид</li></ul></p> | E13: 45482 | H13: https://lk.regmed.ru/Register/GetPDFfromDA?ID=1601683231 | I13: =I12 -> 45116 | J13: 45518 | K13: проверено Елена Савинова
A14: 13 | B14: =VLOOKUP(A14,[1]vaccines!A:B,2) -> ADS_Microgen | C14: В 1 дозе (0,5 мл) содержится: Препарат с консервантом: Действующие вещества: • Анатоксин дифтерийный¹ — 30 Lf; • Анатоксин столбнячный¹ — 10 ЕС. Вспомогательные вещества, наличие которых надо учитывать в составе лекарственного препарата: тиомерсал. Содержит формальдегид — не более 50 мкг. Препарат без консерванта: Действующие вещества: • Анатоксин дифтерийный¹ — 30 Lf; • Анатоксин столбнячный¹ — 10 ЕС. Содержит формальдегид — не более 50 мкг. ¹ Адсорбированный на алюминия гидроксиде (в пересчете на Al³⁺) — не более 0,55 мг. Полный перечень вспомогательных веществ приведен в разделе 6.1. 6.1. Перечень вспомогательных веществ Препарат с консервантом: • Алюминия гидроксид • Тиомерсал (консервант) Препарат без консерванта: • Алюминия гидроксид | D14: <p>В 1&nbsp;дозе (0,5&nbsp;мл) содержится:<br><br> <i>Препарат с консервантом:</i><br><br> Действующие вещества: <ul><li>Анатоксин дифтерийный¹ — 30&nbsp;Lf;</li> <li>Анатоксин столбнячный¹ — 10&nbsp;ЕС.</li></ul> Вспомогательные вещества, наличие которых надо учитывать в составе лекарственного препарата: тиомерсал.<br> Содержит формальдегид — не более 50&nbsp;мкг.<br><br> <i>Препарат без консерванта:</i><br><br> Действующие вещества: <ul><li>Анатоксин дифтерийный¹ — 30&nbsp;Lf;</li> <li>Анатоксин столбнячный¹ — 10&nbsp;ЕС.</li></ul> Содержит формальдегид — не более 50&nbsp;мкг.<br><br> ¹&nbsp;Адсорбированный на алюминия гидроксиде (в пересчете на Al³⁺) — не более 0,55&nbsp;мг.<br><br> Полный перечень вспомогательных веществ приведен в разделе&nbsp;6.1.</p> <p><b>6.1.&nbsp;Перечень вспомогательных веществ</b><br><br> <i>Препарат с консервантом:</i> <ul><li>Алюминия гидроксид</li> <li>Тиомерсал (консервант)</li></ul> <i>Препарат без консерванта:</i> <ul><li>Алюминия гидроксид</li></ul></p> | E14: 45488 | H14: https://lk.regmed.ru/Register/GetPDFfromDA?ID=1605321651 | I14: =I13 -> 45116 | J14: 45518
A15: 14 | B15: =VLOOKUP(A15,[1]vaccines!A:B,2) -> ADS_M_Microgen | C15: В 1 дозе (0,5 мл) содержится: Препарат с консервантом: Действующие вещества: • Анатоксин дифтерийный¹ — 5 Lf; • Анатоксин столбнячный¹ — 5 ЕС. Вспомогательные вещества: • Формальдегид — не более 50 мкг. ¹ Адсорбированный на алюминия гидроксиде (в пересчете на Al³⁺) — не более 0,55 мг. Препарат без консерванта: Действующие вещества: • Анатоксин дифтерийный¹ — 5 Lf; • Анатоксин столбнячный¹ — 5 ЕС. Вспомогательные вещества: • Формальдегид — не более 50 мкг. ¹ Адсорбированный на алюминия гидроксиде (в пересчете на Al³⁺) — не более 0,55 мг. Полный перечень вспомогательных веществ приведен в разделе 6.1. 6.1. Перечень вспомогательных веществ Препарат с консервантом: • Алюминия гидроксид (в пересчете на алюминий Аl³⁺) • Тиомерсал (консервант) Препарат без консерванта: • Алюминия гидроксид (в пересчете на алюминий Аl³⁺) | D15: <p>В 1&nbsp;дозе (0,5&nbsp;мл) содержится:<br><br> <i>Препарат с консервантом:</i><br><br> Действующие вещества: <ul><li>Анатоксин дифтерийный¹ — 5&nbsp;Lf;</li> <li>Анатоксин столбнячный¹ — 5&nbsp;ЕС.</li></ul> Вспомогательные вещества: <ul><li>Формальдегид — не более 50&nbsp;мкг.</li></ul> ¹&nbsp;Адсорбированный на алюминия гидроксиде (в пересчете на Al³⁺) — не более 0,55&nbsp;мг.<br><br> <i>Препарат без консерванта:</i><br><br> Действующие вещества: <ul><li>Анатоксин дифтерийный¹ — 5&nbsp;Lf;</li> <li>Анатоксин столбнячный¹ — 5&nbsp;ЕС.</li></ul> Вспомогательные вещества: <ul><li>Формальдегид — не более 50&nbsp;мкг.</li></ul> ¹&nbsp;Адсорбированный на алюминия гидроксиде (в пересчете на Al³⁺) — не более 0,55&nbsp;мг.<br><br> Полный перечень вспомогательных веществ приведен в разделе&nbsp;6.1.</p> <p><b>6.1.&nbsp;Перечень вспомогательных веществ</b><br><br> <i>Препарат с консервантом:</i> <ul><li>Алюминия гидроксид (в пересчете на алюминий Аl³⁺)</li> <li>Тиомерсал (консервант)</li></ul> <i>Препарат без консерванта:</i> <ul><li>Алюминия гидроксид (в пересчете на алюминий Аl³⁺)</li></ul></p> | E15: 45623 | F15: 1 | G15: 0 | H15: https://grls.rosminzdrav.ru/InstrImg/2024/12/16/1511954/43eafc3c-33ac-4e33-969c-259e9a175ebb.pdf | I15: =I14 -> 45116 | J15: 45861
A16: 15 | B16: =VLOOKUP(A16,[1]vaccines!A:B,2) -> ADS_M_Biomed | C16: В одной дозе препарата (0,5 мл) содержится: Активные вещества: 5 флокулирующих единиц (Lf) дифтерийного и 5 единиц связывания (EC) столбнячного анатоксинов. Вспомогательные вещества: от 0,25 до 0,55 мг алюминия гидроксида в пересчете на алюминий (сорбент), от 42,5 до 57,5 мкг тиомерсала (консервант). | D16: <p>В одной дозе препарата (0,5&nbsp;мл) содержится:</p> <p>Активные вещества: 5&nbsp;флокулирующих единиц (Lf) дифтерийного и 5&nbsp;единиц связывания (EC) столбнячного анатоксинов.</p> <p>Вспомогательные вещества: от 0,25 до 0,55&nbsp;мг алюминия гидроксида в пересчете на алюминий (сорбент), от 42,5 до 57,5&nbsp;мкг тиомерсала (консервант).</p> | E16: 41046 | F16: 1 | G16: 0 | H16: https://grls.rosminzdrav.ru/InstrImg/2018/7/19/1423955/%D0%A0_N002668_01[2012]_0.pdf | I16: 45116
A17: 16 | B17: =VLOOKUP(A17,[1]vaccines!A:B,2) -> Adacel | C17: 1 доза вакцины (0,5 мл) содержит действующие вещества: • Столбнячный анатоксин, адсорбированный¹ — 5 Lf (не менее 20 ME). • Дифтерийный анатоксин, адсорбированный¹ — 2 Lf (не менее 2 ME). • Бесклеточная коклюшная вакцина, содержащая: коклюшный анатоксин (КА), адсорбированный¹ — 2,5 мкг. филаментозный гемагглютинин (ФГА), адсорбированный¹ — 5 мкг. агглютиногены фимбрий типов 2 и 3 (ФИМ), адсорбированные¹ — 5 мкг. пертактин (ПРН), адсорбированный¹ — 3 мкг. ¹ — адсорбирована на алюминия фосфате (в пересчете на алюминий) — 1,5 мг (0,33 мг). Остаточные продукты производственного процесса, присутствующие в 1 дозе вакцины (0,5 мл) в следовых количествах (указано их расчетное количество): формальдегид (≤ 5 мкг) и глутаральдегид (< 50 нг). Перечень вспомогательных веществ: • Алюминия фосфат. • 2-феноксиэтанол (не консервант). • Вода для инъекций. | D17: <p>1&nbsp;доза вакцины (0,5&nbsp;мл) содержит действующие вещества: <ul><li>Столбнячный анатоксин, адсорбированный¹ — 5&nbsp;Lf (не менее 20&nbsp;ME).</li> <li>Дифтерийный анатоксин, адсорбированный¹ — 2&nbsp;Lf (не менее 2&nbsp;ME).</li> <li>Бесклеточная коклюшная вакцина, содержащая:<br> коклюшный анатоксин (КА), адсорбированный¹ — 2,5&nbsp;мкг.<br> филаментозный гемагглютинин (ФГА), адсорбированный¹ — 5&nbsp;мкг.<br> агглютиногены фимбрий типов 2 и 3 (ФИМ), адсорбированные¹ — 5&nbsp;мкг.<br> пертактин (ПРН), адсорбированный¹ — 3&nbsp;мкг.</li></ul> ¹ — адсорбирована на алюминия фосфате (в пересчете на алюминий) — 1,5&nbsp;мг (0,33&nbsp;мг).</p> <p>Остаточные продукты производственного процесса, присутствующие в 1&nbsp;дозе вакцины (0,5&nbsp;мл) в следовых количествах (указано их расчетное количество): формальдегид (≤&nbsp;5&nbsp;мкг) и глутаральдегид (<&nbsp;50&nbsp;нг).</p> <p>Перечень вспомогательных веществ: <ul><li>Алюминия фосфат. <li>2-феноксиэтанол (не консервант).</li> <li>Вода для инъекций.</li></ul></p> | E17: 45456 | H17: https://lk.regmed.ru/Register/GetPDFfromDA?ID=1592320751 | I17: 45117 | J17: 45589
A18: 17 | B18: =VLOOKUP(A18,[1]vaccines!A:B,2) -> Algavac_M | C18: 1 прививочная доза для взрослых (1 мл) содержит: Действующее вещество: Инактивированный антиген вируса гепатита А (АГ ВГА) — не менее 320 ИФА ЕД. Вспомогательные вещества: Алюминия гидроксид, формальдегид, 0,01 М фосфатно-солевой буферный раствор (натрия гидрофосфата додекагидрат, натрия хлорид, вода для инъекций). Вакцина не содержит консервантов и антибиотиков. 1 прививочная доза для детей (0,5 мл) содержит: Действующее вещество: Инактивированный антиген вируса гепатита А (АГ ВГА) — не менее 160 ИФА ЕД. Вспомогательные вещества: Алюминия гидроксид, формальдегид, 0,01 М фосфатно-солевой буферный раствор (натрия гидрофосфата додекагидрат, натрия хлорид, вода для инъекций). Вакцина не содержит консервантов и антибиотиков. | D18: <p>1&nbsp;прививочная доза для взрослых (1&nbsp;мл) содержит:</p> <p><i>Действующее вещество:</i> <ul>Инактивированный антиген вируса гепатита А (АГ ВГА) — не менее 320&nbsp;ИФА ЕД.</ul> <i>Вспомогательные вещества:</i> <ul>Алюминия гидроксид, формальдегид, 0,01&nbsp;М фосфатно-солевой буферный раствор (натрия гидрофосфата додекагидрат, натрия хлорид, вода для инъекций).</ul></p> <p>Вакцина не содержит консервантов и антибиотиков.</p> <p>1&nbsp;прививочная доза для детей (0,5&nbsp;мл) содержит:</p> <p><i>Действующее вещество:</i> <ul>Инактивированный антиген вируса гепатита А (АГ ВГА) — не менее 160&nbsp;ИФА ЕД.</ul> <i>Вспомогательные вещества:</i> <ul>Алюминия гидроксид, формальдегид, 0,01&nbsp;М фосфатно-солевой буферный раствор (натрия гидрофосфата додекагидрат, натрия хлорид, вода для инъекций).</ul></p> <p>Вакцина не содержит консервантов и антибиотиков.</p> | E18: 43369 | F18: 1 | G18: 0 | H18: https://grls.rosminzdrav.ru/InstrImg/2020/9/29/1461721/%D0%A0_N000461_01[2018]_0.pdf | I18: 45117
A19: 18 | B19: =VLOOKUP(A19,[1]vaccines!A:B,2) -> Algavac | C19: 1 доза для взрослых (1 мл) содержит: Действующее вещество: • Инактивированный антиген вируса гепатита А (АГ ВГА) — не менее 320 ИФА ЕД (получен с использованием клеток почки зеленой мартышки 4647) Адсорбент • Алюминия гидроксид (в пересчете на Al³⁺) — 0,35-0,65 мг Вакцина не содержит консервантов и антибиотиков. Перечень вспомогательных веществ: • Алюминия гидроксид; • Формальдегид; • 0,01&nbsp;М фосфатно-солевой буферный раствор, содержащий: - натрия гидрофосфата додекагидрат; - натрия хлорид; - воду для инъекций. | D19: <p>1&nbsp;доза для взрослых (1&nbsp;мл) содержит:<br><br> <i>Действующее вещество:</i> <ul><li>Инактивированный антиген вируса гепатита А (АГ ВГА) — не менее 320&nbsp;ИФА ЕД<br> (получен с использованием клеток почки зеленой мартышки&nbsp;4647)</li></ul> <i>Адсорбент</i> <ul><li>Алюминия гидроксид (в пересчете на Al³⁺) — 0,35-0,65&nbsp;мг</li></ul> Вакцина не содержит консервантов и антибиотиков.<br><br> <i>Перечень вспомогательных веществ:</i> <ul><li>Алюминия гидроксид;</li> <li>Формальдегид;</li> <li>0,01&nbsp;М фосфатно-солевой буферный раствор, содержащий: <ul><li>натрия гидрофосфата додекагидрат;</li> <li>натрия хлорид;</li> <li>воду для инъекций.</li></ul></p> | E19: 46111 | F19: 1 | G19: 0 | H19: https://grls.rosminzdrav.ru/InstrImg/2026/05/07/1529632/54e13522-5efa-4c8c-a9b0-7ea539b4f9d1.pdf | I19: =I18 -> 45117 | J19: 46188
A20: 19 | B20: =VLOOKUP(A20,[1]vaccines!A:B,2) -> Havrix_720 | C20: Одна прививочная доза содержит: Действующее вещество: • Антиген вируса гепатита А — 720 ИФА единиц. Адъювант: • Алюминия гидроксид — 0,25 мг. Вакцина содержит следовые количества неомицина сульфата. Вспомогательные вещества, наличие которых надо учитывать в составе лекарственного препарата: фенилаланин, натрия гидрофосфат, натрия хлорид, калия дигидрофосфат, калия хлорид. Полный перечень вспомогательных веществ приведен в разделе 6.1. 6.1. Перечень вспомогательных веществ • Алюминия гидроксид — 0,25 мг; • Полисорбат-20 — 0,025 мг; • Натрия гидрофосфат — Не более 0,575 мг; • Калия дигидрофосфат — Не более 0,10 мг; • Натрия хлорид — Не более 4,50 мг; • Калия хлорид — Не более 0,115 мг; • Аминокислотный компонент¹ — 1,50 мг; • Вода для инъекций — до 0,5 мл. ¹ Аминокислотный компонент: L-аланин, L-аргинин, глицин, L-гистидин, L-изолейцин, L-лейцин, L-лизин, L-метионин, L-фенилаланин, L-пролин, L-серин, L-треонин, L-триптофан, L-тирозин, L-валин. | D20: <p>Одна прививочная доза содержит:<br><br> <i>Действующее вещество:</i> <ul><li>Антиген вируса гепатита А — 720&nbsp;ИФА единиц.</li></ul> <i>Адъювант:</i> <ul><li>Алюминия гидроксид — 0,25&nbsp;мг.</li></ul> Вакцина содержит следовые количества неомицина сульфата.<br> Вспомогательные вещества, наличие которых надо учитывать в составе лекарственного препарата: фенилаланин, натрия гидрофосфат, натрия хлорид, калия дигидрофосфат, калия хлорид.<br> Полный перечень вспомогательных веществ приведен в разделе&nbsp;6.1.</p> <p><b>6.1. Перечень вспомогательных веществ</b> <ul><li>Алюминия гидроксид — 0,25&nbsp;мг;</li> <li>Полисорбат-20 — 0,025&nbsp;мг;</li> <li>Натрия гидрофосфат — Не более 0,575&nbsp;мг;</li> <li>Калия дигидрофосфат — Не более 0,10&nbsp;мг;</li> <li>Натрия хлорид — Не более 4,50&nbsp;мг;</li> <li>Калия хлорид — Не более 0,115&nbsp;мг;</li> <li>Аминокислотный компонент¹ — 1,50&nbsp;мг;</li> <li>Вода для инъекций — до 0,5&nbsp;мл.</li></ul> ¹&nbsp;Аминокислотный компонент: L-аланин, L-аргинин, глицин, L-гистидин, L-изолейцин, L-лейцин, L-лизин, L-метионин, L-фенилаланин, L-пролин, L-серин, L-треонин, L-триптофан, L-тирозин, L-валин.</p> | E20: 45490 | H20: https://lk.regmed.ru/Register/GetPDFfromDA?ID=1607490831 | I20: 45119 | J20: 45558
A21: 20 | B21: =VLOOKUP(A21,[1]vaccines!A:B,2) -> Havrix_1440 | C21: Одна прививочная доза содержит: Действующее вещество: • Антиген вируса гепатита А — 1440 ИФА единиц. Адъювант: • Алюминия гидроксид — 0,50 мг. Вакцина содержит следовые количества неомицина сульфата. Вспомогательные вещества, наличие которых надо учитывать в составе лекарственного препарата: фенилаланин, натрия гидрофосфат, натрия хлорид, калия дигидрофосфат, калия хлорид. Полный перечень вспомогательных веществ приведен в разделе 6.1. 6.1. Перечень вспомогательных веществ • Алюминия гидроксид — 0,50 мг; • Полисорбат-20 — 0,050 мг; • Натрия гидрофосфат — Не более 1,150 мг; • Калия дигидрофосфат — Не более 0,20 мг; • Натрия хлорид — Не более 9,00 мг; • Калия хлорид — Не более 0,230 мг; • Аминокислотный компонент¹ — 3,00 мг; • Вода для инъекций — до 1,0 мл. ¹ Аминокислотный компонент: L-аланин, L-аргинин, глицин, L-гистидин, L-изолейцин, L-лейцин, L-лизин, L-метионин, L-фенилаланин, L-пролин, L-серин, L-треонин, L-триптофан, L-тирозин, L-валин. | D21: <p>Одна прививочная доза содержит:<br><br> <i>Действующее вещество:</i> <ul><li>Антиген вируса гепатита А — 1440&nbsp;ИФА единиц.</li></ul> <i>Адъювант:</i> <ul><li>Алюминия гидроксид — 0,50&nbsp;мг.</li></ul> Вакцина содержит следовые количества неомицина сульфата.<br> Вспомогательные вещества, наличие которых надо учитывать в составе лекарственного препарата: фенилаланин, натрия гидрофосфат, натрия хлорид, калия дигидрофосфат, калия хлорид.<br> Полный перечень вспомогательных веществ приведен в разделе&nbsp;6.1.</p> <p><b>6.1. Перечень вспомогательных веществ</b> <ul><li>Алюминия гидроксид — 0,50&nbsp;мг;</li> <li>Полисорбат-20 — 0,050&nbsp;мг;</li> <li>Натрия гидрофосфат — Не более 1,150&nbsp;мг;</li> <li>Калия дигидрофосфат — Не более 0,20&nbsp;мг;</li> <li>Натрия хлорид — Не более 9,00&nbsp;мг;</li> <li>Калия хлорид — Не более 0,230&nbsp;мг;</li> <li>Аминокислотный компонент¹ — 3,00&nbsp;мг;</li> <li>Вода для инъекций — до 1,0&nbsp;мл.</li></ul> ¹&nbsp;Аминокислотный компонент: L-аланин, L-аргинин, глицин, L-гистидин, L-изолейцин, L-лейцин, L-лизин, L-метионин, L-фенилаланин, L-пролин, L-серин, L-треонин, L-триптофан, L-тирозин, L-валин.</p> | E21: 45490 | H21: https://lk.regmed.ru/Register/GetPDFfromDA?ID=1607490831 | I21: 45119 | J21: 45558
A22: 21 | B22: =VLOOKUP(A22,[1]vaccines!A:B,2) -> Avaxim_80 | C22: На 1 дозу (0,5 мл): Активный компонент: • Вирус гепатита А¹·² инактивированный — 80 единиц антигена³. ¹ - штамм GBM, культивированный в культуре диплоидных клеток человека MRC-5; ² - инактивированный формальдегидом и адсорбированный на алюминия гидроксиде; ³ - содержание антигена выражено с использованием внутреннего референс-стандарта компании-производителя. Вспомогательные вещества: • Алюминия гидроксид (в пересчете на алюминий) — 0,15 мг, 2-феноксиэтанол — 2,5 мкл, формальдегид — 12,5 мкг, среда Хэнкс 199⁴ — до 0,5 мл, кислота хлористоводородная или натрия гидроксид для регулировки значения pH. • Неомицин (производственная примесь) — не более 5 мкг/мл. ⁴ - среда Хэнкс 199 (без фенолового красного) является смесью аминокислот (D,L-аланин, L-аргинина гидрохлорид, D,L-аспарагиновая кислота, L-цистеина гидрохлорида моногидрат, L-цистина дигидрохлорид, D,L-глутаминовой кислоты моногидрат, L-глутамин, глицин, L-гистидина гидрохлорида моногидрат, D,L-изолейцин, L-гидроксипролин, D,L-лейцин, L-лизина гидрохлорид, D,L-метионин, D,L-фенилаланин, L-пролин, D,L-серин, D,L-треонин, D,L-триптофан, L-тирозин динатрия, D,L-валин), минеральных солей(кальция хлорид безводный, железа нитрата нонагидрат, калия хлорид, магния сульфата гептагидрат, натрия хлорид, калия дигидрофосфат, натрия гидрофосфат безводный), витаминов (аскорбиновая кислота, D-биотин, эргокальциферол, кальция пантотенат, холина хлорид, фолиевая кислота, I-инозитол, менадион, никотиновая кислота, никотинамид, парааминобензойная кислота, пиридоксаля гидрохлорид, пиридоксина гидрохлорид, рибофлавин, тиамина гидрохлорид, ретинола ацетат, альфа-токоферола фосфат натрия) и других компонентов (аденина сульфат, трифосаденин динатрия, аденозина фосфат, холестерол, дезоксирибоза, декстроза, глутатион восстановленный, гуанина гидрохлорид, гипоксантин динатрия, рибоза, натрия ацетат, тимин, полисорбат 80, урацил, ксантин динатрия), растворенных в воде для инъекций. | D22: <p>На 1&nbsp;дозу (0,5&nbsp;мл):</p> <p><i>Активный компонент:</i> <ul><li>Вирус гепатита&nbsp;А¹<sup>,</sup>² инактивированный — 80&nbsp;единиц антигена³.</li></ul></p> <p>¹ - штамм GBM, культивированный в культуре диплоидных клеток человека MRC-5;<br> ² - инактивированный формальдегидом и адсорбированный на алюминия гидроксиде;<br> ³ - содержание антигена выражено с использованием внутреннего референс-стандарта компании-производителя.</p> <p><i>Вспомогательные вещества:</i> <ul><li>Алюминия гидроксид (в пересчете на алюминий) — 0,15&nbsp;мг, 2-феноксиэтанол — 2,5&nbsp;мкл, формальдегид — 12,5&nbsp;мкг, среда Хэнкс&nbsp;199⁴ — до 0,5&nbsp;мл, кислота хлористоводородная или натрия гидроксид для регулировки значения pH.</li> <li>Неомицин (производственная примесь) — не более 5&nbsp;мкг/мл.</li></ul></p> <p>⁴ - среда Хэнкс&nbsp;199 (без фенолового красного) является смесью аминокислот (D,L-аланин, L-аргинина гидрохлорид, D,L-аспарагиновая кислота, L-цистеина гидрохлорида моногидрат, L-цистина дигидрохлорид, D,L-глутаминовой кислоты моногидрат, L-глутамин, глицин, L-гистидина гидрохлорида моногидрат, D,L-изолейцин, L-гидроксипролин, D,L-лейцин, L-лизина гидрохлорид, D,L-метионин, D,L-фенилаланин, L-пролин, D,L-серин, D,L-треонин, D,L-триптофан, L-тирозин динатрия, D,L-валин), минеральных солей(кальция хлорид безводный, железа нитрата нонагидрат, калия хлорид, магния сульфата гептагидрат, натрия хлорид, калия дигидрофосфат, натрия гидрофосфат безводный), витаминов (аскорбиновая кислота, D-биотин, эргокальциферол, кальция пантотенат, холина хлорид, фолиевая кислота, I-инозитол, менадион, никотиновая кислота, никотинамид, парааминобензойная кислота, пиридоксаля гидрохлорид, пиридоксина гидрохлорид, рибофлавин, тиамина гидрохлорид, ретинола ацетат, альфа-токоферола фосфат натрия) и других компонентов (аденина сульфат, трифосаденин динатрия, аденозина фосфат, холестерол, дезоксирибоза, декстроза, глутатион восстановленный, гуанина гидрохлорид, гипоксантин динатрия, рибоза, натрия ацетат, тимин, полисорбат 80, урацил, ксантин динатрия), растворенных в воде для инъекций.</p> | E22: 42367 | F22: 2 | G22: 1 | H22: https://grls.rosminzdrav.ru/InstrImg/2021/10/06/1474149/bd8cf367-32be-419a-a06f-cb35a0ecd9d1.pdf | I22: 45119
A23: 22 | B23: =VLOOKUP(A23,[1]vaccines!A:B,2) -> Avaxim_160 | C23: На 1 дозу (0,5 мл): Активный компонент: • Вирус гепатита А¹·² инактивированный — 160 единиц антигена³. ¹ - штамм GBM, культивированный в культуре диплоидных клеток человека MRC-5; ² - инактивированный формальдегидом и адсорбированный на алюминия гидроксиде; ³ - содержание антигена выражено с использованием внутреннего референс-стандарта компании-производителя. Вспомогательные вещества: • Алюминия гидроксид (в пересчете на алюминий) — 0,3 мг, 2-феноксиэтанол — 2,5 мкл, формальдегид — 12,5 мкг, среда Хэнкс 199⁴ — до 0,5 мл, кислота хлористоводородная или натрия гидроксид для регулировки значения pH. • Неомицин (производственная примесь) — не более 5 мкг/мл. ⁴ - среда Хэнкс 199 (без фенолового красного) является смесью аминокислот (D,L-аланин, L-аргинина гидрохлорид, D,L-аспарагиновая кислота, L-цистеина гидрохлорида моногидрат, L-цистина дигидрохлорид, D,L-глутаминовой кислоты моногидрат, L-глутамин, глицин, L-гистидина гидрохлорида моногидрат, D,L-изолейцин, L-гидроксипролин, D,L-лейцин, L-лизина гидрохлорид, D,L-метионин, D,L-фенилаланин, L-пролин, D,L-серин, D,L-треонин, D,L-триптофан, L-тирозин динатрия, D,L-валин), минеральных солей(кальция хлорид безводный, железа нитрата нонагидрат, калия хлорид, магния сульфата гептагидрат, натрия хлорид, калия дигидрофосфат, натрия гидрофосфат безводный), витаминов (аскорбиновая кислота, D-биотин, эргокальциферол, кальция пантотенат, холина хлорид, фолиевая кислота, I-инозитол, менадион, никотиновая кислота, никотинамид, парааминобензойная кислота, пиридоксаля гидрохлорид, пиридоксина гидрохлорид, рибофлавин, тиамина гидрохлорид, ретинола ацетат, альфа-токоферола фосфат натрия) и других компонентов (аденина сульфат, трифосаденин динатрия, аденозина фосфат, холестерол, дезоксирибоза, декстроза, глутатион восстановленный, гуанина гидрохлорид, гипоксантин динатрия, рибоза, натрия ацетат, тимин, полисорбат 80, урацил, ксантин динатрия), растворенных в воде для инъекций. | D23: <p>На 1&nbsp;дозу (0,5&nbsp;мл):</p> <p><i>Активный компонент:</i> <ul><li>Вирус гепатита&nbsp;А¹<sup>,</sup>² инактивированный — 160&nbsp;единиц антигена³.</li></ul></p> <p>¹ - штамм GBM, культивированный в культуре диплоидных клеток человека MRC-5;<br> ² - инактивированный формальдегидом и адсорбированный на алюминия гидроксиде;<br> ³ - содержание антигена выражено с использованием внутреннего референс-стандарта компании-производителя.</p> <p><i>Вспомогательные вещества:</i> <ul><li>Алюминия гидроксид (в пересчете на алюминий) — 0,3&nbsp;мг, 2-феноксиэтанол — 2,5&nbsp;мкл, формальдегид — 12,5&nbsp;мкг, среда Хэнкс&nbsp;199⁴ — до 0,5&nbsp;мл, кислота хлористоводородная или натрия гидроксид для регулировки значения pH.</li> <li>Неомицин (производственная примесь) — не более 5&nbsp;мкг/мл.</li></ul></p> <p>⁴ - среда Хэнкс&nbsp;199 (без фенолового красного) является смесью аминокислот (D,L-аланин, L-аргинина гидрохлорид, D,L-аспарагиновая кислота, L-цистеина гидрохлорида моногидрат, L-цистина дигидрохлорид, D,L-глутаминовой кислоты моногидрат, L-глутамин, глицин, L-гистидина гидрохлорида моногидрат, D,L-изолейцин, L-гидроксипролин, D,L-лейцин, L-лизина гидрохлорид, D,L-метионин, D,L-фенилаланин, L-пролин, D,L-серин, D,L-треонин, D,L-триптофан, L-тирозин динатрия, D,L-валин), минеральных солей(кальция хлорид безводный, железа нитрата нонагидрат, калия хлорид, магния сульфата гептагидрат, натрия хлорид, калия дигидрофосфат, натрия гидрофосфат безводный), витаминов (аскорбиновая кислота, D-биотин, эргокальциферол, кальция пантотенат, холина хлорид, фолиевая кислота, I-инозитол, менадион, никотиновая кислота, никотинамид, парааминобензойная кислота, пиридоксаля гидрохлорид, пиридоксина гидрохлорид, рибофлавин, тиамина гидрохлорид, ретинола ацетат, альфа-токоферола фосфат натрия) и других компонентов (аденина сульфат, трифосаденин динатрия, аденозина фосфат, холестерол, дезоксирибоза, декстроза, глутатион восстановленный, гуанина гидрохлорид, гипоксантин динатрия, рибоза, натрия ацетат, тимин, полисорбат 80, урацил, ксантин динатрия), растворенных в воде для инъекций.</p> | E23: 42131 | F23: 1 | G23: 0 | H23: https://grls.rosminzdrav.ru/InstrImg/2021/10/06/1474147/01e6e663-0f1b-4047-bdc9-365d6ba31c8a.pdf | I23: 45119
A24: 23 | B24: =VLOOKUP(A24,[1]vaccines!A:B,2) -> Regevac_0_5 | C24: 1 детская доза (0,5 мл) вакцины содержит: Действующее вещество: очищенный поверхностный антиген вируса гепатита В (HBsAg) — 10 мкг. Вспомогательные вещества: алюминия гидроксид — 0,25 мг. Компоненты буферного раствора: натрия хлорид; натрия гидрофосфат; натрия дигидрофосфата дигидрат; 2 М раствор натрия гидроксида до рН 6,95–7,05; вода для инъекций. Данный препарат содержит менее 1 ммоль (23 мг) натрия на дозу. | D24: <p>1&nbsp;детская доза (0,5&nbsp;мл) вакцины содержит:</p> <p><i>Действующее вещество:</i> очищенный поверхностный антиген вируса гепатита В (HBsAg) — 10&nbsp;мкг.</p> <p><i>Вспомогательные вещества:</i> алюминия гидроксид — 0,25&nbsp;мг.</p> <p><i>Компоненты буферного раствора:</i> натрия хлорид; натрия гидрофосфат; натрия дигидрофосфата дигидрат; 2&nbsp;М раствор натрия гидроксида до рН&nbsp;6,95–7,05; вода для инъекций.</p> <p>Данный препарат содержит менее 1&nbsp;ммоль (23&nbsp;мг) натрия на дозу.</p> | E24: 45216 | F24: 1 | G24: 0 | H24: https://grls.rosminzdrav.ru/InstrImg/2025/06/16/1518193/6df836e1-9750-4ca5-be05-590641b808ac.pdf | I24: =I23 -> 45119 | J24: 45988
A25: 24 | B25: =VLOOKUP(A25,[1]vaccines!A:B,2) -> HepB_Combiotech_0_5 | C25: 1 доза для детей (0,5 мл) содержит: • Антиген вируса гепатита В поверхностный рекомбинантный (HBsAg) (серотип ау и/или ad)¹·² — 10 мкг ¹ Получен из дрожжевых клеток Saccharomyces cerevisiae (серотип ау) и/или Hansenula polymorpha (серотип ау и/или ad) по технологии рекомбинантной ДНК. ² Адсорбированный на алюминия гидроксиде (0,25 мг Al³⁺). Перечень вспомогательных веществ: • Натрия дигидрофосфат дигидрат; • Натрия хлорид; • Натрия гидроксид; • Вода для инъекций. | D25: <p>1&nbsp;доза для детей (0,5&nbsp;мл) содержит: <ul><li>Антиген вируса гепатита В поверхностный рекомбинантный (HBsAg) (серотип <i>ау</i> и/или <i>ad</i>)¹<sup>,</sup>² — 10&nbsp;мкг</li></ul> ¹&nbsp;Получен из дрожжевых клеток <i>Saccharomyces cerevisiae</i> (серотип <i>ау</i>) и/или <i>Hansenula polymorpha</i> (серотип <i>ау</i> и/или <i>ad</i>) по технологии рекомбинантной ДНК.<br> ²&nbsp;Адсорбированный на алюминия гидроксиде (0,25&nbsp;мг Al³⁺).<br><br> <i>Перечень вспомогательных веществ:</i> <ul><li>Натрия дигидрофосфат дигидрат;</li> <li>Натрия хлорид;</li> <li>Натрия гидроксид;</li> <li>Вода для инъекций.</li></ul></p> | E25: 46056 | F25: 1 | G25: 0 | H25: https://grls.rosminzdrav.ru/InstrImg/2026/03/04/1527238/fe2adafe-5094-4da2-bbba-1a640a0ceb4e.pdf | I25: =I24 -> 45119 | J25: 46130
A26: 25 | B26: =VLOOKUP(A26,[1]vaccines!A:B,2) -> Euvax_B_0_5 | C26: Доза для детей (0,5 мл): Активный компонент: • Поверхностный антиген вируса гепатита В (HBsAg) очищенный — 10 мкг. Вспомогательные вещества: • Гель алюминия гидроксида (по алюминию) — 0,25 мг. • Калия дигидрофосфат (буферный агент) — q.s. • Натрия гидрофосфат (буферный агент) — q.s. • Натрия хлорид — 4,25 мг. • Вода для инъекций — до 0,5 мл. | D26: <p>Доза для детей (0,5&nbsp;мл):</p> <p><i>Активный компонент:</i> <ul><li>Поверхностный антиген вируса гепатита В (HBsAg) очищенный — 10&nbsp;мкг.</li></ul> <i>Вспомогательные вещества:</i> <ul><li>Гель алюминия гидроксида (по алюминию) — 0,25&nbsp;мг.</li> <li>Калия дигидрофосфат (буферный агент) — q.s.</li> <li>Натрия гидрофосфат (буферный агент) — q.s.</li> <li>Натрия хлорид — 4,25&nbsp;мг.</li> <li>Вода для инъекций — до 0,5&nbsp;мл.</li></ul></p> | E26: 42410 | F26: 2 | G26: 1 | H26: https://grls.rosminzdrav.ru/InstrImg/2019/8/6/1445331/%D0%9F_N011073[2016]_1.pdf | I26: 45120
A27: 26 | B27: =VLOOKUP(A27,[1]vaccines!A:B,2) -> Euvax_B_1_0 | C27: Доза для взрослых (1,0 мл): Активный компонент: • Поверхностный антиген вируса гепатита В (HBsAg) очищенный — 20 мкг. Вспомогательные вещества: • Гель алюминия гидроксида (по алюминию) — 0,50 мг. • Калия дигидрофосфат (буферный агент) — q.s. • Натрия гидрофосфат (буферный агент) — q.s. • Натрия хлорид — 8,50 мг. • Вода для инъекций — до 1,0 мл. | D27: <p>Доза для взрослых (1,0&nbsp;мл):</p> <p><i>Активный компонент:</i> <ul><li>Поверхностный антиген вируса гепатита В (HBsAg) очищенный — 20&nbsp;мкг.</li></ul> <i>Вспомогательные вещества:</i> <ul><li>Гель алюминия гидроксида (по алюминию) — 0,50&nbsp;мг.</li> <li>Калия дигидрофосфат (буферный агент) — q.s.</li> <li>Натрия гидрофосфат (буферный агент) — q.s.</li> <li>Натрия хлорид — 8,50&nbsp;мг.</li> <li>Вода для инъекций — до 1,0&nbsp;мл.</li></ul></p> | E27: 42410 | F27: 2 | G27: 1 | H27: https://grls.rosminzdrav.ru/InstrImg/2019/8/6/1445331/%D0%9F_N011073[2016]_1.pdf | I27: 45120
A28: 27 | B28: =VLOOKUP(A28,[1]vaccines!A:B,2) -> Cervarix | C28: 1 прививочная доза (0,5 мл) содержит: Действующие вещества: • L1 протеин вируса папилломы человека типа 16 (ВПЧ-16L1) — 20 мкг. • L1 протеин вируса папилломы человека типа 18 (ВПЧ-18L1) — 20 мкг. Адъювантная система AS04: • Алюминия гидроксид — 0,5 мг. • 3-О-дезацил-4’-монофосфориллипид А — 50 мкг. Перечень вспомогательных веществ: • Натрия хлорид — 4,4 мг. • Натрия дигидрофосфата дигидрат — 0,624 мг. • Вода для инъекций — q.s. до 0,5 мл. | D28: <p>1&nbsp;прививочная доза (0,5&nbsp;мл) содержит:</p> <p><i>Действующие вещества:</i> <ul><li>L1&nbsp;протеин вируса папилломы человека типа&nbsp;16 (ВПЧ-16L1) — 20&nbsp;мкг.</li> <li>L1&nbsp;протеин вируса папилломы человека типа&nbsp;18 (ВПЧ-18L1) — 20&nbsp;мкг.</li></ul> <i>Адъювантная система AS04:</i> <ul><li>Алюминия гидроксид — 0,5&nbsp;мг.</li> <li>3-О-дезацил-4’-монофосфориллипид&nbsp;А — 50&nbsp;мкг.</li></ul> <i>Перечень вспомогательных веществ:</i> <ul><li>Натрия хлорид — 4,4&nbsp;мг.</li> <li>Натрия дигидрофосфата дигидрат — 0,624&nbsp;мг.</li> <li>Вода для инъекций — q.s. до 0,5&nbsp;мл.</li></ul></p> | E28: 45513 | H28: https://lk.regmed.ru/Register/GetPDFfromDA?ID=1611660161 | I28: =I27 -> 45120 | J28: 45589
A29: 28 | B29: =VLOOKUP(A29,[1]vaccines!A:B,2) -> Gardasil_4 | C29: Одна доза (0,5 мл) содержит Действующие вещества: рекомбинантные антигены — L1 белок вируса папилломы человека в следующих количествах: тип 6 — 20 мкг, тип 11 — 40 мкг, тип 16 — 40 мкг, тип 18 — 20 мкг. Перечень вспомогательных веществ: • Алюминий в виде алюминия гидроксифосфата сульфата аморфного. • Натрия хлорид. • L-гистидин. • Полисорбат-80. • Натрия борат. • Вода для инъекций. Консервантов и антибиотиков не содержит. | D29: <p>Одна доза (0,5&nbsp;мл) содержит </p> <p><i>Действующие вещества:</i> рекомбинантные антигены — L1&nbsp;белок вируса папилломы человека в следующих количествах: тип&nbsp;6 — 20&nbsp;мкг, тип&nbsp;11 — 40&nbsp;мкг, тип&nbsp;16 — 40&nbsp;мкг, тип&nbsp;18 — 20&nbsp;мкг.</p> <p><i>Перечень вспомогательных веществ:</i> <ul><li>Алюминий в виде алюминия гидроксифосфата сульфата аморфного.</li> <li>Натрия хлорид.</li> <li>L-гистидин.</li> <li>Полисорбат-80.</li> <li>Натрия борат.</li> <li>Вода для инъекций.</li></ul> Консервантов и антибиотиков не содержит.</p> | E29: 45386 | H29: https://lk.regmed.ru/Register/GetPDFfromDA?ID=1575625191 | I29: 45120 | J29: 45483
A30: 29 | B30: =VLOOKUP(A30,[1]vaccines!A:B,2) -> Sputnik | C30: 1 доза (0,5 мл) содержит: Компонент I рекомбинантные аденовирусные частицы 26 серотипа¹, содержащие ген белка S вируса SARS-CoV-2² — (1,0±0,5)х10¹¹ частиц; Компонент II рекомбинантные аденовирусные частицы 5 серотипа¹, содержащие ген белка S вируса SARS-CoV-2² — (1,0±0,5)х10¹¹ частиц. ¹ получены из клеток человека (НЕК29З) после трансдукции этих клеток. ² вариант ХВВ штамма омикрон коронавируса SARS-CoV-2. Перечень вспомогательных веществ: Компонент I • Трис(гидроксиметил)аминометан; • Натрия хлорид; • Сахароза; • Полисорбат 80; • Магния хлорида гексагидрат; • ЭДТА динатриевая соль дигидрат; • Этанол 95 %; • Вода для инъекций. Компонент II • Трис(гидроксиметил)аминометан; • Натрия хлорид; • Сахароза; • Полисорбат 80; • Магния хлорида гексагидрат; • ЭДТА динатриевая соль дигидрат; • Этанол 95 %; • Вода для инъекций. | D30: <p>1&nbsp;доза (0,5&nbsp;мл) содержит: <ul><i>Компонент&nbsp;I</i><br> <li>рекомбинантные аденовирусные частицы 26&nbsp;серотипа¹, содержащие ген белка&nbsp;S вируса SARS-CoV-2² — (1,0±0,5)х10¹¹&nbsp;частиц;</li><br> <i>Компонент&nbsp;II</i><br> <li>рекомбинантные аденовирусные частицы 5&nbsp;серотипа¹, содержащие ген белка&nbsp;S вируса SARS-CoV-2² — (1,0±0,5)х10¹¹&nbsp;частиц.</li></ul> ¹&nbsp;получены из клеток человека (НЕК29З) после трансдукции этих клеток.<br> ²&nbsp;вариант ХВВ штамма омикрон коронавируса SARS-CoV-2.<br><br> Перечень вспомогательных веществ: <ul><i>Компонент&nbsp;I</i><br> <li>Трис(гидроксиметил)аминометан;</li> <li>Натрия хлорид;</li> <li>Сахароза;</li> <li>Полисорбат&nbsp;80;</li> <li>Магния хлорида гексагидрат;</li> <li>ЭДТА динатриевая соль дигидрат;</li> <li>Этанол 95&nbsp;%;</li> <li>Вода для инъекций.</li><br> <i>Компонент&nbsp;II</i><br> <li>Трис(гидроксиметил)аминометан;</li> <li>Натрия хлорид;</li> <li>Сахароза;</li> <li>Полисорбат&nbsp;80;</li> <li>Магния хлорида гексагидрат;</li> <li>ЭДТА динатриевая соль дигидрат;</li> <li>Этанол 95&nbsp;%;</li> <li>Вода для инъекций.</li></ul></p> | E30: 45839 | F30: 1 | G30: 0 | H30: https://grls.rosminzdrav.ru/InstrImg/2025/07/21/1519595/f7c8e9e3-baf4-4c2e-949f-a41b75a8ad7c.pdf | I30: 45121 | J30: 45923
A31: 30 | B31: =VLOOKUP(A31,[1]vaccines!A:B,2) -> Sputnik_Lyo | C31: Состав на 1 дозу: Компонент I содержит: Действующее вещество: рекомбинантные аденовирусные частицы 26 серотипа, содержащие ген белка S вируса SARS-CoV-2, в количестве (1,0±0,5)х10¹¹ частиц. Вспомогательные вещества: трис(гидроксиметил)аминометан — 0,24 мг, натрия хлорид — 1,40 мг, сахароза — 73,5 мг, магния хлорида гексагидрат — 20,4 мкг, ЭДТА динатриевая соль дигидрат — 3,8 мкг, полисорбат 80 — 0,05 мкг. Компонент II содержит: Действующее вещество: рекомбинантные аденовирусные частицы 5 серотипа, содержащие ген белка S вируса SARS-CoV-2, в количестве (1,0±0,5)х10¹¹ частиц. Вспомогательные вещества: трис(гидроксиметил)аминометан — 0,24 мг, натрия хлорид — 1,40 мг, сахароза — 73,5 мг, магния хлорида гексагидрат — 20,4 мкг, ЭДТА динатриевая соль дигидрат — 3,8 мкг, полисорбат 80 — 0,05 мкг. | D31: <p>Состав на 1&nbsp;дозу:</p> <p>Компонент&nbsp;I содержит:</p> <p><i>Действующее вещество:</i> рекомбинантные аденовирусные частицы 26&nbsp;серотипа, содержащие ген белка&nbsp;S вируса SARS-CoV-2, в количестве (1,0±0,5)х10¹¹&nbsp;частиц.</p> <p><i>Вспомогательные вещества:</i> трис(гидроксиметил)аминометан — 0,24&nbsp;мг, натрия хлорид — 1,40&nbsp;мг, сахароза — 73,5&nbsp;мг, магния хлорида гексагидрат — 20,4&nbsp;мкг, ЭДТА динатриевая соль дигидрат — 3,8&nbsp;мкг, полисорбат&nbsp;80 — 0,05&nbsp;мкг.</p> <p>Компонент&nbsp;II содержит:</p> <p><i>Действующее вещество:</i> рекомбинантные аденовирусные частицы 5&nbsp;серотипа, содержащие ген белка&nbsp;S вируса SARS-CoV-2, в количестве (1,0±0,5)х10¹¹&nbsp;частиц.</p> <p><i>Вспомогательные вещества:</i> трис(гидроксиметил)аминометан — 0,24&nbsp;мг, натрия хлорид — 1,40&nbsp;мг, сахароза — 73,5&nbsp;мг, магния хлорида гексагидрат — 20,4&nbsp;мкг, ЭДТА динатриевая соль дигидрат — 3,8&nbsp;мкг, полисорбат&nbsp;80 — 0,05&nbsp;мкг.</p> | E31: 44631 | F31: 2 | G31: 1 | H31: https://grls.rosminzdrav.ru/InstrImg/2022/03/24/1479420/567f4c1a-9b51-46b3-aa9d-6be72c91e48b.pdf | I31: 45121
A32: 31 | B32: =VLOOKUP(A32,[1]vaccines!A:B,2) -> EpiVacCorona | C32: 1 доза (0,5 мл) вакцины содержит: Действующие вещества: • пептидный антиген № 1 белка S вируса SARS-CoV-2, конъюгированный на белок-носитель — (75±15) мкг; • пептидный антиген № 2 белка S вируса SARS-CoV-2, конъюгированный на белок-носитель — (75±15) мкг; • пептидный антиген № 3 белка S вируса SARS-CoV-2, конъюгированный на белок-носитель — (75±15) мкг. Вспомогательные вещества: • алюминия гидроксид в пересчете на (Al³⁺) — (0,60±0,10) мг; • калия дигидрофосфат — (0,12±0,01) мг; • калия хлорид — (0,10±0,01) мг; • натрия гидрофосфата додекагидрат — (1,82±0,10) мг; • натрия хлорид — (4,00±0,20) мг; • вода для инъекций — до 0,5 мл. Консервантов и антибиотиков не содержит. | D32: <p>1&nbsp;доза (0,5&nbsp;мл) вакцины содержит:</p> <p><i>Действующие вещества:</i> <ul><li>пептидный антиген №&nbsp;1 белка&nbsp;S вируса SARS-CoV-2, конъюгированный на белок-носитель — (75±15)&nbsp;мкг;</li> <li>пептидный антиген №&nbsp;2 белка&nbsp;S вируса SARS-CoV-2, конъюгированный на белок-носитель — (75±15)&nbsp;мкг;</li> <li>пептидный антиген №&nbsp;3 белка&nbsp;S вируса SARS-CoV-2, конъюгированный на белок-носитель — (75±15)&nbsp;мкг.</li></ul> <i>Вспомогательные вещества:</i> <ul><li>алюминия гидроксид в пересчете на (Al³⁺) — (0,60±0,10)&nbsp;мг;</li> <li>калия дигидрофосфат — (0,12±0,01)&nbsp;мг;</li> <li>калия хлорид — (0,10±0,01)&nbsp;мг;</li> <li>натрия гидрофосфата додекагидрат — (1,82±0,10)&nbsp;мг;</li> <li>натрия хлорид — (4,00±0,20)&nbsp;мг;</li> <li>вода для инъекций — до 0,5&nbsp;мл.</li></ul> Консервантов и антибиотиков не содержит.</p> | E32: 44911 | F32: 1 | G32: 0 | H32: https://grls.rosminzdrav.ru/InstrImg/2023/01/09/1490224/e76560fa-e72e-49eb-8daf-91f3d1403e22.pdf | I32: 45122
A33: 32 | B33: =VLOOKUP(A33,[1]vaccines!A:B,2) -> Grippol_Microgen | C33: 1 доза (0,5 мл) содержит: Вакцина без консерванта: • гемагглютинин вируса гриппа подтипа A(H₁N₁) — 5 мкг; • гемагглютинин вируса гриппа подтипа A(H₃N₂) — 5 мкг; • гемагглютинин вируса гриппа типа В — 11 мкг; • азоксимера бромид (Полиоксидоний) — 500 мкг. Вакцина с консервантом: • гемагглютинин вируса гриппа подтипа A(H₁N₁) — 5 мкг; • гемагглютинин вируса гриппа подтипа A(H₃N₂) — 5 мкг; • гемагглютинин вируса гриппа типа В — 11 мкг; • азоксимера бромид (Полиоксидоний) — 500 мкг; • консервант — тиомерсал (мертиолят) — (50,0±7,5) мкг. Примечание. 1. На стадиях производства препарата в качестве растворителя и стабилизатора pH используется фосфатный буферный раствор (ФБР): для препарата без консерванта ФБР №1, препарата с консервантом — ФБР №2. Состав ФБР №1: 9 г натрия хлорида, 1,5 г натрия гидрофосфата, 0,12 – 0,14 г калия дигидрофосфата, вода для инъекций до 1 л. Состав ФБР №2: 9 г натрия хлорида, 1,5 г натрия гидрофосфата, 0,12 – 0,14 г калия дигидрофосфата, 0,85 мл тиомерсала (мертиолята) раствора 1%, вода для инъекций до 1 л. 2. Полиоксидоний представляет собой смесь активного вещества полиоксидония (азоксимера бромида) и вспомогательных веществ: маннитола, повидона и бета-каротена водного раствора, получаемая в результате непрерывного технологического цикла. | D33: <p>1&nbsp;доза (0,5&nbsp;мл) содержит:</p> <p><i>Вакцина без консерванта:</i> <ul><li>гемагглютинин вируса гриппа подтипа&nbsp;A(H₁N₁) — 5&nbsp;мкг;</li> <li>гемагглютинин вируса гриппа подтипа&nbsp;A(H₃N₂) — 5&nbsp;мкг;</li> <li>гемагглютинин вируса гриппа типа&nbsp;В — 11&nbsp;мкг;</li> <li>азоксимера бромид (Полиоксидоний) — 500&nbsp;мкг.</li></ul> <i>Вакцина с консервантом:</i> <ul><li>гемагглютинин вируса гриппа подтипа&nbsp;A(H₁N₁) — 5&nbsp;мкг;</li> <li>гемагглютинин вируса гриппа подтипа&nbsp;A(H₃N₂) — 5&nbsp;мкг;</li> <li>гемагглютинин вируса гриппа типа&nbsp;В — 11&nbsp;мкг;</li> <li>азоксимера бромид (Полиоксидоний) — 500&nbsp;мкг;</li> <li>консервант — тиомерсал (мертиолят) — (50,0±7,5)&nbsp;мкг.</li></ul></p> <p><ul>Примечание. 1. На стадиях производства препарата в качестве растворителя и стабилизатора pH используется фосфатный буферный раствор (ФБР):<br> для препарата без консерванта ФБР&nbsp;№1,<br> препарата с консервантом — ФБР&nbsp;№2.<br> Состав ФБР&nbsp;№1: 9&nbsp;г натрия хлорида, 1,5&nbsp;г натрия гидрофосфата, 0,12&nbsp;–&nbsp;0,14&nbsp;г калия дигидрофосфата, вода для инъекций до 1&nbsp;л.<br> Состав ФБР&nbsp;№2: 9&nbsp;г натрия хлорида, 1,5&nbsp;г натрия гидрофосфата, 0,12&nbsp;–&nbsp;0,14&nbsp;г калия дигидрофосфата, 0,85&nbsp;мл тиомерсала (мертиолята) раствора 1%, вода для инъекций до 1&nbsp;л.<br> 2. Полиоксидоний представляет собой смесь активного вещества полиоксидония (азоксимера бромида) и вспомогательных веществ: маннитола, повидона и бета-каротена водного раствора, получаемая в результате непрерывного технологического цикла.</ul></p> | E33: 41411 | F33: 1 | G33: 0 | H33: https://grls.rosminzdrav.ru/InstrImg/2020/11/12/37422/bb3f3b49-b450-42cf-a999-bcc087b2eb05.pdf | I33: 45122 | K33: проверено Елена Савинова
A34: 33 | B34: =VLOOKUP(A34,[1]vaccines!A:B,2) -> Grippol_Petrovax | C34: Одна иммунизирующая доза (0,5 мл) содержит по 5 мкг гемагглютинина эпидемически актуальных штаммов вирусов гриппа подтипов A (H₁N₁ и H₃N₂) и 11 мкг гемагглютинина вируса гриппа типа В, 500 мкг иммуноадъюванта Полиоксидоний® в фосфатно-солевом буферном растворе; консервант: мертиолят — 50 мкг. | D34: <p>Одна иммунизирующая доза (0,5&nbsp;мл) содержит по 5&nbsp;мкг гемагглютинина эпидемически актуальных штаммов вирусов гриппа подтипов&nbsp;A (H₁N₁ и H₃N₂) и 11&nbsp;мкг гемагглютинина вируса гриппа типа&nbsp;В, 500&nbsp;мкг иммуноадъюванта Полиоксидоний® в фосфатно-солевом буферном растворе; консервант: мертиолят — 50&nbsp;мкг.</p> | E34: 40634 | F34: 1 | G34: 0 | H34: https://grls.rosminzdrav.ru/InstrImg/2020/11/23/1413288/cb3a391e-05f5-41e6-9963-8f102193f7e0.pdf | I34: 45122
A35: 34 | B35: =VLOOKUP(A35,[1]vaccines!A:B,2) -> Grippol_plus_0_5 | C35: 1 доза (0,5 мл) содержит: Действующие вещества: Антиген вируса гриппа типа А (H₁N₁)* с содержанием гемагглютинина — 5 мкг Антиген вируса гриппа типа А (H₃N₂)* с содержанием гемагглютинина — 5 мкг Антиген вируса гриппа типа В* с содержанием гемагглютинина — 5 мкг Полиоксидоний® (Азоксимера бромид) — 500 мкг * Штаммы антигенов вируса гриппа в соответствии с рекомендациями Всемирной организации здравоохранения (ВОЗ) на текущий эпидемический сезон для Северного полушария. Вакцинные штаммы выращены на куриных эмбрионах. Перечень вспомогательных веществ: Фосфатно-солевой буферный раствор Состав фосфатно-солевого буферного раствора на 1 дозу (0,5 мл) лекарственного средства: калия хлорид — 100 мкг, калия дигидрофосфат — 100 мкг, динатрия гидрофосфат дигидрат — 670 мкг, натрия хлорид — 4000 мкг, вода для инъекций — до 0,5 мл. Данный препарат содержит менее 1 ммоль (23 мг) натрия на 1 дозу, то есть по сути не содержит натрия. Данный препарат содержит калий менее 1 ммоль (39 мг) на 1 дозу, то есть по сути не содержит калия. | D35: <p>1&nbsp;доза (0,5&nbsp;мл) содержит:<br><br> <i>Действующие вещества:</i> <ul><li>Антиген вируса гриппа типа А (H₁N₁)* с содержанием гемагглютинина — 5&nbsp;мкг</li> <li>Антиген вируса гриппа типа А (H₃N₂)* с содержанием гемагглютинина — 5&nbsp;мкг</li> <li>Антиген вируса гриппа типа В* с содержанием гемагглютинина — 5&nbsp;мкг</li> <li>Полиоксидоний® (Азоксимера бромид) — 500&nbsp;мкг</li></ul> *&nbsp;Штаммы антигенов вируса гриппа в соответствии с рекомендациями Всемирной организации здравоохранения (ВОЗ) на текущий эпидемический сезон для Северного полушария.<br><br> Вакцинные штаммы выращены на куриных эмбрионах.</p> <p><i>Перечень вспомогательных веществ:</i> <ul><li>Фосфатно-солевой буферный раствор</li> Состав фосфатно-солевого буферного раствора на 1&nbsp;дозу (0,5&nbsp;мл) лекарственного средства: калия хлорид — 100&nbsp;мкг, калия дигидрофосфат — 100&nbsp;мкг, динатрия гидрофосфат дигидрат — 670&nbsp;мкг, натрия хлорид — 4000&nbsp;мкг, вода для инъекций — до 0,5&nbsp;мл.</ul> Данный препарат содержит менее 1&nbsp;ммоль (23&nbsp;мг) натрия на 1&nbsp;дозу, то есть по сути не содержит натрия.<br> Данный препарат содержит калий менее 1&nbsp;ммоль (39&nbsp;мг) на 1&nbsp;дозу, то есть по сути не содержит калия.</p> | E35: 45182 | H35: https://lk.regmed.ru/Register/GetPDFfromDA?ID=1512826451 | I35: 45122 | J35: 45483
A36: 35 | B36: =VLOOKUP(A36,[1]vaccines!A:B,2) -> Sovigripp | C36: Действующие вещества*: гемагглютинин вируса гриппа подтипа А(H₁N₁); гемагглютинин вируса гриппа подтипа А(H₃N₂); гемагглютинин вируса гриппа типа В. 0,5 мл (1 доза) содержит: Вакцина с консервантом • гемагглютинин вируса гриппа подтипа A(H₁N₁) — 5 мкг; • гемагглютинин вируса гриппа подтипа A(H₃N₂) — 5 мкг; • гемагглютинин вируса гриппа типа В — 11 мкг. Вакцина без консерванта • гемагглютинин вируса гриппа подтипа A(H₁N₁) — 5 мкг; • гемагглютинин вируса гриппа подтипа A(H₃N₂) — 5 мкг; • гемагглютинин вируса гриппа типа В — 11 мкг. * Действующие вещества выделены из очищенных вирионов вируса гриппа А и В, полученных из вируссодержащей аллантоисной жидкости куриных эмбрионов от клинически здоровых кур с использованием в производственном процессе двух технологий (эритроцитарной или безэритроцитарной). Штаммовый состав вакцины соответствует рекомендациям Всемирной организации здравоохранения (ВОЗ) для Северного полушария. Вакцина содержит адъювант: сополимер 2-метил-5-винилпиридина и N-винилпирролидона (торговое наименование — СОВИДОН) — 500 мкг. СОВИГРИПП Вакцина гриппозная инактивированная субъединичная может содержать следы яиц (белки куриного яйца, в том числе овальбумин не более 0,1 мкг/мл). Перечень вспомогательных веществ: Вакцина с консервантом • Сополимер 2-метил-5-винилпиридина и N-винилпирролидона (адъювант). • Тиомерсал (консервант). • Фосфатно-солевой буферный раствор (натрия хлорид, динатрия гидрофосфат додекагидрат, калия дигидрофосфат, тиомерсал, вода для инъекций). Вакцина без консерванта • Сополимер 2-метил-5-винилпиридина и N-винилпирролидона (адъювант). • Фосфатно-солевой буферный раствор (натрия хлорид, динатрия гидрофосфат додекагидрат, калия дигидрофосфат, вода для инъекций). | D36: <p>Действующие вещества*: гемагглютинин вируса гриппа подтипа А(H₁N₁); гемагглютинин вируса гриппа подтипа А(H₃N₂); гемагглютинин вируса гриппа типа В.<br><br> 0,5&nbsp;мл (1&nbsp;доза) содержит:<br> <i>Вакцина с консервантом</i> <ul><li>гемагглютинин вируса гриппа подтипа&nbsp;A(H₁N₁) — 5&nbsp;мкг;</li> <li>гемагглютинин вируса гриппа подтипа&nbsp;A(H₃N₂) — 5&nbsp;мкг;</li> <li>гемагглютинин вируса гриппа типа&nbsp;В — 11&nbsp;мкг.</li></ul> <i>Вакцина без консерванта</i> <ul><li>гемагглютинин вируса гриппа подтипа&nbsp;A(H₁N₁) — 5&nbsp;мкг;</li> <li>гемагглютинин вируса гриппа подтипа&nbsp;A(H₃N₂) — 5&nbsp;мкг;</li> <li>гемагглютинин вируса гриппа типа&nbsp;В — 11&nbsp;мкг.</li></ul> *&nbsp;Действующие вещества выделены из очищенных вирионов вируса гриппа А и В, полученных из вируссодержащей аллантоисной жидкости куриных эмбрионов от клинически здоровых кур с использованием в производственном процессе двух технологий (эритроцитарной или безэритроцитарной).<br><br> Штаммовый состав вакцины соответствует рекомендациям Всемирной организации здравоохранения (ВОЗ) для Северного полушария.<br> Вакцина содержит адъювант: сополимер 2-метил-5-винилпиридина и N-винилпирролидона (торговое наименование — СОВИДОН) — 500&nbsp;мкг.<br> СОВИГРИПП Вакцина гриппозная инактивированная субъединичная может содержать следы яиц (белки куриного яйца, в том числе овальбумин не более 0,1&nbsp;мкг/мл).<br><br> Перечень вспомогательных веществ:<br> <i>Вакцина с консервантом</i> <ul><li>Сополимер 2-метил-5-винилпиридина и N-винилпирролидона (адъювант).</li> <li>Тиомерсал (консервант).</li> <li>Фосфатно-солевой буферный раствор (натрия хлорид, динатрия гидрофосфат додекагидрат, калия дигидрофосфат, тиомерсал, вода для инъекций).</li></ul> <i>Вакцина без консерванта</i> <ul><li>Сополимер 2-метил-5-винилпиридина и N-винилпирролидона (адъювант).</li> <li>Фосфатно-солевой буферный раствор (натрия хлорид, динатрия гидрофосфат додекагидрат, калия дигидрофосфат, вода для инъекций).</li></ul></p> | E36: 45580 | H36: https://lk.regmed.ru/Register/GetPDFfromDA?ID=1633580161 | I36: =I35 -> 45122 | J36: 45622
A37: 36 | B37: =VLOOKUP(A37,[1]vaccines!A:B,2) -> Ultrix | C37: 1 доза (0,5 мл) содержит Действующие вещества: Вирусы гриппа, культивированные на куриных эмбрионах, инактивированные, расщепленные, представленные штаммами, эквивалентными следующим: • А/(H₁N₁) — (15±2,0) мкг ГА; • А/(H₃N₂) — (15±2,0) мкг ГА; • В/ — (15±2,0) мкг ГА. Перечень вспомогательных веществ: Консервант – мертиолят или не содержит консерванта, фосфатно-солевой буферный раствор (натрия хлорид, динатрия гидрофосфат дигидрат, натрия дигидрофосфат дигидрат, вода для инъекций). | D37: <p>1&nbsp;доза (0,5&nbsp;мл) содержит</p> <p><i>Действующие вещества:</i><br> Вирусы гриппа, культивированные на куриных эмбрионах, инактивированные, расщепленные, представленные штаммами, эквивалентными следующим: <ul><li>А/(H₁N₁) — (15±2,0)&nbsp;мкг ГА;</li> <li>А/(H₃N₂) — (15±2,0)&nbsp;мкг ГА;</li> <li>В/ — (15±2,0)&nbsp;мкг ГА.</li></ul> <i>Перечень вспомогательных веществ:</i><br> Консервант – мертиолят или не содержит консерванта, фосфатно-солевой буферный раствор (натрия хлорид, динатрия гидрофосфат дигидрат, натрия дигидрофосфат дигидрат, вода для инъекций).</p> | E37: 45211 | H37: https://lk.regmed.ru/Register/GetPDFfromDA?ID=1523760571 | I37: 45123 | J37: 45483
A38: 37 | B38: =VLOOKUP(A38,[1]vaccines!A:B,2) -> Flu_M | C38: 1 доза (0,5 мл) содержит: Препарат с консервантом: • Гемагглютинин вируса гриппа подтипа А(Н1N1)¹·² — 15 мкг • Гемагглютинин вируса гриппа подтипа A(H3N2)¹·² — 15 мкг • Гемагглютинин вируса гриппа типа В¹·² — 15 мкг Препарат без консерванта: • Гемагглютинин вируса гриппа подтипа А(Н1N1)¹·² — 15 мкг • Гемагглютинин вируса гриппа подтипа A(H3N2)¹·² — 15 мкг • Гемагглютинин вируса гриппа типа В¹·² — 15 мкг ¹ Действующие вещества выделены из очищенных вирионов вируса гриппа А и В, полученных из вируссодержащей аллантоисной жидкости куриных эмбрионов. ² Штаммовый состав вакцины изменяется каждый год в соответствии с эпидемиологической ситуацией и рекомендациями Всемирной организации здравоохранения (ВОЗ) для Северного полушария. Вспомогательные вещества препарата с консервантом: • Тиомерсал (консервант) • Тритон Х-100 (стабилизатор) • Фосфатно-солевой буферный раствор Вспомогательные вещества препарата без консерванта: • Тритон Х-100 (стабилизатор) • Фосфатно-солевой буферный раствор Состав фосфатно-солевого буферного раствора на дозу лекарственного препарата (0,5 мл): натрия хлорид, динатрия фосфата додекагидрат, калия дигидрофосфат, вода для инъекций. | D38: <p>1&nbsp;доза (0,5&nbsp;мл) содержит:<br><br> <i>Препарат с консервантом:</i> <ul><li>Гемагглютинин вируса гриппа подтипа А(Н1N1)¹<sup>,</sup>² — 15&nbsp;мкг</li> <li>Гемагглютинин вируса гриппа подтипа A(H3N2)¹<sup>,</sup>² — 15&nbsp;мкг</li> <li>Гемагглютинин вируса гриппа типа В¹<sup>,</sup>² — 15&nbsp;мкг</li></ul> <i>Препарат без консерванта:</i> <ul><li>Гемагглютинин вируса гриппа подтипа А(Н1N1)¹<sup>,</sup>² — 15&nbsp;мкг</li> <li>Гемагглютинин вируса гриппа подтипа A(H3N2)¹<sup>,</sup>² — 15&nbsp;мкг</li> <li>Гемагглютинин вируса гриппа типа В¹<sup>,</sup>² — 15&nbsp;мкг</li></ul> ¹ Действующие вещества выделены из очищенных вирионов вируса гриппа А и В, полученных из вируссодержащей аллантоисной жидкости куриных эмбрионов.<br> ² Штаммовый состав вакцины изменяется каждый год в соответствии с эпидемиологической ситуацией и рекомендациями Всемирной организации здравоохранения (ВОЗ) для Северного полушария.<br><br> <i>Вспомогательные вещества препарата с консервантом:</i> <ul><li>Тиомерсал (консервант)</li> <li>Тритон Х-100 (стабилизатор)</li> <li>Фосфатно-солевой буферный раствор</li></ul> <i>Вспомогательные вещества препарата без консерванта:</i> <ul><li>Тритон Х-100 (стабилизатор)</li> <li>Фосфатно-солевой буферный раствор</li></ul> Состав фосфатно-солевого буферного раствора на дозу лекарственного препарата (0,5&nbsp;мл): натрия хлорид, динатрия фосфата додекагидрат, калия дигидрофосфат, вода для инъекций.</p> | E38: 46035 | F38: 1 | G38: 0 | H38: https://grls.rosminzdrav.ru/InstrImg/2026/02/10/1526281/07a2f661-6334-4894-8117-0ad7563ba4ef.pdf | I38: =I37 -> 45123 | J38: 46130
A39: 38 | B39: =VLOOKUP(A39,[1]vaccines!A:B,2) -> Vaxigrip | C39: На 1 дозу вакцины (0,5 мл): Действующие вещества: Вирусы гриппа, культивированные на куриных эмбрионах, инактивированные расщепленные, представленные штаммами, эквивалентными следующим: • А/(H₁N₁)* — 15 мкг гемагглютинина; • А/(H₃N₂)* — 15 мкг гемагглютинина; • В/* — 15 мкг гемагглютинина. * - Указываются актуальные штаммы, рекомендованные ВОЗ и решением ЕС для Северного полушария на текущий эпидемический сезон. Вспомогательные вещества: • Буферный раствор, содержащий натрия хлорид, калия хлорид, натрия гидрофосфата дигидрат, калия дигидрофосфат, воду для инъекций — до 0,5 мл. Не содержит адъювантов и консервантов. Производственные примеси (в следовых количествах): формальдегид, октоксинол-9, неомицин, овальбумин. | D39: <p>На 1&nbsp;дозу вакцины (0,5&nbsp;мл):</p> <p><i>Действующие вещества:</i></p> <p>Вирусы гриппа, культивированные на куриных эмбрионах, инактивированные расщепленные, представленные штаммами, эквивалентными следующим: <ul><li>А/(H₁N₁)* — 15&nbsp;мкг гемагглютинина;</li> <li>А/(H₃N₂)* — 15&nbsp;мкг гемагглютинина;</li> <li>В/* — 15&nbsp;мкг гемагглютинина.</li></ul></p> <p>* - Указываются актуальные штаммы, рекомендованные ВОЗ и решением ЕС для Северного полушария на текущий эпидемический сезон.</p> <p><i>Вспомогательные вещества:</i> <ul><li>Буферный раствор, содержащий натрия хлорид, калия хлорид, натрия гидрофосфата дигидрат, калия дигидрофосфат, воду для инъекций — до 0,5&nbsp;мл.</li></ul></p> <p>Не содержит адъювантов и консервантов.<p> <p>Производственные примеси (в следовых количествах): формальдегид, октоксинол-9, неомицин, овальбумин.</p> | E39: 43598 | F39: 1 | G39: 0 | H39: https://grls.rosminzdrav.ru/InstrImg/2021/12/14/1476333/f3799188-0d95-48db-a0ce-bb1396d44765.pdf | I39: 45123
A40: 39 | B40: =VLOOKUP(A40,[1]vaccines!A:B,2) -> Influvac | C40: 1 доза (0,5 мл) содержит: • Гемагглютинин вируса гриппа¹ подтипа A(H1N1)²·³ — 15 мкг • Гемагглютинин вируса гриппа¹ подтипа A(H3N2)²·³ — 15 мкг • Гемагглютинин вируса гриппа¹ подтипа B²·³ — 15 мкг ¹ Выращены на куриных эмбрионах здоровых кур. ² После названия типа антигена выносится название штамма, рекомендованного Всемирной организацией здравоохранения (ВОЗ) на текущий эпидемический сезон гриппа для Северного полушария. ³ Штаммовый состав вакцины соответствует рекомендациям Всемирной организации здравоохранения (ВОЗ) для Северного полушария и решению компетентного регуляторного органа по составу гриппозных вакцин в отношении данного сезона (год/год). Перечень вспомогательных веществ: • Калия хлорид; • Калия дигидрофосфат; • Динатрия фосфата дигидрат; • Натрия хлорид; • Кальция хлорида дигидрат; • Магния хлорида гексагидрат; • Вода для инъекций. | D40: <p>1&nbsp;доза (0,5&nbsp;мл) содержит: <ul><li>Гемагглютинин вируса гриппа¹ подтипа A(H1N1)²<sup>,</sup>³ — 15 &nbsp;мкг</li> <li>Гемагглютинин вируса гриппа¹ подтипа A(H3N2)²<sup>,</sup>³ — 15&nbsp;мкг</li> <li>Гемагглютинин вируса гриппа¹ подтипа B²<sup>,</sup>³ — 15&nbsp;мкг</li></ul> ¹&nbsp;Выращены на куриных эмбрионах здоровых кур.<br> ²&nbsp;После названия типа антигена выносится название штамма, рекомендованного Всемирной организацией здравоохранения (ВОЗ) на текущий эпидемический сезон гриппа для Северного полушария.<br> ³&nbsp;Штаммовый состав вакцины соответствует рекомендациям Всемирной организации здравоохранения (ВОЗ) для Северного полушария и решению компетентного регуляторного органа по составу гриппозных вакцин в отношении данного сезона (год/год).<br><br> <i>Перечень вспомогательных веществ:</i> <ul><li>Калия хлорид;</li> <li>Калия дигидрофосфат;</li> <li>Динатрия фосфата дигидрат;</li> <li>Натрия хлорид;</li> <li>Кальция хлорида дигидрат;</li> <li>Магния хлорида гексагидрат;</li> <li>Вода для инъекций.</li></ul></p> | E40: 46066 | F40: 1 | G40: 0 | H40: https://grls.rosminzdrav.ru/InstrImg/2026/03/05/1527284/4a34f8fb-090f-4a41-bab9-0d4194977316.pdf | I40: =I39 -> 45123 | J40: 46130
A41: 40 | B41: =VLOOKUP(A41,[1]vaccines!A:B,2) -> Ultrix_quadri | C41: 0,5 мл (1 доза) содержит Действующие вещества: • Антиген вируса гриппа типа A (H₁N₁) — (15±2,0) мкг ГА; • Антиген вируса гриппа типа А (H₃N₂) — (15±2,0) мкг ГА; • Антиген вируса гриппа типа В (линия Yamagata) — (15±2,0) мкг ГА; • Антиген вируса гриппа типа В (линия Victoria) — (15±2,0) мкг ГА. Перечень вспомогательных веществ: Полисорбат 80, октоксинол-10, фосфатно-солевой буферный раствор (натрия хлорид, динатрия гидрофосфат дигидрат, натрия дигидрофосфат дигидрат, вода для инъекций). Ультрикс® Квадри содержит менее 1 ммоль (23 мг) натрия на дозу, то есть, по сути, не содержит натрия. Ультрикс® Квадри может содержать следовые количества яичного белка — овальбумина (не более 1 мкг на дозу), используемого в производственном процессе. | D41: <p>0,5&nbsp;мл (1&nbsp;доза) содержит</p> <p><i>Действующие вещества:</i> <ul><li>Антиген вируса гриппа типа&nbsp;A (H₁N₁) — (15±2,0)&nbsp;мкг ГА;</li> <li>Антиген вируса гриппа типа&nbsp;А (H₃N₂) — (15±2,0)&nbsp;мкг ГА;</li> <li>Антиген вируса гриппа типа&nbsp;В (линия Yamagata) — (15±2,0)&nbsp;мкг ГА;</li> <li>Антиген вируса гриппа типа&nbsp;В (линия Victoria) — (15±2,0)&nbsp;мкг ГА.</li></ul> <i>Перечень вспомогательных веществ:</i><br> Полисорбат&nbsp;80, октоксинол-10, фосфатно-солевой буферный раствор (натрия хлорид, динатрия гидрофосфат дигидрат, натрия дигидрофосфат дигидрат, вода для инъекций).<br><br> Ультрикс® Квадри содержит менее 1&nbsp;ммоль (23&nbsp;мг) натрия на дозу, то есть, по сути, не содержит натрия.<br> Ультрикс® Квадри может содержать следовые количества яичного белка — овальбумина (не более 1&nbsp;мкг на дозу), используемого в производственном процессе.</p> | E41: 45524 | H41: https://lk.regmed.ru/Register/GetPDFfromDA?ID=1612604181 | I41: 45124 | J41: 45589
A42: 41 | B42: =VLOOKUP(A42,[1]vaccines!A:B,2) -> Grippol_quadrivalent | C42: 1 доза (0,5 мл) содержит: Действующие вещества: • Антиген вируса гриппа типа A (H₁N₁)* с содержанием гемагглютинина — 5 мкг. • Антиген вируса гриппа типа A (H₃N₂)* с содержанием гемагглютинина — 5 мкг. • Антиген вируса гриппа типа В (линия Yamagata)* с содержанием гемагглютинина — 5 мкг. • Антиген вируса гриппа типа В (линия Victoria)* с содержанием гемагглютинина — 5 мкг. • Полиоксидоний®, субстанция-лиофилизат (Азоксимера бромид) — 500 мкг. * Штаммы антигенов вируса гриппа в соответствии с рекомендациями Всемирной организации здравоохранения (ВОЗ) на текущий эпидемический сезон для Северного полушария. Вакцинные штаммы выращены на куриных эмбрионах. Перечень вспомогательных веществ: • Фосфатно-солевой буферный раствор. В составе фосфатно-солевого буферного раствора: калия хлорид, калия дигидрофосфат, динатрия гидрофосфат дигидрат, натрия хлорид, вода для инъекций. | D42: <p>1&nbsp;доза (0,5&nbsp;мл) содержит:<br><br> <i>Действующие вещества:</i> <ul><li>Антиген вируса гриппа типа&nbsp;A (H₁N₁)* с содержанием гемагглютинина — 5&nbsp;мкг.</li> <li>Антиген вируса гриппа типа&nbsp;A (H₃N₂)* с содержанием гемагглютинина — 5&nbsp;мкг.</li> <li>Антиген вируса гриппа типа&nbsp;В (линия Yamagata)* с содержанием гемагглютинина — 5&nbsp;мкг.</li> <li>Антиген вируса гриппа типа&nbsp;В (линия Victoria)* с содержанием гемагглютинина — 5&nbsp;мкг.</li> <li>Полиоксидоний®, субстанция-лиофилизат (Азоксимера бромид) — 500&nbsp;мкг.</li></ul> *&nbsp;Штаммы антигенов вируса гриппа в соответствии с рекомендациями Всемирной организации здравоохранения (ВОЗ) на текущий эпидемический сезон для Северного полушария.<br> Вакцинные штаммы выращены на куриных эмбрионах.<br><br> <i>Перечень вспомогательных веществ:</i> <ul><li>Фосфатно-солевой буферный раствор.</li> В составе фосфатно-солевого буферного раствора: калия хлорид, калия дигидрофосфат, динатрия гидрофосфат дигидрат, натрия хлорид, вода для инъекций.</ul></p> | E42: 45727 | F42: 1 | G42: 0 | H42: https://grls.rosminzdrav.ru/InstrImg/2025/05/26/1517557/95b8d8b7-23f5-4e99-a4f7-efc667459b50.pdf | I42: =I41 -> 45124 | J42: 45818
A43: 42 | B43: =VLOOKUP(A43,[1]vaccines!A:B,2) -> measles_Microgen | C43: Одна прививочная доза препарата содержит: • Вирус кори — не менее 1000 (3,0 lg) тканевых цитопатогенных доз (ТЦД₅₀). • Содержит остаточную (технологическую) примесь гентамицина сульфат — не более 20 мкг. Перечень вспомогательных веществ: • водный раствор ЛС-18¹; • желатина раствор 10%. ¹ Состав водного раствора ЛС-18: сахароза, лактоза, натрий глутаминовокислый, глицин, L-пролин, Хенкса сухая смесь с феноловым красным, вода для инъекций. | D43: <p>Одна прививочная доза препарата содержит: <ul><li>Вирус кори — не менее 1000&nbsp;(3,0&nbsp;lg) тканевых цитопатогенных доз (ТЦД₅₀).</li> <li>Содержит остаточную (технологическую) примесь гентамицина сульфат — не более 20&nbsp;мкг.</li></ul> <i>Перечень вспомогательных веществ:</i> <ul><li>водный раствор ЛС-18¹;</li> <li>желатина раствор 10%.</li></ul> ¹&nbsp;Состав водного раствора ЛС-18: сахароза, лактоза, натрий глутаминовокислый, глицин, L-пролин, Хенкса сухая смесь с феноловым красным, вода для инъекций.</p> | E43: 45404 | H43: https://lk.regmed.ru/Register/GetPDFfromDA?ID=1581220991 | I43: 45124 | J43: 45483 | K43: проверено Елена Савинова
A44: 43 | B44: =VLOOKUP(A44,[1]vaccines!A:B,2) -> measles_Serum_India | C44: После восстановления 1 доза (0,5 мл) содержит: • Вирус кори¹, штамм Эдмонстон-Загреб (живой, аттенуированный) — не менее 1000 (3,0 lg) ТЦД₅₀² ¹ культивированный на диплоидных клетках человека MRC-5 ² ТЦД₅₀ — статистически определяемое количество вируса, которое должно инфицировать 50% клеточной культуры Перечень вспомогательных веществ Лиофилизат: • сорбитол; • частично гидролизованный желатин L-гистидин; • L-аланин; • трицин; • L-аргинина гидрохлорид лактальбумина гидролизат; • среда МЕМ. Растворитель: • вода для инъекций. | D44: <p>После восстановления 1&nbsp;доза (0,5&nbsp;мл) содержит: <ul><li>Вирус кори¹, штамм Эдмонстон-Загреб (живой, аттенуированный) — не менее 1000&nbsp;(3,0&nbsp;lg)&nbsp;ТЦД₅₀²</li></ul> ¹ культивированный на диплоидных клетках человека MRC-5<br> ² ТЦД₅₀ — статистически определяемое количество вируса, которое должно инфицировать 50% клеточной культуры<br><br> Перечень вспомогательных веществ<br><br> <i>Лиофилизат:</i> <ul><li>сорбитол;</li> <li>частично гидролизованный желатин L-гистидин;</li> <li>L-аланин;</li> <li>трицин;</li> <li>L-аргинина гидрохлорид лактальбумина гидролизат;</li> <li>среда МЕМ.</li></ul> <i>Растворитель:</i> <ul><li>вода для инъекций.</li></ul></p> | E44: 45981 | F44: 1 | G44: 0 | H44: https://grls.rosminzdrav.ru/InstrImg/2025/12/30/1524922/f74ec015-a175-4792-8828-9d0c1f6547ab.pdf | I44: =I43 -> 45124 | J44: 46053
A45: 44 | B45: =VLOOKUP(A45,[1]vaccines!A:B,2) -> measles_Vector | C45: Одна прививочная доза (0,5 мл) содержит: • не менее 1000 тканевых цитопатогенных доз (ТЦД₅₀) вируса кори; • стабилизатор — смесь 0,04-0,08 мл ЛС-18 и 0,001-0,002 г желатина; • или смесь по 0,005-0,01 г сорбита и желатозы; • гентамицина сульфат — не более 10 мкг. | D45: <p>Одна прививочная доза (0,5&nbsp;мл) содержит: <ul><li>не менее 1000&nbsp;тканевых цитопатогенных доз (ТЦД₅₀) вируса кори;</li> <li>стабилизатор — смесь 0,04-0,08&nbsp;мл ЛС-18 и 0,001-0,002&nbsp;г желатина;</li> <li>или смесь по 0,005-0,01&nbsp;г сорбита и желатозы;</li> <li>гентамицина сульфат — не более 10&nbsp;мкг.</li></ul></p> | E45: 39421 | F45: 1 | G45: 0 | H45: https://grls.rosminzdrav.ru/InstrImg/2020/10/15/1462300/%D0%A0_N001586_01[2007]_0.pdf | I45: 45124
A46: 45 | B46: =VLOOKUP(A46,[1]vaccines!A:B,2) -> measles_mumps_Microgen | C46: Одна прививочная доза препарата содержит: Действующие вещества: • вирус кори — не менее 1000 (3,0 lg) тканевых цитопатогенных доз (ТЦД₅₀); • вирус паротита — не менее 20000 (4,3 lg) ТЦД₅₀. Примечание. Содержит остаточную (технологическую) примесь гентамицина сульфат — не более 20 мкг. Перечень вспомогательных веществ: • водный раствор ЛС-18¹; • желатина раствор 10 %. ¹ Состав водного раствора ЛС-18: сахароза, лактоза, натрий глутаминовокислый, глицин, L-пролин, Хенкса сухая смесь с феноловым красным, вода для инъекций. | D46: <p>Одна прививочная доза препарата содержит:</p> <p><i>Действующие вещества:</i> <ul><li>вирус кори — не менее 1000&nbsp;(3,0&nbsp;lg)&nbsp;тканевых цитопатогенных доз (ТЦД₅₀);</li> <li>вирус паротита — не менее 20000&nbsp;(4,3&nbsp;lg)&nbsp;ТЦД₅₀.</li></ul> Примечание. Содержит остаточную (технологическую) примесь гентамицина сульфат — не более 20&nbsp;мкг.</p> <p><i>Перечень вспомогательных веществ:</i> <ul><li>водный раствор ЛС-18¹;</li> <li>желатина раствор 10&nbsp;%.</li></ul> ¹&nbsp;Состав водного раствора ЛС-18: сахароза, лактоза, натрий глутаминовокислый, глицин, L-пролин, Хенкса сухая смесь с феноловым красным, вода для инъекций.</p> | E46: 45460 | H46: https://lk.regmed.ru/Register/GetPDFfromDA?ID=1597558391 | I46: =I45 -> 45124 | J46: 45589
A47: 46 | B47: =VLOOKUP(A47,[1]vaccines!A:B,2) -> Vactrivir | C47: Действующие вещества: После восстановления 1 доза (0,5 мл) содержит: • Вирус кори¹, штамм Ленинград-16 (Л-16) (живой, аттенуированный) — не менее 1000 (3,0 lg) ТЦД₅₀²; • Вирус краснухи³, штамм RA 27/3 (живой, аттенуированный) — не менее 1000 (3,0 lg) ТЦД₅₀²; • Вирус паротита¹, штамм Ленинград-3 (Л-3) (живой, аттенуированный) — не менее 20000 (4,3 lg) ТЦД₅₀². ¹ культивированный на первичной культуре клеток эмбрионов перепелов; ² ТЦД₅₀ — 50-процентная тканевая цитопатическая доза; ³ культивированный на диплоидных клетках человека MRC-5. Перечень вспомогательных веществ: Лиофилизат: • водный раствор ЛС-18; • желатина раствор 10 %. Состав водного раствора ЛС-18: сахароза, лактоза, натрий глутаминовокислый, глицин, L-пролин, Хенкса сухая смесь с феноловым красным, вода для инъекций. Растворитель: • вода для инъекций. | D47: <p><i>Действующие вещества:</i><br><br> После восстановления 1&nbsp;доза (0,5&nbsp;мл) содержит: <ul><li>Вирус кори¹, штамм Ленинград-16 (Л-16) (живой, аттенуированный) — не&nbsp;менее 1000&nbsp;(3,0&nbsp;lg)&nbsp;ТЦД₅₀²;</li> <li>Вирус краснухи³, штамм RA&nbsp;27/3 (живой, аттенуированный) — не&nbsp;менее 1000&nbsp;(3,0&nbsp;lg)&nbsp;ТЦД₅₀²;</li> <li>Вирус паротита¹, штамм Ленинград-3 (Л-3) (живой, аттенуированный) — не&nbsp;менее 20000&nbsp;(4,3&nbsp;lg)&nbsp;ТЦД₅₀².</li></ul> ¹&nbsp;культивированный на первичной культуре клеток эмбрионов перепелов;<br> ²&nbsp;ТЦД₅₀ — 50-процентная тканевая цитопатическая доза;<br> ³&nbsp;культивированный на диплоидных клетках человека MRC-5.<br><br> <i>Перечень вспомогательных веществ:</i><br><br> Лиофилизат: <ul><li>водный раствор ЛС-18;</li> <li>желатина раствор 10&nbsp;%.</li> Состав водного раствора ЛС-18: сахароза, лактоза, натрий глутаминовокислый, глицин, L-пролин, Хенкса сухая смесь с феноловым красным, вода для инъекций.</ul> Растворитель: <ul><li>вода для инъекций.</li></ul></p> | E47: 45817 | F47: 1 | G47: 0 | H47: https://grls.rosminzdrav.ru/InstrImg/2025/06/19/1518378/557245be-23d7-4913-9af3-4fa130d3c97f.pdf | I47: =I46 -> 45124 | J47: 45830
A48: 47 | B48: =VLOOKUP(A48,[1]vaccines!A:B,2) -> MMR_II | C48: 1 доза содержит: Действующие вещества: • вирус кори с низкой вирулентностью, полученный из аттенуированного (Enders') штамма Edmonston и выращенный в культуре клеток куриного эмбриона, не менее 1000 ТЦД₅₀; • вирус паротита, полученный из штамма Jeryl Lynn™ (уровень В) и выращенный в культуре клеток куриного эмбриона, не менее 12500 ТЦД₅₀; • вирус краснухи, полученный из живого аттенуированного штамма Wistar RA 27/3 и выращенный в культуре диплоидных клеток легочных фибробластов человека (WI-38), не менее 1000 ТЦД₅₀. Вспомогательные вещества: натрия гидрофосфат 2,2 мг, натрия дигидрофосфата моногидрат 3,1 мг, натрия гидрокарбонат 0,5 мг, среда 199 с солями Хенкса 3,3 мг, среда MЕM Игла 0,1 мг, неомицина сульфат 25 мкг, феноловый красный 3,4 мкг, сорбитол 14,5 мг, калия гидрофосфат 30 мкг, калия дигидрофосфат 20 мкг, желатин гидролизованный 14,5 мг, сахароза 1,9 мг, натрия L-глутамата моногидрат 20 мкг. Примечание: препарат содержит следовые количества альбумина человека рекомбинантного (не более 0,3 мг) и бычьего сывороточного альбумина (не более 50 нг). Примечание: среда 199 с солями Хенкса представляет собой все порошкообразные Среды 199, которые входят в состав лекарственного препарата, включая Среду 199 с солями Хенкса, Среду 199 10Х модифицированную без глутамина и дополнительные компоненты витамин К и L-глутамин. Стерильный растворитель: • вода для инъекций: 0,7 мл. Примечание: первичная упаковка содержит 0,7 мл растворителя для растворения лиофилизата до необходимого объема (0,7 мл). Избыток 0,2 мл необходим для компенсации потерь и обеспечения введения 1 дозы вакцины в объеме 0,5 мл. | D48: <p>1&nbsp;доза содержит:</p> <p><i>Действующие вещества:</i> <ul><li>вирус кори с низкой вирулентностью, полученный из аттенуированного (Enders') штамма Edmonston и выращенный в культуре клеток куриного эмбриона, не менее 1000&nbsp;ТЦД₅₀;</li> <li>вирус паротита, полученный из штамма Jeryl Lynn™ (уровень В) и выращенный в культуре клеток куриного эмбриона, не менее 12500&nbsp;ТЦД₅₀;</li> <li>вирус краснухи, полученный из живого аттенуированного штамма Wistar&nbsp;RA&nbsp;27/3 и выращенный в культуре диплоидных клеток легочных фибробластов человека (WI-38), не менее 1000&nbsp;ТЦД₅₀.</li></ul> <i>Вспомогательные вещества:</i> <ul>натрия гидрофосфат 2,2&nbsp;мг, натрия дигидрофосфата моногидрат 3,1&nbsp;мг, натрия гидрокарбонат 0,5&nbsp;мг, среда&nbsp;199 с солями Хенкса 3,3&nbsp;мг, среда&nbsp;MЕM&nbsp;Игла 0,1&nbsp;мг, неомицина сульфат 25&nbsp;мкг, феноловый красный 3,4&nbsp;мкг, сорбитол 14,5&nbsp;мг, калия гидрофосфат 30&nbsp;мкг, калия дигидрофосфат 20&nbsp;мкг, желатин гидролизованный 14,5&nbsp;мг, сахароза 1,9&nbsp;мг, натрия L-глутамата моногидрат 20&nbsp;мкг.</ul></p> <p>Примечание: препарат содержит следовые количества альбумина человека рекомбинантного (не более 0,3&nbsp;мг) и бычьего сывороточного альбумина (не более 50&nbsp;нг).</p> <p>Примечание: среда&nbsp;199 с солями Хенкса представляет собой все порошкообразные Среды&nbsp;199, которые входят в состав лекарственного препарата, включая Среду&nbsp;199 с солями Хенкса, Среду&nbsp;199&nbsp;10Х модифицированную без глутамина и дополнительные компоненты витамин К и L-глутамин.</p> <p><i>Стерильный растворитель:</i> <ul><li>вода для инъекций: 0,7&nbsp;мл.</li></ul> Примечание: первичная упаковка содержит 0,7&nbsp;мл растворителя для растворения лиофилизата до необходимого объема (0,7&nbsp;мл). Избыток 0,2&nbsp;мл необходим для компенсации потерь и обеспечения введения 1&nbsp;дозы вакцины в объеме 0,5&nbsp;мл.</p> | E48: 43959 | F48: 5 | G48: 5 | H48: https://grls.rosminzdrav.ru/InstrImg/2022/09/20/1485497/ec14bfcf-e7ae-4d2a-8916-3a79e74272eb.pdf | I48: 45124
A49: 48 | B49: =VLOOKUP(A49,[1]vaccines!A:B,2) -> MenA_Microgen | C49: Действующее вещество: очищенный капсульный специфический полисахарид штамма Neisseria meningitidis серогруппы А. 1 ампула содержит 250 мкг полисахарида. Перечень вспомогательных веществ: лактозы моногидрат. Растворитель: натрия хлорид растворитель для приготовления лекарственных форм для инъекций 0,9%. | D49: <p>Действующее вещество: очищенный капсульный специфический полисахарид штамма Neisseria meningitidis серогруппы А.<br> 1&nbsp;ампула содержит 250&nbsp;мкг полисахарида.<br> Перечень вспомогательных веществ: лактозы моногидрат.<br> Растворитель: натрия хлорид растворитель для приготовления лекарственных форм для инъекций 0,9%.</p> | E49: 45414 | H49: https://lk.regmed.ru/Register/GetPDFfromDA?ID=1583272671 | I49: =I48 -> 45124 | J49: 45460
A50: 49 | B50: =VLOOKUP(A50,[1]vaccines!A:B,2) -> MeningoVac_A_C | C50: Действующие вещества: • очищенный капсульный специфический полисахарид штамма N. meningitidis серогруппы А; • очищенный капсульный специфический полисахарид штамма N. meningitidis серогруппы С. 1 ампула содержит по 250 мкг каждого из полисахаридов. Перечень вспомогательных веществ: лактозы моногидрат. Растворитель: натрия хлорид растворитель для приготовления лекарственных форм для инъекций 0,9%. | D50: <p>Действующие вещества: <ul><li>очищенный капсульный специфический полисахарид штамма N. meningitidis серогруппы А;</li> <li>очищенный капсульный специфический полисахарид штамма N. meningitidis серогруппы С.</li></ul> 1&nbsp;ампула содержит по 250&nbsp;мкг каждого из полисахаридов.<br> Перечень вспомогательных веществ: лактозы моногидрат.<br> Растворитель: натрия хлорид растворитель для приготовления лекарственных форм для инъекций 0,9%.</p> | E50: 45414 | H50: https://lk.regmed.ru/Register/GetPDFfromDA?ID=1581523381 | I50: =I49 -> 45124 | J50: 45460
A51: 50 | B51: =VLOOKUP(A51,[1]vaccines!A:B,2) -> Menactra | C51: Одна доза вакцины (0,5 мл) содержит: Действующие вещества: • Менингококковый полисахарид серогруппы А¹ — 4 мкг. • Менингококковый полисахарид серогруппы C¹ — 4 мкг. • Менингококковый полисахарид серогруппы Y¹ — 4 мкг. • Менингококковый полисахарид серогруппы W-135¹ — 4 мкг. ¹ Конъюгированный с белком-носителем — дифтерийным анатоксином — ∼48 мкг. Перечень вспомогательных веществ: Натрия хлорид, натрия гидрофосфат, натрия дигидрофосфата моногидрат, вода для инъекций. | D51: <p>Одна доза вакцины (0,5&nbsp;мл) содержит:<br><br> <i>Действующие вещества:</i> <ul><li>Менингококковый полисахарид серогруппы А¹ — 4&nbsp;мкг.</li> <li>Менингококковый полисахарид серогруппы C¹ — 4&nbsp;мкг.</li> <li>Менингококковый полисахарид серогруппы Y¹ — 4&nbsp;мкг.</li> <li>Менингококковый полисахарид серогруппы W-135¹ — 4&nbsp;мкг.</li></ul> ¹&nbsp;Конъюгированный с белком-носителем — дифтерийным анатоксином — ∼48&nbsp;мкг.<br><br> <i>Перечень вспомогательных веществ:</i><br> Натрия хлорид, натрия гидрофосфат, натрия дигидрофосфата моногидрат, вода для инъекций.</p> | E51: 45188 | H51: https://lk.regmed.ru/Register/GetPDFfromDA?ID=1574028031 | I51: =I50 -> 45124 | J51: 45483
A52: 51 | B52: =VLOOKUP(A52,[1]vaccines!A:B,2) -> mumps_Microgen | C52: Одна прививочная доза препарата содержит: • Вирус паротита — не менее 20000 (4,3 lg) тканевых цитопатогенных доз ТЦД₅₀. Содержит остаточную (технологическую) примесь гентамицина сульфат не более 20 мкг. Перечень вспомогательных веществ: • водный раствор ЛС-18¹; • желатина раствор 10%. Примечание. ¹ Состав водного раствора ЛС-18: сахароза, лактоза, натрий глутаминовокислый, глицин, L-пролин, Хенкса сухая смесь с феноловым красным, вода для инъекций. | D52: <p>Одна прививочная доза препарата содержит: <ul><li>Вирус паротита — не менее 20000 (4,3&nbsp;lg) тканевых цитопатогенных доз ТЦД₅₀.</li></ul> Содержит остаточную (технологическую) примесь гентамицина сульфат не более 20&nbsp;мкг.<br><br> <i>Перечень вспомогательных веществ:</i> <ul><li>водный раствор ЛС-18¹;</li> <li>желатина раствор 10%.</li></ul> Примечание.<br> ¹&nbsp;Состав водного раствора ЛС-18: сахароза, лактоза, натрий глутаминовокислый, глицин, L-пролин, Хенкса сухая смесь с феноловым красным, вода для инъекций.</p> | E52: 45454 | H52: https://lk.regmed.ru/Register/GetPDFfromDA?ID=1594767771 | I52: =I51 -> 45124 | J52: 45589
A53: 52 | B53: =VLOOKUP(A53,[1]vaccines!A:B,2) -> Prevenar_13 | C53: Одна доза (0,5 мл) суспензии содержит: Действующие вещества: Пневмококковые конъюгаты¹ (полисахарид — CRM₁₉₇): • пневмококковый полисахарид серотипа 1 — 2,2 мкг; • пневмококковый полисахарид серотипа 3 — 2,2 мкг; • пневмококковый полисахарид серотипа 4 — 2,2 мкг; • пневмококковый полисахарид серотипа 5 — 2,2 мкг; • пневмококковый полисахарид серотипа 6A — 2,2 мкг; • пневмококковый полисахарид серотипа 6B — 4,4 мкг; • пневмококковый полисахарид серотипа 7F — 2,2 мкг; • пневмококковый полисахарид серотипа 9V — 2,2 мкг; • пневмококковый полисахарид серотипа 14 — 2,2 мкг; • пневмококковый олигосахарид серотипа 18C — 2,2 мкг; • пневмококковый полисахарид серотипа 19A — 2,2 мкг; • пневмококковый полисахарид серотипа 19F — 2,2 мкг; • пневмококковый полисахарид серотипа 23F — 2,2 мкг. ¹ Конъюгированы с белком-носителем CRM₁₉₇ и адсорбированы на фосфате алюминия. 1 доза (0,5 мл) содержит приблизительно 32 мкг белка-носителя CRM₁₉₇ и 0,125 мг алюминия (в качестве адъюванта). Перечень вспомогательных веществ: • Натрия хлорид. • Янтарная кислота. • Полисорбат 80. • Вода для инъекций. | D53: <p>Одна доза (0,5&nbsp;мл) суспензии содержит:<br><br> <i>Действующие вещества:</i> <ul>Пневмококковые конъюгаты¹ (полисахарид — CRM₁₉₇): <li>пневмококковый полисахарид серотипа 1 — 2,2&nbsp;мкг;</li> <li>пневмококковый полисахарид серотипа 3 — 2,2&nbsp;мкг;</li> <li>пневмококковый полисахарид серотипа 4 — 2,2&nbsp;мкг;</li> <li>пневмококковый полисахарид серотипа 5 — 2,2&nbsp;мкг;</li> <li>пневмококковый полисахарид серотипа 6A — 2,2&nbsp;мкг;</li> <li>пневмококковый полисахарид серотипа 6B — 4,4&nbsp;мкг;</li> <li>пневмококковый полисахарид серотипа 7F — 2,2&nbsp;мкг;</li> <li>пневмококковый полисахарид серотипа 9V — 2,2&nbsp;мкг;</li> <li>пневмококковый полисахарид серотипа 14 — 2,2&nbsp;мкг;</li> <li>пневмококковый олигосахарид серотипа 18C — 2,2&nbsp;мкг;</li> <li>пневмококковый полисахарид серотипа 19A — 2,2&nbsp;мкг;</li> <li>пневмококковый полисахарид серотипа 19F — 2,2&nbsp;мкг;</li> <li>пневмококковый полисахарид серотипа 23F — 2,2&nbsp;мкг.</li></ul> ¹&nbsp;Конъюгированы с белком-носителем CRM₁₉₇ и адсорбированы на фосфате алюминия.</p> <p>1&nbsp;доза (0,5&nbsp;мл) содержит приблизительно 32&nbsp;мкг белка-носителя CRM₁₉₇ и 0,125&nbsp;мг алюминия (в качестве адъюванта).<br><br> <i>Перечень вспомогательных веществ:</i> <ul><li>Натрия хлорид.</li> <li>Янтарная кислота.</li> <li>Полисорбат&nbsp;80.</li> <li>Вода для инъекций.</li></ul></p> | E53: 45267 | H53: https://lk.regmed.ru/Register/GetPDFfromDA?ID=1544529771 | I53: 45125 | J53: 45481 | K53: проверено Елена Савинова
A54: 53 | B54: =VLOOKUP(A54,[1]vaccines!A:B,2) -> Synflorix | C54: 1 доза (0,5 мл) содержит: Действующие вещества: Полисахариды Streptococcus pneumoniae, конъюгированные с белками-носителями: • Полисахарид серотипа 1 — 1 мкг/PD. • Полисахарид серотипа 4 — 3 мкг/PD. • Полисахарид серотипа 5 — 1 мкг/PD. • Полисахарид серотипа 6B — 1 мкг/PD. • Полисахарид серотипа 7F — 1 мкг/PD. • Полисахарид серотипа 9V — 1 мкг/PD. • Полисахарид серотипа 14 — 1 мкг/PD. • Полисахарид серотипа 18C — 3 мкг/TT. • Полисахарид серотипа 19F — - 3 мкг/DT. • Полисахарид серотипа 23F — 1 мкг/PD. Белки-носители (общее количество): • PD: D-протеин Haemophilus influenzae — 9-16 мкг*. • TT: анатоксин столбнячный — 5-10 мкг*. • DT: анатоксин дифтерийный — 3-6 мкг*. Вспомогательные вещества: • Алюминия фосфат (в пересчете на алюминий) — 0,5 мг. • Натрия хлорид — ∼4,4 мг. • Вода для инъекций — до 0,5 мл. * - Состав препарата основан на содержании полисахаридов, а индивидуальное содержание белка-носителя зависит от отношения «полисахарид/белок». | D54: <p>1&nbsp;доза (0,5&nbsp;мл) содержит:</p> <p><i>Действующие вещества:</i> <ul><i>Полисахариды Streptococcus pneumoniae, конъюгированные с белками-носителями:</i> <li>Полисахарид серотипа&nbsp;1 — 1&nbsp;мкг/PD.</li> <li>Полисахарид серотипа&nbsp;4 — 3&nbsp;мкг/PD.</li> <li>Полисахарид серотипа&nbsp;5 — 1&nbsp;мкг/PD.</li> <li>Полисахарид серотипа&nbsp;6B — 1&nbsp;мкг/PD.</li> <li>Полисахарид серотипа&nbsp;7F — 1&nbsp;мкг/PD.</li> <li>Полисахарид серотипа&nbsp;9V — 1&nbsp;мкг/PD.</li> <li>Полисахарид серотипа&nbsp;14 — 1&nbsp;мкг/PD.</li> <li>Полисахарид серотипа&nbsp;18C — 3&nbsp;мкг/TT.</li> <li>Полисахарид серотипа&nbsp;19F — 3&nbsp;мкг/DT.</li> <li>Полисахарид серотипа&nbsp;23F — 1&nbsp;мкг/PD.</li></ul> <ul><i>Белки-носители (общее количество):</i> <li>PD: D-протеин Haemophilus influenzae — 9-16&nbsp;мкг*.</li> <li>TT: анатоксин столбнячный — 5-10&nbsp;мкг*.</li> <li>DT: анатоксин дифтерийный — 3-6&nbsp;мкг*.</li></ul></p> <p><i>Вспомогательные вещества:</i> <ul><li>Алюминия фосфат (в пересчете на алюминий) — 0,5&nbsp;мг.</li> <li>Натрия хлорид — ∼4,4&nbsp;мг.</li> <li>Вода для инъекций — до 0,5&nbsp;мл.</li></ul></p> <p>* - Состав препарата основан на содержании полисахаридов, а индивидуальное содержание белка-носителя зависит от отношения «полисахарид/белок».</p> | E54: 43605 | F54: 1 | G54: 0 | H54: https://grls.rosminzdrav.ru/InstrImg/2021/1/12/1464953/%D0%9B%D0%9F-001412[2019]_0.pdf | I54: 45125
A55: 54 | B55: =VLOOKUP(A55,[1]vaccines!A:B,2) -> Pneumovax_23 | C55: Одна доза (0,5 мл) содержит: Действующие вещества: Streptococcus pneumoniae полисахариды (по датской номенклатуре серотипы 1, 2, 3, 4, 5, 6B, 7F, 8, 9N, 9V, 10А, 11А, 12F, 14, 15В, 17F, 18С, 19А, 19F, 20, 22F, 23F, 33F) по 25 мкг каждого серотипа. Перечень вспомогательных веществ: • Натрия хлорид. • Фенол. • Вода для инъекций. | D55: <p>Одна доза (0,5&nbsp;мл) содержит:</p> <p><i>Действующие вещества:</i><br> <i>Streptococcus pneumoniae</i> полисахариды (по датской номенклатуре серотипы 1, 2, 3, 4, 5, 6B, 7F, 8, 9N, 9V, 10А, 11А, 12F, 14, 15В, 17F, 18С, 19А, 19F, 20, 22F, 23F, 33F) по 25&nbsp;мкг каждого серотипа.<br><br> <i>Перечень вспомогательных веществ:</i> <ul><li>Натрия хлорид.</li> <li>Фенол.</li> <li>Вода для инъекций.</li></ul></p> | E55: 45051 | H55: https://lk.regmed.ru/Register/GetPDFfromDA?ID=1509638211 | I55: =I54 -> 45125 | J55: 45489
A56: 55 | B56: =VLOOKUP(A56,[1]vaccines!A:B,2) -> MonoVac_Polio | C56: Одна прививочная доза 0,2 мл — 4 капли содержит: Действующее вещество: Вирус полиомиелита, аттенуированный штамм Сэбина 2 типа не менее 10⁵·⁰ инфекционных единиц (ИЕ) вируса, выраженных в тканевых цитопатогенных дозах (ТЦД₅₀). Вспомогательные вещества: Магния хлорид — 0,018 г. | D56: <p>Одна прививочная доза 0,2&nbsp;мл — 4&nbsp;капли содержит:</p> <p><i>Действующее вещество:</i><br> Вирус полиомиелита, аттенуированный штамм Сэбина 2&nbsp;типа не менее 10⁵<sup>,</sup>⁰&nbsp;инфекционных единиц (ИЕ) вируса, выраженных в тканевых цитопатогенных дозах (ТЦД₅₀).</p> <p><i>Вспомогательные вещества:</i><br> Магния хлорид — 0,018&nbsp;г.</p> | E56: 44454 | F56: 1 | G56: 1 | H56: https://grls.rosminzdrav.ru/InstrImg/2022/07/11/1482961/7ca870d6-4357-4c0d-8ba4-f49b758dfd88.pdf | I56: 45125
A57: 56 | B57: =VLOOKUP(A57,[1]vaccines!A:B,2) -> BiVac_Polio | C57: Одна доза 0,2 мл — 4 капли содержит: Действующее вещество: вирус полиомиелита, аттенуированные штаммы Сэбина тип 1 не менее 10⁶·⁰ ТЦД₅₀, тип 3 не менее 10⁵·⁵ ТЦД₅₀ инфекционных единиц (ИЕ) вируса, выраженных в тканевых цитопатогенных дозах (ТЦД₅₀). Вспомогательные вещества: магния хлорид 0,018 г. | D57: <p>Одна доза 0,2&nbsp;мл — 4&nbsp;капли содержит:</p> <p><i>Действующее вещество:</i> вирус полиомиелита, аттенуированные штаммы Сэбина тип&nbsp;1 не менее 10⁶<sup>,</sup>⁰&nbsp;ТЦД₅₀, тип&nbsp;3 не менее 10⁵<sup>,</sup>⁵&nbsp;ТЦД₅₀ инфекционных единиц (ИЕ) вируса, выраженных в тканевых цитопатогенных дозах (ТЦД₅₀).</p> <p><i>Вспомогательные вещества:</i> магния хлорид 0,018&nbsp;г.</p> | E57: 45736 | F57: 1 | G57: 0 | H57: https://grls.rosminzdrav.ru/InstrImg/2025/07/25/1519625/ca601e77-829c-48a9-b9b5-204e5b86aa88.pdf | I57: =I56 -> 45125 | J57: 45988
