Workbook

Sheet vaccines
A1: =IFERROR(__xludf.DUMMYFUNCTION("importrange(""https://docs.google.com/spreadsheets/d/1sGRvhluuPcwgfCszZJeTSVDmdr-8joz4WvlOQo2gfes/edit?usp=drivesdk"",""vaccines!A:M"")"),"id") -> id | B1: =IFERROR(__xludf.DUMMYFUNCTION("""COMPUTED_VALUE"""),"code_name") -> code_name | C1: =IFERROR(__xludf.DUMMYFUNCTION("""COMPUTED_VALUE"""),"product_characteristics_link_primary_field_for_version_1") -> product_characteristics_link_primary_field_for_version_1 | D1: =IFERROR(__xludf.DUMMYFUNCTION("""COMPUTED_VALUE"""),"short_name") -> short_name | E1: =IFERROR(__xludf.DUMMYFUNCTION("""COMPUTED_VALUE"""),"long_name") -> long_name | F1: =IFERROR(__xludf.DUMMYFUNCTION("""COMPUTED_VALUE"""),"manufacturer") -> manufacturer | G1: =IFERROR(__xludf.DUMMYFUNCTION("""COMPUTED_VALUE"""),"in_use_in_Russia") -> in_use_in_Russia | H1: =IFERROR(__xludf.DUMMYFUNCTION("""COMPUTED_VALUE"""),"comment_to_show") -> comment_to_show | I1: =IFERROR(__xludf.DUMMYFUNCTION("""COMPUTED_VALUE"""),"comment_to_show_wo_html") -> comment_to_show_wo_html | J1: =IFERROR(__xludf.DUMMYFUNCTION("""COMPUTED_VALUE"""),"dosage") -> dosage | K1: =IFERROR(__xludf.DUMMYFUNCTION("""COMPUTED_VALUE"""),"creation_date") -> creation_date | L1: =IFERROR(__xludf.DUMMYFUNCTION("""COMPUTED_VALUE"""),"update_date") -> update_date | M1: =IFERROR(__xludf.DUMMYFUNCTION("""COMPUTED_VALUE"""),"OKhLP_specialists_link") -> OKhLP_specialists_link
A2: =IFERROR(__xludf.DUMMYFUNCTION("""COMPUTED_VALUE"""),1.0) -> 1 | B2: =IFERROR(__xludf.DUMMYFUNCTION("""COMPUTED_VALUE"""),"BCG_Microgen") -> BCG_Microgen | C2: =IFERROR(__xludf.DUMMYFUNCTION("""COMPUTED_VALUE"""),"https://grls.rosminzdrav.ru/Grls_View_v2.aspx?routingGuid=9f91626d-1063-4ea5-9346-800cc6ef9b44") -> https://grls.rosminzdrav.ru/Grls_View_v2.aspx?routingGuid=9f91626d-1063-4ea5-9346-800cc6ef9b44 | D2: =IFERROR(__xludf.DUMMYFUNCTION("""COMPUTED_VALUE"""),"БЦЖ (Микроген)") -> БЦЖ (Микроген) | E2: =IFERROR(__xludf.DUMMYFUNCTION("""COMPUTED_VALUE"""),"Вакцина туберкулезная (БЦЖ)") -> Вакцина туберкулезная (БЦЖ) | F2: =IFERROR(__xludf.DUMMYFUNCTION("""COMPUTED_VALUE"""),"Микроген") -> Микроген | G2: =IFERROR(__xludf.DUMMYFUNCTION("""COMPUTED_VALUE"""),"in use") -> in use | H2: =IFERROR(__xludf.DUMMYFUNCTION("""COMPUTED_VALUE"""),"<p>Используется в двух случаях: <ol><li>на тех территориях, где показатель заболеваемости туберкулеза превышает 80&nbsp;случаев на 100&nbsp;000&nbsp;населения;</li> <li>если в окружении новорожденного есть больной туберкулезом.</li></ol></p>") -> <p>Используется в двух случаях: <ol><li>на тех территориях, где показатель заболеваемости туберкулеза превышает 80&nbsp;случаев на 100&nbsp;000&nbsp;населения;</li> <li>если в окружении новорожденного есть больной туберкулезом.</li></ol></p> | I2: =IFERROR(__xludf.DUMMYFUNCTION("""COMPUTED_VALUE"""),"Используется в двух случаях: 1. на тех территориях, где показатель заболеваемости туберкулеза превышает 80 случаев на 100 000 населения; 2. если в окружении новорожденного есть больной туберкулезом.") -> Используется в двух случаях: 1. на тех территориях, где показатель заболеваемости туберкулеза превышает 80 случаев на 100 000 населения; 2. если в окружении новорожденного есть больной туберкулезом. | J2: =IFERROR(__xludf.DUMMYFUNCTION("""COMPUTED_VALUE"""),0.05) -> 0.05 | K2: =IFERROR(__xludf.DUMMYFUNCTION("""COMPUTED_VALUE"""),44712.0) -> 44712 | L2: =IFERROR(__xludf.DUMMYFUNCTION("""COMPUTED_VALUE"""),45689.0) -> 45689 | M2: =IFERROR(__xludf.DUMMYFUNCTION("""COMPUTED_VALUE"""),"есть") -> есть
A3: =IFERROR(__xludf.DUMMYFUNCTION("""COMPUTED_VALUE"""),2.0) -> 2 | B3: =IFERROR(__xludf.DUMMYFUNCTION("""COMPUTED_VALUE"""),"BCG_M_Microgen") -> BCG_M_Microgen | C3: =IFERROR(__xludf.DUMMYFUNCTION("""COMPUTED_VALUE"""),"https://grls.rosminzdrav.ru/Grls_View_v2.aspx?routingGuid=115ba81b-7cb9-4737-9e63-163458ef9d0b") -> https://grls.rosminzdrav.ru/Grls_View_v2.aspx?routingGuid=115ba81b-7cb9-4737-9e63-163458ef9d0b | D3: =IFERROR(__xludf.DUMMYFUNCTION("""COMPUTED_VALUE"""),"БЦЖ-М (Микроген)") -> БЦЖ-М (Микроген) | E3: =IFERROR(__xludf.DUMMYFUNCTION("""COMPUTED_VALUE"""),"Вакцина туберкулезная для щадящей первичной иммунизации (БЦЖ-М)") -> Вакцина туберкулезная для щадящей первичной иммунизации (БЦЖ-М) | F3: =IFERROR(__xludf.DUMMYFUNCTION("""COMPUTED_VALUE"""),"Микроген") -> Микроген | G3: =IFERROR(__xludf.DUMMYFUNCTION("""COMPUTED_VALUE"""),"in use") -> in use | H3: =IFERROR(__xludf.DUMMYFUNCTION("""COMPUTED_VALUE"""),"<p>Используется по умолчанию для вакцинации детей против туберкулеза. Однако на территориях с повышенной заболеваемостью туберкулезом, а также если в окружении новорожденного есть больной туберкулезом, используется другая вакцина — ""БЦЖ"".</p>") -> <p>Используется по умолчанию для вакцинации детей против туберкулеза. Однако на территориях с повышенной заболеваемостью туберкулезом, а также если в окружении новорожденного есть больной туберкулезом, используется другая вакцина — "БЦЖ".</p> | I3: =IFERROR(__xludf.DUMMYFUNCTION("""COMPUTED_VALUE"""),"Используется по умолчанию для вакцинации детей против туберкулеза. Однако на территориях с повышенной заболеваемостью туберкулезом, а также если в окружении новорожденного есть больной туберкулезом, используется другая вакцина — ""БЦЖ"".") -> Используется по умолчанию для вакцинации детей против туберкулеза. Однако на территориях с повышенной заболеваемостью туберкулезом, а также если в окружении новорожденного есть больной туберкулезом, используется другая вакцина — "БЦЖ". | J3: =IFERROR(__xludf.DUMMYFUNCTION("""COMPUTED_VALUE"""),0.025) -> 0.025 | K3: =IFERROR(__xludf.DUMMYFUNCTION("""COMPUTED_VALUE"""),44712.0) -> 44712 | L3: =IFERROR(__xludf.DUMMYFUNCTION("""COMPUTED_VALUE"""),45689.0) -> 45689 | M3: =IFERROR(__xludf.DUMMYFUNCTION("""COMPUTED_VALUE"""),"есть") -> есть
A4: =IFERROR(__xludf.DUMMYFUNCTION("""COMPUTED_VALUE"""),3.0) -> 3 | B4: =IFERROR(__xludf.DUMMYFUNCTION("""COMPUTED_VALUE"""),"BCG_Gamaleya") -> BCG_Gamaleya | C4: =IFERROR(__xludf.DUMMYFUNCTION("""COMPUTED_VALUE"""),"https://grls.rosminzdrav.ru/Grls_View_v2.aspx?routingGuid=4215760f-875d-476b-a9b6-af2e398c3025") -> https://grls.rosminzdrav.ru/Grls_View_v2.aspx?routingGuid=4215760f-875d-476b-a9b6-af2e398c3025 | D4: =IFERROR(__xludf.DUMMYFUNCTION("""COMPUTED_VALUE"""),"БЦЖ (Гамалеи)") -> БЦЖ (Гамалеи) | E4: =IFERROR(__xludf.DUMMYFUNCTION("""COMPUTED_VALUE"""),"Вакцина туберкулезная (БЦЖ)") -> Вакцина туберкулезная (БЦЖ) | F4: =IFERROR(__xludf.DUMMYFUNCTION("""COMPUTED_VALUE"""),"НИЦЭМ им. Н.Ф. Гамалеи") -> НИЦЭМ им. Н.Ф. Гамалеи | G4: =IFERROR(__xludf.DUMMYFUNCTION("""COMPUTED_VALUE"""),"in use") -> in use | H4: =IFERROR(__xludf.DUMMYFUNCTION("""COMPUTED_VALUE"""),"<p>Используется в двух случаях: <ol><li>на тех территориях, где показатель заболеваемости туберкулеза превышает 80&nbsp;случаев на 100&nbsp;000&nbsp;населения;</li> <li>если в окружении новорожденного есть больной туберкулезом.</li></ol></p>") -> <p>Используется в двух случаях: <ol><li>на тех территориях, где показатель заболеваемости туберкулеза превышает 80&nbsp;случаев на 100&nbsp;000&nbsp;населения;</li> <li>если в окружении новорожденного есть больной туберкулезом.</li></ol></p> | I4: =IFERROR(__xludf.DUMMYFUNCTION("""COMPUTED_VALUE"""),"Используется в двух случаях: 1. на тех территориях, где показатель заболеваемости туберкулеза превышает 80 случаев на 100 000 населения; 2. если в окружении новорожденного есть больной туберкулезом.") -> Используется в двух случаях: 1. на тех территориях, где показатель заболеваемости туберкулеза превышает 80 случаев на 100 000 населения; 2. если в окружении новорожденного есть больной туберкулезом. | J4: =IFERROR(__xludf.DUMMYFUNCTION("""COMPUTED_VALUE"""),0.05) -> 0.05 | K4: =IFERROR(__xludf.DUMMYFUNCTION("""COMPUTED_VALUE"""),44712.0) -> 44712 | L4: =IFERROR(__xludf.DUMMYFUNCTION("""COMPUTED_VALUE"""),45801.0) -> 45801 | M4: =IFERROR(__xludf.DUMMYFUNCTION("""COMPUTED_VALUE"""),"есть") -> есть
A5: =IFERROR(__xludf.DUMMYFUNCTION("""COMPUTED_VALUE"""),4.0) -> 4 | B5: =IFERROR(__xludf.DUMMYFUNCTION("""COMPUTED_VALUE"""),"BCG_M_Gamaleya") -> BCG_M_Gamaleya | C5: =IFERROR(__xludf.DUMMYFUNCTION("""COMPUTED_VALUE"""),"https://grls.rosminzdrav.ru/Grls_View_v2.aspx?routingGuid=30fc01db-b288-495f-9e55-e1dd798d18a9") -> https://grls.rosminzdrav.ru/Grls_View_v2.aspx?routingGuid=30fc01db-b288-495f-9e55-e1dd798d18a9 | D5: =IFERROR(__xludf.DUMMYFUNCTION("""COMPUTED_VALUE"""),"БЦЖ-М (Гамалеи)") -> БЦЖ-М (Гамалеи) | E5: =IFERROR(__xludf.DUMMYFUNCTION("""COMPUTED_VALUE"""),"Вакцина туберкулезная для щадящей первичной иммунизации (БЦЖ-М)") -> Вакцина туберкулезная для щадящей первичной иммунизации (БЦЖ-М) | F5: =IFERROR(__xludf.DUMMYFUNCTION("""COMPUTED_VALUE"""),"НИЦЭМ им. Н.Ф. Гамалеи") -> НИЦЭМ им. Н.Ф. Гамалеи | G5: =IFERROR(__xludf.DUMMYFUNCTION("""COMPUTED_VALUE"""),"in use") -> in use | H5: =IFERROR(__xludf.DUMMYFUNCTION("""COMPUTED_VALUE"""),"<p>Используется по умолчанию для вакцинации детей против туберкулеза. Однако на территориях с повышенной заболеваемостью туберкулезом, а также если в окружении новорожденного есть больной туберкулезом, используется другая вакцина — ""БЦЖ"".</p>") -> <p>Используется по умолчанию для вакцинации детей против туберкулеза. Однако на территориях с повышенной заболеваемостью туберкулезом, а также если в окружении новорожденного есть больной туберкулезом, используется другая вакцина — "БЦЖ".</p> | I5: =IFERROR(__xludf.DUMMYFUNCTION("""COMPUTED_VALUE"""),"Используется по умолчанию для вакцинации детей против туберкулеза. Однако на территориях с повышенной заболеваемостью туберкулезом, а также если в окружении новорожденного есть больной туберкулезом, используется другая вакцина — ""БЦЖ"".") -> Используется по умолчанию для вакцинации детей против туберкулеза. Однако на территориях с повышенной заболеваемостью туберкулезом, а также если в окружении новорожденного есть больной туберкулезом, используется другая вакцина — "БЦЖ". | J5: =IFERROR(__xludf.DUMMYFUNCTION("""COMPUTED_VALUE"""),0.025) -> 0.025 | K5: =IFERROR(__xludf.DUMMYFUNCTION("""COMPUTED_VALUE"""),44712.0) -> 44712 | L5: =IFERROR(__xludf.DUMMYFUNCTION("""COMPUTED_VALUE"""),45818.0) -> 45818 | M5: =IFERROR(__xludf.DUMMYFUNCTION("""COMPUTED_VALUE"""),"есть") -> есть
A6: =IFERROR(__xludf.DUMMYFUNCTION("""COMPUTED_VALUE"""),5.0) -> 5 | B6: =IFERROR(__xludf.DUMMYFUNCTION("""COMPUTED_VALUE"""),"Infanrix") -> Infanrix | C6: =IFERROR(__xludf.DUMMYFUNCTION("""COMPUTED_VALUE"""),"https://grls.rosminzdrav.ru/Grls_View_v2.aspx?routingGuid=60b8bad6-1fec-492d-a07c-25eee3daa0b5") -> https://grls.rosminzdrav.ru/Grls_View_v2.aspx?routingGuid=60b8bad6-1fec-492d-a07c-25eee3daa0b5 | D6: =IFERROR(__xludf.DUMMYFUNCTION("""COMPUTED_VALUE"""),"Инфанрикс") -> Инфанрикс | E6: =IFERROR(__xludf.DUMMYFUNCTION("""COMPUTED_VALUE"""),"Инфанрикс® (Вакцина для профилактики дифтерии, столбняка, коклюша (бесклеточная) трехкомпонентная адсорбированная жидкая)") -> Инфанрикс® (Вакцина для профилактики дифтерии, столбняка, коклюша (бесклеточная) трехкомпонентная адсорбированная жидкая) | F6: =IFERROR(__xludf.DUMMYFUNCTION("""COMPUTED_VALUE"""),"GSK") -> GSK | G6: =IFERROR(__xludf.DUMMYFUNCTION("""COMPUTED_VALUE"""),"not in use") -> not in use | H6: =IFERROR(__xludf.DUMMYFUNCTION("""COMPUTED_VALUE"""),"<p>DTaP, бесклеточный коклюшный компонент</p>") -> <p>DTaP, бесклеточный коклюшный компонент</p> | I6: =IFERROR(__xludf.DUMMYFUNCTION("""COMPUTED_VALUE"""),"DTaP, бесклеточный коклюшный компонент") -> DTaP, бесклеточный коклюшный компонент | J6: =IFERROR(__xludf.DUMMYFUNCTION("""COMPUTED_VALUE"""),0.5) -> 0.5 | K6: =IFERROR(__xludf.DUMMYFUNCTION("""COMPUTED_VALUE"""),44712.0) -> 44712 | L6: =IFERROR(__xludf.DUMMYFUNCTION("""COMPUTED_VALUE"""),45689.0) -> 45689 | M6: =IFERROR(__xludf.DUMMYFUNCTION("""COMPUTED_VALUE"""),"есть") -> есть
A7: =IFERROR(__xludf.DUMMYFUNCTION("""COMPUTED_VALUE"""),6.0) -> 6 | B7: =IFERROR(__xludf.DUMMYFUNCTION("""COMPUTED_VALUE"""),"AKDS_Microgen") -> AKDS_Microgen | C7: =IFERROR(__xludf.DUMMYFUNCTION("""COMPUTED_VALUE"""),"https://grls.rosminzdrav.ru/Grls_View_v2.aspx?routingGuid=73faea00-ddd0-427e-9f40-49dfea9a2470") -> https://grls.rosminzdrav.ru/Grls_View_v2.aspx?routingGuid=73faea00-ddd0-427e-9f40-49dfea9a2470 | D7: =IFERROR(__xludf.DUMMYFUNCTION("""COMPUTED_VALUE"""),"АКДС (Микроген)") -> АКДС (Микроген) | E7: =IFERROR(__xludf.DUMMYFUNCTION("""COMPUTED_VALUE"""),"Вакцина коклюшно-дифтерийно-столбнячная адсорбированная (АКДС-вакцина)") -> Вакцина коклюшно-дифтерийно-столбнячная адсорбированная (АКДС-вакцина) | F7: =IFERROR(__xludf.DUMMYFUNCTION("""COMPUTED_VALUE"""),"Микроген") -> Микроген | G7: =IFERROR(__xludf.DUMMYFUNCTION("""COMPUTED_VALUE"""),"in use") -> in use | H7: =IFERROR(__xludf.DUMMYFUNCTION("""COMPUTED_VALUE"""),"<p>DTaP, цельноклеточный коклюшный компонент</p>") -> <p>DTaP, цельноклеточный коклюшный компонент</p> | I7: =IFERROR(__xludf.DUMMYFUNCTION("""COMPUTED_VALUE"""),"DTaP, цельноклеточный коклюшный компонент") -> DTaP, цельноклеточный коклюшный компонент | J7: =IFERROR(__xludf.DUMMYFUNCTION("""COMPUTED_VALUE"""),0.5) -> 0.5 | K7: =IFERROR(__xludf.DUMMYFUNCTION("""COMPUTED_VALUE"""),44712.0) -> 44712 | L7: =IFERROR(__xludf.DUMMYFUNCTION("""COMPUTED_VALUE"""),45689.0) -> 45689 | M7: =IFERROR(__xludf.DUMMYFUNCTION("""COMPUTED_VALUE"""),"есть") -> есть
A8: =IFERROR(__xludf.DUMMYFUNCTION("""COMPUTED_VALUE"""),7.0) -> 7 | B8: =IFERROR(__xludf.DUMMYFUNCTION("""COMPUTED_VALUE"""),"AKDS_Biomed") -> AKDS_Biomed | C8: =IFERROR(__xludf.DUMMYFUNCTION("""COMPUTED_VALUE"""),"https://grls.rosminzdrav.ru/Grls_View_v2.aspx?routingGuid=aba4f9bd-407e-42a8-a32c-1105beece2f6") -> https://grls.rosminzdrav.ru/Grls_View_v2.aspx?routingGuid=aba4f9bd-407e-42a8-a32c-1105beece2f6 | D8: =IFERROR(__xludf.DUMMYFUNCTION("""COMPUTED_VALUE"""),"АКДС (Биомед)") -> АКДС (Биомед) | E8: =IFERROR(__xludf.DUMMYFUNCTION("""COMPUTED_VALUE"""),"Вакцина коклюшно-дифтерийно-столбнячная адсорбированная (АКДС-вакцина)") -> Вакцина коклюшно-дифтерийно-столбнячная адсорбированная (АКДС-вакцина) | F8: =IFERROR(__xludf.DUMMYFUNCTION("""COMPUTED_VALUE"""),"Биомед") -> Биомед | G8: =IFERROR(__xludf.DUMMYFUNCTION("""COMPUTED_VALUE"""),"in use") -> in use | H8: =IFERROR(__xludf.DUMMYFUNCTION("""COMPUTED_VALUE"""),"<p>DTaP, цельноклеточный коклюшный компонент</p>") -> <p>DTaP, цельноклеточный коклюшный компонент</p> | I8: =IFERROR(__xludf.DUMMYFUNCTION("""COMPUTED_VALUE"""),"DTaP, цельноклеточный коклюшный компонент") -> DTaP, цельноклеточный коклюшный компонент | J8: =IFERROR(__xludf.DUMMYFUNCTION("""COMPUTED_VALUE"""),0.5) -> 0.5 | K8: =IFERROR(__xludf.DUMMYFUNCTION("""COMPUTED_VALUE"""),44712.0) -> 44712 | L8: =IFERROR(__xludf.DUMMYFUNCTION("""COMPUTED_VALUE"""),45079.0) -> 45079 | M8: =IFERROR(__xludf.DUMMYFUNCTION("""COMPUTED_VALUE"""),"нет") -> нет
A9: =IFERROR(__xludf.DUMMYFUNCTION("""COMPUTED_VALUE"""),8.0) -> 8 | B9: =IFERROR(__xludf.DUMMYFUNCTION("""COMPUTED_VALUE"""),"Bubo_kok") -> Bubo_kok | C9: =IFERROR(__xludf.DUMMYFUNCTION("""COMPUTED_VALUE"""),"https://grls.rosminzdrav.ru/Grls_View_v2.aspx?routingGuid=81b39c46-e795-4993-b85b-0cf51e164f6b") -> https://grls.rosminzdrav.ru/Grls_View_v2.aspx?routingGuid=81b39c46-e795-4993-b85b-0cf51e164f6b | D9: =IFERROR(__xludf.DUMMYFUNCTION("""COMPUTED_VALUE"""),"Бубо-Кок") -> Бубо-Кок | E9: =IFERROR(__xludf.DUMMYFUNCTION("""COMPUTED_VALUE"""),"Бубо®-Кок") -> Бубо®-Кок | F9: =IFERROR(__xludf.DUMMYFUNCTION("""COMPUTED_VALUE"""),"Комбиотех") -> Комбиотех | G9: =IFERROR(__xludf.DUMMYFUNCTION("""COMPUTED_VALUE"""),"not in use") -> not in use | J9: =IFERROR(__xludf.DUMMYFUNCTION("""COMPUTED_VALUE"""),0.5) -> 0.5 | K9: =IFERROR(__xludf.DUMMYFUNCTION("""COMPUTED_VALUE"""),44712.0) -> 44712 | L9: =IFERROR(__xludf.DUMMYFUNCTION("""COMPUTED_VALUE"""),44712.0) -> 44712 | M9: =IFERROR(__xludf.DUMMYFUNCTION("""COMPUTED_VALUE"""),"нет") -> нет
A10: =IFERROR(__xludf.DUMMYFUNCTION("""COMPUTED_VALUE"""),9.0) -> 9 | B10: =IFERROR(__xludf.DUMMYFUNCTION("""COMPUTED_VALUE"""),"Pentaxim") -> Pentaxim | C10: =IFERROR(__xludf.DUMMYFUNCTION("""COMPUTED_VALUE"""),"https://grls.rosminzdrav.ru/Grls_View_v2.aspx?routingGuid=04b887e5-95d7-44df-beaa-a539fe956444") -> https://grls.rosminzdrav.ru/Grls_View_v2.aspx?routingGuid=04b887e5-95d7-44df-beaa-a539fe956444 | D10: =IFERROR(__xludf.DUMMYFUNCTION("""COMPUTED_VALUE"""),"Пентаксим") -> Пентаксим | E10: =IFERROR(__xludf.DUMMYFUNCTION("""COMPUTED_VALUE"""),"Пентаксим® (вакцина для профилактики дифтерии и столбняка адсорбированная, коклюша ацеллюлярная, полиомиелита инактивированная и инфекций, вызываемых Haemophilus influenzae тип b, конъюгированная)") -> Пентаксим® (вакцина для профилактики дифтерии и столбняка адсорбированная, коклюша ацеллюлярная, полиомиелита инактивированная и инфекций, вызываемых Haemophilus influenzae тип b, конъюгированная) | F10: =IFERROR(__xludf.DUMMYFUNCTION("""COMPUTED_VALUE"""),"Sanofi Pasteur") -> Sanofi Pasteur | G10: =IFERROR(__xludf.DUMMYFUNCTION("""COMPUTED_VALUE"""),"in use") -> in use | H10: =IFERROR(__xludf.DUMMYFUNCTION("""COMPUTED_VALUE"""),"<p>DTaP-IPV-Hib, бесклеточный коклюшный компонент</p>") -> <p>DTaP-IPV-Hib, бесклеточный коклюшный компонент</p> | I10: =IFERROR(__xludf.DUMMYFUNCTION("""COMPUTED_VALUE"""),"DTaP-IPV-Hib, бесклеточный коклюшный компонент") -> DTaP-IPV-Hib, бесклеточный коклюшный компонент | J10: =IFERROR(__xludf.DUMMYFUNCTION("""COMPUTED_VALUE"""),0.5) -> 0.5 | K10: =IFERROR(__xludf.DUMMYFUNCTION("""COMPUTED_VALUE"""),44712.0) -> 44712 | L10: =IFERROR(__xludf.DUMMYFUNCTION("""COMPUTED_VALUE"""),46204.0) -> 46204 | M10: =IFERROR(__xludf.DUMMYFUNCTION("""COMPUTED_VALUE"""),"есть") -> есть
A11: =IFERROR(__xludf.DUMMYFUNCTION("""COMPUTED_VALUE"""),10.0) -> 10 | B11: =IFERROR(__xludf.DUMMYFUNCTION("""COMPUTED_VALUE"""),"Infanrix_Hexa") -> Infanrix_Hexa | C11: =IFERROR(__xludf.DUMMYFUNCTION("""COMPUTED_VALUE"""),"https://grls.rosminzdrav.ru/Grls_View_v2.aspx?routingGuid=f9454b06-083d-4c13-8eda-e54a19450d13") -> https://grls.rosminzdrav.ru/Grls_View_v2.aspx?routingGuid=f9454b06-083d-4c13-8eda-e54a19450d13 | D11: =IFERROR(__xludf.DUMMYFUNCTION("""COMPUTED_VALUE"""),"Инфанрикс Гекса") -> Инфанрикс Гекса | E11: =IFERROR(__xludf.DUMMYFUNCTION("""COMPUTED_VALUE"""),"Инфанрикс® Гекса (Вакцина для профилактики дифтерии, столбняка, коклюша (бесклеточная), полиомиелита (инактивированная), гепатита B комбинированная, адсорбированная в комплекте с вакциной для профилактики инфекции, вызываемой Haemophilus influenzae тип b "&"конъюгированной, адсорбированной)") -> Инфанрикс® Гекса (Вакцина для профилактики дифтерии, столбняка, коклюша (бесклеточная), полиомиелита (инактивированная), гепатита B комбинированная, адсорбированная в комплекте с вакциной для профилактики инфекции, вызываемой Haemophilus influenzae тип b конъюгированной, адсорбированной) | F11: =IFERROR(__xludf.DUMMYFUNCTION("""COMPUTED_VALUE"""),"GSK") -> GSK | G11: =IFERROR(__xludf.DUMMYFUNCTION("""COMPUTED_VALUE"""),"in use") -> in use | H11: =IFERROR(__xludf.DUMMYFUNCTION("""COMPUTED_VALUE"""),"<p>DTaP-IPV-Hib-HepB, бесклеточный коклюшный компонент</p>") -> <p>DTaP-IPV-Hib-HepB, бесклеточный коклюшный компонент</p> | I11: =IFERROR(__xludf.DUMMYFUNCTION("""COMPUTED_VALUE"""),"DTaP-IPV-Hib-HepB, бесклеточный коклюшный компонент") -> DTaP-IPV-Hib-HepB, бесклеточный коклюшный компонент | J11: =IFERROR(__xludf.DUMMYFUNCTION("""COMPUTED_VALUE"""),0.5) -> 0.5 | K11: =IFERROR(__xludf.DUMMYFUNCTION("""COMPUTED_VALUE"""),44712.0) -> 44712 | L11: =IFERROR(__xludf.DUMMYFUNCTION("""COMPUTED_VALUE"""),46000.0) -> 46000 | M11: =IFERROR(__xludf.DUMMYFUNCTION("""COMPUTED_VALUE"""),"есть") -> есть
A12: =IFERROR(__xludf.DUMMYFUNCTION("""COMPUTED_VALUE"""),11.0) -> 11 | B12: =IFERROR(__xludf.DUMMYFUNCTION("""COMPUTED_VALUE"""),"Bubo_M") -> Bubo_M | C12: =IFERROR(__xludf.DUMMYFUNCTION("""COMPUTED_VALUE"""),"https://grls.rosminzdrav.ru/Grls_View_v2.aspx?routingGuid=0b7d30f1-b40f-453c-9c7b-800a072aa409") -> https://grls.rosminzdrav.ru/Grls_View_v2.aspx?routingGuid=0b7d30f1-b40f-453c-9c7b-800a072aa409 | D12: =IFERROR(__xludf.DUMMYFUNCTION("""COMPUTED_VALUE"""),"Бубо-М") -> Бубо-М | E12: =IFERROR(__xludf.DUMMYFUNCTION("""COMPUTED_VALUE"""),"Бубо®-М (Вакцина комбинированная гепатита B и анатоксина дифтерийно-столбнячного с уменьшенным содержанием антигенов адсорбированная жидкая)") -> Бубо®-М (Вакцина комбинированная гепатита B и анатоксина дифтерийно-столбнячного с уменьшенным содержанием антигенов адсорбированная жидкая) | F12: =IFERROR(__xludf.DUMMYFUNCTION("""COMPUTED_VALUE"""),"Комбиотех") -> Комбиотех | G12: =IFERROR(__xludf.DUMMYFUNCTION("""COMPUTED_VALUE"""),"not in use") -> not in use | J12: =IFERROR(__xludf.DUMMYFUNCTION("""COMPUTED_VALUE"""),0.5) -> 0.5 | K12: =IFERROR(__xludf.DUMMYFUNCTION("""COMPUTED_VALUE"""),44712.0) -> 44712 | L12: =IFERROR(__xludf.DUMMYFUNCTION("""COMPUTED_VALUE"""),46188.0) -> 46188 | M12: =IFERROR(__xludf.DUMMYFUNCTION("""COMPUTED_VALUE"""),"есть") -> есть
A13: =IFERROR(__xludf.DUMMYFUNCTION("""COMPUTED_VALUE"""),12.0) -> 12 | B13: =IFERROR(__xludf.DUMMYFUNCTION("""COMPUTED_VALUE"""),"AD_M_Microgen") -> AD_M_Microgen | C13: =IFERROR(__xludf.DUMMYFUNCTION("""COMPUTED_VALUE"""),"https://grls.rosminzdrav.ru/Grls_View_v2.aspx?routingGuid=fa42329f-9433-4dc6-af8a-f811be13fb87") -> https://grls.rosminzdrav.ru/Grls_View_v2.aspx?routingGuid=fa42329f-9433-4dc6-af8a-f811be13fb87 | D13: =IFERROR(__xludf.DUMMYFUNCTION("""COMPUTED_VALUE"""),"АД-М (Микроген)") -> АД-М (Микроген) | E13: =IFERROR(__xludf.DUMMYFUNCTION("""COMPUTED_VALUE"""),"Анатоксин дифтерийный очищенный адсорбированный с уменьшенным содержанием антигена жидкий (АД-М-анатоксин)") -> Анатоксин дифтерийный очищенный адсорбированный с уменьшенным содержанием антигена жидкий (АД-М-анатоксин) | F13: =IFERROR(__xludf.DUMMYFUNCTION("""COMPUTED_VALUE"""),"Микроген") -> Микроген | G13: =IFERROR(__xludf.DUMMYFUNCTION("""COMPUTED_VALUE"""),"in use") -> in use | J13: =IFERROR(__xludf.DUMMYFUNCTION("""COMPUTED_VALUE"""),0.5) -> 0.5 | K13: =IFERROR(__xludf.DUMMYFUNCTION("""COMPUTED_VALUE"""),44712.0) -> 44712 | L13: =IFERROR(__xludf.DUMMYFUNCTION("""COMPUTED_VALUE"""),45689.0) -> 45689 | M13: =IFERROR(__xludf.DUMMYFUNCTION("""COMPUTED_VALUE"""),"https://lk.regmed.ru/Register/GetPDFfromDAToken?Token=9916a334-02fd-4f23-ad64-c996916ac2d6") -> https://lk.regmed.ru/Register/GetPDFfromDAToken?Token=9916a334-02fd-4f23-ad64-c996916ac2d6
A14: =IFERROR(__xludf.DUMMYFUNCTION("""COMPUTED_VALUE"""),13.0) -> 13 | B14: =IFERROR(__xludf.DUMMYFUNCTION("""COMPUTED_VALUE"""),"ADS_Microgen") -> ADS_Microgen | C14: =IFERROR(__xludf.DUMMYFUNCTION("""COMPUTED_VALUE"""),"https://grls.rosminzdrav.ru/Grls_View_v2.aspx?routingGuid=82af2230-6ada-4cb2-a263-0a2c1f841be2") -> https://grls.rosminzdrav.ru/Grls_View_v2.aspx?routingGuid=82af2230-6ada-4cb2-a263-0a2c1f841be2 | D14: =IFERROR(__xludf.DUMMYFUNCTION("""COMPUTED_VALUE"""),"АДС (Микроген)") -> АДС (Микроген) | E14: =IFERROR(__xludf.DUMMYFUNCTION("""COMPUTED_VALUE"""),"Анатоксин дифтерийно-столбнячный очищенный адсорбированный жидкий (АДС-анатоксин)") -> Анатоксин дифтерийно-столбнячный очищенный адсорбированный жидкий (АДС-анатоксин) | F14: =IFERROR(__xludf.DUMMYFUNCTION("""COMPUTED_VALUE"""),"Микроген") -> Микроген | G14: =IFERROR(__xludf.DUMMYFUNCTION("""COMPUTED_VALUE"""),"in use") -> in use | J14: =IFERROR(__xludf.DUMMYFUNCTION("""COMPUTED_VALUE"""),0.5) -> 0.5 | K14: =IFERROR(__xludf.DUMMYFUNCTION("""COMPUTED_VALUE"""),44712.0) -> 44712 | L14: =IFERROR(__xludf.DUMMYFUNCTION("""COMPUTED_VALUE"""),45689.0) -> 45689 | M14: =IFERROR(__xludf.DUMMYFUNCTION("""COMPUTED_VALUE"""),"https://lk.regmed.ru/Register/GetPDFfromDAToken?Token=ff0cddac-c2c3-4fac-84e2-d026f4f71869") -> https://lk.regmed.ru/Register/GetPDFfromDAToken?Token=ff0cddac-c2c3-4fac-84e2-d026f4f71869
A15: =IFERROR(__xludf.DUMMYFUNCTION("""COMPUTED_VALUE"""),14.0) -> 14 | B15: =IFERROR(__xludf.DUMMYFUNCTION("""COMPUTED_VALUE"""),"ADS_M_Microgen") -> ADS_M_Microgen | C15: =IFERROR(__xludf.DUMMYFUNCTION("""COMPUTED_VALUE"""),"https://grls.rosminzdrav.ru/Grls_View_v2.aspx?routingGuid=7901c857-1397-49d2-9a93-f8c171091efa") -> https://grls.rosminzdrav.ru/Grls_View_v2.aspx?routingGuid=7901c857-1397-49d2-9a93-f8c171091efa | D15: =IFERROR(__xludf.DUMMYFUNCTION("""COMPUTED_VALUE"""),"АДС-М (Микроген)") -> АДС-М (Микроген) | E15: =IFERROR(__xludf.DUMMYFUNCTION("""COMPUTED_VALUE"""),"Анатоксин дифтерийно-столбнячный очищенный адсорбированный с уменьшенным содержанием антигенов жидкий (АДС-М-анатоксин)") -> Анатоксин дифтерийно-столбнячный очищенный адсорбированный с уменьшенным содержанием антигенов жидкий (АДС-М-анатоксин) | F15: =IFERROR(__xludf.DUMMYFUNCTION("""COMPUTED_VALUE"""),"Микроген") -> Микроген | G15: =IFERROR(__xludf.DUMMYFUNCTION("""COMPUTED_VALUE"""),"in use") -> in use | J15: =IFERROR(__xludf.DUMMYFUNCTION("""COMPUTED_VALUE"""),0.5) -> 0.5 | K15: =IFERROR(__xludf.DUMMYFUNCTION("""COMPUTED_VALUE"""),44712.0) -> 44712 | L15: =IFERROR(__xludf.DUMMYFUNCTION("""COMPUTED_VALUE"""),45861.0) -> 45861 | M15: =IFERROR(__xludf.DUMMYFUNCTION("""COMPUTED_VALUE"""),"https://lk.regmed.ru/Register/GetPDFfromDAToken?Token=67df064e-3139-49b6-917f-a5131fbd35d6") -> https://lk.regmed.ru/Register/GetPDFfromDAToken?Token=67df064e-3139-49b6-917f-a5131fbd35d6
A16: =IFERROR(__xludf.DUMMYFUNCTION("""COMPUTED_VALUE"""),15.0) -> 15 | B16: =IFERROR(__xludf.DUMMYFUNCTION("""COMPUTED_VALUE"""),"ADS_M_Biomed") -> ADS_M_Biomed | C16: =IFERROR(__xludf.DUMMYFUNCTION("""COMPUTED_VALUE"""),"https://grls.rosminzdrav.ru/Grls_View_v2.aspx?routingGuid=795940d7 – 9c11-423c-98fe-44a1d739a593") -> https://grls.rosminzdrav.ru/Grls_View_v2.aspx?routingGuid=795940d7 – 9c11-423c-98fe-44a1d739a593 | D16: =IFERROR(__xludf.DUMMYFUNCTION("""COMPUTED_VALUE"""),"АДС-М (Биомед)") -> АДС-М (Биомед) | E16: =IFERROR(__xludf.DUMMYFUNCTION("""COMPUTED_VALUE"""),"Анатоксин дифтерийно-столбнячный очищенный адсорбированный с уменьшенным содержанием антигенов жидкий (АДС-М анатоксин)") -> Анатоксин дифтерийно-столбнячный очищенный адсорбированный с уменьшенным содержанием антигенов жидкий (АДС-М анатоксин) | F16: =IFERROR(__xludf.DUMMYFUNCTION("""COMPUTED_VALUE"""),"Биомед") -> Биомед | G16: =IFERROR(__xludf.DUMMYFUNCTION("""COMPUTED_VALUE"""),"in use") -> in use | J16: =IFERROR(__xludf.DUMMYFUNCTION("""COMPUTED_VALUE"""),0.5) -> 0.5 | K16: =IFERROR(__xludf.DUMMYFUNCTION("""COMPUTED_VALUE"""),44712.0) -> 44712 | L16: =IFERROR(__xludf.DUMMYFUNCTION("""COMPUTED_VALUE"""),44712.0) -> 44712 | M16: =IFERROR(__xludf.DUMMYFUNCTION("""COMPUTED_VALUE"""),"нет") -> нет
A17: =IFERROR(__xludf.DUMMYFUNCTION("""COMPUTED_VALUE"""),16.0) -> 16 | B17: =IFERROR(__xludf.DUMMYFUNCTION("""COMPUTED_VALUE"""),"Adacel") -> Adacel | C17: =IFERROR(__xludf.DUMMYFUNCTION("""COMPUTED_VALUE"""),"https://grls.rosminzdrav.ru/Grls_View_v2.aspx?routingGuid=d8627a3c-16a5-46d0-b31f-e60eb2448d80") -> https://grls.rosminzdrav.ru/Grls_View_v2.aspx?routingGuid=d8627a3c-16a5-46d0-b31f-e60eb2448d80 | D17: =IFERROR(__xludf.DUMMYFUNCTION("""COMPUTED_VALUE"""),"Адасель") -> Адасель | E17: =IFERROR(__xludf.DUMMYFUNCTION("""COMPUTED_VALUE"""),"АДАСЕЛЬ® [Вакцина для профилактики дифтерии (с уменьшенным содержанием антигена), коклюша (с уменьшенным содержанием антигена, бесклеточная) и столбняка, комбинированная, адсорбированная]") -> АДАСЕЛЬ® [Вакцина для профилактики дифтерии (с уменьшенным содержанием антигена), коклюша (с уменьшенным содержанием антигена, бесклеточная) и столбняка, комбинированная, адсорбированная] | F17: =IFERROR(__xludf.DUMMYFUNCTION("""COMPUTED_VALUE"""),"Санофи Пастер Лимитед") -> Санофи Пастер Лимитед | G17: =IFERROR(__xludf.DUMMYFUNCTION("""COMPUTED_VALUE"""),"in use") -> in use | H17: =IFERROR(__xludf.DUMMYFUNCTION("""COMPUTED_VALUE"""),"<p>Tdap, сниженное содержание дифтерийного и коклюшного компонента, бесклеточный коклюшный компонент</p>") -> <p>Tdap, сниженное содержание дифтерийного и коклюшного компонента, бесклеточный коклюшный компонент</p> | I17: =IFERROR(__xludf.DUMMYFUNCTION("""COMPUTED_VALUE"""),"Tdap, сниженное содержание дифтерийного и коклюшного компонента, бесклеточный коклюшный компонент") -> Tdap, сниженное содержание дифтерийного и коклюшного компонента, бесклеточный коклюшный компонент | J17: =IFERROR(__xludf.DUMMYFUNCTION("""COMPUTED_VALUE"""),0.5) -> 0.5 | K17: =IFERROR(__xludf.DUMMYFUNCTION("""COMPUTED_VALUE"""),44712.0) -> 44712 | L17: =IFERROR(__xludf.DUMMYFUNCTION("""COMPUTED_VALUE"""),45689.0) -> 45689 | M17: =IFERROR(__xludf.DUMMYFUNCTION("""COMPUTED_VALUE"""),"https://lk.regmed.ru/Register/GetPDFfromDAToken?Token=7fabfdf2-4fe8-448e-859f-9a4b20cc3213") -> https://lk.regmed.ru/Register/GetPDFfromDAToken?Token=7fabfdf2-4fe8-448e-859f-9a4b20cc3213
A18: =IFERROR(__xludf.DUMMYFUNCTION("""COMPUTED_VALUE"""),17.0) -> 17 | B18: =IFERROR(__xludf.DUMMYFUNCTION("""COMPUTED_VALUE"""),"Algavac_M") -> Algavac_M | C18: =IFERROR(__xludf.DUMMYFUNCTION("""COMPUTED_VALUE"""),"https://grls.rosminzdrav.ru/Grls_View_v2.aspx?routingGuid=2bf12380-3a71-4642-a9a3-ef0e4ca9b815") -> https://grls.rosminzdrav.ru/Grls_View_v2.aspx?routingGuid=2bf12380-3a71-4642-a9a3-ef0e4ca9b815 | D18: =IFERROR(__xludf.DUMMYFUNCTION("""COMPUTED_VALUE"""),"Альгавак М") -> Альгавак М | E18: =IFERROR(__xludf.DUMMYFUNCTION("""COMPUTED_VALUE"""),"АЛЬГАВАК® М") -> АЛЬГАВАК® М | G18: =IFERROR(__xludf.DUMMYFUNCTION("""COMPUTED_VALUE"""),"in use") -> in use | K18: =IFERROR(__xludf.DUMMYFUNCTION("""COMPUTED_VALUE"""),44712.0) -> 44712 | L18: =IFERROR(__xludf.DUMMYFUNCTION("""COMPUTED_VALUE"""),45715.0) -> 45715 | M18: =IFERROR(__xludf.DUMMYFUNCTION("""COMPUTED_VALUE"""),"нет") -> нет
A19: =IFERROR(__xludf.DUMMYFUNCTION("""COMPUTED_VALUE"""),18.0) -> 18 | B19: =IFERROR(__xludf.DUMMYFUNCTION("""COMPUTED_VALUE"""),"Algavac") -> Algavac | C19: =IFERROR(__xludf.DUMMYFUNCTION("""COMPUTED_VALUE"""),"https://grls.rosminzdrav.ru/Grls_View_v2.aspx?routingGuid=4f6d874c-7745-4c6b-8c90-228a1f2f3484") -> https://grls.rosminzdrav.ru/Grls_View_v2.aspx?routingGuid=4f6d874c-7745-4c6b-8c90-228a1f2f3484 | D19: =IFERROR(__xludf.DUMMYFUNCTION("""COMPUTED_VALUE"""),"Альгавак") -> Альгавак | E19: =IFERROR(__xludf.DUMMYFUNCTION("""COMPUTED_VALUE"""),"АЛЬГАВАК®") -> АЛЬГАВАК® | G19: =IFERROR(__xludf.DUMMYFUNCTION("""COMPUTED_VALUE"""),"not in use") -> not in use | H19: =IFERROR(__xludf.DUMMYFUNCTION("""COMPUTED_VALUE"""),"<p>Вакцину АЛЬГАВАК можно использовать для ревакцинации в тех случаях, когда предыдущая вакцинация осуществлялась другими инактивированными вакцинами для профилактики гепатита А.</p>") -> <p>Вакцину АЛЬГАВАК можно использовать для ревакцинации в тех случаях, когда предыдущая вакцинация осуществлялась другими инактивированными вакцинами для профилактики гепатита А.</p> | I19: =IFERROR(__xludf.DUMMYFUNCTION("""COMPUTED_VALUE"""),"Вакцину АЛЬГАВАК можно использовать для ревакцинации в тех случаях, когда предыдущая вакцинация осуществлялась другими инактивированными вакцинами для профилактики гепатита А.") -> Вакцину АЛЬГАВАК можно использовать для ревакцинации в тех случаях, когда предыдущая вакцинация осуществлялась другими инактивированными вакцинами для профилактики гепатита А. | K19: =IFERROR(__xludf.DUMMYFUNCTION("""COMPUTED_VALUE"""),44712.0) -> 44712 | L19: =IFERROR(__xludf.DUMMYFUNCTION("""COMPUTED_VALUE"""),46188.0) -> 46188 | M19: =IFERROR(__xludf.DUMMYFUNCTION("""COMPUTED_VALUE"""),"есть") -> есть
A20: =IFERROR(__xludf.DUMMYFUNCTION("""COMPUTED_VALUE"""),19.0) -> 19 | B20: =IFERROR(__xludf.DUMMYFUNCTION("""COMPUTED_VALUE"""),"Havrix_720") -> Havrix_720 | C20: =IFERROR(__xludf.DUMMYFUNCTION("""COMPUTED_VALUE"""),"https://grls.rosminzdrav.ru/Grls_View_v2.aspx?routingGuid=b8dfef4d-a4cf-4d18-9599-1a3fb42864c7") -> https://grls.rosminzdrav.ru/Grls_View_v2.aspx?routingGuid=b8dfef4d-a4cf-4d18-9599-1a3fb42864c7 | D20: =IFERROR(__xludf.DUMMYFUNCTION("""COMPUTED_VALUE"""),"Хаврикс 720") -> Хаврикс 720 | E20: =IFERROR(__xludf.DUMMYFUNCTION("""COMPUTED_VALUE"""),"Хаврикс® (вакцина против гепатита А инактивированная)") -> Хаврикс® (вакцина против гепатита А инактивированная) | F20: =IFERROR(__xludf.DUMMYFUNCTION("""COMPUTED_VALUE"""),"GSK") -> GSK | G20: =IFERROR(__xludf.DUMMYFUNCTION("""COMPUTED_VALUE"""),"in use") -> in use | K20: =IFERROR(__xludf.DUMMYFUNCTION("""COMPUTED_VALUE"""),44712.0) -> 44712 | L20: =IFERROR(__xludf.DUMMYFUNCTION("""COMPUTED_VALUE"""),45689.0) -> 45689 | M20: =IFERROR(__xludf.DUMMYFUNCTION("""COMPUTED_VALUE"""),"https://lk.regmed.ru/Register/GetPDFfromDAToken?Token=6d0a7c06-3859-4f01-8d37-bf8887046a88") -> https://lk.regmed.ru/Register/GetPDFfromDAToken?Token=6d0a7c06-3859-4f01-8d37-bf8887046a88
A21: =IFERROR(__xludf.DUMMYFUNCTION("""COMPUTED_VALUE"""),20.0) -> 20 | B21: =IFERROR(__xludf.DUMMYFUNCTION("""COMPUTED_VALUE"""),"Havrix_1440") -> Havrix_1440 | C21: =IFERROR(__xludf.DUMMYFUNCTION("""COMPUTED_VALUE"""),"https://grls.rosminzdrav.ru/Grls_View_v2.aspx?routingGuid=b8dfef4d-a4cf-4d18-9599-1a3fb42864c7") -> https://grls.rosminzdrav.ru/Grls_View_v2.aspx?routingGuid=b8dfef4d-a4cf-4d18-9599-1a3fb42864c7 | D21: =IFERROR(__xludf.DUMMYFUNCTION("""COMPUTED_VALUE"""),"Хаврикс 1440") -> Хаврикс 1440 | E21: =IFERROR(__xludf.DUMMYFUNCTION("""COMPUTED_VALUE"""),"Хаврикс® (вакцина против гепатита А инактивированная)") -> Хаврикс® (вакцина против гепатита А инактивированная) | F21: =IFERROR(__xludf.DUMMYFUNCTION("""COMPUTED_VALUE"""),"GSK") -> GSK | G21: =IFERROR(__xludf.DUMMYFUNCTION("""COMPUTED_VALUE"""),"not in use") -> not in use | K21: =IFERROR(__xludf.DUMMYFUNCTION("""COMPUTED_VALUE"""),44712.0) -> 44712 | L21: =IFERROR(__xludf.DUMMYFUNCTION("""COMPUTED_VALUE"""),45689.0) -> 45689 | M21: =IFERROR(__xludf.DUMMYFUNCTION("""COMPUTED_VALUE"""),"https://lk.regmed.ru/Register/GetPDFfromDAToken?Token=6d0a7c06-3859-4f01-8d37-bf8887046a88") -> https://lk.regmed.ru/Register/GetPDFfromDAToken?Token=6d0a7c06-3859-4f01-8d37-bf8887046a88
A22: =IFERROR(__xludf.DUMMYFUNCTION("""COMPUTED_VALUE"""),21.0) -> 21 | B22: =IFERROR(__xludf.DUMMYFUNCTION("""COMPUTED_VALUE"""),"Avaxim_80") -> Avaxim_80 | C22: =IFERROR(__xludf.DUMMYFUNCTION("""COMPUTED_VALUE"""),"https://grls.rosminzdrav.ru/Grls_View_v2.aspx?routingGuid=0814c0aa-66c2-4566-a774-02de4c45b6ac") -> https://grls.rosminzdrav.ru/Grls_View_v2.aspx?routingGuid=0814c0aa-66c2-4566-a774-02de4c45b6ac | D22: =IFERROR(__xludf.DUMMYFUNCTION("""COMPUTED_VALUE"""),"Аваксим 80") -> Аваксим 80 | E22: =IFERROR(__xludf.DUMMYFUNCTION("""COMPUTED_VALUE"""),"Аваксим 80 (вакцина для профилактики гепатита A инактивированная, адсорбированная)") -> Аваксим 80 (вакцина для профилактики гепатита A инактивированная, адсорбированная) | G22: =IFERROR(__xludf.DUMMYFUNCTION("""COMPUTED_VALUE"""),"not in use") -> not in use | K22: =IFERROR(__xludf.DUMMYFUNCTION("""COMPUTED_VALUE"""),44712.0) -> 44712 | L22: =IFERROR(__xludf.DUMMYFUNCTION("""COMPUTED_VALUE"""),44916.0) -> 44916 | M22: =IFERROR(__xludf.DUMMYFUNCTION("""COMPUTED_VALUE"""),"нет") -> нет
A23: =IFERROR(__xludf.DUMMYFUNCTION("""COMPUTED_VALUE"""),22.0) -> 22 | B23: =IFERROR(__xludf.DUMMYFUNCTION("""COMPUTED_VALUE"""),"Avaxim_160") -> Avaxim_160 | C23: =IFERROR(__xludf.DUMMYFUNCTION("""COMPUTED_VALUE"""),"https://grls.rosminzdrav.ru/Grls_View_v2.aspx?routingGuid=658e07cb-fcb9-412f-9392-b9e9e21a6343") -> https://grls.rosminzdrav.ru/Grls_View_v2.aspx?routingGuid=658e07cb-fcb9-412f-9392-b9e9e21a6343 | D23: =IFERROR(__xludf.DUMMYFUNCTION("""COMPUTED_VALUE"""),"Аваксим 160") -> Аваксим 160 | E23: =IFERROR(__xludf.DUMMYFUNCTION("""COMPUTED_VALUE"""),"Аваксим 160 (вакцина для профилактики гепатита A инактивированная, адсорбированная)") -> Аваксим 160 (вакцина для профилактики гепатита A инактивированная, адсорбированная) | G23: =IFERROR(__xludf.DUMMYFUNCTION("""COMPUTED_VALUE"""),"not in use") -> not in use | K23: =IFERROR(__xludf.DUMMYFUNCTION("""COMPUTED_VALUE"""),44712.0) -> 44712 | L23: =IFERROR(__xludf.DUMMYFUNCTION("""COMPUTED_VALUE"""),44916.0) -> 44916 | M23: =IFERROR(__xludf.DUMMYFUNCTION("""COMPUTED_VALUE"""),"нет") -> нет
A24: =IFERROR(__xludf.DUMMYFUNCTION("""COMPUTED_VALUE"""),23.0) -> 23 | B24: =IFERROR(__xludf.DUMMYFUNCTION("""COMPUTED_VALUE"""),"Regevac_0_5") -> Regevac_0_5 | C24: =IFERROR(__xludf.DUMMYFUNCTION("""COMPUTED_VALUE"""),"https://grls.rosminzdrav.ru/Grls_View_v2.aspx?routingGuid=ec6e3b51-e76b-4abf-99cf-7c02bab06091") -> https://grls.rosminzdrav.ru/Grls_View_v2.aspx?routingGuid=ec6e3b51-e76b-4abf-99cf-7c02bab06091 | D24: =IFERROR(__xludf.DUMMYFUNCTION("""COMPUTED_VALUE"""),"Регевак детский") -> Регевак детский | E24: =IFERROR(__xludf.DUMMYFUNCTION("""COMPUTED_VALUE"""),"Регевак® В (Вакцина против гепатита В, рекомбинантная дрожжевая жидкая)") -> Регевак® В (Вакцина против гепатита В, рекомбинантная дрожжевая жидкая) | G24: =IFERROR(__xludf.DUMMYFUNCTION("""COMPUTED_VALUE"""),"in use") -> in use | K24: =IFERROR(__xludf.DUMMYFUNCTION("""COMPUTED_VALUE"""),44712.0) -> 44712 | L24: =IFERROR(__xludf.DUMMYFUNCTION("""COMPUTED_VALUE"""),45988.0) -> 45988 | M24: =IFERROR(__xludf.DUMMYFUNCTION("""COMPUTED_VALUE"""),"есть") -> есть
A25: =IFERROR(__xludf.DUMMYFUNCTION("""COMPUTED_VALUE"""),24.0) -> 24 | B25: =IFERROR(__xludf.DUMMYFUNCTION("""COMPUTED_VALUE"""),"HepB_Combiotech_0_5") -> HepB_Combiotech_0_5 | C25: =IFERROR(__xludf.DUMMYFUNCTION("""COMPUTED_VALUE"""),"https://grls.rosminzdrav.ru/Grls_View_v2.aspx?routingGuid=0cc60fe9-635e-4134-80d2-59a7787e33fb") -> https://grls.rosminzdrav.ru/Grls_View_v2.aspx?routingGuid=0cc60fe9-635e-4134-80d2-59a7787e33fb | D25: =IFERROR(__xludf.DUMMYFUNCTION("""COMPUTED_VALUE"""),"гепатита B (Комбиотех) детская") -> гепатита B (Комбиотех) детская | E25: =IFERROR(__xludf.DUMMYFUNCTION("""COMPUTED_VALUE"""),"Вакцина гепатита В рекомбинантная дрожжевая") -> Вакцина гепатита В рекомбинантная дрожжевая | F25: =IFERROR(__xludf.DUMMYFUNCTION("""COMPUTED_VALUE"""),"Комбиотех") -> Комбиотех | G25: =IFERROR(__xludf.DUMMYFUNCTION("""COMPUTED_VALUE"""),"in use") -> in use | H25: =IFERROR(__xludf.DUMMYFUNCTION("""COMPUTED_VALUE"""),"<p>Препарат выпускается в виде «взрослой» и «детской» вакцины с консервантом и без консерванта.</p>") -> <p>Препарат выпускается в виде «взрослой» и «детской» вакцины с консервантом и без консерванта.</p> | I25: =IFERROR(__xludf.DUMMYFUNCTION("""COMPUTED_VALUE"""),"Препарат выпускается в виде «взрослой» и «детской» вакцины с консервантом и без консерванта.") -> Препарат выпускается в виде «взрослой» и «детской» вакцины с консервантом и без консерванта. | K25: =IFERROR(__xludf.DUMMYFUNCTION("""COMPUTED_VALUE"""),44712.0) -> 44712 | L25: =IFERROR(__xludf.DUMMYFUNCTION("""COMPUTED_VALUE"""),46130.0) -> 46130 | M25: =IFERROR(__xludf.DUMMYFUNCTION("""COMPUTED_VALUE"""),"есть") -> есть
A26: =IFERROR(__xludf.DUMMYFUNCTION("""COMPUTED_VALUE"""),25.0) -> 25 | B26: =IFERROR(__xludf.DUMMYFUNCTION("""COMPUTED_VALUE"""),"Euvax_B_0_5") -> Euvax_B_0_5 | C26: =IFERROR(__xludf.DUMMYFUNCTION("""COMPUTED_VALUE"""),"https://grls.rosminzdrav.ru/Grls_View_v2.aspx?routingGuid=0d28b2ad-18b2-4e7a-8c27-436c0feea6d4") -> https://grls.rosminzdrav.ru/Grls_View_v2.aspx?routingGuid=0d28b2ad-18b2-4e7a-8c27-436c0feea6d4 | D26: =IFERROR(__xludf.DUMMYFUNCTION("""COMPUTED_VALUE"""),"Эувакс В детский") -> Эувакс В детский | E26: =IFERROR(__xludf.DUMMYFUNCTION("""COMPUTED_VALUE"""),"Эувакс В (вакцина для профилактики гепатита B рекомбинантная)") -> Эувакс В (вакцина для профилактики гепатита B рекомбинантная) | G26: =IFERROR(__xludf.DUMMYFUNCTION("""COMPUTED_VALUE"""),"not in use") -> not in use | K26: =IFERROR(__xludf.DUMMYFUNCTION("""COMPUTED_VALUE"""),44712.0) -> 44712 | L26: =IFERROR(__xludf.DUMMYFUNCTION("""COMPUTED_VALUE"""),44712.0) -> 44712 | M26: =IFERROR(__xludf.DUMMYFUNCTION("""COMPUTED_VALUE"""),"нет") -> нет
A27: =IFERROR(__xludf.DUMMYFUNCTION("""COMPUTED_VALUE"""),26.0) -> 26 | B27: =IFERROR(__xludf.DUMMYFUNCTION("""COMPUTED_VALUE"""),"Euvax_B_1_0") -> Euvax_B_1_0 | C27: =IFERROR(__xludf.DUMMYFUNCTION("""COMPUTED_VALUE"""),"https://grls.rosminzdrav.ru/Grls_View_v2.aspx?routingGuid=0d28b2ad-18b2-4e7a-8c27-436c0feea6d4") -> https://grls.rosminzdrav.ru/Grls_View_v2.aspx?routingGuid=0d28b2ad-18b2-4e7a-8c27-436c0feea6d4 | D27: =IFERROR(__xludf.DUMMYFUNCTION("""COMPUTED_VALUE"""),"Эувакс В взрослый") -> Эувакс В взрослый | E27: =IFERROR(__xludf.DUMMYFUNCTION("""COMPUTED_VALUE"""),"Эувакс В (вакцина для профилактики гепатита B рекомбинантная)") -> Эувакс В (вакцина для профилактики гепатита B рекомбинантная) | G27: =IFERROR(__xludf.DUMMYFUNCTION("""COMPUTED_VALUE"""),"not in use") -> not in use | K27: =IFERROR(__xludf.DUMMYFUNCTION("""COMPUTED_VALUE"""),44712.0) -> 44712 | L27: =IFERROR(__xludf.DUMMYFUNCTION("""COMPUTED_VALUE"""),44712.0) -> 44712 | M27: =IFERROR(__xludf.DUMMYFUNCTION("""COMPUTED_VALUE"""),"нет") -> нет
A28: =IFERROR(__xludf.DUMMYFUNCTION("""COMPUTED_VALUE"""),27.0) -> 27 | B28: =IFERROR(__xludf.DUMMYFUNCTION("""COMPUTED_VALUE"""),"Cervarix") -> Cervarix | C28: =IFERROR(__xludf.DUMMYFUNCTION("""COMPUTED_VALUE"""),"https://grls.rosminzdrav.ru/Grls_View_v2.aspx?routingGuid=eb109c11-f04c-4753-b278-73a5bd064e47") -> https://grls.rosminzdrav.ru/Grls_View_v2.aspx?routingGuid=eb109c11-f04c-4753-b278-73a5bd064e47 | D28: =IFERROR(__xludf.DUMMYFUNCTION("""COMPUTED_VALUE"""),"Церварикс") -> Церварикс | E28: =IFERROR(__xludf.DUMMYFUNCTION("""COMPUTED_VALUE"""),"Церварикс®") -> Церварикс® | G28: =IFERROR(__xludf.DUMMYFUNCTION("""COMPUTED_VALUE"""),"in use") -> in use | K28: =IFERROR(__xludf.DUMMYFUNCTION("""COMPUTED_VALUE"""),44712.0) -> 44712 | L28: =IFERROR(__xludf.DUMMYFUNCTION("""COMPUTED_VALUE"""),45689.0) -> 45689 | M28: =IFERROR(__xludf.DUMMYFUNCTION("""COMPUTED_VALUE"""),"https://lk.regmed.ru/Register/GetPDFfromDAToken?Token=f88d9e07-3794-4fde-9c2d-fd91c377cc95") -> https://lk.regmed.ru/Register/GetPDFfromDAToken?Token=f88d9e07-3794-4fde-9c2d-fd91c377cc95
A29: =IFERROR(__xludf.DUMMYFUNCTION("""COMPUTED_VALUE"""),28.0) -> 28 | B29: =IFERROR(__xludf.DUMMYFUNCTION("""COMPUTED_VALUE"""),"Gardasil_4") -> Gardasil_4 | C29: =IFERROR(__xludf.DUMMYFUNCTION("""COMPUTED_VALUE"""),"https://grls.rosminzdrav.ru/Grls_View_v2.aspx?routingGuid=2ae3187f-3553-4a0f-953d-db66a9c16d23") -> https://grls.rosminzdrav.ru/Grls_View_v2.aspx?routingGuid=2ae3187f-3553-4a0f-953d-db66a9c16d23 | D29: =IFERROR(__xludf.DUMMYFUNCTION("""COMPUTED_VALUE"""),"Гардасил 4") -> Гардасил 4 | E29: =IFERROR(__xludf.DUMMYFUNCTION("""COMPUTED_VALUE"""),"Гардасил®") -> Гардасил® | F29: =IFERROR(__xludf.DUMMYFUNCTION("""COMPUTED_VALUE"""),"MSD") -> MSD | G29: =IFERROR(__xludf.DUMMYFUNCTION("""COMPUTED_VALUE"""),"in use") -> in use | H29: =IFERROR(__xludf.DUMMYFUNCTION("""COMPUTED_VALUE"""),"<p>4-валентная</p>") -> <p>4-валентная</p> | I29: =IFERROR(__xludf.DUMMYFUNCTION("""COMPUTED_VALUE"""),"4-валентная") -> 4-валентная | J29: =IFERROR(__xludf.DUMMYFUNCTION("""COMPUTED_VALUE"""),0.5) -> 0.5 | K29: =IFERROR(__xludf.DUMMYFUNCTION("""COMPUTED_VALUE"""),44712.0) -> 44712 | L29: =IFERROR(__xludf.DUMMYFUNCTION("""COMPUTED_VALUE"""),45689.0) -> 45689 | M29: =IFERROR(__xludf.DUMMYFUNCTION("""COMPUTED_VALUE"""),"https://lk.regmed.ru/Register/GetPDFfromDAToken?Token=ba26e648-28b3-4eac-b578-0748c8e03c4e") -> https://lk.regmed.ru/Register/GetPDFfromDAToken?Token=ba26e648-28b3-4eac-b578-0748c8e03c4e
A30: =IFERROR(__xludf.DUMMYFUNCTION("""COMPUTED_VALUE"""),29.0) -> 29 | B30: =IFERROR(__xludf.DUMMYFUNCTION("""COMPUTED_VALUE"""),"Sputnik") -> Sputnik | C30: =IFERROR(__xludf.DUMMYFUNCTION("""COMPUTED_VALUE"""),"https://grls.rosminzdrav.ru/Grls_View_v2.aspx?routingGuid=579be5e3-09cf-46b4-8238-f3087cd4e808") -> https://grls.rosminzdrav.ru/Grls_View_v2.aspx?routingGuid=579be5e3-09cf-46b4-8238-f3087cd4e808 | D30: =IFERROR(__xludf.DUMMYFUNCTION("""COMPUTED_VALUE"""),"Спутник V") -> Спутник V | E30: =IFERROR(__xludf.DUMMYFUNCTION("""COMPUTED_VALUE"""),"Гам-КОВИД-Вак Комбинированная векторная вакцина для профилактики коронавирусной инфекции, вызываемой вирусом SARS-CoV-2") -> Гам-КОВИД-Вак Комбинированная векторная вакцина для профилактики коронавирусной инфекции, вызываемой вирусом SARS-CoV-2 | F30: =IFERROR(__xludf.DUMMYFUNCTION("""COMPUTED_VALUE"""),"НИЦЭМ им. Н.Ф. Гамалеи") -> НИЦЭМ им. Н.Ф. Гамалеи | G30: =IFERROR(__xludf.DUMMYFUNCTION("""COMPUTED_VALUE"""),"in use") -> in use | J30: =IFERROR(__xludf.DUMMYFUNCTION("""COMPUTED_VALUE"""),0.5) -> 0.5 | K30: =IFERROR(__xludf.DUMMYFUNCTION("""COMPUTED_VALUE"""),44712.0) -> 44712 | L30: =IFERROR(__xludf.DUMMYFUNCTION("""COMPUTED_VALUE"""),45923.0) -> 45923 | M30: =IFERROR(__xludf.DUMMYFUNCTION("""COMPUTED_VALUE"""),"https://lk.regmed.ru/Register/GetPDFfromDAToken?Token=dc4e4486-14e8-430b-b506-5364c1e11fe7") -> https://lk.regmed.ru/Register/GetPDFfromDAToken?Token=dc4e4486-14e8-430b-b506-5364c1e11fe7
A31: =IFERROR(__xludf.DUMMYFUNCTION("""COMPUTED_VALUE"""),30.0) -> 30 | B31: =IFERROR(__xludf.DUMMYFUNCTION("""COMPUTED_VALUE"""),"Sputnik_Lyo") -> Sputnik_Lyo | C31: =IFERROR(__xludf.DUMMYFUNCTION("""COMPUTED_VALUE"""),"https://grls.rosminzdrav.ru/Grls_View_v2.aspx?routingGuid=ff05de13-f90b-475b-a47c-609c8a0539a7") -> https://grls.rosminzdrav.ru/Grls_View_v2.aspx?routingGuid=ff05de13-f90b-475b-a47c-609c8a0539a7 | D31: =IFERROR(__xludf.DUMMYFUNCTION("""COMPUTED_VALUE"""),"Спутник V (лиофилизат)") -> Спутник V (лиофилизат) | E31: =IFERROR(__xludf.DUMMYFUNCTION("""COMPUTED_VALUE"""),"Гам-КОВИД-Вак-Лио Комбинированная векторная вакцина для профилактики коронавирусной инфекции, вызываемой вирусом SARS-CoV-2") -> Гам-КОВИД-Вак-Лио Комбинированная векторная вакцина для профилактики коронавирусной инфекции, вызываемой вирусом SARS-CoV-2 | G31: =IFERROR(__xludf.DUMMYFUNCTION("""COMPUTED_VALUE"""),"not in use") -> not in use | K31: =IFERROR(__xludf.DUMMYFUNCTION("""COMPUTED_VALUE"""),44712.0) -> 44712 | L31: =IFERROR(__xludf.DUMMYFUNCTION("""COMPUTED_VALUE"""),44712.0) -> 44712 | M31: =IFERROR(__xludf.DUMMYFUNCTION("""COMPUTED_VALUE"""),"нет") -> нет
A32: =IFERROR(__xludf.DUMMYFUNCTION("""COMPUTED_VALUE"""),31.0) -> 31 | B32: =IFERROR(__xludf.DUMMYFUNCTION("""COMPUTED_VALUE"""),"EpiVacCorona") -> EpiVacCorona | C32: =IFERROR(__xludf.DUMMYFUNCTION("""COMPUTED_VALUE"""),"https://grls.rosminzdrav.ru/Grls_View_v2.aspx?routingGuid=fd7355d2-abfa-4846-99da-a1c5c6e8991a") -> https://grls.rosminzdrav.ru/Grls_View_v2.aspx?routingGuid=fd7355d2-abfa-4846-99da-a1c5c6e8991a | D32: =IFERROR(__xludf.DUMMYFUNCTION("""COMPUTED_VALUE"""),"ЭпиВакКорона") -> ЭпиВакКорона | E32: =IFERROR(__xludf.DUMMYFUNCTION("""COMPUTED_VALUE"""),"ЭпиВакКорона Вакцина на основе пептидных антигенов для профилактики COVID-19") -> ЭпиВакКорона Вакцина на основе пептидных антигенов для профилактики COVID-19 | F32: =IFERROR(__xludf.DUMMYFUNCTION("""COMPUTED_VALUE"""),"Вектор") -> Вектор | G32: =IFERROR(__xludf.DUMMYFUNCTION("""COMPUTED_VALUE"""),"not in use") -> not in use | J32: =IFERROR(__xludf.DUMMYFUNCTION("""COMPUTED_VALUE"""),0.5) -> 0.5 | K32: =IFERROR(__xludf.DUMMYFUNCTION("""COMPUTED_VALUE"""),44712.0) -> 44712 | L32: =IFERROR(__xludf.DUMMYFUNCTION("""COMPUTED_VALUE"""),45078.0) -> 45078 | M32: =IFERROR(__xludf.DUMMYFUNCTION("""COMPUTED_VALUE"""),"нет") -> нет
A33: =IFERROR(__xludf.DUMMYFUNCTION("""COMPUTED_VALUE"""),32.0) -> 32 | B33: =IFERROR(__xludf.DUMMYFUNCTION("""COMPUTED_VALUE"""),"Grippol_Microgen") -> Grippol_Microgen | C33: =IFERROR(__xludf.DUMMYFUNCTION("""COMPUTED_VALUE"""),"https://grls.rosminzdrav.ru/Grls_View_v2.aspx?routingGuid=70f8f0f0-7bac-41ec-a36d-51dcd6ebce84") -> https://grls.rosminzdrav.ru/Grls_View_v2.aspx?routingGuid=70f8f0f0-7bac-41ec-a36d-51dcd6ebce84 | D33: =IFERROR(__xludf.DUMMYFUNCTION("""COMPUTED_VALUE"""),"Гриппол (Микроген)") -> Гриппол (Микроген) | E33: =IFERROR(__xludf.DUMMYFUNCTION("""COMPUTED_VALUE"""),"Гриппол® Вакцина гриппозная тривалентная полимер-субъединичная жидкая") -> Гриппол® Вакцина гриппозная тривалентная полимер-субъединичная жидкая | F33: =IFERROR(__xludf.DUMMYFUNCTION("""COMPUTED_VALUE"""),"Микроген") -> Микроген | G33: =IFERROR(__xludf.DUMMYFUNCTION("""COMPUTED_VALUE"""),"not in use") -> not in use | K33: =IFERROR(__xludf.DUMMYFUNCTION("""COMPUTED_VALUE"""),44712.0) -> 44712 | L33: =IFERROR(__xludf.DUMMYFUNCTION("""COMPUTED_VALUE"""),44712.0) -> 44712 | M33: =IFERROR(__xludf.DUMMYFUNCTION("""COMPUTED_VALUE"""),"нет") -> нет
A34: =IFERROR(__xludf.DUMMYFUNCTION("""COMPUTED_VALUE"""),33.0) -> 33 | B34: =IFERROR(__xludf.DUMMYFUNCTION("""COMPUTED_VALUE"""),"Grippol_Petrovax") -> Grippol_Petrovax | C34: =IFERROR(__xludf.DUMMYFUNCTION("""COMPUTED_VALUE"""),"https://grls.rosminzdrav.ru/Grls_View_v2.aspx?routingGuid=ce700a9a-2b35-47e5-a73b-3cf65afee43b") -> https://grls.rosminzdrav.ru/Grls_View_v2.aspx?routingGuid=ce700a9a-2b35-47e5-a73b-3cf65afee43b | D34: =IFERROR(__xludf.DUMMYFUNCTION("""COMPUTED_VALUE"""),"Гриппол (Петровакс)") -> Гриппол (Петровакс) | E34: =IFERROR(__xludf.DUMMYFUNCTION("""COMPUTED_VALUE"""),"Гриппол® [Вакцина гриппозная тривалентная полимер-субъединичная жидкая]") -> Гриппол® [Вакцина гриппозная тривалентная полимер-субъединичная жидкая] | F34: =IFERROR(__xludf.DUMMYFUNCTION("""COMPUTED_VALUE"""),"Петровакс") -> Петровакс | G34: =IFERROR(__xludf.DUMMYFUNCTION("""COMPUTED_VALUE"""),"not in use") -> not in use | K34: =IFERROR(__xludf.DUMMYFUNCTION("""COMPUTED_VALUE"""),44712.0) -> 44712 | L34: =IFERROR(__xludf.DUMMYFUNCTION("""COMPUTED_VALUE"""),44712.0) -> 44712 | M34: =IFERROR(__xludf.DUMMYFUNCTION("""COMPUTED_VALUE"""),"нет") -> нет
A35: =IFERROR(__xludf.DUMMYFUNCTION("""COMPUTED_VALUE"""),34.0) -> 34 | B35: =IFERROR(__xludf.DUMMYFUNCTION("""COMPUTED_VALUE"""),"Grippol_plus_0_5") -> Grippol_plus_0_5 | C35: =IFERROR(__xludf.DUMMYFUNCTION("""COMPUTED_VALUE"""),"https://grls.rosminzdrav.ru/Grls_View_v2.aspx?routingGuid=907b510e-7f7f-46df-b43a-f6541b9871fc") -> https://grls.rosminzdrav.ru/Grls_View_v2.aspx?routingGuid=907b510e-7f7f-46df-b43a-f6541b9871fc | D35: =IFERROR(__xludf.DUMMYFUNCTION("""COMPUTED_VALUE"""),"Гриппол плюс 0,5 мл") -> Гриппол плюс 0,5 мл | E35: =IFERROR(__xludf.DUMMYFUNCTION("""COMPUTED_VALUE"""),"Гриппол® плюс [Вакцина гриппозная тривалентная инактивированная полимер-субъединичная]") -> Гриппол® плюс [Вакцина гриппозная тривалентная инактивированная полимер-субъединичная] | F35: =IFERROR(__xludf.DUMMYFUNCTION("""COMPUTED_VALUE"""),"Петровакс") -> Петровакс | G35: =IFERROR(__xludf.DUMMYFUNCTION("""COMPUTED_VALUE"""),"in use") -> in use | K35: =IFERROR(__xludf.DUMMYFUNCTION("""COMPUTED_VALUE"""),44712.0) -> 44712 | L35: =IFERROR(__xludf.DUMMYFUNCTION("""COMPUTED_VALUE"""),45689.0) -> 45689 | M35: =IFERROR(__xludf.DUMMYFUNCTION("""COMPUTED_VALUE"""),"https://lk.regmed.ru/Register/GetPDFfromDAToken?Token=8cc54647-279e-4b2f-82d7-b1ed3161d86a") -> https://lk.regmed.ru/Register/GetPDFfromDAToken?Token=8cc54647-279e-4b2f-82d7-b1ed3161d86a
A36: =IFERROR(__xludf.DUMMYFUNCTION("""COMPUTED_VALUE"""),35.0) -> 35 | B36: =IFERROR(__xludf.DUMMYFUNCTION("""COMPUTED_VALUE"""),"Sovigripp") -> Sovigripp | C36: =IFERROR(__xludf.DUMMYFUNCTION("""COMPUTED_VALUE"""),"https://grls.rosminzdrav.ru/Grls_View_v2.aspx?routingGuid=b287b682-550a-418f-8189-05dac16da4ae") -> https://grls.rosminzdrav.ru/Grls_View_v2.aspx?routingGuid=b287b682-550a-418f-8189-05dac16da4ae | D36: =IFERROR(__xludf.DUMMYFUNCTION("""COMPUTED_VALUE"""),"Совигрипп") -> Совигрипп | E36: =IFERROR(__xludf.DUMMYFUNCTION("""COMPUTED_VALUE"""),"СОВИГРИПП® Вакцина гриппозная инактивированная субъединичная") -> СОВИГРИПП® Вакцина гриппозная инактивированная субъединичная | F36: =IFERROR(__xludf.DUMMYFUNCTION("""COMPUTED_VALUE"""),"Микроген") -> Микроген | G36: =IFERROR(__xludf.DUMMYFUNCTION("""COMPUTED_VALUE"""),"in use") -> in use | K36: =IFERROR(__xludf.DUMMYFUNCTION("""COMPUTED_VALUE"""),44712.0) -> 44712 | L36: =IFERROR(__xludf.DUMMYFUNCTION("""COMPUTED_VALUE"""),45689.0) -> 45689 | M36: =IFERROR(__xludf.DUMMYFUNCTION("""COMPUTED_VALUE"""),"https://lk.regmed.ru/Register/GetPDFfromDAToken?Token=4d1562e5-05e7-405f-9673-b89a20ffd447") -> https://lk.regmed.ru/Register/GetPDFfromDAToken?Token=4d1562e5-05e7-405f-9673-b89a20ffd447
A37: =IFERROR(__xludf.DUMMYFUNCTION("""COMPUTED_VALUE"""),36.0) -> 36 | B37: =IFERROR(__xludf.DUMMYFUNCTION("""COMPUTED_VALUE"""),"Ultrix") -> Ultrix | C37: =IFERROR(__xludf.DUMMYFUNCTION("""COMPUTED_VALUE"""),"https://grls.rosminzdrav.ru/Grls_View_v2.aspx?routingGuid=b90698f2-e111-4450-b82c-5c3ca26a25f5") -> https://grls.rosminzdrav.ru/Grls_View_v2.aspx?routingGuid=b90698f2-e111-4450-b82c-5c3ca26a25f5 | D37: =IFERROR(__xludf.DUMMYFUNCTION("""COMPUTED_VALUE"""),"Ультрикс") -> Ультрикс | E37: =IFERROR(__xludf.DUMMYFUNCTION("""COMPUTED_VALUE"""),"Ультрикс® Вакцина гриппозная инактивированная расщепленная") -> Ультрикс® Вакцина гриппозная инактивированная расщепленная | F37: =IFERROR(__xludf.DUMMYFUNCTION("""COMPUTED_VALUE"""),"ФОРТ") -> ФОРТ | G37: =IFERROR(__xludf.DUMMYFUNCTION("""COMPUTED_VALUE"""),"not in use") -> not in use | K37: =IFERROR(__xludf.DUMMYFUNCTION("""COMPUTED_VALUE"""),44712.0) -> 44712 | L37: =IFERROR(__xludf.DUMMYFUNCTION("""COMPUTED_VALUE"""),45689.0) -> 45689 | M37: =IFERROR(__xludf.DUMMYFUNCTION("""COMPUTED_VALUE"""),"https://lk.regmed.ru/Register/GetPDFfromDAToken?Token=ebfed185-d787-4d31-8be8-d3cbc95b7794") -> https://lk.regmed.ru/Register/GetPDFfromDAToken?Token=ebfed185-d787-4d31-8be8-d3cbc95b7794
A38: =IFERROR(__xludf.DUMMYFUNCTION("""COMPUTED_VALUE"""),37.0) -> 37 | B38: =IFERROR(__xludf.DUMMYFUNCTION("""COMPUTED_VALUE"""),"Flu_M") -> Flu_M | C38: =IFERROR(__xludf.DUMMYFUNCTION("""COMPUTED_VALUE"""),"https://grls.rosminzdrav.ru/Grls_View_v2.aspx?routingGuid=e7496b1f-1be9-46a3-b43f-e1c83a5b6cc8") -> https://grls.rosminzdrav.ru/Grls_View_v2.aspx?routingGuid=e7496b1f-1be9-46a3-b43f-e1c83a5b6cc8 | D38: =IFERROR(__xludf.DUMMYFUNCTION("""COMPUTED_VALUE"""),"Флю-М") -> Флю-М | E38: =IFERROR(__xludf.DUMMYFUNCTION("""COMPUTED_VALUE"""),"Флю-М [Вакцина гриппозная инактивированная расщепленная]") -> Флю-М [Вакцина гриппозная инактивированная расщепленная] | F38: =IFERROR(__xludf.DUMMYFUNCTION("""COMPUTED_VALUE"""),"СПбНИИВС") -> СПбНИИВС | G38: =IFERROR(__xludf.DUMMYFUNCTION("""COMPUTED_VALUE"""),"in use") -> in use | K38: =IFERROR(__xludf.DUMMYFUNCTION("""COMPUTED_VALUE"""),44712.0) -> 44712 | L38: =IFERROR(__xludf.DUMMYFUNCTION("""COMPUTED_VALUE"""),46130.0) -> 46130 | M38: =IFERROR(__xludf.DUMMYFUNCTION("""COMPUTED_VALUE"""),"нет") -> нет
A39: =IFERROR(__xludf.DUMMYFUNCTION("""COMPUTED_VALUE"""),38.0) -> 38 | B39: =IFERROR(__xludf.DUMMYFUNCTION("""COMPUTED_VALUE"""),"Vaxigrip") -> Vaxigrip | C39: =IFERROR(__xludf.DUMMYFUNCTION("""COMPUTED_VALUE"""),"https://grls.rosminzdrav.ru/Grls_View_v2.aspx?routingGuid=34537f7c-cc43 – 45ef-bc9a-9820641bf718") -> https://grls.rosminzdrav.ru/Grls_View_v2.aspx?routingGuid=34537f7c-cc43 – 45ef-bc9a-9820641bf718 | D39: =IFERROR(__xludf.DUMMYFUNCTION("""COMPUTED_VALUE"""),"Ваксигрип") -> Ваксигрип | E39: =IFERROR(__xludf.DUMMYFUNCTION("""COMPUTED_VALUE"""),"Ваксигрип® (инактивированная сплит-вакцина для профилактики гриппа)") -> Ваксигрип® (инактивированная сплит-вакцина для профилактики гриппа) | G39: =IFERROR(__xludf.DUMMYFUNCTION("""COMPUTED_VALUE"""),"not in use") -> not in use | K39: =IFERROR(__xludf.DUMMYFUNCTION("""COMPUTED_VALUE"""),44712.0) -> 44712 | L39: =IFERROR(__xludf.DUMMYFUNCTION("""COMPUTED_VALUE"""),45078.0) -> 45078 | M39: =IFERROR(__xludf.DUMMYFUNCTION("""COMPUTED_VALUE"""),"нет") -> нет
A40: =IFERROR(__xludf.DUMMYFUNCTION("""COMPUTED_VALUE"""),39.0) -> 39 | B40: =IFERROR(__xludf.DUMMYFUNCTION("""COMPUTED_VALUE"""),"Influvac") -> Influvac | C40: =IFERROR(__xludf.DUMMYFUNCTION("""COMPUTED_VALUE"""),"https://grls.rosminzdrav.ru/Grls_View_v2.aspx?routingGuid=f0e5ea62-1cea-4427-923d-201a87349492") -> https://grls.rosminzdrav.ru/Grls_View_v2.aspx?routingGuid=f0e5ea62-1cea-4427-923d-201a87349492 | D40: =IFERROR(__xludf.DUMMYFUNCTION("""COMPUTED_VALUE"""),"Инфлювак") -> Инфлювак | E40: =IFERROR(__xludf.DUMMYFUNCTION("""COMPUTED_VALUE"""),"Инфлювак® (вакцина гриппозная субъединичная инактивированная)") -> Инфлювак® (вакцина гриппозная субъединичная инактивированная) | G40: =IFERROR(__xludf.DUMMYFUNCTION("""COMPUTED_VALUE"""),"in use") -> in use | K40: =IFERROR(__xludf.DUMMYFUNCTION("""COMPUTED_VALUE"""),44712.0) -> 44712 | L40: =IFERROR(__xludf.DUMMYFUNCTION("""COMPUTED_VALUE"""),46130.0) -> 46130 | M40: =IFERROR(__xludf.DUMMYFUNCTION("""COMPUTED_VALUE"""),"есть") -> есть
A41: =IFERROR(__xludf.DUMMYFUNCTION("""COMPUTED_VALUE"""),40.0) -> 40 | B41: =IFERROR(__xludf.DUMMYFUNCTION("""COMPUTED_VALUE"""),"Ultrix_quadri") -> Ultrix_quadri | C41: =IFERROR(__xludf.DUMMYFUNCTION("""COMPUTED_VALUE"""),"https://grls.rosminzdrav.ru/Grls_View_v2.aspx?routingGuid=39b44822-0ca7-409d-bc25-db49ef3d5471") -> https://grls.rosminzdrav.ru/Grls_View_v2.aspx?routingGuid=39b44822-0ca7-409d-bc25-db49ef3d5471 | D41: =IFERROR(__xludf.DUMMYFUNCTION("""COMPUTED_VALUE"""),"Ультрикс Квадри") -> Ультрикс Квадри | E41: =IFERROR(__xludf.DUMMYFUNCTION("""COMPUTED_VALUE"""),"Ультрикс® Квадри Вакцина гриппозная четырехвалентная инактивированная расщепленная") -> Ультрикс® Квадри Вакцина гриппозная четырехвалентная инактивированная расщепленная | G41: =IFERROR(__xludf.DUMMYFUNCTION("""COMPUTED_VALUE"""),"in use") -> in use | K41: =IFERROR(__xludf.DUMMYFUNCTION("""COMPUTED_VALUE"""),44712.0) -> 44712 | L41: =IFERROR(__xludf.DUMMYFUNCTION("""COMPUTED_VALUE"""),45689.0) -> 45689 | M41: =IFERROR(__xludf.DUMMYFUNCTION("""COMPUTED_VALUE"""),"https://lk.regmed.ru/Register/GetPDFfromDAToken?Token=6b6de448-9da8-4025-8b7a-e10951e7ff00") -> https://lk.regmed.ru/Register/GetPDFfromDAToken?Token=6b6de448-9da8-4025-8b7a-e10951e7ff00
A42: =IFERROR(__xludf.DUMMYFUNCTION("""COMPUTED_VALUE"""),41.0) -> 41 | B42: =IFERROR(__xludf.DUMMYFUNCTION("""COMPUTED_VALUE"""),"Grippol_quadrivalent") -> Grippol_quadrivalent | C42: =IFERROR(__xludf.DUMMYFUNCTION("""COMPUTED_VALUE"""),"https://grls.rosminzdrav.ru/Grls_View_v2.aspx?routingGuid=9d163668-04c5-490d-81ed-287f1cc6ac47") -> https://grls.rosminzdrav.ru/Grls_View_v2.aspx?routingGuid=9d163668-04c5-490d-81ed-287f1cc6ac47 | D42: =IFERROR(__xludf.DUMMYFUNCTION("""COMPUTED_VALUE"""),"Гриппол Квадривалент") -> Гриппол Квадривалент | E42: =IFERROR(__xludf.DUMMYFUNCTION("""COMPUTED_VALUE"""),"Гриппол® Квадривалент Вакцина гриппозная четырехвалентная инактивированная субъединичная адъювантная") -> Гриппол® Квадривалент Вакцина гриппозная четырехвалентная инактивированная субъединичная адъювантная | G42: =IFERROR(__xludf.DUMMYFUNCTION("""COMPUTED_VALUE"""),"in use") -> in use | K42: =IFERROR(__xludf.DUMMYFUNCTION("""COMPUTED_VALUE"""),44712.0) -> 44712 | L42: =IFERROR(__xludf.DUMMYFUNCTION("""COMPUTED_VALUE"""),45818.0) -> 45818 | M42: =IFERROR(__xludf.DUMMYFUNCTION("""COMPUTED_VALUE"""),"https://lk.regmed.ru/Register/GetPDFfromDAToken?Token=21d09ab4-e8b0-4241-88e6-6f4a8868109c") -> https://lk.regmed.ru/Register/GetPDFfromDAToken?Token=21d09ab4-e8b0-4241-88e6-6f4a8868109c
A43: =IFERROR(__xludf.DUMMYFUNCTION("""COMPUTED_VALUE"""),42.0) -> 42 | B43: =IFERROR(__xludf.DUMMYFUNCTION("""COMPUTED_VALUE"""),"measles_Microgen") -> measles_Microgen | C43: =IFERROR(__xludf.DUMMYFUNCTION("""COMPUTED_VALUE"""),"https://grls.rosminzdrav.ru/Grls_View_v2.aspx?routingGuid=21ef9e10-0802-4099-9f29-815fab9bf24f") -> https://grls.rosminzdrav.ru/Grls_View_v2.aspx?routingGuid=21ef9e10-0802-4099-9f29-815fab9bf24f | D43: =IFERROR(__xludf.DUMMYFUNCTION("""COMPUTED_VALUE"""),"коревая (Микроген)") -> коревая (Микроген) | E43: =IFERROR(__xludf.DUMMYFUNCTION("""COMPUTED_VALUE"""),"Вакцина коревая культуральная живая") -> Вакцина коревая культуральная живая | F43: =IFERROR(__xludf.DUMMYFUNCTION("""COMPUTED_VALUE"""),"Микроген") -> Микроген | G43: =IFERROR(__xludf.DUMMYFUNCTION("""COMPUTED_VALUE"""),"in use") -> in use | K43: =IFERROR(__xludf.DUMMYFUNCTION("""COMPUTED_VALUE"""),44712.0) -> 44712 | L43: =IFERROR(__xludf.DUMMYFUNCTION("""COMPUTED_VALUE"""),45689.0) -> 45689 | M43: =IFERROR(__xludf.DUMMYFUNCTION("""COMPUTED_VALUE"""),"https://lk.regmed.ru/Register/GetPDFfromDAToken?Token=7542b90d-b67b-4205-9d82-117e106aba6c") -> https://lk.regmed.ru/Register/GetPDFfromDAToken?Token=7542b90d-b67b-4205-9d82-117e106aba6c
A44: =IFERROR(__xludf.DUMMYFUNCTION("""COMPUTED_VALUE"""),43.0) -> 43 | B44: =IFERROR(__xludf.DUMMYFUNCTION("""COMPUTED_VALUE"""),"measles_Serum_India") -> measles_Serum_India | C44: =IFERROR(__xludf.DUMMYFUNCTION("""COMPUTED_VALUE"""),"https://grls.rosminzdrav.ru/Grls_View_v2.aspx?routingGuid=af4dd5ba-8e11-450c-83f0-3c6db2b13cf6") -> https://grls.rosminzdrav.ru/Grls_View_v2.aspx?routingGuid=af4dd5ba-8e11-450c-83f0-3c6db2b13cf6 | D44: =IFERROR(__xludf.DUMMYFUNCTION("""COMPUTED_VALUE"""),"коревая (Серум Инститьют)") -> коревая (Серум Инститьют) | E44: =IFERROR(__xludf.DUMMYFUNCTION("""COMPUTED_VALUE"""),"Вакцина против кори живая аттенуированная") -> Вакцина против кори живая аттенуированная | F44: =IFERROR(__xludf.DUMMYFUNCTION("""COMPUTED_VALUE"""),"Серум Инститьют") -> Серум Инститьют | G44: =IFERROR(__xludf.DUMMYFUNCTION("""COMPUTED_VALUE"""),"not in use") -> not in use | K44: =IFERROR(__xludf.DUMMYFUNCTION("""COMPUTED_VALUE"""),44712.0) -> 44712 | L44: =IFERROR(__xludf.DUMMYFUNCTION("""COMPUTED_VALUE"""),46053.0) -> 46053 | M44: =IFERROR(__xludf.DUMMYFUNCTION("""COMPUTED_VALUE"""),"есть") -> есть
A45: =IFERROR(__xludf.DUMMYFUNCTION("""COMPUTED_VALUE"""),44.0) -> 44 | B45: =IFERROR(__xludf.DUMMYFUNCTION("""COMPUTED_VALUE"""),"measles_Vector") -> measles_Vector | C45: =IFERROR(__xludf.DUMMYFUNCTION("""COMPUTED_VALUE"""),"https://grls.rosminzdrav.ru/Grls_View_v2.aspx?routingGuid=1c26875c-896c-488d-b713-142d18c1310f") -> https://grls.rosminzdrav.ru/Grls_View_v2.aspx?routingGuid=1c26875c-896c-488d-b713-142d18c1310f | D45: =IFERROR(__xludf.DUMMYFUNCTION("""COMPUTED_VALUE"""),"коревая (Вектор)") -> коревая (Вектор) | E45: =IFERROR(__xludf.DUMMYFUNCTION("""COMPUTED_VALUE"""),"Вакцина коревая культуральная живая") -> Вакцина коревая культуральная живая | F45: =IFERROR(__xludf.DUMMYFUNCTION("""COMPUTED_VALUE"""),"Вектор") -> Вектор | G45: =IFERROR(__xludf.DUMMYFUNCTION("""COMPUTED_VALUE"""),"in use") -> in use | K45: =IFERROR(__xludf.DUMMYFUNCTION("""COMPUTED_VALUE"""),44712.0) -> 44712 | L45: =IFERROR(__xludf.DUMMYFUNCTION("""COMPUTED_VALUE"""),44750.0) -> 44750 | M45: =IFERROR(__xludf.DUMMYFUNCTION("""COMPUTED_VALUE"""),"нет") -> нет
A46: =IFERROR(__xludf.DUMMYFUNCTION("""COMPUTED_VALUE"""),45.0) -> 45 | B46: =IFERROR(__xludf.DUMMYFUNCTION("""COMPUTED_VALUE"""),"measles_mumps_Microgen") -> measles_mumps_Microgen | C46: =IFERROR(__xludf.DUMMYFUNCTION("""COMPUTED_VALUE"""),"https://grls.rosminzdrav.ru/Grls_View_v2.aspx?routingGuid=bbcf7276-a503-4968-abd0-286f29aa80a7") -> https://grls.rosminzdrav.ru/Grls_View_v2.aspx?routingGuid=bbcf7276-a503-4968-abd0-286f29aa80a7 | D46: =IFERROR(__xludf.DUMMYFUNCTION("""COMPUTED_VALUE"""),"паротитно-коревая (Микроген)") -> паротитно-коревая (Микроген) | E46: =IFERROR(__xludf.DUMMYFUNCTION("""COMPUTED_VALUE"""),"Вакцина паротитно-коревая культуральная живая") -> Вакцина паротитно-коревая культуральная живая | F46: =IFERROR(__xludf.DUMMYFUNCTION("""COMPUTED_VALUE"""),"Микроген") -> Микроген | G46: =IFERROR(__xludf.DUMMYFUNCTION("""COMPUTED_VALUE"""),"in use") -> in use | K46: =IFERROR(__xludf.DUMMYFUNCTION("""COMPUTED_VALUE"""),44712.0) -> 44712 | L46: =IFERROR(__xludf.DUMMYFUNCTION("""COMPUTED_VALUE"""),45689.0) -> 45689 | M46: =IFERROR(__xludf.DUMMYFUNCTION("""COMPUTED_VALUE"""),"https://lk.regmed.ru/Register/GetPDFfromDAToken?Token=871cc235-deab-47cc-ac2f-13a865cc2b7f") -> https://lk.regmed.ru/Register/GetPDFfromDAToken?Token=871cc235-deab-47cc-ac2f-13a865cc2b7f
A47: =IFERROR(__xludf.DUMMYFUNCTION("""COMPUTED_VALUE"""),46.0) -> 46 | B47: =IFERROR(__xludf.DUMMYFUNCTION("""COMPUTED_VALUE"""),"Vactrivir") -> Vactrivir | C47: =IFERROR(__xludf.DUMMYFUNCTION("""COMPUTED_VALUE"""),"https://grls.rosminzdrav.ru/Grls_View_v2.aspx?routingGuid=a4090b86-5da6-4481-8230-dd9e607b60af") -> https://grls.rosminzdrav.ru/Grls_View_v2.aspx?routingGuid=a4090b86-5da6-4481-8230-dd9e607b60af | D47: =IFERROR(__xludf.DUMMYFUNCTION("""COMPUTED_VALUE"""),"Вактривир") -> Вактривир | E47: =IFERROR(__xludf.DUMMYFUNCTION("""COMPUTED_VALUE"""),"ВАКТРИВИР Комбинированная вакцина против кори, краснухи и паротита культуральная живая") -> ВАКТРИВИР Комбинированная вакцина против кори, краснухи и паротита культуральная живая | G47: =IFERROR(__xludf.DUMMYFUNCTION("""COMPUTED_VALUE"""),"in use") -> in use | H47: =IFERROR(__xludf.DUMMYFUNCTION("""COMPUTED_VALUE"""),"<p>При необходимости вакцинации детей в возрасте младше 12&nbsp;месяцев, если это предусмотрено Национальными рекомендациями, вакцину следует вводить в возрасте не ранее 9&nbsp;месяцев.</p>") -> <p>При необходимости вакцинации детей в возрасте младше 12&nbsp;месяцев, если это предусмотрено Национальными рекомендациями, вакцину следует вводить в возрасте не ранее 9&nbsp;месяцев.</p> | I47: =IFERROR(__xludf.DUMMYFUNCTION("""COMPUTED_VALUE"""),"При необходимости вакцинации детей в возрасте младше 12 месяцев, если это предусмотрено Национальными рекомендациями, вакцину следует вводить в возрасте не ранее 9 месяцев.") -> При необходимости вакцинации детей в возрасте младше 12 месяцев, если это предусмотрено Национальными рекомендациями, вакцину следует вводить в возрасте не ранее 9 месяцев. | K47: =IFERROR(__xludf.DUMMYFUNCTION("""COMPUTED_VALUE"""),44712.0) -> 44712 | L47: =IFERROR(__xludf.DUMMYFUNCTION("""COMPUTED_VALUE"""),45830.0) -> 45830 | M47: =IFERROR(__xludf.DUMMYFUNCTION("""COMPUTED_VALUE"""),"https://lk.regmed.ru/Register/GetPDFfromDAToken?Token=8415d4f4-69df-4249-bc87-8ca7cad24c51") -> https://lk.regmed.ru/Register/GetPDFfromDAToken?Token=8415d4f4-69df-4249-bc87-8ca7cad24c51
A48: =IFERROR(__xludf.DUMMYFUNCTION("""COMPUTED_VALUE"""),47.0) -> 47 | B48: =IFERROR(__xludf.DUMMYFUNCTION("""COMPUTED_VALUE"""),"MMR_II") -> MMR_II | C48: =IFERROR(__xludf.DUMMYFUNCTION("""COMPUTED_VALUE"""),"https://grls.rosminzdrav.ru/Grls_View_v2.aspx?routingGuid=aa975a20-f44a-451e-bf3e-3dcc80435b61") -> https://grls.rosminzdrav.ru/Grls_View_v2.aspx?routingGuid=aa975a20-f44a-451e-bf3e-3dcc80435b61 | D48: =IFERROR(__xludf.DUMMYFUNCTION("""COMPUTED_VALUE"""),"М-М-Р II") -> М-М-Р II | E48: =IFERROR(__xludf.DUMMYFUNCTION("""COMPUTED_VALUE"""),"М-М-Р II® (Вакцина против кори, паротита и краснухи, живая)") -> М-М-Р II® (Вакцина против кори, паротита и краснухи, живая) | G48: =IFERROR(__xludf.DUMMYFUNCTION("""COMPUTED_VALUE"""),"not in use") -> not in use | K48: =IFERROR(__xludf.DUMMYFUNCTION("""COMPUTED_VALUE"""),44712.0) -> 44712 | L48: =IFERROR(__xludf.DUMMYFUNCTION("""COMPUTED_VALUE"""),45715.0) -> 45715 | M48: =IFERROR(__xludf.DUMMYFUNCTION("""COMPUTED_VALUE"""),"нет") -> нет
A49: =IFERROR(__xludf.DUMMYFUNCTION("""COMPUTED_VALUE"""),48.0) -> 48 | B49: =IFERROR(__xludf.DUMMYFUNCTION("""COMPUTED_VALUE"""),"MenA_Microgen") -> MenA_Microgen | C49: =IFERROR(__xludf.DUMMYFUNCTION("""COMPUTED_VALUE"""),"https://grls.rosminzdrav.ru/Grls_View_v2.aspx?routingGuid=573dc2fd-b104-4a0c-a56a-486f57764912") -> https://grls.rosminzdrav.ru/Grls_View_v2.aspx?routingGuid=573dc2fd-b104-4a0c-a56a-486f57764912 | D49: =IFERROR(__xludf.DUMMYFUNCTION("""COMPUTED_VALUE"""),"Менингококковая гр. A") -> Менингококковая гр. A | E49: =IFERROR(__xludf.DUMMYFUNCTION("""COMPUTED_VALUE"""),"Вакцина менингококковая группы А полисахаридная") -> Вакцина менингококковая группы А полисахаридная | F49: =IFERROR(__xludf.DUMMYFUNCTION("""COMPUTED_VALUE"""),"Микроген") -> Микроген | G49: =IFERROR(__xludf.DUMMYFUNCTION("""COMPUTED_VALUE"""),"in use") -> in use | H49: =IFERROR(__xludf.DUMMYFUNCTION("""COMPUTED_VALUE"""),"<p>менингококки группы&nbsp;A</p>") -> <p>менингококки группы&nbsp;A</p> | I49: =IFERROR(__xludf.DUMMYFUNCTION("""COMPUTED_VALUE"""),"менингококки группы A") -> менингококки группы A | K49: =IFERROR(__xludf.DUMMYFUNCTION("""COMPUTED_VALUE"""),44712.0) -> 44712 | L49: =IFERROR(__xludf.DUMMYFUNCTION("""COMPUTED_VALUE"""),45689.0) -> 45689 | M49: =IFERROR(__xludf.DUMMYFUNCTION("""COMPUTED_VALUE"""),"https://lk.regmed.ru/Register/GetPDFfromDAToken?Token=22a07d8d-d541-45f6-8093-29d650df9705") -> https://lk.regmed.ru/Register/GetPDFfromDAToken?Token=22a07d8d-d541-45f6-8093-29d650df9705
A50: =IFERROR(__xludf.DUMMYFUNCTION("""COMPUTED_VALUE"""),49.0) -> 49 | B50: =IFERROR(__xludf.DUMMYFUNCTION("""COMPUTED_VALUE"""),"MeningoVac_A_C") -> MeningoVac_A_C | C50: =IFERROR(__xludf.DUMMYFUNCTION("""COMPUTED_VALUE"""),"https://grls.rosminzdrav.ru/Grls_View_v2.aspx?routingGuid=162087a7-8c2e-4c1c-ada9-b2d41a7fc06d") -> https://grls.rosminzdrav.ru/Grls_View_v2.aspx?routingGuid=162087a7-8c2e-4c1c-ada9-b2d41a7fc06d | D50: =IFERROR(__xludf.DUMMYFUNCTION("""COMPUTED_VALUE"""),"Менингококковая гр. А+С") -> Менингококковая гр. А+С | E50: =IFERROR(__xludf.DUMMYFUNCTION("""COMPUTED_VALUE"""),"Вакцина менингококковая групп А и С полисахаридная") -> Вакцина менингококковая групп А и С полисахаридная | F50: =IFERROR(__xludf.DUMMYFUNCTION("""COMPUTED_VALUE"""),"Микроген") -> Микроген | G50: =IFERROR(__xludf.DUMMYFUNCTION("""COMPUTED_VALUE"""),"not in use") -> not in use | H50: =IFERROR(__xludf.DUMMYFUNCTION("""COMPUTED_VALUE"""),"<p>менингококки группы&nbsp;A, C</p>") -> <p>менингококки группы&nbsp;A, C</p> | I50: =IFERROR(__xludf.DUMMYFUNCTION("""COMPUTED_VALUE"""),"менингококки группы A, C") -> менингококки группы A, C | J50: =IFERROR(__xludf.DUMMYFUNCTION("""COMPUTED_VALUE"""),0.5) -> 0.5 | K50: =IFERROR(__xludf.DUMMYFUNCTION("""COMPUTED_VALUE"""),44712.0) -> 44712 | L50: =IFERROR(__xludf.DUMMYFUNCTION("""COMPUTED_VALUE"""),45689.0) -> 45689 | M50: =IFERROR(__xludf.DUMMYFUNCTION("""COMPUTED_VALUE"""),"https://lk.regmed.ru/Register/GetPDFfromDAToken?Token=023326ba-2394-4cee-8436-d2d7251635d0") -> https://lk.regmed.ru/Register/GetPDFfromDAToken?Token=023326ba-2394-4cee-8436-d2d7251635d0
A51: =IFERROR(__xludf.DUMMYFUNCTION("""COMPUTED_VALUE"""),50.0) -> 50 | B51: =IFERROR(__xludf.DUMMYFUNCTION("""COMPUTED_VALUE"""),"Menactra") -> Menactra | C51: =IFERROR(__xludf.DUMMYFUNCTION("""COMPUTED_VALUE"""),"https://grls.rosminzdrav.ru/Grls_View_v2.aspx?routingGuid=f79c63df-14fc-4066-a985-f34555bed179") -> https://grls.rosminzdrav.ru/Grls_View_v2.aspx?routingGuid=f79c63df-14fc-4066-a985-f34555bed179 | D51: =IFERROR(__xludf.DUMMYFUNCTION("""COMPUTED_VALUE"""),"Менактра") -> Менактра | E51: =IFERROR(__xludf.DUMMYFUNCTION("""COMPUTED_VALUE"""),"МЕНАКТРА® [вакцина менингококковая полисахаридная (серогрупп A, C, Y и W-135), конъюгированная с дифтерийным анатоксином]") -> МЕНАКТРА® [вакцина менингококковая полисахаридная (серогрупп A, C, Y и W-135), конъюгированная с дифтерийным анатоксином] | F51: =IFERROR(__xludf.DUMMYFUNCTION("""COMPUTED_VALUE"""),"Санофи Пастер Лимитед") -> Санофи Пастер Лимитед | G51: =IFERROR(__xludf.DUMMYFUNCTION("""COMPUTED_VALUE"""),"in use") -> in use | H51: =IFERROR(__xludf.DUMMYFUNCTION("""COMPUTED_VALUE"""),"<p>менингококки группы&nbsp;A, C, W, Y</p>") -> <p>менингококки группы&nbsp;A, C, W, Y</p> | I51: =IFERROR(__xludf.DUMMYFUNCTION("""COMPUTED_VALUE"""),"менингококки группы A, C, W, Y") -> менингококки группы A, C, W, Y | K51: =IFERROR(__xludf.DUMMYFUNCTION("""COMPUTED_VALUE"""),44712.0) -> 44712 | L51: =IFERROR(__xludf.DUMMYFUNCTION("""COMPUTED_VALUE"""),45689.0) -> 45689 | M51: =IFERROR(__xludf.DUMMYFUNCTION("""COMPUTED_VALUE"""),"https://lk.regmed.ru/Register/GetPDFfromDAToken?Token=daa21352-7464-4e37-a24b-31888db79e80") -> https://lk.regmed.ru/Register/GetPDFfromDAToken?Token=daa21352-7464-4e37-a24b-31888db79e80
A52: =IFERROR(__xludf.DUMMYFUNCTION("""COMPUTED_VALUE"""),51.0) -> 51 | B52: =IFERROR(__xludf.DUMMYFUNCTION("""COMPUTED_VALUE"""),"mumps_Microgen") -> mumps_Microgen | C52: =IFERROR(__xludf.DUMMYFUNCTION("""COMPUTED_VALUE"""),"https://grls.rosminzdrav.ru/Grls_View_v2.aspx?routingGuid=4f505e78-1d02-4b8f-aaf9-618368787be0") -> https://grls.rosminzdrav.ru/Grls_View_v2.aspx?routingGuid=4f505e78-1d02-4b8f-aaf9-618368787be0 | D52: =IFERROR(__xludf.DUMMYFUNCTION("""COMPUTED_VALUE"""),"паротитная (Микроген)") -> паротитная (Микроген) | E52: =IFERROR(__xludf.DUMMYFUNCTION("""COMPUTED_VALUE"""),"Вакцина паротитная культуральная живая") -> Вакцина паротитная культуральная живая | F52: =IFERROR(__xludf.DUMMYFUNCTION("""COMPUTED_VALUE"""),"Микроген") -> Микроген | G52: =IFERROR(__xludf.DUMMYFUNCTION("""COMPUTED_VALUE"""),"in use") -> in use | K52: =IFERROR(__xludf.DUMMYFUNCTION("""COMPUTED_VALUE"""),44712.0) -> 44712 | L52: =IFERROR(__xludf.DUMMYFUNCTION("""COMPUTED_VALUE"""),45689.0) -> 45689 | M52: =IFERROR(__xludf.DUMMYFUNCTION("""COMPUTED_VALUE"""),"https://lk.regmed.ru/Register/GetPDFfromDAToken?Token=a03421c1-d658-4466-a600-c80d1005976d") -> https://lk.regmed.ru/Register/GetPDFfromDAToken?Token=a03421c1-d658-4466-a600-c80d1005976d
A53: =IFERROR(__xludf.DUMMYFUNCTION("""COMPUTED_VALUE"""),52.0) -> 52 | B53: =IFERROR(__xludf.DUMMYFUNCTION("""COMPUTED_VALUE"""),"Prevenar_13") -> Prevenar_13 | C53: =IFERROR(__xludf.DUMMYFUNCTION("""COMPUTED_VALUE"""),"https://grls.rosminzdrav.ru/Grls_View_v2.aspx?routingGuid=c88b7ed6-2791-496d-95ac-2bf2453e540b") -> https://grls.rosminzdrav.ru/Grls_View_v2.aspx?routingGuid=c88b7ed6-2791-496d-95ac-2bf2453e540b | D53: =IFERROR(__xludf.DUMMYFUNCTION("""COMPUTED_VALUE"""),"Превенар 13") -> Превенар 13 | E53: =IFERROR(__xludf.DUMMYFUNCTION("""COMPUTED_VALUE"""),"Превенар® 13 (вакцина пневмококковая полисахаридная конъюгированная адсорбированная, тринадцативалентная)") -> Превенар® 13 (вакцина пневмококковая полисахаридная конъюгированная адсорбированная, тринадцативалентная) | F53: =IFERROR(__xludf.DUMMYFUNCTION("""COMPUTED_VALUE"""),"Пфайзер") -> Пфайзер | G53: =IFERROR(__xludf.DUMMYFUNCTION("""COMPUTED_VALUE"""),"in use") -> in use | K53: =IFERROR(__xludf.DUMMYFUNCTION("""COMPUTED_VALUE"""),44712.0) -> 44712 | L53: =IFERROR(__xludf.DUMMYFUNCTION("""COMPUTED_VALUE"""),45689.0) -> 45689 | M53: =IFERROR(__xludf.DUMMYFUNCTION("""COMPUTED_VALUE"""),"https://lk.regmed.ru/Register/GetPDFfromDAToken?Token=3553002d-a459-42b4-8d3c-382ab7278081") -> https://lk.regmed.ru/Register/GetPDFfromDAToken?Token=3553002d-a459-42b4-8d3c-382ab7278081
A54: =IFERROR(__xludf.DUMMYFUNCTION("""COMPUTED_VALUE"""),53.0) -> 53 | B54: =IFERROR(__xludf.DUMMYFUNCTION("""COMPUTED_VALUE"""),"Synflorix") -> Synflorix | C54: =IFERROR(__xludf.DUMMYFUNCTION("""COMPUTED_VALUE"""),"https://grls.rosminzdrav.ru/Grls_View_v2.aspx?routingGuid=98f6f75c-4d06-4e15-8e8e-52e513e2c4c1") -> https://grls.rosminzdrav.ru/Grls_View_v2.aspx?routingGuid=98f6f75c-4d06-4e15-8e8e-52e513e2c4c1 | D54: =IFERROR(__xludf.DUMMYFUNCTION("""COMPUTED_VALUE"""),"Синфлорикс") -> Синфлорикс | E54: =IFERROR(__xludf.DUMMYFUNCTION("""COMPUTED_VALUE"""),"Синфлорикс (Вакцина 10-валентная пневмококковая полисахаридная, конъюгированная с D-протеином нетипируемой Haemophilus influenzae, столбнячным и дифтерийным анатоксинами, адсорбированная)") -> Синфлорикс (Вакцина 10-валентная пневмококковая полисахаридная, конъюгированная с D-протеином нетипируемой Haemophilus influenzae, столбнячным и дифтерийным анатоксинами, адсорбированная) | G54: =IFERROR(__xludf.DUMMYFUNCTION("""COMPUTED_VALUE"""),"not in use") -> not in use | K54: =IFERROR(__xludf.DUMMYFUNCTION("""COMPUTED_VALUE"""),44712.0) -> 44712 | L54: =IFERROR(__xludf.DUMMYFUNCTION("""COMPUTED_VALUE"""),45715.0) -> 45715 | M54: =IFERROR(__xludf.DUMMYFUNCTION("""COMPUTED_VALUE"""),"нет") -> нет
A55: =IFERROR(__xludf.DUMMYFUNCTION("""COMPUTED_VALUE"""),54.0) -> 54 | B55: =IFERROR(__xludf.DUMMYFUNCTION("""COMPUTED_VALUE"""),"Pneumovax_23") -> Pneumovax_23 | C55: =IFERROR(__xludf.DUMMYFUNCTION("""COMPUTED_VALUE"""),"https://grls.rosminzdrav.ru/Grls_View_v2.aspx?routingGuid=7ded6546-8feb-4afd-9a4d-1fce9414a552") -> https://grls.rosminzdrav.ru/Grls_View_v2.aspx?routingGuid=7ded6546-8feb-4afd-9a4d-1fce9414a552 | D55: =IFERROR(__xludf.DUMMYFUNCTION("""COMPUTED_VALUE"""),"Пневмовакс 23") -> Пневмовакс 23 | E55: =IFERROR(__xludf.DUMMYFUNCTION("""COMPUTED_VALUE"""),"Пневмовакс® 23 (Вакцина пневмококковая, поливалентная)") -> Пневмовакс® 23 (Вакцина пневмококковая, поливалентная) | F55: =IFERROR(__xludf.DUMMYFUNCTION("""COMPUTED_VALUE"""),"Мерк Шарп и Доум Б.В.") -> Мерк Шарп и Доум Б.В. | G55: =IFERROR(__xludf.DUMMYFUNCTION("""COMPUTED_VALUE"""),"in use") -> in use | K55: =IFERROR(__xludf.DUMMYFUNCTION("""COMPUTED_VALUE"""),44712.0) -> 44712 | L55: =IFERROR(__xludf.DUMMYFUNCTION("""COMPUTED_VALUE"""),45689.0) -> 45689 | M55: =IFERROR(__xludf.DUMMYFUNCTION("""COMPUTED_VALUE"""),"https://lk.regmed.ru/Register/GetPDFfromDAToken?Token=10e497be-3d4a-43a2-aa31-092ce691668e") -> https://lk.regmed.ru/Register/GetPDFfromDAToken?Token=10e497be-3d4a-43a2-aa31-092ce691668e
A56: =IFERROR(__xludf.DUMMYFUNCTION("""COMPUTED_VALUE"""),55.0) -> 55 | B56: =IFERROR(__xludf.DUMMYFUNCTION("""COMPUTED_VALUE"""),"MonoVac_Polio") -> MonoVac_Polio | C56: =IFERROR(__xludf.DUMMYFUNCTION("""COMPUTED_VALUE"""),"https://grls.rosminzdrav.ru/Grls_View_v2.aspx?routingGuid=94cb6422-2bae-41b1-b881-7019bc1e6c88") -> https://grls.rosminzdrav.ru/Grls_View_v2.aspx?routingGuid=94cb6422-2bae-41b1-b881-7019bc1e6c88 | D56: =IFERROR(__xludf.DUMMYFUNCTION("""COMPUTED_VALUE"""),"МоноВак полио") -> МоноВак полио | E56: =IFERROR(__xludf.DUMMYFUNCTION("""COMPUTED_VALUE"""),"МоноВак полио тип 2 (Вакцина полиомиелитная пероральная, моновалентная, живая аттенуированная 2 типа)") -> МоноВак полио тип 2 (Вакцина полиомиелитная пероральная, моновалентная, живая аттенуированная 2 типа) | G56: =IFERROR(__xludf.DUMMYFUNCTION("""COMPUTED_VALUE"""),"in use") -> in use | K56: =IFERROR(__xludf.DUMMYFUNCTION("""COMPUTED_VALUE"""),44712.0) -> 44712 | L56: =IFERROR(__xludf.DUMMYFUNCTION("""COMPUTED_VALUE"""),44944.0) -> 44944 | M56: =IFERROR(__xludf.DUMMYFUNCTION("""COMPUTED_VALUE"""),"нет") -> нет
A57: =IFERROR(__xludf.DUMMYFUNCTION("""COMPUTED_VALUE"""),56.0) -> 56 | B57: =IFERROR(__xludf.DUMMYFUNCTION("""COMPUTED_VALUE"""),"BiVac_Polio") -> BiVac_Polio | C57: =IFERROR(__xludf.DUMMYFUNCTION("""COMPUTED_VALUE"""),"https://grls.rosminzdrav.ru/Grls_View_v2.aspx?routingGuid=35f3aeab-53d0-4aa3-b370-016ed06e2330") -> https://grls.rosminzdrav.ru/Grls_View_v2.aspx?routingGuid=35f3aeab-53d0-4aa3-b370-016ed06e2330 | D57: =IFERROR(__xludf.DUMMYFUNCTION("""COMPUTED_VALUE"""),"БиВак полио") -> БиВак полио | E57: =IFERROR(__xludf.DUMMYFUNCTION("""COMPUTED_VALUE"""),"БиВак полио (Вакцина полиомиелитная пероральная, двухвалентная, живая аттенуированная 1, 3 типов)") -> БиВак полио (Вакцина полиомиелитная пероральная, двухвалентная, живая аттенуированная 1, 3 типов) | G57: =IFERROR(__xludf.DUMMYFUNCTION("""COMPUTED_VALUE"""),"in use") -> in use | K57: =IFERROR(__xludf.DUMMYFUNCTION("""COMPUTED_VALUE"""),44712.0) -> 44712 | L57: =IFERROR(__xludf.DUMMYFUNCTION("""COMPUTED_VALUE"""),45988.0) -> 45988 | M57: =IFERROR(__xludf.DUMMYFUNCTION("""COMPUTED_VALUE"""),"нет") -> нет
A58: =IFERROR(__xludf.DUMMYFUNCTION("""COMPUTED_VALUE"""),57.0) -> 57 | B58: =IFERROR(__xludf.DUMMYFUNCTION("""COMPUTED_VALUE"""),"Polymilex") -> Polymilex | C58: =IFERROR(__xludf.DUMMYFUNCTION("""COMPUTED_VALUE"""),"https://grls.rosminzdrav.ru/Grls_View_v2.aspx?routingGuid=f91918fb-09b8-4766-8e48-6606a0541073") -> https://grls.rosminzdrav.ru/Grls_View_v2.aspx?routingGuid=f91918fb-09b8-4766-8e48-6606a0541073 | D58: =IFERROR(__xludf.DUMMYFUNCTION("""COMPUTED_VALUE"""),"Полимилекс") -> Полимилекс | E58: =IFERROR(__xludf.DUMMYFUNCTION("""COMPUTED_VALUE"""),"ПОЛИМИЛЕКС® вакцина для профилактики полиомиелита инактивированная") -> ПОЛИМИЛЕКС® вакцина для профилактики полиомиелита инактивированная | G58: =IFERROR(__xludf.DUMMYFUNCTION("""COMPUTED_VALUE"""),"in use") -> in use | K58: =IFERROR(__xludf.DUMMYFUNCTION("""COMPUTED_VALUE"""),44712.0) -> 44712 | L58: =IFERROR(__xludf.DUMMYFUNCTION("""COMPUTED_VALUE"""),45715.0) -> 45715 | M58: =IFERROR(__xludf.DUMMYFUNCTION("""COMPUTED_VALUE"""),"нет") -> нет
A59: =IFERROR(__xludf.DUMMYFUNCTION("""COMPUTED_VALUE"""),58.0) -> 58 | B59: =IFERROR(__xludf.DUMMYFUNCTION("""COMPUTED_VALUE"""),"COCAV") -> COCAV | C59: =IFERROR(__xludf.DUMMYFUNCTION("""COMPUTED_VALUE"""),"https://grls.rosminzdrav.ru/Grls_View_v2.aspx?routingGuid=7da83465-3e51-4a42-99a7-7aff7e64f9e4") -> https://grls.rosminzdrav.ru/Grls_View_v2.aspx?routingGuid=7da83465-3e51-4a42-99a7-7aff7e64f9e4 | D59: =IFERROR(__xludf.DUMMYFUNCTION("""COMPUTED_VALUE"""),"Кокав") -> Кокав | E59: =IFERROR(__xludf.DUMMYFUNCTION("""COMPUTED_VALUE"""),"КОКАВ Вакцина антирабическая культуральная концентрированная очищенная инактивированная") -> КОКАВ Вакцина антирабическая культуральная концентрированная очищенная инактивированная | G59: =IFERROR(__xludf.DUMMYFUNCTION("""COMPUTED_VALUE"""),"in use") -> in use | H59: =IFERROR(__xludf.DUMMYFUNCTION("""COMPUTED_VALUE"""),"<p>Для постэкспозиционной профилактики, то есть в случае укуса потенциально бешеным животным, противопоказания отсутствуют. В том числе прививка может проводиться беременным, если беременная была укушена животным, которое может быть инфицировано вирусом б"&"ешенства.<br> <br> Указанные ниже противопоказания относятся к плановой вакцинации лиц, имеющих высокий профессиональный риск заражения бешенством, — ветеринарных работников, егерей, охотников, лесников, лиц, работающих с уличным вирусом бешенства или вып"&"олняющих работы по отлову и содержанию животных.</p>") -> <p>Для постэкспозиционной профилактики, то есть в случае укуса потенциально бешеным животным, противопоказания отсутствуют. В том числе прививка может проводиться беременным, если беременная была укушена животным, которое может быть инфицировано вирусом бешенства.<br> <br> Указанные ниже противопоказания относятся к плановой вакцинации лиц, имеющих высокий профессиональный риск заражения бешенством, — ветеринарных работников, егерей, охотников, лесников, лиц, работающих с уличным вирусом бешенства или выполняющих работы по отлову и содержанию животных.</p> | I59: =IFERROR(__xludf.DUMMYFUNCTION("""COMPUTED_VALUE"""),"Для постэкспозиционной профилактики, то есть в случае укуса потенциально бешеным животным, противопоказания отсутствуют. В том числе прививка может проводиться беременным, если беременная была укушена животным, которое может быть инфицировано вирусом беше"&"нства. Указанные ниже противопоказания относятся к плановой вакцинации лиц, имеющих высокий профессиональный риск заражения бешенством, — ветеринарных работников, егерей, охотников, лесников, лиц, работающих с уличным вирусом бешенства или выполняющих ра"&"боты по отлову и содержанию животных.") -> Для постэкспозиционной профилактики, то есть в случае укуса потенциально бешеным животным, противопоказания отсутствуют. В том числе прививка может проводиться беременным, если беременная была укушена животным, которое может быть инфицировано вирусом бешенства. Указанные ниже противопоказания относятся к плановой вакцинации лиц, имеющих высокий профессиональный риск заражения бешенством, — ветеринарных работников, егерей, охотников, лесников, лиц, работающих с уличным вирусом бешенства или выполняющих работы по отлову и содержанию животных. | K59: =IFERROR(__xludf.DUMMYFUNCTION("""COMPUTED_VALUE"""),44712.0) -> 44712 | L59: =IFERROR(__xludf.DUMMYFUNCTION("""COMPUTED_VALUE"""),45689.0) -> 45689 | M59: =IFERROR(__xludf.DUMMYFUNCTION("""COMPUTED_VALUE"""),"https://lk.regmed.ru/Register/GetPDFfromDAToken?Token=92b647e6-6e46-4d97-b5db-055d884d1048") -> https://lk.regmed.ru/Register/GetPDFfromDAToken?Token=92b647e6-6e46-4d97-b5db-055d884d1048
A60: =IFERROR(__xludf.DUMMYFUNCTION("""COMPUTED_VALUE"""),59.0) -> 59 | B60: =IFERROR(__xludf.DUMMYFUNCTION("""COMPUTED_VALUE"""),"rabies_Chumakov") -> rabies_Chumakov | C60: =IFERROR(__xludf.DUMMYFUNCTION("""COMPUTED_VALUE"""),"https://grls.rosminzdrav.ru/Grls_View_v2.aspx?routingGuid=91d987ae-568f-4c6b-8623-8abf1ea0cbdc") -> https://grls.rosminzdrav.ru/Grls_View_v2.aspx?routingGuid=91d987ae-568f-4c6b-8623-8abf1ea0cbdc | D60: =IFERROR(__xludf.DUMMYFUNCTION("""COMPUTED_VALUE"""),"антирабическая (Чумакова)") -> антирабическая (Чумакова) | E60: =IFERROR(__xludf.DUMMYFUNCTION("""COMPUTED_VALUE"""),"Вакцина антирабическая культуральная концентрированная очищенная инактивированная сухая") -> Вакцина антирабическая культуральная концентрированная очищенная инактивированная сухая | G60: =IFERROR(__xludf.DUMMYFUNCTION("""COMPUTED_VALUE"""),"in use") -> in use | K60: =IFERROR(__xludf.DUMMYFUNCTION("""COMPUTED_VALUE"""),44712.0) -> 44712 | L60: =IFERROR(__xludf.DUMMYFUNCTION("""COMPUTED_VALUE"""),46188.0) -> 46188 | M60: =IFERROR(__xludf.DUMMYFUNCTION("""COMPUTED_VALUE"""),"нет") -> нет
A61: =IFERROR(__xludf.DUMMYFUNCTION("""COMPUTED_VALUE"""),60.0) -> 60 | B61: =IFERROR(__xludf.DUMMYFUNCTION("""COMPUTED_VALUE"""),"Rabivac_Vnukovo_32") -> Rabivac_Vnukovo_32 | C61: =IFERROR(__xludf.DUMMYFUNCTION("""COMPUTED_VALUE"""),"https://grls.rosminzdrav.ru/Grls_View_v2.aspx?routingGuid=e4ffdd5e-89db-479f-b9a3-4aee83beeb8a") -> https://grls.rosminzdrav.ru/Grls_View_v2.aspx?routingGuid=e4ffdd5e-89db-479f-b9a3-4aee83beeb8a | D61: =IFERROR(__xludf.DUMMYFUNCTION("""COMPUTED_VALUE"""),"Рабивак-Внуково-32") -> Рабивак-Внуково-32 | E61: =IFERROR(__xludf.DUMMYFUNCTION("""COMPUTED_VALUE"""),"Рабивак-Внуково-32 Вакцина антирабическая культуральная инактивированная для иммунизации человека") -> Рабивак-Внуково-32 Вакцина антирабическая культуральная инактивированная для иммунизации человека | G61: =IFERROR(__xludf.DUMMYFUNCTION("""COMPUTED_VALUE"""),"not in use") -> not in use | K61: =IFERROR(__xludf.DUMMYFUNCTION("""COMPUTED_VALUE"""),44712.0) -> 44712 | L61: =IFERROR(__xludf.DUMMYFUNCTION("""COMPUTED_VALUE"""),44748.0) -> 44748 | M61: =IFERROR(__xludf.DUMMYFUNCTION("""COMPUTED_VALUE"""),"нет") -> нет
A62: =IFERROR(__xludf.DUMMYFUNCTION("""COMPUTED_VALUE"""),61.0) -> 61 | B62: =IFERROR(__xludf.DUMMYFUNCTION("""COMPUTED_VALUE"""),"RotaTeq") -> RotaTeq | C62: =IFERROR(__xludf.DUMMYFUNCTION("""COMPUTED_VALUE"""),"https://grls.rosminzdrav.ru/Grls_View_v2.aspx?routingGuid=5a312c4c-479c-463e-85d1-fa7e8990168d") -> https://grls.rosminzdrav.ru/Grls_View_v2.aspx?routingGuid=5a312c4c-479c-463e-85d1-fa7e8990168d | D62: =IFERROR(__xludf.DUMMYFUNCTION("""COMPUTED_VALUE"""),"РотаТек") -> РотаТек | E62: =IFERROR(__xludf.DUMMYFUNCTION("""COMPUTED_VALUE"""),"РотаТек®") -> РотаТек® | G62: =IFERROR(__xludf.DUMMYFUNCTION("""COMPUTED_VALUE"""),"not in use") -> not in use | K62: =IFERROR(__xludf.DUMMYFUNCTION("""COMPUTED_VALUE"""),44712.0) -> 44712 | L62: =IFERROR(__xludf.DUMMYFUNCTION("""COMPUTED_VALUE"""),44787.0) -> 44787 | M62: =IFERROR(__xludf.DUMMYFUNCTION("""COMPUTED_VALUE"""),"нет") -> нет
A63: =IFERROR(__xludf.DUMMYFUNCTION("""COMPUTED_VALUE"""),62.0) -> 62 | B63: =IFERROR(__xludf.DUMMYFUNCTION("""COMPUTED_VALUE"""),"rubella_Microgen") -> rubella_Microgen | C63: =IFERROR(__xludf.DUMMYFUNCTION("""COMPUTED_VALUE"""),"https://grls.rosminzdrav.ru/Grls_View_v2.aspx?routingGuid=0482f816-63ad-49b9-9b56-808b708f6dab") -> https://grls.rosminzdrav.ru/Grls_View_v2.aspx?routingGuid=0482f816-63ad-49b9-9b56-808b708f6dab | D63: =IFERROR(__xludf.DUMMYFUNCTION("""COMPUTED_VALUE"""),"краснушная (Микроген)") -> краснушная (Микроген) | E63: =IFERROR(__xludf.DUMMYFUNCTION("""COMPUTED_VALUE"""),"Вакцина против краснухи культуральная живая") -> Вакцина против краснухи культуральная живая | F63: =IFERROR(__xludf.DUMMYFUNCTION("""COMPUTED_VALUE"""),"Микроген") -> Микроген | G63: =IFERROR(__xludf.DUMMYFUNCTION("""COMPUTED_VALUE"""),"in use") -> in use | K63: =IFERROR(__xludf.DUMMYFUNCTION("""COMPUTED_VALUE"""),44712.0) -> 44712 | L63: =IFERROR(__xludf.DUMMYFUNCTION("""COMPUTED_VALUE"""),45689.0) -> 45689 | M63: =IFERROR(__xludf.DUMMYFUNCTION("""COMPUTED_VALUE"""),"https://lk.regmed.ru/Register/GetPDFfromDAToken?Token=861ea14c-5408-419d-bd47-031af580ecf7") -> https://lk.regmed.ru/Register/GetPDFfromDAToken?Token=861ea14c-5408-419d-bd47-031af580ecf7
A64: =IFERROR(__xludf.DUMMYFUNCTION("""COMPUTED_VALUE"""),63.0) -> 63 | B64: =IFERROR(__xludf.DUMMYFUNCTION("""COMPUTED_VALUE"""),"rubella_Serum") -> rubella_Serum | C64: =IFERROR(__xludf.DUMMYFUNCTION("""COMPUTED_VALUE"""),"https://grls.rosminzdrav.ru/Grls_View_v2.aspx?routingGuid=dee8c37b-28f6-45f1-9773-d691d9fb54ae") -> https://grls.rosminzdrav.ru/Grls_View_v2.aspx?routingGuid=dee8c37b-28f6-45f1-9773-d691d9fb54ae | D64: =IFERROR(__xludf.DUMMYFUNCTION("""COMPUTED_VALUE"""),"краснушная (Серум Инститьют)") -> краснушная (Серум Инститьют) | E64: =IFERROR(__xludf.DUMMYFUNCTION("""COMPUTED_VALUE"""),"Вакцина против краснухи живая аттенуированная") -> Вакцина против краснухи живая аттенуированная | F64: =IFERROR(__xludf.DUMMYFUNCTION("""COMPUTED_VALUE"""),"Серум Инститьют") -> Серум Инститьют | G64: =IFERROR(__xludf.DUMMYFUNCTION("""COMPUTED_VALUE"""),"not in use") -> not in use | K64: =IFERROR(__xludf.DUMMYFUNCTION("""COMPUTED_VALUE"""),44712.0) -> 44712 | L64: =IFERROR(__xludf.DUMMYFUNCTION("""COMPUTED_VALUE"""),44750.0) -> 44750 | M64: =IFERROR(__xludf.DUMMYFUNCTION("""COMPUTED_VALUE"""),"нет") -> нет
A65: =IFERROR(__xludf.DUMMYFUNCTION("""COMPUTED_VALUE"""),64.0) -> 64 | B65: =IFERROR(__xludf.DUMMYFUNCTION("""COMPUTED_VALUE"""),"AS_Microgen") -> AS_Microgen | C65: =IFERROR(__xludf.DUMMYFUNCTION("""COMPUTED_VALUE"""),"https://grls.rosminzdrav.ru/Grls_View_v2.aspx?routingGuid=640af3c6-436c-47e2-a2cb-8cfff245452f") -> https://grls.rosminzdrav.ru/Grls_View_v2.aspx?routingGuid=640af3c6-436c-47e2-a2cb-8cfff245452f | D65: =IFERROR(__xludf.DUMMYFUNCTION("""COMPUTED_VALUE"""),"Анатоксин столбнячный (Микроген)") -> Анатоксин столбнячный (Микроген) | E65: =IFERROR(__xludf.DUMMYFUNCTION("""COMPUTED_VALUE"""),"Анатоксин столбнячный очищенный адсорбированный жидкий (АС-анатоксин)") -> Анатоксин столбнячный очищенный адсорбированный жидкий (АС-анатоксин) | G65: =IFERROR(__xludf.DUMMYFUNCTION("""COMPUTED_VALUE"""),"in use") -> in use | H65: =IFERROR(__xludf.DUMMYFUNCTION("""COMPUTED_VALUE"""),"<p>Анатоксин противопоказан только в первую половину беременности. Во вторую половину беременности введение анатоксина возможно.</p>") -> <p>Анатоксин противопоказан только в первую половину беременности. Во вторую половину беременности введение анатоксина возможно.</p> | I65: =IFERROR(__xludf.DUMMYFUNCTION("""COMPUTED_VALUE"""),"Анатоксин противопоказан только в первую половину беременности. Во вторую половину беременности введение анатоксина возможно.") -> Анатоксин противопоказан только в первую половину беременности. Во вторую половину беременности введение анатоксина возможно. | K65: =IFERROR(__xludf.DUMMYFUNCTION("""COMPUTED_VALUE"""),44712.0) -> 44712 | L65: =IFERROR(__xludf.DUMMYFUNCTION("""COMPUTED_VALUE"""),45689.0) -> 45689 | M65: =IFERROR(__xludf.DUMMYFUNCTION("""COMPUTED_VALUE"""),"есть") -> есть
A66: =IFERROR(__xludf.DUMMYFUNCTION("""COMPUTED_VALUE"""),65.0) -> 65 | B66: =IFERROR(__xludf.DUMMYFUNCTION("""COMPUTED_VALUE"""),"AS_Biomed") -> AS_Biomed | C66: =IFERROR(__xludf.DUMMYFUNCTION("""COMPUTED_VALUE"""),"https://grls.rosminzdrav.ru/Grls_View_v2.aspx?routingGuid=e46d0e09-a66e-402e-8777-b446fa489d1c") -> https://grls.rosminzdrav.ru/Grls_View_v2.aspx?routingGuid=e46d0e09-a66e-402e-8777-b446fa489d1c | D66: =IFERROR(__xludf.DUMMYFUNCTION("""COMPUTED_VALUE"""),"Анатоксин столбнячный (Биомед)") -> Анатоксин столбнячный (Биомед) | E66: =IFERROR(__xludf.DUMMYFUNCTION("""COMPUTED_VALUE"""),"Анатоксин столбнячный очищенный адсорбированный жидкий (АС-анатоксин)") -> Анатоксин столбнячный очищенный адсорбированный жидкий (АС-анатоксин) | G66: =IFERROR(__xludf.DUMMYFUNCTION("""COMPUTED_VALUE"""),"in use") -> in use | K66: =IFERROR(__xludf.DUMMYFUNCTION("""COMPUTED_VALUE"""),44712.0) -> 44712 | L66: =IFERROR(__xludf.DUMMYFUNCTION("""COMPUTED_VALUE"""),44750.0) -> 44750 | M66: =IFERROR(__xludf.DUMMYFUNCTION("""COMPUTED_VALUE"""),"нет") -> нет
A67: =IFERROR(__xludf.DUMMYFUNCTION("""COMPUTED_VALUE"""),66.0) -> 66 | B67: =IFERROR(__xludf.DUMMYFUNCTION("""COMPUTED_VALUE"""),"Vaqta_25") -> Vaqta_25 | C67: =IFERROR(__xludf.DUMMYFUNCTION("""COMPUTED_VALUE"""),"https://grls.rosminzdrav.ru/Grls_View_v2.aspx?routingGuid=2d805292-2bee-4665-b4ef-a466b3e3bc8f") -> https://grls.rosminzdrav.ru/Grls_View_v2.aspx?routingGuid=2d805292-2bee-4665-b4ef-a466b3e3bc8f | D67: =IFERROR(__xludf.DUMMYFUNCTION("""COMPUTED_VALUE"""),"Вакта 25") -> Вакта 25 | E67: =IFERROR(__xludf.DUMMYFUNCTION("""COMPUTED_VALUE"""),"Вакта®") -> Вакта® | G67: =IFERROR(__xludf.DUMMYFUNCTION("""COMPUTED_VALUE"""),"not in use") -> not in use | K67: =IFERROR(__xludf.DUMMYFUNCTION("""COMPUTED_VALUE"""),44712.0) -> 44712 | L67: =IFERROR(__xludf.DUMMYFUNCTION("""COMPUTED_VALUE"""),45079.0) -> 45079 | M67: =IFERROR(__xludf.DUMMYFUNCTION("""COMPUTED_VALUE"""),"нет") -> нет
A68: =IFERROR(__xludf.DUMMYFUNCTION("""COMPUTED_VALUE"""),67.0) -> 67 | B68: =IFERROR(__xludf.DUMMYFUNCTION("""COMPUTED_VALUE"""),"Vaqta_50") -> Vaqta_50 | C68: =IFERROR(__xludf.DUMMYFUNCTION("""COMPUTED_VALUE"""),"https://grls.rosminzdrav.ru/Grls_View_v2.aspx?routingGuid=2d805292-2bee-4665-b4ef-a466b3e3bc8f") -> https://grls.rosminzdrav.ru/Grls_View_v2.aspx?routingGuid=2d805292-2bee-4665-b4ef-a466b3e3bc8f | D68: =IFERROR(__xludf.DUMMYFUNCTION("""COMPUTED_VALUE"""),"Вакта 50") -> Вакта 50 | E68: =IFERROR(__xludf.DUMMYFUNCTION("""COMPUTED_VALUE"""),"Вакта®") -> Вакта® | G68: =IFERROR(__xludf.DUMMYFUNCTION("""COMPUTED_VALUE"""),"not in use") -> not in use | K68: =IFERROR(__xludf.DUMMYFUNCTION("""COMPUTED_VALUE"""),44712.0) -> 44712 | L68: =IFERROR(__xludf.DUMMYFUNCTION("""COMPUTED_VALUE"""),45079.0) -> 45079 | M68: =IFERROR(__xludf.DUMMYFUNCTION("""COMPUTED_VALUE"""),"нет") -> нет
A69: =IFERROR(__xludf.DUMMYFUNCTION("""COMPUTED_VALUE"""),68.0) -> 68 | B69: =IFERROR(__xludf.DUMMYFUNCTION("""COMPUTED_VALUE"""),"Klesh_E_Vac_0_5") -> Klesh_E_Vac_0_5 | C69: =IFERROR(__xludf.DUMMYFUNCTION("""COMPUTED_VALUE"""),"https://grls.rosminzdrav.ru/Grls_View_v2.aspx?routingGuid=708a5616-61d3-4695-a4cb-2e78bcfca33b") -> https://grls.rosminzdrav.ru/Grls_View_v2.aspx?routingGuid=708a5616-61d3-4695-a4cb-2e78bcfca33b | D69: =IFERROR(__xludf.DUMMYFUNCTION("""COMPUTED_VALUE"""),"Клещ-Э-Вак 0,5") -> Клещ-Э-Вак 0,5 | E69: =IFERROR(__xludf.DUMMYFUNCTION("""COMPUTED_VALUE"""),"Клещ-Э-Вак (Вакцина клещевого энцефалита культуральная очищенная концентрированная инактивированная сорбированная)") -> Клещ-Э-Вак (Вакцина клещевого энцефалита культуральная очищенная концентрированная инактивированная сорбированная) | G69: =IFERROR(__xludf.DUMMYFUNCTION("""COMPUTED_VALUE"""),"in use") -> in use | K69: =IFERROR(__xludf.DUMMYFUNCTION("""COMPUTED_VALUE"""),44712.0) -> 44712 | L69: =IFERROR(__xludf.DUMMYFUNCTION("""COMPUTED_VALUE"""),45988.0) -> 45988 | M69: =IFERROR(__xludf.DUMMYFUNCTION("""COMPUTED_VALUE"""),"есть") -> есть
A70: =IFERROR(__xludf.DUMMYFUNCTION("""COMPUTED_VALUE"""),69.0) -> 69 | B70: =IFERROR(__xludf.DUMMYFUNCTION("""COMPUTED_VALUE"""),"Klesh_E_Vac_0_25") -> Klesh_E_Vac_0_25 | C70: =IFERROR(__xludf.DUMMYFUNCTION("""COMPUTED_VALUE"""),"https://grls.rosminzdrav.ru/Grls_View_v2.aspx?routingGuid=708a5616-61d3-4695-a4cb-2e78bcfca33b") -> https://grls.rosminzdrav.ru/Grls_View_v2.aspx?routingGuid=708a5616-61d3-4695-a4cb-2e78bcfca33b | D70: =IFERROR(__xludf.DUMMYFUNCTION("""COMPUTED_VALUE"""),"Клещ-Э-Вак 0,25") -> Клещ-Э-Вак 0,25 | E70: =IFERROR(__xludf.DUMMYFUNCTION("""COMPUTED_VALUE"""),"Клещ-Э-Вак (Вакцина клещевого энцефалита культуральная очищенная концентрированная инактивированная сорбированная)") -> Клещ-Э-Вак (Вакцина клещевого энцефалита культуральная очищенная концентрированная инактивированная сорбированная) | G70: =IFERROR(__xludf.DUMMYFUNCTION("""COMPUTED_VALUE"""),"in use") -> in use | K70: =IFERROR(__xludf.DUMMYFUNCTION("""COMPUTED_VALUE"""),44712.0) -> 44712 | L70: =IFERROR(__xludf.DUMMYFUNCTION("""COMPUTED_VALUE"""),45988.0) -> 45988 | M70: =IFERROR(__xludf.DUMMYFUNCTION("""COMPUTED_VALUE"""),"есть") -> есть
A71: =IFERROR(__xludf.DUMMYFUNCTION("""COMPUTED_VALUE"""),70.0) -> 70 | B71: =IFERROR(__xludf.DUMMYFUNCTION("""COMPUTED_VALUE"""),"EnceVir_0_5") -> EnceVir_0_5 | C71: =IFERROR(__xludf.DUMMYFUNCTION("""COMPUTED_VALUE"""),"https://grls.rosminzdrav.ru/Grls_View_v2.aspx?routingGuid=9ea2867c-ced6-45dd-bf78-db44e14fd708") -> https://grls.rosminzdrav.ru/Grls_View_v2.aspx?routingGuid=9ea2867c-ced6-45dd-bf78-db44e14fd708 | D71: =IFERROR(__xludf.DUMMYFUNCTION("""COMPUTED_VALUE"""),"ЭнцеВир") -> ЭнцеВир | E71: =IFERROR(__xludf.DUMMYFUNCTION("""COMPUTED_VALUE"""),"ЭнцеВир® Вакцина клещевого энцефалита культуральная очищенная концентрированная инактивированная сорбированная") -> ЭнцеВир® Вакцина клещевого энцефалита культуральная очищенная концентрированная инактивированная сорбированная | G71: =IFERROR(__xludf.DUMMYFUNCTION("""COMPUTED_VALUE"""),"in use") -> in use | K71: =IFERROR(__xludf.DUMMYFUNCTION("""COMPUTED_VALUE"""),44712.0) -> 44712 | L71: =IFERROR(__xludf.DUMMYFUNCTION("""COMPUTED_VALUE"""),45689.0) -> 45689 | M71: =IFERROR(__xludf.DUMMYFUNCTION("""COMPUTED_VALUE"""),"https://lk.regmed.ru/Register/GetPDFfromDAToken?Token=1f268f03-9b1c-4d7b-9599-88099428d00f") -> https://lk.regmed.ru/Register/GetPDFfromDAToken?Token=1f268f03-9b1c-4d7b-9599-88099428d00f
A72: =IFERROR(__xludf.DUMMYFUNCTION("""COMPUTED_VALUE"""),71.0) -> 71 | B72: =IFERROR(__xludf.DUMMYFUNCTION("""COMPUTED_VALUE"""),"EnceVir_Neo_kids") -> EnceVir_Neo_kids | C72: =IFERROR(__xludf.DUMMYFUNCTION("""COMPUTED_VALUE"""),"https://grls.rosminzdrav.ru/Grls_View_v2.aspx?routingGuid=c2615365-07f8-416b-be71-d3e983cb1eb3") -> https://grls.rosminzdrav.ru/Grls_View_v2.aspx?routingGuid=c2615365-07f8-416b-be71-d3e983cb1eb3 | D72: =IFERROR(__xludf.DUMMYFUNCTION("""COMPUTED_VALUE"""),"ЭнцеВир Нео детский") -> ЭнцеВир Нео детский | E72: =IFERROR(__xludf.DUMMYFUNCTION("""COMPUTED_VALUE"""),"ЭнцеВир® Нео детский (Вакцина клещевого энцефалита культуральная очищенная концентрированная инактивированная сорбированная)") -> ЭнцеВир® Нео детский (Вакцина клещевого энцефалита культуральная очищенная концентрированная инактивированная сорбированная) | G72: =IFERROR(__xludf.DUMMYFUNCTION("""COMPUTED_VALUE"""),"in use") -> in use | K72: =IFERROR(__xludf.DUMMYFUNCTION("""COMPUTED_VALUE"""),44712.0) -> 44712 | L72: =IFERROR(__xludf.DUMMYFUNCTION("""COMPUTED_VALUE"""),45689.0) -> 45689 | M72: =IFERROR(__xludf.DUMMYFUNCTION("""COMPUTED_VALUE"""),"https://lk.regmed.ru/Register/GetPDFfromDAToken?Token=5a727ed4-b3cb-4f35-8c47-cdc269e90fed") -> https://lk.regmed.ru/Register/GetPDFfromDAToken?Token=5a727ed4-b3cb-4f35-8c47-cdc269e90fed
A73: =IFERROR(__xludf.DUMMYFUNCTION("""COMPUTED_VALUE"""),72.0) -> 72 | B73: =IFERROR(__xludf.DUMMYFUNCTION("""COMPUTED_VALUE"""),"TBE_Chumakov_lyo") -> TBE_Chumakov_lyo | C73: =IFERROR(__xludf.DUMMYFUNCTION("""COMPUTED_VALUE"""),"https://grls.rosminzdrav.ru/Grls_View_v2.aspx?routingGuid=69bf2722-aa8e-4374-a63b-c2e0fd5da7cd") -> https://grls.rosminzdrav.ru/Grls_View_v2.aspx?routingGuid=69bf2722-aa8e-4374-a63b-c2e0fd5da7cd | D73: =IFERROR(__xludf.DUMMYFUNCTION("""COMPUTED_VALUE"""),"клещевого энцефалита (Чумакова)") -> клещевого энцефалита (Чумакова) | E73: =IFERROR(__xludf.DUMMYFUNCTION("""COMPUTED_VALUE"""),"Вакцина клещевого энцефалита культуральная очищенная концентрированная инактивированная сухая") -> Вакцина клещевого энцефалита культуральная очищенная концентрированная инактивированная сухая | G73: =IFERROR(__xludf.DUMMYFUNCTION("""COMPUTED_VALUE"""),"in use") -> in use | K73: =IFERROR(__xludf.DUMMYFUNCTION("""COMPUTED_VALUE"""),44712.0) -> 44712 | L73: =IFERROR(__xludf.DUMMYFUNCTION("""COMPUTED_VALUE"""),45750.0) -> 45750 | M73: =IFERROR(__xludf.DUMMYFUNCTION("""COMPUTED_VALUE"""),"https://lk.regmed.ru/Register/GetPDFfromDAToken?Token=2516e721-6e26-4b63-bc37-7163e862ca17") -> https://lk.regmed.ru/Register/GetPDFfromDAToken?Token=2516e721-6e26-4b63-bc37-7163e862ca17
A74: =IFERROR(__xludf.DUMMYFUNCTION("""COMPUTED_VALUE"""),73.0) -> 73 | B74: =IFERROR(__xludf.DUMMYFUNCTION("""COMPUTED_VALUE"""),"Varilrix") -> Varilrix | C74: =IFERROR(__xludf.DUMMYFUNCTION("""COMPUTED_VALUE"""),"https://grls.rosminzdrav.ru/Grls_View_v2.aspx?routingGuid=cf5179f1-d6f7-4a8b-9251-28065290b167") -> https://grls.rosminzdrav.ru/Grls_View_v2.aspx?routingGuid=cf5179f1-d6f7-4a8b-9251-28065290b167 | D74: =IFERROR(__xludf.DUMMYFUNCTION("""COMPUTED_VALUE"""),"Варилрикс") -> Варилрикс | E74: =IFERROR(__xludf.DUMMYFUNCTION("""COMPUTED_VALUE"""),"Варилрикс® (Вакцина против ветряной оспы живая аттенуированная)") -> Варилрикс® (Вакцина против ветряной оспы живая аттенуированная) | G74: =IFERROR(__xludf.DUMMYFUNCTION("""COMPUTED_VALUE"""),"in use") -> in use | H74: =IFERROR(__xludf.DUMMYFUNCTION("""COMPUTED_VALUE"""),"<p><ul><li>Плановая профилактика ветряной оспы, в том числе у лиц с повышенным риском тяжелого и осложненного течения ветряной оспы;</li> <li>плановая профилактика ветряной оспы у здорового окружения лиц, отнесенных к группам риска;</li> <li>экстренная пр"&"офилактика ветряной оспы в течение 72&nbsp;часов с момента контакта с больным ветряной оспой.</li></ul></p>") -> <p><ul><li>Плановая профилактика ветряной оспы, в том числе у лиц с повышенным риском тяжелого и осложненного течения ветряной оспы;</li> <li>плановая профилактика ветряной оспы у здорового окружения лиц, отнесенных к группам риска;</li> <li>экстренная профилактика ветряной оспы в течение 72&nbsp;часов с момента контакта с больным ветряной оспой.</li></ul></p> | I74: =IFERROR(__xludf.DUMMYFUNCTION("""COMPUTED_VALUE"""),"• Плановая профилактика ветряной оспы, в том числе у лиц с повышенным риском тяжелого и осложненного течения ветряной оспы; • плановая профилактика ветряной оспы у здорового окружения лиц, отнесенных к группам риска; • экстренная профилактика ветряной осп"&"ы в течение 72 часов с момента контакта с больным ветряной оспой.") -> • Плановая профилактика ветряной оспы, в том числе у лиц с повышенным риском тяжелого и осложненного течения ветряной оспы; • плановая профилактика ветряной оспы у здорового окружения лиц, отнесенных к группам риска; • экстренная профилактика ветряной оспы в течение 72 часов с момента контакта с больным ветряной оспой. | K74: =IFERROR(__xludf.DUMMYFUNCTION("""COMPUTED_VALUE"""),44712.0) -> 44712 | L74: =IFERROR(__xludf.DUMMYFUNCTION("""COMPUTED_VALUE"""),45830.0) -> 45830 | M74: =IFERROR(__xludf.DUMMYFUNCTION("""COMPUTED_VALUE"""),"https://lk.regmed.ru/Register/GetPDFfromDAToken?Token=0cff0d2a-3085-4425-a8d9-40621446b45c") -> https://lk.regmed.ru/Register/GetPDFfromDAToken?Token=0cff0d2a-3085-4425-a8d9-40621446b45c
A75: =IFERROR(__xludf.DUMMYFUNCTION("""COMPUTED_VALUE"""),74.0) -> 74 | B75: =IFERROR(__xludf.DUMMYFUNCTION("""COMPUTED_VALUE"""),"YF_Chumakov_lyo") -> YF_Chumakov_lyo | C75: =IFERROR(__xludf.DUMMYFUNCTION("""COMPUTED_VALUE"""),"https://grls.rosminzdrav.ru/Grls_View_v2.aspx?routingGuid=a0eece39-1af9-4420-be24-7ff034677feb") -> https://grls.rosminzdrav.ru/Grls_View_v2.aspx?routingGuid=a0eece39-1af9-4420-be24-7ff034677feb | D75: =IFERROR(__xludf.DUMMYFUNCTION("""COMPUTED_VALUE"""),"желтой лихорадки") -> желтой лихорадки | E75: =IFERROR(__xludf.DUMMYFUNCTION("""COMPUTED_VALUE"""),"Вакцина желтой лихорадки живая сухая") -> Вакцина желтой лихорадки живая сухая | G75: =IFERROR(__xludf.DUMMYFUNCTION("""COMPUTED_VALUE"""),"in use") -> in use | H75: =IFERROR(__xludf.DUMMYFUNCTION("""COMPUTED_VALUE"""),"<p>Профилактика желтой лихорадки у детей с 9-месячного возраста и взрослых, направляющихся, проезжающих, или проживающих в регионах, в которых регистрируется заболеваемость желтой лихорадкой; у лиц, направляющихся в страну, въезд в которую требует наличия"&" международного свидетельства о вакцинации; а также у лиц, работающих с живыми культурами возбудителя желтой лихорадки.</p>") -> <p>Профилактика желтой лихорадки у детей с 9-месячного возраста и взрослых, направляющихся, проезжающих, или проживающих в регионах, в которых регистрируется заболеваемость желтой лихорадкой; у лиц, направляющихся в страну, въезд в которую требует наличия международного свидетельства о вакцинации; а также у лиц, работающих с живыми культурами возбудителя желтой лихорадки.</p> | I75: =IFERROR(__xludf.DUMMYFUNCTION("""COMPUTED_VALUE"""),"Профилактика желтой лихорадки у детей с 9-месячного возраста и взрослых, направляющихся, проезжающих, или проживающих в регионах, в которых регистрируется заболеваемость желтой лихорадкой; у лиц, направляющихся в страну, въезд в которую требует наличия ме"&"ждународного свидетельства о вакцинации; а также у лиц, работающих с живыми культурами возбудителя желтой лихорадки.") -> Профилактика желтой лихорадки у детей с 9-месячного возраста и взрослых, направляющихся, проезжающих, или проживающих в регионах, в которых регистрируется заболеваемость желтой лихорадкой; у лиц, направляющихся в страну, въезд в которую требует наличия международного свидетельства о вакцинации; а также у лиц, работающих с живыми культурами возбудителя желтой лихорадки. | K75: =IFERROR(__xludf.DUMMYFUNCTION("""COMPUTED_VALUE"""),44712.0) -> 44712 | L75: =IFERROR(__xludf.DUMMYFUNCTION("""COMPUTED_VALUE"""),44807.0) -> 44807 | M75: =IFERROR(__xludf.DUMMYFUNCTION("""COMPUTED_VALUE"""),"нет") -> нет
A76: =IFERROR(__xludf.DUMMYFUNCTION("""COMPUTED_VALUE"""),75.0) -> 75 | B76: =IFERROR(__xludf.DUMMYFUNCTION("""COMPUTED_VALUE"""),"tularemia_Microgen") -> tularemia_Microgen | C76: =IFERROR(__xludf.DUMMYFUNCTION("""COMPUTED_VALUE"""),"https://grls.rosminzdrav.ru/Grls_View_v2.aspx?routingGuid=1f496df2-7c22-4ddc-8980-da1023a88a35") -> https://grls.rosminzdrav.ru/Grls_View_v2.aspx?routingGuid=1f496df2-7c22-4ddc-8980-da1023a88a35 | D76: =IFERROR(__xludf.DUMMYFUNCTION("""COMPUTED_VALUE"""),"туляремийная") -> туляремийная | E76: =IFERROR(__xludf.DUMMYFUNCTION("""COMPUTED_VALUE"""),"Вакцина туляремийная живая") -> Вакцина туляремийная живая | F76: =IFERROR(__xludf.DUMMYFUNCTION("""COMPUTED_VALUE"""),"Микроген") -> Микроген | G76: =IFERROR(__xludf.DUMMYFUNCTION("""COMPUTED_VALUE"""),"in use") -> in use | H76: =IFERROR(__xludf.DUMMYFUNCTION("""COMPUTED_VALUE"""),"<p>Прививкам подлежит население, проживающее на энзоотичных по туляремии территориях, а также прибывшие на эти территории лица, выполняющие следующие работы: сельскохозяйственные, гидромелиоративные, строительные, другие работы по выемке и перемещению гру"&"нта, заготовительные, промысловые, геологические, изыскательные, экспедиционные, дератизационные и дезинсекционные, по лесозаготовке, расчистке и благоустройству леса, зон оздоровления и отдыха населения.</p>") -> <p>Прививкам подлежит население, проживающее на энзоотичных по туляремии территориях, а также прибывшие на эти территории лица, выполняющие следующие работы: сельскохозяйственные, гидромелиоративные, строительные, другие работы по выемке и перемещению грунта, заготовительные, промысловые, геологические, изыскательные, экспедиционные, дератизационные и дезинсекционные, по лесозаготовке, расчистке и благоустройству леса, зон оздоровления и отдыха населения.</p> | I76: =IFERROR(__xludf.DUMMYFUNCTION("""COMPUTED_VALUE"""),"Прививкам подлежит население, проживающее на энзоотичных по туляремии территориях, а также прибывшие на эти территории лица, выполняющие следующие работы: сельскохозяйственные, гидромелиоративные, строительные, другие работы по выемке и перемещению грунта"&", заготовительные, промысловые, геологические, изыскательные, экспедиционные, дератизационные и дезинсекционные, по лесозаготовке, расчистке и благоустройству леса, зон оздоровления и отдыха населения.") -> Прививкам подлежит население, проживающее на энзоотичных по туляремии территориях, а также прибывшие на эти территории лица, выполняющие следующие работы: сельскохозяйственные, гидромелиоративные, строительные, другие работы по выемке и перемещению грунта, заготовительные, промысловые, геологические, изыскательные, экспедиционные, дератизационные и дезинсекционные, по лесозаготовке, расчистке и благоустройству леса, зон оздоровления и отдыха населения. | K76: =IFERROR(__xludf.DUMMYFUNCTION("""COMPUTED_VALUE"""),44712.0) -> 44712 | L76: =IFERROR(__xludf.DUMMYFUNCTION("""COMPUTED_VALUE"""),45689.0) -> 45689 | M76: =IFERROR(__xludf.DUMMYFUNCTION("""COMPUTED_VALUE"""),"https://lk.regmed.ru/Register/GetPDFfromDAToken?Token=ec8dbc07-4048-4803-b294-939328173382") -> https://lk.regmed.ru/Register/GetPDFfromDAToken?Token=ec8dbc07-4048-4803-b294-939328173382
A77: =IFERROR(__xludf.DUMMYFUNCTION("""COMPUTED_VALUE"""),76.0) -> 76 | B77: =IFERROR(__xludf.DUMMYFUNCTION("""COMPUTED_VALUE"""),"plague_molecular_lyo_RPN") -> plague_molecular_lyo_RPN | C77: =IFERROR(__xludf.DUMMYFUNCTION("""COMPUTED_VALUE"""),"https://grls.rosminzdrav.ru/Grls_View_v2.aspx?routingGuid=d4e26cea-321e-489e-90b0-10674ba3eaf9") -> https://grls.rosminzdrav.ru/Grls_View_v2.aspx?routingGuid=d4e26cea-321e-489e-90b0-10674ba3eaf9 | D77: =IFERROR(__xludf.DUMMYFUNCTION("""COMPUTED_VALUE"""),"чумная микроинкапсулированная") -> чумная микроинкапсулированная | E77: =IFERROR(__xludf.DUMMYFUNCTION("""COMPUTED_VALUE"""),"Вакцина чумная молекулярная микроинкапсулированная (ВЧММ)") -> Вакцина чумная молекулярная микроинкапсулированная (ВЧММ) | G77: =IFERROR(__xludf.DUMMYFUNCTION("""COMPUTED_VALUE"""),"in use") -> in use | K77: =IFERROR(__xludf.DUMMYFUNCTION("""COMPUTED_VALUE"""),44712.0) -> 44712 | L77: =IFERROR(__xludf.DUMMYFUNCTION("""COMPUTED_VALUE"""),44803.0) -> 44803 | M77: =IFERROR(__xludf.DUMMYFUNCTION("""COMPUTED_VALUE"""),"нет") -> нет
A78: =IFERROR(__xludf.DUMMYFUNCTION("""COMPUTED_VALUE"""),77.0) -> 77 | B78: =IFERROR(__xludf.DUMMYFUNCTION("""COMPUTED_VALUE"""),"plague_live_lyo_48_NII_Minoborony") -> plague_live_lyo_48_NII_Minoborony | C78: =IFERROR(__xludf.DUMMYFUNCTION("""COMPUTED_VALUE"""),"https://grls.rosminzdrav.ru/Grls_View_v2.aspx?routingGuid=0962362a-d8cb-4c53-b4f2-43cc75eea35f") -> https://grls.rosminzdrav.ru/Grls_View_v2.aspx?routingGuid=0962362a-d8cb-4c53-b4f2-43cc75eea35f | D78: =IFERROR(__xludf.DUMMYFUNCTION("""COMPUTED_VALUE"""),"чумная (лиофилизат, 48 НИИ)") -> чумная (лиофилизат, 48 НИИ) | E78: =IFERROR(__xludf.DUMMYFUNCTION("""COMPUTED_VALUE"""),"Вакцина чумная живая") -> Вакцина чумная живая | G78: =IFERROR(__xludf.DUMMYFUNCTION("""COMPUTED_VALUE"""),"in use") -> in use | K78: =IFERROR(__xludf.DUMMYFUNCTION("""COMPUTED_VALUE"""),44712.0) -> 44712 | L78: =IFERROR(__xludf.DUMMYFUNCTION("""COMPUTED_VALUE"""),44803.0) -> 44803 | M78: =IFERROR(__xludf.DUMMYFUNCTION("""COMPUTED_VALUE"""),"нет") -> нет
A79: =IFERROR(__xludf.DUMMYFUNCTION("""COMPUTED_VALUE"""),78.0) -> 78 | B79: =IFERROR(__xludf.DUMMYFUNCTION("""COMPUTED_VALUE"""),"plague_live_tablets_48_NII_Minoborony") -> plague_live_tablets_48_NII_Minoborony | C79: =IFERROR(__xludf.DUMMYFUNCTION("""COMPUTED_VALUE"""),"https://grls.rosminzdrav.ru/Grls_View_v2.aspx?routingGuid=37890f2a-f963 – 4c4a-a9fc-d7738025bf49") -> https://grls.rosminzdrav.ru/Grls_View_v2.aspx?routingGuid=37890f2a-f963 – 4c4a-a9fc-d7738025bf49 | D79: =IFERROR(__xludf.DUMMYFUNCTION("""COMPUTED_VALUE"""),"чумная (таблетки, 48 НИИ)") -> чумная (таблетки, 48 НИИ) | E79: =IFERROR(__xludf.DUMMYFUNCTION("""COMPUTED_VALUE"""),"Вакцина чумная живая") -> Вакцина чумная живая | G79: =IFERROR(__xludf.DUMMYFUNCTION("""COMPUTED_VALUE"""),"in use") -> in use | K79: =IFERROR(__xludf.DUMMYFUNCTION("""COMPUTED_VALUE"""),44712.0) -> 44712 | L79: =IFERROR(__xludf.DUMMYFUNCTION("""COMPUTED_VALUE"""),44803.0) -> 44803 | M79: =IFERROR(__xludf.DUMMYFUNCTION("""COMPUTED_VALUE"""),"нет") -> нет
A80: =IFERROR(__xludf.DUMMYFUNCTION("""COMPUTED_VALUE"""),79.0) -> 79 | B80: =IFERROR(__xludf.DUMMYFUNCTION("""COMPUTED_VALUE"""),"plague_live_lyo_RPN") -> plague_live_lyo_RPN | C80: =IFERROR(__xludf.DUMMYFUNCTION("""COMPUTED_VALUE"""),"https://grls.rosminzdrav.ru/Grls_View_v2.aspx?routingGuid=a55e6d43-fef5-4c3d-af16-a15f6b065685") -> https://grls.rosminzdrav.ru/Grls_View_v2.aspx?routingGuid=a55e6d43-fef5-4c3d-af16-a15f6b065685 | D80: =IFERROR(__xludf.DUMMYFUNCTION("""COMPUTED_VALUE"""),"чумная (лиофилизат, НИИ РПН)") -> чумная (лиофилизат, НИИ РПН) | E80: =IFERROR(__xludf.DUMMYFUNCTION("""COMPUTED_VALUE"""),"Вакцина чумная живая") -> Вакцина чумная живая | G80: =IFERROR(__xludf.DUMMYFUNCTION("""COMPUTED_VALUE"""),"in use") -> in use | K80: =IFERROR(__xludf.DUMMYFUNCTION("""COMPUTED_VALUE"""),44712.0) -> 44712 | L80: =IFERROR(__xludf.DUMMYFUNCTION("""COMPUTED_VALUE"""),44803.0) -> 44803 | M80: =IFERROR(__xludf.DUMMYFUNCTION("""COMPUTED_VALUE"""),"нет") -> нет
A81: =IFERROR(__xludf.DUMMYFUNCTION("""COMPUTED_VALUE"""),80.0) -> 80 | B81: =IFERROR(__xludf.DUMMYFUNCTION("""COMPUTED_VALUE"""),"brucellosis_therapeutic_48_NII_Minoborony") -> brucellosis_therapeutic_48_NII_Minoborony | C81: =IFERROR(__xludf.DUMMYFUNCTION("""COMPUTED_VALUE"""),"https://grls.rosminzdrav.ru/Grls_View_v2.aspx?routingGuid=7da2f9f3 – 53a6-4cbe-9eae-65a3d0bed21b") -> https://grls.rosminzdrav.ru/Grls_View_v2.aspx?routingGuid=7da2f9f3 – 53a6-4cbe-9eae-65a3d0bed21b | D81: =IFERROR(__xludf.DUMMYFUNCTION("""COMPUTED_VALUE"""),"бруцеллезная (лечебная)") -> бруцеллезная (лечебная) | E81: =IFERROR(__xludf.DUMMYFUNCTION("""COMPUTED_VALUE"""),"Вакцина бруцеллезная инактивированная лечебная") -> Вакцина бруцеллезная инактивированная лечебная | G81: =IFERROR(__xludf.DUMMYFUNCTION("""COMPUTED_VALUE"""),"in use") -> in use | K81: =IFERROR(__xludf.DUMMYFUNCTION("""COMPUTED_VALUE"""),44712.0) -> 44712 | L81: =IFERROR(__xludf.DUMMYFUNCTION("""COMPUTED_VALUE"""),44803.0) -> 44803 | M81: =IFERROR(__xludf.DUMMYFUNCTION("""COMPUTED_VALUE"""),"нет") -> нет
A82: =IFERROR(__xludf.DUMMYFUNCTION("""COMPUTED_VALUE"""),81.0) -> 81 | B82: =IFERROR(__xludf.DUMMYFUNCTION("""COMPUTED_VALUE"""),"brucellosis_prophylactic_Microgen") -> brucellosis_prophylactic_Microgen | C82: =IFERROR(__xludf.DUMMYFUNCTION("""COMPUTED_VALUE"""),"https://grls.rosminzdrav.ru/Grls_View_v2.aspx?routingGuid=41231e71-613c-4a24-ab98-462b5d95f938") -> https://grls.rosminzdrav.ru/Grls_View_v2.aspx?routingGuid=41231e71-613c-4a24-ab98-462b5d95f938 | D82: =IFERROR(__xludf.DUMMYFUNCTION("""COMPUTED_VALUE"""),"бруцеллезная (профилактическая)") -> бруцеллезная (профилактическая) | E82: =IFERROR(__xludf.DUMMYFUNCTION("""COMPUTED_VALUE"""),"Вакцина бруцеллезная живая") -> Вакцина бруцеллезная живая | G82: =IFERROR(__xludf.DUMMYFUNCTION("""COMPUTED_VALUE"""),"in use") -> in use | K82: =IFERROR(__xludf.DUMMYFUNCTION("""COMPUTED_VALUE"""),44712.0) -> 44712 | L82: =IFERROR(__xludf.DUMMYFUNCTION("""COMPUTED_VALUE"""),45798.0) -> 45798 | M82: =IFERROR(__xludf.DUMMYFUNCTION("""COMPUTED_VALUE"""),"https://lk.regmed.ru/Register/GetPDFfromDAToken?Token=bbb42574-93e7-4e33-91ef-666773d1f867") -> https://lk.regmed.ru/Register/GetPDFfromDAToken?Token=bbb42574-93e7-4e33-91ef-666773d1f867
A83: =IFERROR(__xludf.DUMMYFUNCTION("""COMPUTED_VALUE"""),82.0) -> 82 | B83: =IFERROR(__xludf.DUMMYFUNCTION("""COMPUTED_VALUE"""),"anthrax_live_48_NII_Minoborony") -> anthrax_live_48_NII_Minoborony | C83: =IFERROR(__xludf.DUMMYFUNCTION("""COMPUTED_VALUE"""),"https://grls.rosminzdrav.ru/Grls_View_v2.aspx?routingGuid=d7622abd-8b68-42cc-aeb2-08d107689bbc") -> https://grls.rosminzdrav.ru/Grls_View_v2.aspx?routingGuid=d7622abd-8b68-42cc-aeb2-08d107689bbc | D83: =IFERROR(__xludf.DUMMYFUNCTION("""COMPUTED_VALUE"""),"сибиреязвенная") -> сибиреязвенная | E83: =IFERROR(__xludf.DUMMYFUNCTION("""COMPUTED_VALUE"""),"Вакцина сибиреязвенная живая") -> Вакцина сибиреязвенная живая | G83: =IFERROR(__xludf.DUMMYFUNCTION("""COMPUTED_VALUE"""),"in use") -> in use | H83: =IFERROR(__xludf.DUMMYFUNCTION("""COMPUTED_VALUE"""),"<p>Подлежат обязательной вакцинации: <ul><li>Лица, работающие с живыми культурами возбудителя сибирской язвы, с зараженными лабораторными животными или производящие исследования материалов, зараженных или подозрительным на инфицирование возбудителем сибир"&"ской язвы.</li> <li>Лица, профессионально занятые содержанием скота, а также производящие убой скота, занятые заготовкой, сбором, хранением, транспортировкой, переработкой и реализацией сырья животного происхождения.</li> <li>Лица, выполняющие сельскохозя"&"йственные, гидромелиоративные, строительные, по выемке и перемещению грунта, заготовительные, промысловые, геологические, изыскательские, экспедиционные на энзоотичных по сибирской язве территориях.</ul></p>") -> <p>Подлежат обязательной вакцинации: <ul><li>Лица, работающие с живыми культурами возбудителя сибирской язвы, с зараженными лабораторными животными или производящие исследования материалов, зараженных или подозрительным на инфицирование возбудителем сибирской язвы.</li> <li>Лица, профессионально занятые содержанием скота, а также производящие убой скота, занятые заготовкой, сбором, хранением, транспортировкой, переработкой и реализацией сырья животного происхождения.</li> <li>Лица, выполняющие сельскохозяйственные, гидромелиоративные, строительные, по выемке и перемещению грунта, заготовительные, промысловые, геологические, изыскательские, экспедиционные на энзоотичных по сибирской язве территориях.</ul></p> | I83: =IFERROR(__xludf.DUMMYFUNCTION("""COMPUTED_VALUE"""),"Подлежат обязательной вакцинации: • Лица, работающие с живыми культурами возбудителя сибирской язвы, с зараженными лабораторными животными или производящие исследования материалов, зараженных или подозрительным на инфицирование возбудителем сибирской язв"&"ы. • Лица, профессионально занятые содержанием скота, а также производящие убой скота, занятые заготовкой, сбором, хранением, транспортировкой, переработкой и реализацией сырья животного происхождения. • Лица, выполняющие сельскохозяйственные, гидромелиор"&"ативные, строительные, по выемке и перемещению грунта, заготовительные, промысловые, геологические, изыскательские, экспедиционные на энзоотичных по сибирской язве территориях.") -> Подлежат обязательной вакцинации: • Лица, работающие с живыми культурами возбудителя сибирской язвы, с зараженными лабораторными животными или производящие исследования материалов, зараженных или подозрительным на инфицирование возбудителем сибирской язвы. • Лица, профессионально занятые содержанием скота, а также производящие убой скота, занятые заготовкой, сбором, хранением, транспортировкой, переработкой и реализацией сырья животного происхождения. • Лица, выполняющие сельскохозяйственные, гидромелиоративные, строительные, по выемке и перемещению грунта, заготовительные, промысловые, геологические, изыскательские, экспедиционные на энзоотичных по сибирской язве территориях. | K83: =IFERROR(__xludf.DUMMYFUNCTION("""COMPUTED_VALUE"""),44712.0) -> 44712 | L83: =IFERROR(__xludf.DUMMYFUNCTION("""COMPUTED_VALUE"""),44807.0) -> 44807 | M83: =IFERROR(__xludf.DUMMYFUNCTION("""COMPUTED_VALUE"""),"нет") -> нет
A84: =IFERROR(__xludf.DUMMYFUNCTION("""COMPUTED_VALUE"""),83.0) -> 83 | B84: =IFERROR(__xludf.DUMMYFUNCTION("""COMPUTED_VALUE"""),"anthrax_combined_48_NII_Minoborony") -> anthrax_combined_48_NII_Minoborony | C84: =IFERROR(__xludf.DUMMYFUNCTION("""COMPUTED_VALUE"""),"https://grls.rosminzdrav.ru/Grls_View_v2.aspx?routingGuid=45ea6a47-5e12-4580-b8ed-b03d229557e4") -> https://grls.rosminzdrav.ru/Grls_View_v2.aspx?routingGuid=45ea6a47-5e12-4580-b8ed-b03d229557e4 | D84: =IFERROR(__xludf.DUMMYFUNCTION("""COMPUTED_VALUE"""),"сибиреязвенная комбинированная") -> сибиреязвенная комбинированная | E84: =IFERROR(__xludf.DUMMYFUNCTION("""COMPUTED_VALUE"""),"Вакцина сибиреязвенная комбинированная") -> Вакцина сибиреязвенная комбинированная | G84: =IFERROR(__xludf.DUMMYFUNCTION("""COMPUTED_VALUE"""),"in use") -> in use | H84: =IFERROR(__xludf.DUMMYFUNCTION("""COMPUTED_VALUE"""),"<p>Плановым прививкам подлежат: <ol><li>Лица, работающие с живыми культурами возбудителя сибирской язвы, с зараженными лабораторными животными или производящие исследования материалов, зараженных возбудителем сибирской язвы.</li> <li>Лица, производящие у"&"бой скота, занятые заготовкой, сбором, хранением, транспортировкой, переработкой и реализацией сырья животного происхождения.</li> <li>Лица, выполняющие следующие работы на энзоотичных по сибирской язве территориях: <ul><li>Обслуживание общественного ско"&"та.</li> <li>Сельскохозяйственные, агро- и гидромелиоративные, строительные и другие работы, связанные с выемкой и перемещением грунта.</li> <li>Заготовительные, промысловые, геологические, изыскательные, экспедиционные.</li></ul></li></ol></p>") -> <p>Плановым прививкам подлежат: <ol><li>Лица, работающие с живыми культурами возбудителя сибирской язвы, с зараженными лабораторными животными или производящие исследования материалов, зараженных возбудителем сибирской язвы.</li> <li>Лица, производящие убой скота, занятые заготовкой, сбором, хранением, транспортировкой, переработкой и реализацией сырья животного происхождения.</li> <li>Лица, выполняющие следующие работы на энзоотичных по сибирской язве территориях: <ul><li>Обслуживание общественного скота.</li> <li>Сельскохозяйственные, агро- и гидромелиоративные, строительные и другие работы, связанные с выемкой и перемещением грунта.</li> <li>Заготовительные, промысловые, геологические, изыскательные, экспедиционные.</li></ul></li></ol></p> | I84: =IFERROR(__xludf.DUMMYFUNCTION("""COMPUTED_VALUE"""),"Плановым прививкам подлежат: 1. Лица, работающие с живыми культурами возбудителя сибирской язвы, с зараженными лабораторными животными или производящие исследования материалов, зараженных возбудителем сибирской язвы. 2. Лица, производящие убой скота, зан"&"ятые заготовкой, сбором, хранением, транспортировкой, переработкой и реализацией сырья животного происхождения. 3. Лица, выполняющие следующие работы на энзоотичных по сибирской язве территориях: • Обслуживание общественного скота. • Сельскохозяйственные"&", агро- и гидромелиоративные, строительные и другие работы, связанные с выемкой и перемещением грунта. • Заготовительные, промысловые, геологические, изыскательные, экспедиционные.") -> Плановым прививкам подлежат: 1. Лица, работающие с живыми культурами возбудителя сибирской язвы, с зараженными лабораторными животными или производящие исследования материалов, зараженных возбудителем сибирской язвы. 2. Лица, производящие убой скота, занятые заготовкой, сбором, хранением, транспортировкой, переработкой и реализацией сырья животного происхождения. 3. Лица, выполняющие следующие работы на энзоотичных по сибирской язве территориях: • Обслуживание общественного скота. • Сельскохозяйственные, агро- и гидромелиоративные, строительные и другие работы, связанные с выемкой и перемещением грунта. • Заготовительные, промысловые, геологические, изыскательные, экспедиционные. | K84: =IFERROR(__xludf.DUMMYFUNCTION("""COMPUTED_VALUE"""),44712.0) -> 44712 | L84: =IFERROR(__xludf.DUMMYFUNCTION("""COMPUTED_VALUE"""),44807.0) -> 44807 | M84: =IFERROR(__xludf.DUMMYFUNCTION("""COMPUTED_VALUE"""),"нет") -> нет
A85: =IFERROR(__xludf.DUMMYFUNCTION("""COMPUTED_VALUE"""),84.0) -> 84 | B85: =IFERROR(__xludf.DUMMYFUNCTION("""COMPUTED_VALUE"""),"Rabipur") -> Rabipur | C85: =IFERROR(__xludf.DUMMYFUNCTION("""COMPUTED_VALUE"""),"https://grls.rosminzdrav.ru/Grls_View_v2.aspx?routingGuid=b5f5bf28-a50c-46a3-8777-66ad5b7b6870") -> https://grls.rosminzdrav.ru/Grls_View_v2.aspx?routingGuid=b5f5bf28-a50c-46a3-8777-66ad5b7b6870 | D85: =IFERROR(__xludf.DUMMYFUNCTION("""COMPUTED_VALUE"""),"Рабипур") -> Рабипур | E85: =IFERROR(__xludf.DUMMYFUNCTION("""COMPUTED_VALUE"""),"Рабипур® (Вакцина антирабическая культуральная очищенная инактивированная)") -> Рабипур® (Вакцина антирабическая культуральная очищенная инактивированная) | F85: =IFERROR(__xludf.DUMMYFUNCTION("""COMPUTED_VALUE"""),"Кайрон Беринг Вакцинс") -> Кайрон Беринг Вакцинс | G85: =IFERROR(__xludf.DUMMYFUNCTION("""COMPUTED_VALUE"""),"not in use") -> not in use | H85: =IFERROR(__xludf.DUMMYFUNCTION("""COMPUTED_VALUE"""),"<p>Иммунизация, проводимая в плановом порядке, рекомендована лицам из групп риска инфицирования вирусом бешенства: лицам, работающим с «уличным» вирусом бешенства, ветеринарным работникам, егерям, охотникам, лесникам, лицам, выполняющим работы по отлову и"&" содержанию животных, работникам скотобоен и лабораторий, а также при планировании поездок в эндемичные по бешенству регионы.</p>") -> <p>Иммунизация, проводимая в плановом порядке, рекомендована лицам из групп риска инфицирования вирусом бешенства: лицам, работающим с «уличным» вирусом бешенства, ветеринарным работникам, егерям, охотникам, лесникам, лицам, выполняющим работы по отлову и содержанию животных, работникам скотобоен и лабораторий, а также при планировании поездок в эндемичные по бешенству регионы.</p> | I85: =IFERROR(__xludf.DUMMYFUNCTION("""COMPUTED_VALUE"""),"Иммунизация, проводимая в плановом порядке, рекомендована лицам из групп риска инфицирования вирусом бешенства: лицам, работающим с «уличным» вирусом бешенства, ветеринарным работникам, егерям, охотникам, лесникам, лицам, выполняющим работы по отлову и со"&"держанию животных, работникам скотобоен и лабораторий, а также при планировании поездок в эндемичные по бешенству регионы.") -> Иммунизация, проводимая в плановом порядке, рекомендована лицам из групп риска инфицирования вирусом бешенства: лицам, работающим с «уличным» вирусом бешенства, ветеринарным работникам, егерям, охотникам, лесникам, лицам, выполняющим работы по отлову и содержанию животных, работникам скотобоен и лабораторий, а также при планировании поездок в эндемичные по бешенству регионы. | K85: =IFERROR(__xludf.DUMMYFUNCTION("""COMPUTED_VALUE"""),44712.0) -> 44712 | L85: =IFERROR(__xludf.DUMMYFUNCTION("""COMPUTED_VALUE"""),44807.0) -> 44807 | M85: =IFERROR(__xludf.DUMMYFUNCTION("""COMPUTED_VALUE"""),"нет") -> нет
A86: =IFERROR(__xludf.DUMMYFUNCTION("""COMPUTED_VALUE"""),85.0) -> 85 | B86: =IFERROR(__xludf.DUMMYFUNCTION("""COMPUTED_VALUE"""),"leptospirosis_Rostov_NII") -> leptospirosis_Rostov_NII | C86: =IFERROR(__xludf.DUMMYFUNCTION("""COMPUTED_VALUE"""),"https://grls.rosminzdrav.ru/Grls_View_v2.aspx?routingGuid=5ef363e0-7cee-48c5-ad35-c352b3fb519e") -> https://grls.rosminzdrav.ru/Grls_View_v2.aspx?routingGuid=5ef363e0-7cee-48c5-ad35-c352b3fb519e | D86: =IFERROR(__xludf.DUMMYFUNCTION("""COMPUTED_VALUE"""),"лептоспирозная") -> лептоспирозная | E86: =IFERROR(__xludf.DUMMYFUNCTION("""COMPUTED_VALUE"""),"Вакцина лептоспирозная концентрированная инактивированная жидкая") -> Вакцина лептоспирозная концентрированная инактивированная жидкая | G86: =IFERROR(__xludf.DUMMYFUNCTION("""COMPUTED_VALUE"""),"in use") -> in use | H86: =IFERROR(__xludf.DUMMYFUNCTION("""COMPUTED_VALUE"""),"<p>Прививкам подлежат лица, выполняющие следующие работы: <ul><li>По заготовке, хранению, обработке сырья и продуктов животноводства, полученных из хозяйств, расположенных на энзоотических по лептоспирозу территориях.</li> <li>По убою скота, больного леп"&"тоспирозом, заготовке и переработке мяса и мясопродуктов, полученных от больных лептоспирозом животных.</li> <li>По отлову и содержанию безнадзорных животных.</li> <li>Работающие с живыми культурами возбудителей лептоспироза.</li></ul></p>") -> <p>Прививкам подлежат лица, выполняющие следующие работы: <ul><li>По заготовке, хранению, обработке сырья и продуктов животноводства, полученных из хозяйств, расположенных на энзоотических по лептоспирозу территориях.</li> <li>По убою скота, больного лептоспирозом, заготовке и переработке мяса и мясопродуктов, полученных от больных лептоспирозом животных.</li> <li>По отлову и содержанию безнадзорных животных.</li> <li>Работающие с живыми культурами возбудителей лептоспироза.</li></ul></p> | I86: =IFERROR(__xludf.DUMMYFUNCTION("""COMPUTED_VALUE"""),"Прививкам подлежат лица, выполняющие следующие работы: • По заготовке, хранению, обработке сырья и продуктов животноводства, полученных из хозяйств, расположенных на энзоотических по лептоспирозу территориях. • По убою скота, больного лептоспирозом, заго"&"товке и переработке мяса и мясопродуктов, полученных от больных лептоспирозом животных. • По отлову и содержанию безнадзорных животных. • Работающие с живыми культурами возбудителей лептоспироза.") -> Прививкам подлежат лица, выполняющие следующие работы: • По заготовке, хранению, обработке сырья и продуктов животноводства, полученных из хозяйств, расположенных на энзоотических по лептоспирозу территориях. • По убою скота, больного лептоспирозом, заготовке и переработке мяса и мясопродуктов, полученных от больных лептоспирозом животных. • По отлову и содержанию безнадзорных животных. • Работающие с живыми культурами возбудителей лептоспироза. | K86: =IFERROR(__xludf.DUMMYFUNCTION("""COMPUTED_VALUE"""),44712.0) -> 44712 | L86: =IFERROR(__xludf.DUMMYFUNCTION("""COMPUTED_VALUE"""),44808.0) -> 44808 | M86: =IFERROR(__xludf.DUMMYFUNCTION("""COMPUTED_VALUE"""),"нет") -> нет
A87: =IFERROR(__xludf.DUMMYFUNCTION("""COMPUTED_VALUE"""),86.0) -> 86 | B87: =IFERROR(__xludf.DUMMYFUNCTION("""COMPUTED_VALUE"""),"Q_fever_M_44_Microgen") -> Q_fever_M_44_Microgen | C87: =IFERROR(__xludf.DUMMYFUNCTION("""COMPUTED_VALUE"""),"https://grls.rosminzdrav.ru/Grls_View_v2.aspx?routingGuid=62187342-c256-42fb-8419-8f916294db89") -> https://grls.rosminzdrav.ru/Grls_View_v2.aspx?routingGuid=62187342-c256-42fb-8419-8f916294db89 | D87: =IFERROR(__xludf.DUMMYFUNCTION("""COMPUTED_VALUE"""),"Ку-лихорадки") -> Ку-лихорадки | E87: =IFERROR(__xludf.DUMMYFUNCTION("""COMPUTED_VALUE"""),"Вакцина Ку-лихорадки М-44 живая (Вакцина Ку-лихорадки М-44)") -> Вакцина Ку-лихорадки М-44 живая (Вакцина Ку-лихорадки М-44) | F87: =IFERROR(__xludf.DUMMYFUNCTION("""COMPUTED_VALUE"""),"Микроген") -> Микроген | G87: =IFERROR(__xludf.DUMMYFUNCTION("""COMPUTED_VALUE"""),"in use") -> in use | K87: =IFERROR(__xludf.DUMMYFUNCTION("""COMPUTED_VALUE"""),44712.0) -> 44712 | L87: =IFERROR(__xludf.DUMMYFUNCTION("""COMPUTED_VALUE"""),45716.0) -> 45716 | M87: =IFERROR(__xludf.DUMMYFUNCTION("""COMPUTED_VALUE"""),"https://lk.regmed.ru/Register/GetPDFfromDAToken?Token=6d636ac5-7688-499c-b16b-bff4c5285c1a") -> https://lk.regmed.ru/Register/GetPDFfromDAToken?Token=6d636ac5-7688-499c-b16b-bff4c5285c1a
A88: =IFERROR(__xludf.DUMMYFUNCTION("""COMPUTED_VALUE"""),87.0) -> 87 | B88: =IFERROR(__xludf.DUMMYFUNCTION("""COMPUTED_VALUE"""),"cholera_NII_Microb") -> cholera_NII_Microb | C88: =IFERROR(__xludf.DUMMYFUNCTION("""COMPUTED_VALUE"""),"https://grls.rosminzdrav.ru/Grls_View_v2.aspx?routingGuid=c27afa22-136b-4a31-96c0-fa7b3d7357f4") -> https://grls.rosminzdrav.ru/Grls_View_v2.aspx?routingGuid=c27afa22-136b-4a31-96c0-fa7b3d7357f4 | D88: =IFERROR(__xludf.DUMMYFUNCTION("""COMPUTED_VALUE"""),"холерная") -> холерная | E88: =IFERROR(__xludf.DUMMYFUNCTION("""COMPUTED_VALUE"""),"Вакцина холерная бивалентная химическая") -> Вакцина холерная бивалентная химическая | G88: =IFERROR(__xludf.DUMMYFUNCTION("""COMPUTED_VALUE"""),"in use") -> in use | K88: =IFERROR(__xludf.DUMMYFUNCTION("""COMPUTED_VALUE"""),44712.0) -> 44712 | L88: =IFERROR(__xludf.DUMMYFUNCTION("""COMPUTED_VALUE"""),44903.0) -> 44903 | M88: =IFERROR(__xludf.DUMMYFUNCTION("""COMPUTED_VALUE"""),"нет") -> нет
A89: =IFERROR(__xludf.DUMMYFUNCTION("""COMPUTED_VALUE"""),88.0) -> 88 | B89: =IFERROR(__xludf.DUMMYFUNCTION("""COMPUTED_VALUE"""),"Vianvac") -> Vianvac | C89: =IFERROR(__xludf.DUMMYFUNCTION("""COMPUTED_VALUE"""),"https://grls.rosminzdrav.ru/Grls_View_v2.aspx?routingGuid=fdfbbbec-8dee-4615-b7eb-26968c926dbf") -> https://grls.rosminzdrav.ru/Grls_View_v2.aspx?routingGuid=fdfbbbec-8dee-4615-b7eb-26968c926dbf | D89: =IFERROR(__xludf.DUMMYFUNCTION("""COMPUTED_VALUE"""),"Вианвак") -> Вианвак | E89: =IFERROR(__xludf.DUMMYFUNCTION("""COMPUTED_VALUE"""),"ВИАНВАК® (Вакцина брюшнотифозная Ви-полисахаридная)") -> ВИАНВАК® (Вакцина брюшнотифозная Ви-полисахаридная) | G89: =IFERROR(__xludf.DUMMYFUNCTION("""COMPUTED_VALUE"""),"in use") -> in use | K89: =IFERROR(__xludf.DUMMYFUNCTION("""COMPUTED_VALUE"""),44712.0) -> 44712 | L89: =IFERROR(__xludf.DUMMYFUNCTION("""COMPUTED_VALUE"""),46130.0) -> 46130 | M89: =IFERROR(__xludf.DUMMYFUNCTION("""COMPUTED_VALUE"""),"есть") -> есть
A90: =IFERROR(__xludf.DUMMYFUNCTION("""COMPUTED_VALUE"""),89.0) -> 89 | B90: =IFERROR(__xludf.DUMMYFUNCTION("""COMPUTED_VALUE"""),"Typhivac") -> Typhivac | C90: =IFERROR(__xludf.DUMMYFUNCTION("""COMPUTED_VALUE"""),"https://grls.rosminzdrav.ru/Grls_View_v2.aspx?routingGuid=0544ac02-95bc-4db8-8c03-e56ad7882e51") -> https://grls.rosminzdrav.ru/Grls_View_v2.aspx?routingGuid=0544ac02-95bc-4db8-8c03-e56ad7882e51 | D90: =IFERROR(__xludf.DUMMYFUNCTION("""COMPUTED_VALUE"""),"Тифивак") -> Тифивак | E90: =IFERROR(__xludf.DUMMYFUNCTION("""COMPUTED_VALUE"""),"Тифивак (Вакцина брюшнотифозная спиртовая)") -> Тифивак (Вакцина брюшнотифозная спиртовая) | G90: =IFERROR(__xludf.DUMMYFUNCTION("""COMPUTED_VALUE"""),"not in use") -> not in use | K90: =IFERROR(__xludf.DUMMYFUNCTION("""COMPUTED_VALUE"""),44712.0) -> 44712 | L90: =IFERROR(__xludf.DUMMYFUNCTION("""COMPUTED_VALUE"""),45139.0) -> 45139 | M90: =IFERROR(__xludf.DUMMYFUNCTION("""COMPUTED_VALUE"""),"нет") -> нет
A91: =IFERROR(__xludf.DUMMYFUNCTION("""COMPUTED_VALUE"""),90.0) -> 90 | B91: =IFERROR(__xludf.DUMMYFUNCTION("""COMPUTED_VALUE"""),"Shigellvac") -> Shigellvac | C91: =IFERROR(__xludf.DUMMYFUNCTION("""COMPUTED_VALUE"""),"https://grls.rosminzdrav.ru/Grls_View_v2.aspx?routingGuid=45faa55d-d1ab-4179-9b8d-7b152e30bfec") -> https://grls.rosminzdrav.ru/Grls_View_v2.aspx?routingGuid=45faa55d-d1ab-4179-9b8d-7b152e30bfec | D91: =IFERROR(__xludf.DUMMYFUNCTION("""COMPUTED_VALUE"""),"Шигеллвак") -> Шигеллвак | E91: =IFERROR(__xludf.DUMMYFUNCTION("""COMPUTED_VALUE"""),"Шигеллвак (Вакцина дизентерийная против шигелл Зонне полисахаридная)") -> Шигеллвак (Вакцина дизентерийная против шигелл Зонне полисахаридная) | G91: =IFERROR(__xludf.DUMMYFUNCTION("""COMPUTED_VALUE"""),"in use") -> in use | K91: =IFERROR(__xludf.DUMMYFUNCTION("""COMPUTED_VALUE"""),44712.0) -> 44712 | L91: =IFERROR(__xludf.DUMMYFUNCTION("""COMPUTED_VALUE"""),46130.0) -> 46130 | M91: =IFERROR(__xludf.DUMMYFUNCTION("""COMPUTED_VALUE"""),"есть") -> есть
A92: =IFERROR(__xludf.DUMMYFUNCTION("""COMPUTED_VALUE"""),91.0) -> 91 | B92: =IFERROR(__xludf.DUMMYFUNCTION("""COMPUTED_VALUE"""),"CoviVac") -> CoviVac | C92: =IFERROR(__xludf.DUMMYFUNCTION("""COMPUTED_VALUE"""),"https://grls.rosminzdrav.ru/Grls_View_v2.aspx?routingGuid=dd8bb917-0073-4bc0-809b-587e89c9a8b0") -> https://grls.rosminzdrav.ru/Grls_View_v2.aspx?routingGuid=dd8bb917-0073-4bc0-809b-587e89c9a8b0 | D92: =IFERROR(__xludf.DUMMYFUNCTION("""COMPUTED_VALUE"""),"КовиВак") -> КовиВак | E92: =IFERROR(__xludf.DUMMYFUNCTION("""COMPUTED_VALUE"""),"КовиВак (Вакцина коронавирусная инактивированная цельновирионная концентрированная очищенная)") -> КовиВак (Вакцина коронавирусная инактивированная цельновирионная концентрированная очищенная) | G92: =IFERROR(__xludf.DUMMYFUNCTION("""COMPUTED_VALUE"""),"in use") -> in use | K92: =IFERROR(__xludf.DUMMYFUNCTION("""COMPUTED_VALUE"""),44712.0) -> 44712 | L92: =IFERROR(__xludf.DUMMYFUNCTION("""COMPUTED_VALUE"""),44903.0) -> 44903 | M92: =IFERROR(__xludf.DUMMYFUNCTION("""COMPUTED_VALUE"""),"нет") -> нет
A93: =IFERROR(__xludf.DUMMYFUNCTION("""COMPUTED_VALUE"""),92.0) -> 92 | B93: =IFERROR(__xludf.DUMMYFUNCTION("""COMPUTED_VALUE"""),"Sputnik_light") -> Sputnik_light | C93: =IFERROR(__xludf.DUMMYFUNCTION("""COMPUTED_VALUE"""),"https://grls.rosminzdrav.ru/Grls_View_v2.aspx?routingGuid=e231ed27-8f9b-48e2-9c90-6d4b5edb2693") -> https://grls.rosminzdrav.ru/Grls_View_v2.aspx?routingGuid=e231ed27-8f9b-48e2-9c90-6d4b5edb2693 | D93: =IFERROR(__xludf.DUMMYFUNCTION("""COMPUTED_VALUE"""),"Спутник Лайт") -> Спутник Лайт | E93: =IFERROR(__xludf.DUMMYFUNCTION("""COMPUTED_VALUE"""),"Спутник Лайт Векторная вакцина для профилактики коронавирусной инфекции, вызываемой вирусом SARS-CoV-2") -> Спутник Лайт Векторная вакцина для профилактики коронавирусной инфекции, вызываемой вирусом SARS-CoV-2 | G93: =IFERROR(__xludf.DUMMYFUNCTION("""COMPUTED_VALUE"""),"in use") -> in use | K93: =IFERROR(__xludf.DUMMYFUNCTION("""COMPUTED_VALUE"""),44712.0) -> 44712 | L93: =IFERROR(__xludf.DUMMYFUNCTION("""COMPUTED_VALUE"""),45830.0) -> 45830 | M93: =IFERROR(__xludf.DUMMYFUNCTION("""COMPUTED_VALUE"""),"https://lk.regmed.ru/Register/GetPDFfromDAToken?Token=50f49d83-55c5-4c3f-95fd-eb87ceb7bbc1") -> https://lk.regmed.ru/Register/GetPDFfromDAToken?Token=50f49d83-55c5-4c3f-95fd-eb87ceb7bbc1
A94: =IFERROR(__xludf.DUMMYFUNCTION("""COMPUTED_VALUE"""),93.0) -> 93 | B94: =IFERROR(__xludf.DUMMYFUNCTION("""COMPUTED_VALUE"""),"Sputnik_M") -> Sputnik_M | C94: =IFERROR(__xludf.DUMMYFUNCTION("""COMPUTED_VALUE"""),"https://grls.rosminzdrav.ru/Grls_View_v2.aspx?routingGuid=3f429426-417a-42af-8212-54d0f9b4f48a") -> https://grls.rosminzdrav.ru/Grls_View_v2.aspx?routingGuid=3f429426-417a-42af-8212-54d0f9b4f48a | D94: =IFERROR(__xludf.DUMMYFUNCTION("""COMPUTED_VALUE"""),"Спутник М") -> Спутник М | E94: =IFERROR(__xludf.DUMMYFUNCTION("""COMPUTED_VALUE"""),"Гам-КОВИД-Вак-М Комбинированная векторная вакцина для профилактики коронавирусной инфекции, вызываемой вирусом SARS-CoV-2") -> Гам-КОВИД-Вак-М Комбинированная векторная вакцина для профилактики коронавирусной инфекции, вызываемой вирусом SARS-CoV-2 | G94: =IFERROR(__xludf.DUMMYFUNCTION("""COMPUTED_VALUE"""),"in use") -> in use | K94: =IFERROR(__xludf.DUMMYFUNCTION("""COMPUTED_VALUE"""),44712.0) -> 44712 | L94: =IFERROR(__xludf.DUMMYFUNCTION("""COMPUTED_VALUE"""),45715.0) -> 45715 | M94: =IFERROR(__xludf.DUMMYFUNCTION("""COMPUTED_VALUE"""),"нет") -> нет
A95: =IFERROR(__xludf.DUMMYFUNCTION("""COMPUTED_VALUE"""),94.0) -> 94 | B95: =IFERROR(__xludf.DUMMYFUNCTION("""COMPUTED_VALUE"""),"Convacel") -> Convacel | C95: =IFERROR(__xludf.DUMMYFUNCTION("""COMPUTED_VALUE"""),"https://grls.rosminzdrav.ru/Grls_View_v2.aspx?routingGuid=f6747520-46db-401c-ac99-b006cfc89abf") -> https://grls.rosminzdrav.ru/Grls_View_v2.aspx?routingGuid=f6747520-46db-401c-ac99-b006cfc89abf | D95: =IFERROR(__xludf.DUMMYFUNCTION("""COMPUTED_VALUE"""),"Конвасэл") -> Конвасэл | E95: =IFERROR(__xludf.DUMMYFUNCTION("""COMPUTED_VALUE"""),"Конвасэл® Вакцина субъединичная рекомбинантная для профилактики коронавирусной инфекции, вызываемой вирусом SARS-CoV-2") -> Конвасэл® Вакцина субъединичная рекомбинантная для профилактики коронавирусной инфекции, вызываемой вирусом SARS-CoV-2 | G95: =IFERROR(__xludf.DUMMYFUNCTION("""COMPUTED_VALUE"""),"in use") -> in use | K95: =IFERROR(__xludf.DUMMYFUNCTION("""COMPUTED_VALUE"""),44712.0) -> 44712 | L95: =IFERROR(__xludf.DUMMYFUNCTION("""COMPUTED_VALUE"""),46053.0) -> 46053 | M95: =IFERROR(__xludf.DUMMYFUNCTION("""COMPUTED_VALUE"""),"есть") -> есть
A96: =IFERROR(__xludf.DUMMYFUNCTION("""COMPUTED_VALUE"""),95.0) -> 95 | B96: =IFERROR(__xludf.DUMMYFUNCTION("""COMPUTED_VALUE"""),"Aurora") -> Aurora | C96: =IFERROR(__xludf.DUMMYFUNCTION("""COMPUTED_VALUE"""),"https://grls.rosminzdrav.ru/Grls_View_v2.aspx?routingGuid=e674fd41-ea9d-4a0b-9f4b-7f728da76cf0") -> https://grls.rosminzdrav.ru/Grls_View_v2.aspx?routingGuid=e674fd41-ea9d-4a0b-9f4b-7f728da76cf0 | D96: =IFERROR(__xludf.DUMMYFUNCTION("""COMPUTED_VALUE"""),"АВРОРА-КоВ") -> АВРОРА-КоВ | E96: =IFERROR(__xludf.DUMMYFUNCTION("""COMPUTED_VALUE"""),"АВРОРА-КоВ Вакцина на основе пептидных антигенов для профилактики COVID-19") -> АВРОРА-КоВ Вакцина на основе пептидных антигенов для профилактики COVID-19 | G96: =IFERROR(__xludf.DUMMYFUNCTION("""COMPUTED_VALUE"""),"in use") -> in use | K96: =IFERROR(__xludf.DUMMYFUNCTION("""COMPUTED_VALUE"""),44712.0) -> 44712 | L96: =IFERROR(__xludf.DUMMYFUNCTION("""COMPUTED_VALUE"""),44904.0) -> 44904 | M96: =IFERROR(__xludf.DUMMYFUNCTION("""COMPUTED_VALUE"""),"нет") -> нет
A97: =IFERROR(__xludf.DUMMYFUNCTION("""COMPUTED_VALUE"""),96.0) -> 96 | B97: =IFERROR(__xludf.DUMMYFUNCTION("""COMPUTED_VALUE"""),"Rota_V_Aid") -> Rota_V_Aid | C97: =IFERROR(__xludf.DUMMYFUNCTION("""COMPUTED_VALUE"""),"https://grls.rosminzdrav.ru/Grls_View_v2.aspx?routingGuid=3e6a77c5-d2ae-4f34-b737-7803e65abe65") -> https://grls.rosminzdrav.ru/Grls_View_v2.aspx?routingGuid=3e6a77c5-d2ae-4f34-b737-7803e65abe65 | D97: =IFERROR(__xludf.DUMMYFUNCTION("""COMPUTED_VALUE"""),"Рота-V-Эйд") -> Рота-V-Эйд | E97: =IFERROR(__xludf.DUMMYFUNCTION("""COMPUTED_VALUE"""),"Рота-V-Эйд® ") -> Рота-V-Эйд® | F97: =IFERROR(__xludf.DUMMYFUNCTION("""COMPUTED_VALUE"""),"Серум Инститьют") -> Серум Инститьют | G97: =IFERROR(__xludf.DUMMYFUNCTION("""COMPUTED_VALUE"""),"in use") -> in use | K97: =IFERROR(__xludf.DUMMYFUNCTION("""COMPUTED_VALUE"""),44712.0) -> 44712 | L97: =IFERROR(__xludf.DUMMYFUNCTION("""COMPUTED_VALUE"""),45689.0) -> 45689 | M97: =IFERROR(__xludf.DUMMYFUNCTION("""COMPUTED_VALUE"""),"https://lk.regmed.ru/Register/GetPDFfromDAToken?Token=0f30d250-b996-4595-b47d-8966e076423c") -> https://lk.regmed.ru/Register/GetPDFfromDAToken?Token=0f30d250-b996-4595-b47d-8966e076423c
A98: =IFERROR(__xludf.DUMMYFUNCTION("""COMPUTED_VALUE"""),97.0) -> 97 | B98: =IFERROR(__xludf.DUMMYFUNCTION("""COMPUTED_VALUE"""),"Hib_Rostov") -> Hib_Rostov | C98: =IFERROR(__xludf.DUMMYFUNCTION("""COMPUTED_VALUE"""),"https://grls.rosminzdrav.ru/Grls_View_v2.aspx?routingGuid=8790c6b6-9ab5-4df0-8084-075d18ec2595") -> https://grls.rosminzdrav.ru/Grls_View_v2.aspx?routingGuid=8790c6b6-9ab5-4df0-8084-075d18ec2595 | D98: =IFERROR(__xludf.DUMMYFUNCTION("""COMPUTED_VALUE"""),"гемофильная (ростовский НИИ)") -> гемофильная (ростовский НИИ) | E98: =IFERROR(__xludf.DUMMYFUNCTION("""COMPUTED_VALUE"""),"Вакцина гемофильная тип b конъюгированная") -> Вакцина гемофильная тип b конъюгированная | F98: =IFERROR(__xludf.DUMMYFUNCTION("""COMPUTED_VALUE"""),"ФБУН ""Ростовский научно-исследовательский институт микробиологии и паразитологии""") -> ФБУН "Ростовский научно-исследовательский институт микробиологии и паразитологии" | G98: =IFERROR(__xludf.DUMMYFUNCTION("""COMPUTED_VALUE"""),"in use") -> in use | K98: =IFERROR(__xludf.DUMMYFUNCTION("""COMPUTED_VALUE"""),44712.0) -> 44712 | L98: =IFERROR(__xludf.DUMMYFUNCTION("""COMPUTED_VALUE"""),44904.0) -> 44904 | M98: =IFERROR(__xludf.DUMMYFUNCTION("""COMPUTED_VALUE"""),"нет") -> нет
A99: =IFERROR(__xludf.DUMMYFUNCTION("""COMPUTED_VALUE"""),98.0) -> 98 | B99: =IFERROR(__xludf.DUMMYFUNCTION("""COMPUTED_VALUE"""),"HepB_Combiotech_1_0") -> HepB_Combiotech_1_0 | C99: =IFERROR(__xludf.DUMMYFUNCTION("""COMPUTED_VALUE"""),"https://grls.rosminzdrav.ru/Grls_View_v2.aspx?routingGuid=0cc60fe9-635e-4134-80d2-59a7787e33fb") -> https://grls.rosminzdrav.ru/Grls_View_v2.aspx?routingGuid=0cc60fe9-635e-4134-80d2-59a7787e33fb | D99: =IFERROR(__xludf.DUMMYFUNCTION("""COMPUTED_VALUE"""),"гепатита B (Комбиотех) взрослая") -> гепатита B (Комбиотех) взрослая | E99: =IFERROR(__xludf.DUMMYFUNCTION("""COMPUTED_VALUE"""),"Вакцина гепатита В рекомбинантная дрожжевая") -> Вакцина гепатита В рекомбинантная дрожжевая | F99: =IFERROR(__xludf.DUMMYFUNCTION("""COMPUTED_VALUE"""),"Комбиотех") -> Комбиотех | G99: =IFERROR(__xludf.DUMMYFUNCTION("""COMPUTED_VALUE"""),"in use") -> in use | H99: =IFERROR(__xludf.DUMMYFUNCTION("""COMPUTED_VALUE"""),"<p>Препарат выпускается в виде «взрослой» и «детской» вакцины с консервантом и без консерванта.</p>") -> <p>Препарат выпускается в виде «взрослой» и «детской» вакцины с консервантом и без консерванта.</p> | I99: =IFERROR(__xludf.DUMMYFUNCTION("""COMPUTED_VALUE"""),"Препарат выпускается в виде «взрослой» и «детской» вакцины с консервантом и без консерванта.") -> Препарат выпускается в виде «взрослой» и «детской» вакцины с консервантом и без консерванта. | K99: =IFERROR(__xludf.DUMMYFUNCTION("""COMPUTED_VALUE"""),44712.0) -> 44712 | L99: =IFERROR(__xludf.DUMMYFUNCTION("""COMPUTED_VALUE"""),46130.0) -> 46130 | M99: =IFERROR(__xludf.DUMMYFUNCTION("""COMPUTED_VALUE"""),"есть") -> есть
A100: =IFERROR(__xludf.DUMMYFUNCTION("""COMPUTED_VALUE"""),99.0) -> 99 | B100: =IFERROR(__xludf.DUMMYFUNCTION("""COMPUTED_VALUE"""),"Regevac_1_0") -> Regevac_1_0 | C100: =IFERROR(__xludf.DUMMYFUNCTION("""COMPUTED_VALUE"""),"https://grls.rosminzdrav.ru/Grls_View_v2.aspx?routingGuid=ec6e3b51-e76b-4abf-99cf-7c02bab06091") -> https://grls.rosminzdrav.ru/Grls_View_v2.aspx?routingGuid=ec6e3b51-e76b-4abf-99cf-7c02bab06091 | D100: =IFERROR(__xludf.DUMMYFUNCTION("""COMPUTED_VALUE"""),"Регевак взрослый") -> Регевак взрослый | E100: =IFERROR(__xludf.DUMMYFUNCTION("""COMPUTED_VALUE"""),"Регевак® В (Вакцина против гепатита В, рекомбинантная дрожжевая жидкая)") -> Регевак® В (Вакцина против гепатита В, рекомбинантная дрожжевая жидкая) | G100: =IFERROR(__xludf.DUMMYFUNCTION("""COMPUTED_VALUE"""),"in use") -> in use | K100: =IFERROR(__xludf.DUMMYFUNCTION("""COMPUTED_VALUE"""),44712.0) -> 44712 | L100: =IFERROR(__xludf.DUMMYFUNCTION("""COMPUTED_VALUE"""),45988.0) -> 45988 | M100: =IFERROR(__xludf.DUMMYFUNCTION("""COMPUTED_VALUE"""),"есть") -> есть
...

Sheet ingredients_text
A1: vaccine_id | B1: code_name | C1: ingredients_text_w/o_html | D1: ingredients_text_html | E1: ingredients_date | F1: ingredients_view_number | G1: ingredients_version | H1: ingredients_version_link | I1: creation_date | J1: update_date | K1: comment
A2: 1 | B2: =VLOOKUP(A2,vaccines!A:B,2) -> BCG_Microgen | C2: 1 доза (0,1 мл) содержит: Действующее вещество: микробные клетки Mycobacterium bovis BCG-I — 0,05 мг*. Полный перечень вспомогательных веществ приведен в разделе 6.1. Препарат не содержит консервантов и антибиотиков. Выпускается в комплекте с растворителем — натрия хлорид растворитель для приготовления лекарственных форм для инъекций 0,9 %. * расчетное содержание в 1 дозе. 6.1. Перечень вспомогательных веществ Лиофилизат: • Натрия глутамата моногидрат. | D2: <p>1&nbsp;доза (0,1&nbsp;мл) содержит:<br><br> Действующее вещество: микробные клетки <i>Mycobacterium bovis BCG-I</i> — 0,05&nbsp;мг*.<br> Полный перечень вспомогательных веществ приведен в разделе&nbsp;6.1.<br> Препарат не содержит консервантов и антибиотиков.<br> Выпускается в комплекте с растворителем — натрия хлорид растворитель для приготовления лекарственных форм для инъекций 0,9&nbsp;%.<br><br> *&nbsp;расчетное содержание в 1&nbsp;дозе.<br><br> <b>6.1.&nbsp;Перечень вспомогательных веществ</b><br><br> <i>Лиофилизат:</i> <ul><li>Натрия глутамата моногидрат.</li></ul></p> | E2: 45461 | H2: https://lk.regmed.ru/Register/GetPDFfromDA?ID=1597322951 | I2: 45105 | J2: 45517 | K2: добавлено Елена Савинова
A3: 2 | B3: =VLOOKUP(A3,vaccines!A:B,2) -> BCG_M_Microgen | C3: 1 доза (0,1 мл) содержит: Действующее вещество: микробные клетки Mycobacterium bovis BCG-I — 0,025 мг*. Полный перечень вспомогательных веществ приведен в разделе 6.1. Препарат не содержит консервантов и антибиотиков. Выпускается в комплекте с растворителем — натрия хлорид растворитель для приготовления лекарственных форм для инъекций 0,9 %. * расчетное содержание в 1 дозе. 6.1. Перечень вспомогательных веществ • Натрия глутамата моногидрат. | D3: <p>1&nbsp;доза (0,1&nbsp;мл) содержит:<br><br> Действующее вещество: микробные клетки <i>Mycobacterium bovis BCG-I</i> — 0,025&nbsp;мг*.<br> Полный перечень вспомогательных веществ приведен в разделе&nbsp;6.1.<br> Препарат не содержит консервантов и антибиотиков.<br> Выпускается в комплекте с растворителем — натрия хлорид растворитель для приготовления лекарственных форм для инъекций 0,9&nbsp;%.<br><br> *&nbsp;расчетное содержание в 1&nbsp;дозе.<br><br> <b>6.1.&nbsp;Перечень вспомогательных веществ</b> <ul><li>Натрия глутамата моногидрат.</li></ul></p> | E3: 45461 | H3: https://lk.regmed.ru/Register/GetPDFfromDA?ID=1597318981 | I3: 45107 | J3: 45517 | K3: проверено Елена Савинова
A4: 3 | B4: =VLOOKUP(A4,vaccines!A:B,2) -> BCG_Gamaleya | C4: В одной дозе содержится: • 0,05 мг Микобактерий вакцинного штамма Mycobacterium bovis, субштамм BCG-1 (Russia). Перечень вспомогательных веществ: • Стабилизатор — натрия глутамат моногидрат — не более 0,3 мг; • Раствор натрия хлорида 0,9 % для инъекций — до 0,1 мл. | D4: <p>В одной дозе содержится: <ul><li>0,05&nbsp;мг Микобактерий вакцинного штамма <i>Mycobacterium bovis</i>, субштамм BCG-1 (Russia).</li></ul> Перечень вспомогательных веществ: <ul><li>Стабилизатор — натрия глутамат моногидрат — не более 0,3&nbsp;мг;</li> <li>Раствор натрия хлорида 0,9&nbsp;% для инъекций — до 0,1&nbsp;мл.</li></ul></p> | E4: 45769 | F4: 1 | G4: 0 | H4: https://grls.rosminzdrav.ru/InstrImg/2025/05/19/1517351/3bec22d2-65bc-4a94-9482-413901e57760.pdf | I4: 45108 | J4: 45801
A5: 4 | B5: =VLOOKUP(A5,vaccines!A:B,2) -> BCG_M_Gamaleya | C5: В одной дозе содержится: • 0,025 мг Микобактерий вакцинного штамма Mycobacterium bovis, субштамм BCG-1 (Russia). Перечень вспомогательных веществ: • Стабилизатор — натрия глутамат моногидрат — не более 0,15 мг; • Раствор натрия хлорида 0,9 % для инъекций — до 0,1 мл. | D5: <p>В одной дозе содержится: <ul><li>0,025&nbsp;мг Микобактерий вакцинного штамма Mycobacterium bovis, субштамм BCG-1 (Russia).</li></ul> Перечень вспомогательных веществ: <ul><li>Стабилизатор — натрия глутамат моногидрат — не более 0,15&nbsp;мг;</li> <li>Раствор натрия хлорида 0,9&nbsp;% для инъекций — до 0,1&nbsp;мл.</li></ul></p> | E5: 45771 | F5: 1 | G5: 0 | H5: https://grls.rosminzdrav.ru/InstrImg/2025/06/02/1517794/d7367d9e-e745-46a7-b297-5a093bf3738a.pdf | I5: =I4 -> 45108 | J5: 45818
A6: 5 | B6: =VLOOKUP(A6,vaccines!A:B,2) -> Infanrix | C6: 1 доза (0,5 мл) вакцины содержит: Действующие вещества: • анатоксин дифтерийный¹·³ — не менее 30 МЕ; • анатоксин столбнячный²·³ — не менее 40 МЕ; • анатоксин коклюшный (АК)³ — 25 мкг; • гемагглютинин филаментозный (ФГА)³ — 25 мкг; • пертактин (ПРН)³ (белок наружной мембраны 69 кДа) — 8 мкг. ¹ Содержание дифтерийного анатоксина 25 Lf (флоккулирующих единиц). ² Содержание столбнячного анатоксина 10 Lf (флоккулирующих единиц). ³ Адсорбированный на алюминия гидроксиде (0,5 мг в пересчете на алюминий). Перечень вспомогательных веществ: • Натрия хлорид. • Вода для инъекций. | D6: <p>1&nbsp;доза (0,5&nbsp;мл) вакцины содержит:<br><br> <i>Действующие вещества:</i> <ul><li>анатоксин дифтерийный¹<sup>,</sup>³ — не менее 30&nbsp;МЕ;</li> <li>анатоксин столбнячный²<sup>,</sup>³ — не менее 40&nbsp;МЕ;</li> <li>анатоксин коклюшный (АК)³ — 25&nbsp;мкг;</li> <li>гемагглютинин филаментозный (ФГА)³ — 25&nbsp;мкг;</li> <li>пертактин (ПРН)³ (белок наружной мембраны 69&nbsp;кДа) — 8&nbsp;мкг.</li></ul> ¹&nbsp;Содержание дифтерийного анатоксина 25&nbsp;Lf (флоккулирующих единиц).<br> ²&nbsp;Содержание столбнячного анатоксина 10&nbsp;Lf (флоккулирующих единиц).<br> ³&nbsp;Адсорбированный на алюминия гидроксиде (0,5&nbsp;мг в пересчете на алюминий).<br><br> <i>Перечень вспомогательных веществ:</i> <ul><li>Натрия хлорид.</li> <li>Вода для инъекций.</li></ul></p> | E6: 44211 | H6: https://lk.regmed.ru/Register/GetPDFfromDA?ID=1484709711 | I6: 45105 | J6: 45481 | K6: добавлено Елена Савинова
A7: 6 | B7: =VLOOKUP(A7,vaccines!A:B,2) -> AKDS_Microgen | C7: В 1 дозе (0,5 мл) содержится: Препарат с консервантом. Действующие вещества: • анатоксин дифтерийный¹ — 15 флокулирующих единиц (Lf); • анатоксин столбнячный¹ — 5 единиц связывания (EC); • коклюшная суспензия инактивированная — 10 млрд коклюшных микробных клеток. ¹ - Адсорбированный на алюминия гидроксиде (в пересчете на Al³⁺) — не более 0,55 мг; Препарат без консерванта. Действующие вещества: • анатоксин дифтерийный¹ — 15 флокулирующих единиц (Lf); • анатоксин столбнячный¹ — 5 единиц связывания (EC); • коклюшная суспензия инактивированная без тиомерсала — 10 млрд коклюшных микробных клеток. ¹ - Адсорбированный на алюминия гидроксиде (в пересчете на Al³⁺) — не более 0,55 мг; Перечень вспомогательных веществ: Препарат с консервантом. • Алюминия гидроксид; • Формальдегид; • Консервант — тиомерсал. Препарат без консерванта. • Алюминия гидроксид; • Формальдегид. | D7: <p>В 1&nbsp;дозе (0,5&nbsp;мл) содержится:<br><br> <i>Препарат с консервантом.</i><br><br> Действующие вещества: <ul><li>анатоксин дифтерийный¹ — 15&nbsp;флокулирующих единиц (Lf);</li> <li>анатоксин столбнячный¹ — 5&nbsp;единиц связывания (EC);</li> <li>коклюшная суспензия инактивированная — 10&nbsp;млрд коклюшных микробных клеток.</li></ul> ¹&nbsp;- Адсорбированный на алюминия гидроксиде (в пересчете на Al³⁺) — не более 0,55&nbsp;мг;<br><br> <i>Препарат без консерванта.</i><br><br> Действующие вещества: <ul><li>анатоксин дифтерийный¹ — 15&nbsp;флокулирующих единиц (Lf);</li> <li>анатоксин столбнячный¹ — 5&nbsp;единиц связывания (EC);</li> <li>коклюшная суспензия инактивированная без тиомерсала — 10&nbsp;млрд коклюшных микробных клеток.</li></ul> ¹&nbsp;- Адсорбированный на алюминия гидроксиде (в пересчете на Al³⁺) — не более 0,55&nbsp;мг;<br><br> Перечень вспомогательных веществ:<br><br> <i>Препарат с консервантом.</i> <ul><li>Алюминия гидроксид;</li> <li>Формальдегид;</li> <li>Консервант — тиомерсал.</li></ul> <i>Препарат без консерванта.</i> <ul><li>Алюминия гидроксид;</li> <li>Формальдегид.</li></ul></p> | E7: 45415 | H7: https://lk.regmed.ru/Register/GetPDFfromDA?ID=1587927891 | I7: 45115 | J7: 45461
A8: 7 | B8: =VLOOKUP(A8,vaccines!A:B,2) -> AKDS_Biomed | C8: АКДС-вакцина состоит из взвеси убитых коклюшных микробов и очищенных дифтерийного и столбнячного анатоксинов, сорбированных на алюминия гидроксиде. В одной дозе препарата (0,5 мл) содержится 10 международных единиц (МЕ) инактивированных коклюшных микробов, 15 флокулирующих единиц (Lf) дифтерийного, 5 единиц связывания (EC) столбнячного анатоксинов, от 0,25 до 0,55 мг алюминия гидроксида в пересчете на алюминий (сорбент), от 42,5 до 57,5 мкг тиомерсала (консервант). | D8: <p>В одной дозе препарата (0,5&nbsp;мл) содержится 10&nbsp;международных единиц (МЕ) инактивированных коклюшных микробов, 15&nbsp;флокулирующих единиц (Lf) дифтерийного, 5&nbsp;единиц связывания (EC) столбнячного анатоксинов, от 0,25 до 0,55&nbsp;мг алюминия гидроксида в пересчете на алюминий (сорбент), от 42,5 до 57,5&nbsp;мкг тиомерсала (консервант).</p> | E8: 41388 | F8: 1 | G8: 0 | H8: https://grls.rosminzdrav.ru/InstrImg/2017/4/26/1416322/%D0%A0_N002666_01[2013]_0.pdf | I8: 45115
A9: 8 | B9: =VLOOKUP(A9,vaccines!A:B,2) -> Bubo_kok | C9: Препарат содержит в одной дозе (0,5 мл): 15 флокулирующих единиц (Lf) дифтерийного, 5 единиц связывания (EC) столбнячного анатоксинов, 10 млрд коклюшных бактерий, 5 мкг HBsAg, 0,4 мг алюминия гидроксида (Al³⁺), 50 мкг мертиолята (консервант). | D9: <p>Препарат содержит в одной дозе (0,5&nbsp;мл): 15&nbsp;флокулирующих единиц (Lf) дифтерийного, 5&nbsp;единиц связывания (EC) столбнячного анатоксинов, 10&nbsp;млрд коклюшных бактерий, 5&nbsp;мкг HBsAg, 0,4&nbsp;мг алюминия гидроксида (Al³⁺), 50&nbsp;мкг мертиолята (консервант).</p> | E9: 40395 | F9: 1 | G9: 0 | H9: https://grls.rosminzdrav.ru/InstrImg/2020/05/28/10700/9d141b34-47e7-48c8-9480-616cbbc792fc.pdf | I9: 45115
A10: 9 | B10: =VLOOKUP(A10,vaccines!A:B,2) -> Pentaxim | C10: Действующими веществами являются: После восстановления 1 доза (0,5 мл) содержит: Изначально в виде суспензии: • Анатоксин дифтерийный¹ — 30 Lf (≥ 30 МЕ²)³; • Анатоксин столбнячный¹ — 10 LF (≥ 40 МЕ⁴)³; • Анатоксин коклюшный¹ — 25 мкг; • Гемагглютинин филаментозный¹ — 25 мкг; • Вирус полиомиелита 1-го типа инактивированный (Mahoney)⁵ — 40 единиц D антигена⁶; • Вирус полиомиелита 2-го типа инактивированный (MEF-1)⁵ — 8 единиц D антигена⁶; • Вирус полиомиелита 3-го типа инактивированный (Saukett)⁵ — 32 единицы D антигена⁶. Изначально в виде лиофилизата для приготовления суспензии: • Полисахарид Haemophilus influenzae тип b (полирибозилрибитол фосфат) — 10 мкг, конъюгированный со столбнячным анатоксином — 18-30 мкг. ¹ — адсорбирован на алюминия гидроксида гидрате (0,3 мг в пересчете на алюминий); ² — в качестве среднего значения, нижний предел доверительного интервала (р = 0,95) не менее 20 МЕ/доза; ³ — или эквивалентная активность, определенная при оценке иммуногенности; ⁴ — нижний предел доверительного интервала (р = 0,95); ⁵ — культивированный на клетках VERO; ⁶ — или эквивалентное содержание антигена, определенное подходящим иммунохимическим методом. Антибиотики (стрептомицин, неомицин и полимиксин В) и глутаральдегид используются при производстве вакцины, но не присутствуют в определяемых количествах в конечном продукте. Вспомогательные вещества, наличие которых надо учитывать в составе вакцины: фенилаланин Перечень вспомогательных веществ: Суспензия для внутримышечного введения: • Алюминия гидроксида гидрат; • Раствор формальдегида; • Феноксиэтанол; • Этанол безводный; • Среда Хенкса 199 (10×) без фенолового красного (представляет собой сложную смесь аминокислот (включая фенилаланин), минералов, витаминов и других компонентов (таких как глюкоза), разведенную в воде для инъекций); • Натрия гидроксид или ледяная уксусная кислота используются для корректировки рН; • Вода для инъекций. Лиофилизат для приготовления суспензии для внутримышечного введения: • Трометамол; • Сахароза; • Концентрированная хлористоводородная кислота для корректировки рН (до 7,2 ± 0,1). | D10: <p>Действующими веществами являются:<br> После восстановления 1&nbsp;доза (0,5&nbsp;мл) содержит:<br><br> <i>Изначально в виде суспензии:</i> <ul><li>Анатоксин дифтерийный¹ — 30&nbsp;Lf (≥&nbsp;30&nbsp;МЕ²)³;</li> <li>Анатоксин столбнячный¹ — 10&nbsp;LF (≥&nbsp;40&nbsp;МЕ⁴)³;</li> <li>Анатоксин коклюшный¹ — 25&nbsp;мкг;</li> <li>Гемагглютинин филаментозный¹ — 25&nbsp;мкг;</li> <li>Вирус полиомиелита 1-го&nbsp;типа инактивированный (Mahoney)⁵ — 40&nbsp;единиц D&nbsp;антигена⁶;</li> <li>Вирус полиомиелита 2-го&nbsp;типа инактивированный (MEF-1)⁵ — 8&nbsp;единиц D&nbsp;антигена⁶;</li> <li>Вирус полиомиелита 3-го&nbsp;типа инактивированный (Saukett)⁵ — 32&nbsp;единицы D&nbsp;антигена⁶.</li></ul> <i>Изначально в виде лиофилизата для приготовления суспензии:</i> <ul><li>Полисахарид Haemophilus influenzae тип b (полирибозилрибитол фосфат) — 10&nbsp;мкг,<br> конъюгированный со столбнячным анатоксином — 18-30&nbsp;мкг.</li></ul> ¹ — адсорбирован на алюминия гидроксида гидрате (0,3&nbsp;мг в пересчете на алюминий);<br> ² — в качестве среднего значения, нижний предел доверительного интервала (р&nbsp;=&nbsp;0,95) не менее 20&nbsp;МЕ/доза;<br> ³ — или эквивалентная активность, определенная при оценке иммуногенности;<br> ⁴ — нижний предел доверительного интервала (р&nbsp;=&nbsp;0,95);<br> ⁵ — культивированный на клетках VERO;<br> ⁶ — или эквивалентное содержание антигена, определенное подходящим иммунохимическим методом.<br><br> Антибиотики (стрептомицин, неомицин и полимиксин В) и глутаральдегид используются при производстве вакцины, но не присутствуют в определяемых количествах в конечном продукте.<br> Вспомогательные вещества, наличие которых надо учитывать в составе вакцины: фенилаланин<br><br> Перечень вспомогательных веществ:<br> <i>Суспензия для внутримышечного введения:</i> <ul><li>Алюминия гидроксида гидрат;</li> <li>Раствор формальдегида;</li> <li>Феноксиэтанол;</li> <li>Этанол безводный;</li> <li>Среда Хенкса&nbsp;199 (10×) без фенолового красного (представляет собой сложную смесь аминокислот (включая фенилаланин), минералов, витаминов и других компонентов (таких как глюкоза), разведенную в воде для инъекций);</li> <li>Натрия гидроксид или ледяная уксусная кислота используются для корректировки рН;</li> <li>Вода для инъекций.</li></ul> <i>Лиофилизат для приготовления суспензии для внутримышечного введения:</i> <ul><li>Трометамол;</li> <li>Сахароза;</li> <li>Концентрированная хлористоводородная кислота для корректировки рН (до 7,2&nbsp;±&nbsp;0,1).</li></ul></p> | E10: 45980 | F10: 1 | G10: 0 | H10: https://grls.rosminzdrav.ru/InstrImg/2026/05/27/1530421/6bdc8421-6c08-4bf7-be7f-0ae5d96a478d.pdf | I10: =I9 -> 45115 | J10: 46204 | K10: zaytseva@vaccina.info не нашла символ запятой в верхнем индексе, который бы нормально копировался сюда, поэтому здесь и далее в столбце "ingredients_text_w/o_html" вместо него символ "·". В столбце "ingredients_text_html" запятая в верхнем индексе поставлена с помощью тэга <sup>.
A11: 10 | B11: =VLOOKUP(A11,vaccines!A:B,2) -> Infanrix_Hexa | C11: 1 доза (0,5 мл) вакцины содержит: Вакцина для профилактики дифтерии, столбняка, коклюша (бесклеточная), полиомиелита (инактивированная), гепатита В комбинированная, адсорбированная Действующие вещества: • Анатоксин дифтерийный¹·³ — Не менее 30 МЕ; • Анатоксин столбнячный²·³ — Не менее 40 МЕ; • Анатоксин коклюшный (АК)³ — 25 мкг; • Гемагглютинин филаментозный (ФГА)³ — 25 мкг; • Пертактин (белок наружной мембраны 69 кДа)³ — 8 мкг; • Антиген поверхностный рекомбинантный вируса гепатита B (HBsAg)⁴ — 10 мкг; • Вирус полиомиелита тип 1 инактивированный — 40 ЕД D-антигена; • Вирус полиомиелита тип 2 инактивированный — 8 ЕД D-антигена; • Вирус полиомиелита тип 3 инактивированный — 32 ЕД D-антигена. Вакцина для профилактики инфекции, вызываемой Haemophilus influenzae тип b конъюгированная, адсорбированная Действующее вещество: • Капсульный полисахарид Haemophilus influenzae тип b⁴ — 10 мкг; конъюгированный со столбнячным анатоксином — ≈25 мкг. ¹ Содержание дифтерийного анатоксина 25 Lf (флоккулирующих единиц). ² Содержание столбнячного анатоксина 10 Lf (флоккулирующих единиц). ³ Адсорбированный на алюминия гидроксиде (0,5 мг в пересчете на алюминий). ⁴ Адсорбированный на алюминия фосфате (0,32 мг в пересчете на алюминий). Перечень вспомогательных веществ: Вакцина для профилактики дифтерии, столбняка, коклюша (бесклеточная), полиомиелита (инактивированная), гепатита В комбинированная, адсорбированная: • Натрия хлорид. • Среда 199 (М 199)¹ (включая аминокислоты). • Вода для инъекций. ¹ Состав среды 199 (М 199): кальция хлорида дигидрат, железа нитрата нонагидрат, калия хлорид, калия дигидрофосфат, магния сульфата гептагидрат, натрия хлорид, натрия гидрокарбонат, натрия гидрофосфат, L-аланин, L-аргинина гидрохлорид, L-аспарагиновая кислота, L-цистеина гидрохлорид, L-цистин, L-глутаминовая кислота, L-глутамин, глицин, L-гистидина гидрохлорида моногидрат, L-гидроксипролин, L-изолейцин, L-лейцин, L-лизина гидрохлорид, L-метионин, L-фенилаланин, L-пролин, L-серин, L-треонин, L-триптофан, L-тирозин, L-валин, аскорбиновая кислота, альфа-токоферол, биотин, кальциферол, кальция пантотенат, холина хлорид, фолиевая кислота, инозитол, менадион, никотиновая кислота, никотинамид, пара-аминобензойная кислота, пиридоксаль гидрохлорид, пиридоксина гидрохлорид, рибофлавин, тиамина гидрохлорид, ретинола ацетат, аденин, аденозина фосфат, аденозина трифосфат натрия, холестерол, дезоксирибоза, глюкоза, глутатион, гуанина гидрохлорид, гипоксантин, рибоза, натрия ацетат, тимин, твин-80, урацил, ксантин. Вакцина для профилактики инфекции, вызываемой Haemophilus influenzae тип b, конъюгированная, адсорбированная: • Лактоза. Данный препарат содержит менее 1 ммоль (23 мг) натрия на 1 дозу, то есть по сути не содержит натрия. | D11: <p>1&nbsp;доза (0,5&nbsp;мл) вакцины содержит:<br><br> Вакцина для профилактики дифтерии, столбняка, коклюша (бесклеточная), полиомиелита (инактивированная), гепатита В комбинированная, адсорбированная <ul><i>Действующие вещества:</i> <li>Анатоксин дифтерийный¹<sup>,</sup>³ — Не менее 30&nbsp;МЕ;</li> <li>Анатоксин столбнячный²<sup>,</sup>³ — Не менее 40&nbsp;МЕ;</li> <li>Анатоксин коклюшный (АК)³ — 25&nbsp;мкг;</li> <li>Гемагглютинин филаментозный (ФГА)³ — 25&nbsp;мкг;</li> <li>Пертактин (белок наружной мембраны 69&nbsp;кДа)³ — 8&nbsp;мкг;</li> <li>Антиген поверхностный рекомбинантный вируса гепатита B (HBsAg)⁴ — 10&nbsp;мкг;</li> <li>Вирус полиомиелита тип&nbsp;1 инактивированный — 40&nbsp;ЕД D-антигена;</li> <li>Вирус полиомиелита тип&nbsp;2 инактивированный — 8&nbsp;ЕД D-антигена;</li> <li>Вирус полиомиелита тип&nbsp;3 инактивированный — 32&nbsp;ЕД D-антигена.</li></ul> Вакцина для профилактики инфекции, вызываемой <i>Haemophilus influenzae</i> тип <i>b</i> конъюгированная, адсорбированная <ul><i>Действующее вещество:</i> <li>Капсульный полисахарид Haemophilus influenzae тип b⁴ — 10&nbsp;мкг;<br> конъюгированный со столбнячным анатоксином — ≈25&nbsp;мкг.</li></ul> ¹ Содержание дифтерийного анатоксина 25&nbsp;Lf (флоккулирующих единиц).<br> ² Содержание столбнячного анатоксина 10&nbsp;Lf (флоккулирующих единиц).<br> ³ Адсорбированный на алюминия гидроксиде (0,5&nbsp;мг в пересчете на алюминий).<br> ⁴ Адсорбированный на алюминия фосфате (0,32&nbsp;мг в пересчете на алюминий).</p> <p><i>Перечень вспомогательных веществ:</i><br><br> Вакцина для профилактики дифтерии, столбняка, коклюша (бесклеточная), полиомиелита (инактивированная), гепатита В комбинированная, адсорбированная: <ul><li>Натрия хлорид.</li> <li>Среда&nbsp;199 (М&nbsp;199)¹ (включая аминокислоты).</li> <li>Вода для инъекций.</li></ul> ¹ Состав среды&nbsp;199 (М&nbsp;199):<br> кальция хлорида дигидрат, железа нитрата нонагидрат, калия хлорид, калия дигидрофосфат, магния сульфата гептагидрат, натрия хлорид, натрия гидрокарбонат, натрия гидрофосфат, L-аланин, L-аргинина гидрохлорид, L-аспарагиновая кислота, L-цистеина гидрохлорид, L-цистин, L-глутаминовая кислота, L-глутамин, глицин, L-гистидина гидрохлорида моногидрат, L-гидроксипролин, L-изолейцин, L-лейцин, L-лизина гидрохлорид, L-метионин, L-фенилаланин, L-пролин, L-серин, L-треонин, L-триптофан, L-тирозин, L-валин, аскорбиновая кислота, альфа-токоферол, биотин, кальциферол, кальция пантотенат, холина хлорид, фолиевая кислота, инозитол, менадион, никотиновая кислота, никотинамид, пара-аминобензойная кислота, пиридоксаль гидрохлорид, пиридоксина гидрохлорид, рибофлавин, тиамина гидрохлорид, ретинола ацетат, аденин, аденозина фосфат, аденозина трифосфат натрия, холестерол, дезоксирибоза, глюкоза, глутатион, гуанина гидрохлорид, гипоксантин, рибоза, натрия ацетат, тимин, твин-80, урацил, ксантин.<br><br> Вакцина для профилактики инфекции, вызываемой <i>Haemophilus influenzae</i> тип <i>b</i>, конъюгированная, адсорбированная: <ul><li>Лактоза.</li></ul> Данный препарат содержит менее 1&nbsp;ммоль (23&nbsp;мг) натрия на 1&nbsp;дозу, то есть по сути не содержит натрия.</p> | E11: 45953 | F11: 1 | G11: 0 | H11: https://grls.rosminzdrav.ru/InstrImg/2025/12/04/1523945/374687b9-516b-4eb9-9e34-640e88c2e1e2.pdf | I11: =I10 -> 45115 | J11: 46000
A12: 11 | B12: =VLOOKUP(A12,vaccines!A:B,2) -> Bubo_M | C12: 1 доза (0,5 мл) содержит действующие вещества: • Антиген вируса гепатита В поверхностный рекомбинантный (HBsAg) (серотип ay и/или ad)¹ — 10 мкг; • дифтерийный анатоксин очищенный концентрированный жидкий (ОКДА)¹ — 5 Lf (флокулирующих единиц); • столбнячный анатоксин очищенный концентрированный жидкий (ОКСА)¹ — 5 ЕС (антитоксинсвязывающих единиц). ¹ — адсорбированный на алюминия гидроксиде (Al³⁺) — 0,45 мг. Перечень вспомогательных веществ: • Тиомерсал (консервант). | D12: <p>1&nbsp;доза (0,5&nbsp;мл) содержит действующие вещества: <ul><li>Антиген вируса гепатита&nbsp;В поверхностный рекомбинантный (HBsAg) (серотип ay и/или ad)¹ — 10&nbsp;мкг;</li> <li>дифтерийный анатоксин очищенный концентрированный жидкий (ОКДА)¹ — 5&nbsp;Lf (флокулирующих единиц);</li> <li>столбнячный анатоксин очищенный концентрированный жидкий (ОКСА)¹ — 5&nbsp;ЕС (антитоксинсвязывающих единиц).</li></ul> ¹&nbsp;—&nbsp;адсорбированный на алюминия гидроксиде (Al³⁺) — 0,45&nbsp;мг.<br><br> <i>Перечень вспомогательных веществ:</i> <ul><li>Тиомерсал (консервант).</li></ul></p> | E12: 46136 | F12: 1 | G12: 0 | H12: https://grls.rosminzdrav.ru/InstrImg/2026/06/02/1530636/e301156c-c7d5-45d7-bf58-5346c270c493.pdf | I12: 45116 | J12: 46188
A13: 12 | B13: =VLOOKUP(A13,vaccines!A:B,2) -> AD_M_Microgen | C13: В 1 дозе (0,5 мл) содержится: Препарат с консервантом и без консерванта Действующее вещество: • Анатоксин дифтерийный¹ — 5 Lf. Вспомогательные вещества, наличие которых надо учитывать в составе лекарственного препарата: • Содержит формальдегид — не более 50 мкг. ¹ Адсорбированный на алюминия гидроксиде (в пересчете на Al³⁺) — не более 0,55 мг. Полный перечень вспомогательных веществ приведен в разделе 6.1. 6.1. Перечень вспомогательных веществ Препарат с консервантом: • Алюминия гидроксид • Тиомерсал (консервант) Препарат без консерванта: • Алюминия гидроксид | D13: <p>В 1&nbsp;дозе (0,5&nbsp;мл) содержится:<br><br> <i>Препарат с консервантом и без консерванта</i><br><br> Действующее вещество: <ul><li>Анатоксин дифтерийный¹ — 5&nbsp;Lf.</li></ul> Вспомогательные вещества, наличие которых надо учитывать в составе лекарственного препарата: <ul><li>Содержит формальдегид — не более 50&nbsp;мкг.</li></ul> ¹&nbsp;Адсорбированный на алюминия гидроксиде (в пересчете на Al³⁺) — не более 0,55&nbsp;мг.<br><br> Полный перечень вспомогательных веществ приведен в разделе&nbsp;6.1.</p> <p><b>6.1.&nbsp;Перечень вспомогательных веществ</b><br><br> <i>Препарат с консервантом:</i> <ul><li>Алюминия гидроксид</li> <li>Тиомерсал (консервант)</li></ul> <i>Препарат без консерванта:</i> <ul><li>Алюминия гидроксид</li></ul></p> | E13: 45482 | H13: https://lk.regmed.ru/Register/GetPDFfromDA?ID=1601683231 | I13: =I12 -> 45116 | J13: 45518 | K13: проверено Елена Савинова
A14: 13 | B14: =VLOOKUP(A14,vaccines!A:B,2) -> ADS_Microgen | C14: В 1 дозе (0,5 мл) содержится: Препарат с консервантом: Действующие вещества: • Анатоксин дифтерийный¹ — 30 Lf; • Анатоксин столбнячный¹ — 10 ЕС. Вспомогательные вещества, наличие которых надо учитывать в составе лекарственного препарата: тиомерсал. Содержит формальдегид — не более 50 мкг. Препарат без консерванта: Действующие вещества: • Анатоксин дифтерийный¹ — 30 Lf; • Анатоксин столбнячный¹ — 10 ЕС. Содержит формальдегид — не более 50 мкг. ¹ Адсорбированный на алюминия гидроксиде (в пересчете на Al³⁺) — не более 0,55 мг. Полный перечень вспомогательных веществ приведен в разделе 6.1. 6.1. Перечень вспомогательных веществ Препарат с консервантом: • Алюминия гидроксид • Тиомерсал (консервант) Препарат без консерванта: • Алюминия гидроксид | D14: <p>В 1&nbsp;дозе (0,5&nbsp;мл) содержится:<br><br> <i>Препарат с консервантом:</i><br><br> Действующие вещества: <ul><li>Анатоксин дифтерийный¹ — 30&nbsp;Lf;</li> <li>Анатоксин столбнячный¹ — 10&nbsp;ЕС.</li></ul> Вспомогательные вещества, наличие которых надо учитывать в составе лекарственного препарата: тиомерсал.<br> Содержит формальдегид — не более 50&nbsp;мкг.<br><br> <i>Препарат без консерванта:</i><br><br> Действующие вещества: <ul><li>Анатоксин дифтерийный¹ — 30&nbsp;Lf;</li> <li>Анатоксин столбнячный¹ — 10&nbsp;ЕС.</li></ul> Содержит формальдегид — не более 50&nbsp;мкг.<br><br> ¹&nbsp;Адсорбированный на алюминия гидроксиде (в пересчете на Al³⁺) — не более 0,55&nbsp;мг.<br><br> Полный перечень вспомогательных веществ приведен в разделе&nbsp;6.1.</p> <p><b>6.1.&nbsp;Перечень вспомогательных веществ</b><br><br> <i>Препарат с консервантом:</i> <ul><li>Алюминия гидроксид</li> <li>Тиомерсал (консервант)</li></ul> <i>Препарат без консерванта:</i> <ul><li>Алюминия гидроксид</li></ul></p> | E14: 45488 | H14: https://lk.regmed.ru/Register/GetPDFfromDA?ID=1605321651 | I14: =I13 -> 45116 | J14: 45518
A15: 14 | B15: =VLOOKUP(A15,vaccines!A:B,2) -> ADS_M_Microgen | C15: В 1 дозе (0,5 мл) содержится: Препарат с консервантом: Действующие вещества: • Анатоксин дифтерийный¹ — 5 Lf; • Анатоксин столбнячный¹ — 5 ЕС. Вспомогательные вещества: • Формальдегид — не более 50 мкг. ¹ Адсорбированный на алюминия гидроксиде (в пересчете на Al³⁺) — не более 0,55 мг. Препарат без консерванта: Действующие вещества: • Анатоксин дифтерийный¹ — 5 Lf; • Анатоксин столбнячный¹ — 5 ЕС. Вспомогательные вещества: • Формальдегид — не более 50 мкг. ¹ Адсорбированный на алюминия гидроксиде (в пересчете на Al³⁺) — не более 0,55 мг. Полный перечень вспомогательных веществ приведен в разделе 6.1. 6.1. Перечень вспомогательных веществ Препарат с консервантом: • Алюминия гидроксид (в пересчете на алюминий Аl³⁺) • Тиомерсал (консервант) Препарат без консерванта: • Алюминия гидроксид (в пересчете на алюминий Аl³⁺) | D15: <p>В 1&nbsp;дозе (0,5&nbsp;мл) содержится:<br><br> <i>Препарат с консервантом:</i><br><br> Действующие вещества: <ul><li>Анатоксин дифтерийный¹ — 5&nbsp;Lf;</li> <li>Анатоксин столбнячный¹ — 5&nbsp;ЕС.</li></ul> Вспомогательные вещества: <ul><li>Формальдегид — не более 50&nbsp;мкг.</li></ul> ¹&nbsp;Адсорбированный на алюминия гидроксиде (в пересчете на Al³⁺) — не более 0,55&nbsp;мг.<br><br> <i>Препарат без консерванта:</i><br><br> Действующие вещества: <ul><li>Анатоксин дифтерийный¹ — 5&nbsp;Lf;</li> <li>Анатоксин столбнячный¹ — 5&nbsp;ЕС.</li></ul> Вспомогательные вещества: <ul><li>Формальдегид — не более 50&nbsp;мкг.</li></ul> ¹&nbsp;Адсорбированный на алюминия гидроксиде (в пересчете на Al³⁺) — не более 0,55&nbsp;мг.<br><br> Полный перечень вспомогательных веществ приведен в разделе&nbsp;6.1.</p> <p><b>6.1.&nbsp;Перечень вспомогательных веществ</b><br><br> <i>Препарат с консервантом:</i> <ul><li>Алюминия гидроксид (в пересчете на алюминий Аl³⁺)</li> <li>Тиомерсал (консервант)</li></ul> <i>Препарат без консерванта:</i> <ul><li>Алюминия гидроксид (в пересчете на алюминий Аl³⁺)</li></ul></p> | E15: 45623 | F15: 1 | G15: 0 | H15: https://grls.rosminzdrav.ru/InstrImg/2024/12/16/1511954/43eafc3c-33ac-4e33-969c-259e9a175ebb.pdf | I15: =I14 -> 45116 | J15: 45861
A16: 15 | B16: =VLOOKUP(A16,vaccines!A:B,2) -> ADS_M_Biomed | C16: В одной дозе препарата (0,5 мл) содержится: Активные вещества: 5 флокулирующих единиц (Lf) дифтерийного и 5 единиц связывания (EC) столбнячного анатоксинов. Вспомогательные вещества: от 0,25 до 0,55 мг алюминия гидроксида в пересчете на алюминий (сорбент), от 42,5 до 57,5 мкг тиомерсала (консервант). | D16: <p>В одной дозе препарата (0,5&nbsp;мл) содержится:</p> <p>Активные вещества: 5&nbsp;флокулирующих единиц (Lf) дифтерийного и 5&nbsp;единиц связывания (EC) столбнячного анатоксинов.</p> <p>Вспомогательные вещества: от 0,25 до 0,55&nbsp;мг алюминия гидроксида в пересчете на алюминий (сорбент), от 42,5 до 57,5&nbsp;мкг тиомерсала (консервант).</p> | E16: 41046 | F16: 1 | G16: 0 | H16: https://grls.rosminzdrav.ru/InstrImg/2018/7/19/1423955/%D0%A0_N002668_01[2012]_0.pdf | I16: 45116
A17: 16 | B17: =VLOOKUP(A17,vaccines!A:B,2) -> Adacel | C17: 1 доза вакцины (0,5 мл) содержит действующие вещества: • Столбнячный анатоксин, адсорбированный¹ — 5 Lf (не менее 20 ME). • Дифтерийный анатоксин, адсорбированный¹ — 2 Lf (не менее 2 ME). • Бесклеточная коклюшная вакцина, содержащая: коклюшный анатоксин (КА), адсорбированный¹ — 2,5 мкг. филаментозный гемагглютинин (ФГА), адсорбированный¹ — 5 мкг. агглютиногены фимбрий типов 2 и 3 (ФИМ), адсорбированные¹ — 5 мкг. пертактин (ПРН), адсорбированный¹ — 3 мкг. ¹ — адсорбирована на алюминия фосфате (в пересчете на алюминий) — 1,5 мг (0,33 мг). Остаточные продукты производственного процесса, присутствующие в 1 дозе вакцины (0,5 мл) в следовых количествах (указано их расчетное количество): формальдегид (≤ 5 мкг) и глутаральдегид (< 50 нг). Перечень вспомогательных веществ: • Алюминия фосфат. • 2-феноксиэтанол (не консервант). • Вода для инъекций. | D17: <p>1&nbsp;доза вакцины (0,5&nbsp;мл) содержит действующие вещества: <ul><li>Столбнячный анатоксин, адсорбированный¹ — 5&nbsp;Lf (не менее 20&nbsp;ME).</li> <li>Дифтерийный анатоксин, адсорбированный¹ — 2&nbsp;Lf (не менее 2&nbsp;ME).</li> <li>Бесклеточная коклюшная вакцина, содержащая:<br> коклюшный анатоксин (КА), адсорбированный¹ — 2,5&nbsp;мкг.<br> филаментозный гемагглютинин (ФГА), адсорбированный¹ — 5&nbsp;мкг.<br> агглютиногены фимбрий типов 2 и 3 (ФИМ), адсорбированные¹ — 5&nbsp;мкг.<br> пертактин (ПРН), адсорбированный¹ — 3&nbsp;мкг.</li></ul> ¹ — адсорбирована на алюминия фосфате (в пересчете на алюминий) — 1,5&nbsp;мг (0,33&nbsp;мг).</p> <p>Остаточные продукты производственного процесса, присутствующие в 1&nbsp;дозе вакцины (0,5&nbsp;мл) в следовых количествах (указано их расчетное количество): формальдегид (≤&nbsp;5&nbsp;мкг) и глутаральдегид (<&nbsp;50&nbsp;нг).</p> <p>Перечень вспомогательных веществ: <ul><li>Алюминия фосфат. <li>2-феноксиэтанол (не консервант).</li> <li>Вода для инъекций.</li></ul></p> | E17: 45456 | H17: https://lk.regmed.ru/Register/GetPDFfromDA?ID=1592320751 | I17: 45117 | J17: 45589
A18: 17 | B18: =VLOOKUP(A18,vaccines!A:B,2) -> Algavac_M | C18: 1 прививочная доза для взрослых (1 мл) содержит: Действующее вещество: Инактивированный антиген вируса гепатита А (АГ ВГА) — не менее 320 ИФА ЕД. Вспомогательные вещества: Алюминия гидроксид, формальдегид, 0,01 М фосфатно-солевой буферный раствор (натрия гидрофосфата додекагидрат, натрия хлорид, вода для инъекций). Вакцина не содержит консервантов и антибиотиков. 1 прививочная доза для детей (0,5 мл) содержит: Действующее вещество: Инактивированный антиген вируса гепатита А (АГ ВГА) — не менее 160 ИФА ЕД. Вспомогательные вещества: Алюминия гидроксид, формальдегид, 0,01 М фосфатно-солевой буферный раствор (натрия гидрофосфата додекагидрат, натрия хлорид, вода для инъекций). Вакцина не содержит консервантов и антибиотиков. | D18: <p>1&nbsp;прививочная доза для взрослых (1&nbsp;мл) содержит:</p> <p><i>Действующее вещество:</i> <ul>Инактивированный антиген вируса гепатита А (АГ ВГА) — не менее 320&nbsp;ИФА ЕД.</ul> <i>Вспомогательные вещества:</i> <ul>Алюминия гидроксид, формальдегид, 0,01&nbsp;М фосфатно-солевой буферный раствор (натрия гидрофосфата додекагидрат, натрия хлорид, вода для инъекций).</ul></p> <p>Вакцина не содержит консервантов и антибиотиков.</p> <p>1&nbsp;прививочная доза для детей (0,5&nbsp;мл) содержит:</p> <p><i>Действующее вещество:</i> <ul>Инактивированный антиген вируса гепатита А (АГ ВГА) — не менее 160&nbsp;ИФА ЕД.</ul> <i>Вспомогательные вещества:</i> <ul>Алюминия гидроксид, формальдегид, 0,01&nbsp;М фосфатно-солевой буферный раствор (натрия гидрофосфата додекагидрат, натрия хлорид, вода для инъекций).</ul></p> <p>Вакцина не содержит консервантов и антибиотиков.</p> | E18: 43369 | F18: 1 | G18: 0 | H18: https://grls.rosminzdrav.ru/InstrImg/2020/9/29/1461721/%D0%A0_N000461_01[2018]_0.pdf | I18: 45117
A19: 18 | B19: =VLOOKUP(A19,vaccines!A:B,2) -> Algavac | C19: 1 доза для взрослых (1 мл) содержит: Действующее вещество: • Инактивированный антиген вируса гепатита А (АГ ВГА) — не менее 320 ИФА ЕД (получен с использованием клеток почки зеленой мартышки 4647) Адсорбент • Алюминия гидроксид (в пересчете на Al³⁺) — 0,35-0,65 мг Вакцина не содержит консервантов и антибиотиков. Перечень вспомогательных веществ: • Алюминия гидроксид; • Формальдегид; • 0,01&nbsp;М фосфатно-солевой буферный раствор, содержащий: - натрия гидрофосфата додекагидрат; - натрия хлорид; - воду для инъекций. | D19: <p>1&nbsp;доза для взрослых (1&nbsp;мл) содержит:<br><br> <i>Действующее вещество:</i> <ul><li>Инактивированный антиген вируса гепатита А (АГ ВГА) — не менее 320&nbsp;ИФА ЕД<br> (получен с использованием клеток почки зеленой мартышки&nbsp;4647)</li></ul> <i>Адсорбент</i> <ul><li>Алюминия гидроксид (в пересчете на Al³⁺) — 0,35-0,65&nbsp;мг</li></ul> Вакцина не содержит консервантов и антибиотиков.<br><br> <i>Перечень вспомогательных веществ:</i> <ul><li>Алюминия гидроксид;</li> <li>Формальдегид;</li> <li>0,01&nbsp;М фосфатно-солевой буферный раствор, содержащий: <ul><li>натрия гидрофосфата додекагидрат;</li> <li>натрия хлорид;</li> <li>воду для инъекций.</li></ul></p> | E19: 46111 | F19: 1 | G19: 0 | H19: https://grls.rosminzdrav.ru/InstrImg/2026/05/07/1529632/54e13522-5efa-4c8c-a9b0-7ea539b4f9d1.pdf | I19: =I18 -> 45117 | J19: 46188
A20: 19 | B20: =VLOOKUP(A20,vaccines!A:B,2) -> Havrix_720 | C20: Одна прививочная доза содержит: Действующее вещество: • Антиген вируса гепатита А — 720 ИФА единиц. Адъювант: • Алюминия гидроксид — 0,25 мг. Вакцина содержит следовые количества неомицина сульфата. Вспомогательные вещества, наличие которых надо учитывать в составе лекарственного препарата: фенилаланин, натрия гидрофосфат, натрия хлорид, калия дигидрофосфат, калия хлорид. Полный перечень вспомогательных веществ приведен в разделе 6.1. 6.1. Перечень вспомогательных веществ • Алюминия гидроксид — 0,25 мг; • Полисорбат-20 — 0,025 мг; • Натрия гидрофосфат — Не более 0,575 мг; • Калия дигидрофосфат — Не более 0,10 мг; • Натрия хлорид — Не более 4,50 мг; • Калия хлорид — Не более 0,115 мг; • Аминокислотный компонент¹ — 1,50 мг; • Вода для инъекций — до 0,5 мл. ¹ Аминокислотный компонент: L-аланин, L-аргинин, глицин, L-гистидин, L-изолейцин, L-лейцин, L-лизин, L-метионин, L-фенилаланин, L-пролин, L-серин, L-треонин, L-триптофан, L-тирозин, L-валин. | D20: <p>Одна прививочная доза содержит:<br><br> <i>Действующее вещество:</i> <ul><li>Антиген вируса гепатита А — 720&nbsp;ИФА единиц.</li></ul> <i>Адъювант:</i> <ul><li>Алюминия гидроксид — 0,25&nbsp;мг.</li></ul> Вакцина содержит следовые количества неомицина сульфата.<br> Вспомогательные вещества, наличие которых надо учитывать в составе лекарственного препарата: фенилаланин, натрия гидрофосфат, натрия хлорид, калия дигидрофосфат, калия хлорид.<br> Полный перечень вспомогательных веществ приведен в разделе&nbsp;6.1.</p> <p><b>6.1. Перечень вспомогательных веществ</b> <ul><li>Алюминия гидроксид — 0,25&nbsp;мг;</li> <li>Полисорбат-20 — 0,025&nbsp;мг;</li> <li>Натрия гидрофосфат — Не более 0,575&nbsp;мг;</li> <li>Калия дигидрофосфат — Не более 0,10&nbsp;мг;</li> <li>Натрия хлорид — Не более 4,50&nbsp;мг;</li> <li>Калия хлорид — Не более 0,115&nbsp;мг;</li> <li>Аминокислотный компонент¹ — 1,50&nbsp;мг;</li> <li>Вода для инъекций — до 0,5&nbsp;мл.</li></ul> ¹&nbsp;Аминокислотный компонент: L-аланин, L-аргинин, глицин, L-гистидин, L-изолейцин, L-лейцин, L-лизин, L-метионин, L-фенилаланин, L-пролин, L-серин, L-треонин, L-триптофан, L-тирозин, L-валин.</p> | E20: 45490 | H20: https://lk.regmed.ru/Register/GetPDFfromDA?ID=1607490831 | I20: 45119 | J20: 45558
A21: 20 | B21: =VLOOKUP(A21,vaccines!A:B,2) -> Havrix_1440 | C21: Одна прививочная доза содержит: Действующее вещество: • Антиген вируса гепатита А — 1440 ИФА единиц. Адъювант: • Алюминия гидроксид — 0,50 мг. Вакцина содержит следовые количества неомицина сульфата. Вспомогательные вещества, наличие которых надо учитывать в составе лекарственного препарата: фенилаланин, натрия гидрофосфат, натрия хлорид, калия дигидрофосфат, калия хлорид. Полный перечень вспомогательных веществ приведен в разделе 6.1. 6.1. Перечень вспомогательных веществ • Алюминия гидроксид — 0,50 мг; • Полисорбат-20 — 0,050 мг; • Натрия гидрофосфат — Не более 1,150 мг; • Калия дигидрофосфат — Не более 0,20 мг; • Натрия хлорид — Не более 9,00 мг; • Калия хлорид — Не более 0,230 мг; • Аминокислотный компонент¹ — 3,00 мг; • Вода для инъекций — до 1,0 мл. ¹ Аминокислотный компонент: L-аланин, L-аргинин, глицин, L-гистидин, L-изолейцин, L-лейцин, L-лизин, L-метионин, L-фенилаланин, L-пролин, L-серин, L-треонин, L-триптофан, L-тирозин, L-валин. | D21: <p>Одна прививочная доза содержит:<br><br> <i>Действующее вещество:</i> <ul><li>Антиген вируса гепатита А — 1440&nbsp;ИФА единиц.</li></ul> <i>Адъювант:</i> <ul><li>Алюминия гидроксид — 0,50&nbsp;мг.</li></ul> Вакцина содержит следовые количества неомицина сульфата.<br> Вспомогательные вещества, наличие которых надо учитывать в составе лекарственного препарата: фенилаланин, натрия гидрофосфат, натрия хлорид, калия дигидрофосфат, калия хлорид.<br> Полный перечень вспомогательных веществ приведен в разделе&nbsp;6.1.</p> <p><b>6.1. Перечень вспомогательных веществ</b> <ul><li>Алюминия гидроксид — 0,50&nbsp;мг;</li> <li>Полисорбат-20 — 0,050&nbsp;мг;</li> <li>Натрия гидрофосфат — Не более 1,150&nbsp;мг;</li> <li>Калия дигидрофосфат — Не более 0,20&nbsp;мг;</li> <li>Натрия хлорид — Не более 9,00&nbsp;мг;</li> <li>Калия хлорид — Не более 0,230&nbsp;мг;</li> <li>Аминокислотный компонент¹ — 3,00&nbsp;мг;</li> <li>Вода для инъекций — до 1,0&nbsp;мл.</li></ul> ¹&nbsp;Аминокислотный компонент: L-аланин, L-аргинин, глицин, L-гистидин, L-изолейцин, L-лейцин, L-лизин, L-метионин, L-фенилаланин, L-пролин, L-серин, L-треонин, L-триптофан, L-тирозин, L-валин.</p> | E21: 45490 | H21: https://lk.regmed.ru/Register/GetPDFfromDA?ID=1607490831 | I21: 45119 | J21: 45558
A22: 21 | B22: =VLOOKUP(A22,vaccines!A:B,2) -> Avaxim_80 | C22: На 1 дозу (0,5 мл): Активный компонент: • Вирус гепатита А¹·² инактивированный — 80 единиц антигена³. ¹ - штамм GBM, культивированный в культуре диплоидных клеток человека MRC-5; ² - инактивированный формальдегидом и адсорбированный на алюминия гидроксиде; ³ - содержание антигена выражено с использованием внутреннего референс-стандарта компании-производителя. Вспомогательные вещества: • Алюминия гидроксид (в пересчете на алюминий) — 0,15 мг, 2-феноксиэтанол — 2,5 мкл, формальдегид — 12,5 мкг, среда Хэнкс 199⁴ — до 0,5 мл, кислота хлористоводородная или натрия гидроксид для регулировки значения pH. • Неомицин (производственная примесь) — не более 5 мкг/мл. ⁴ - среда Хэнкс 199 (без фенолового красного) является смесью аминокислот (D,L-аланин, L-аргинина гидрохлорид, D,L-аспарагиновая кислота, L-цистеина гидрохлорида моногидрат, L-цистина дигидрохлорид, D,L-глутаминовой кислоты моногидрат, L-глутамин, глицин, L-гистидина гидрохлорида моногидрат, D,L-изолейцин, L-гидроксипролин, D,L-лейцин, L-лизина гидрохлорид, D,L-метионин, D,L-фенилаланин, L-пролин, D,L-серин, D,L-треонин, D,L-триптофан, L-тирозин динатрия, D,L-валин), минеральных солей(кальция хлорид безводный, железа нитрата нонагидрат, калия хлорид, магния сульфата гептагидрат, натрия хлорид, калия дигидрофосфат, натрия гидрофосфат безводный), витаминов (аскорбиновая кислота, D-биотин, эргокальциферол, кальция пантотенат, холина хлорид, фолиевая кислота, I-инозитол, менадион, никотиновая кислота, никотинамид, парааминобензойная кислота, пиридоксаля гидрохлорид, пиридоксина гидрохлорид, рибофлавин, тиамина гидрохлорид, ретинола ацетат, альфа-токоферола фосфат натрия) и других компонентов (аденина сульфат, трифосаденин динатрия, аденозина фосфат, холестерол, дезоксирибоза, декстроза, глутатион восстановленный, гуанина гидрохлорид, гипоксантин динатрия, рибоза, натрия ацетат, тимин, полисорбат 80, урацил, ксантин динатрия), растворенных в воде для инъекций. | D22: <p>На 1&nbsp;дозу (0,5&nbsp;мл):</p> <p><i>Активный компонент:</i> <ul><li>Вирус гепатита&nbsp;А¹<sup>,</sup>² инактивированный — 80&nbsp;единиц антигена³.</li></ul></p> <p>¹ - штамм GBM, культивированный в культуре диплоидных клеток человека MRC-5;<br> ² - инактивированный формальдегидом и адсорбированный на алюминия гидроксиде;<br> ³ - содержание антигена выражено с использованием внутреннего референс-стандарта компании-производителя.</p> <p><i>Вспомогательные вещества:</i> <ul><li>Алюминия гидроксид (в пересчете на алюминий) — 0,15&nbsp;мг, 2-феноксиэтанол — 2,5&nbsp;мкл, формальдегид — 12,5&nbsp;мкг, среда Хэнкс&nbsp;199⁴ — до 0,5&nbsp;мл, кислота хлористоводородная или натрия гидроксид для регулировки значения pH.</li> <li>Неомицин (производственная примесь) — не более 5&nbsp;мкг/мл.</li></ul></p> <p>⁴ - среда Хэнкс&nbsp;199 (без фенолового красного) является смесью аминокислот (D,L-аланин, L-аргинина гидрохлорид, D,L-аспарагиновая кислота, L-цистеина гидрохлорида моногидрат, L-цистина дигидрохлорид, D,L-глутаминовой кислоты моногидрат, L-глутамин, глицин, L-гистидина гидрохлорида моногидрат, D,L-изолейцин, L-гидроксипролин, D,L-лейцин, L-лизина гидрохлорид, D,L-метионин, D,L-фенилаланин, L-пролин, D,L-серин, D,L-треонин, D,L-триптофан, L-тирозин динатрия, D,L-валин), минеральных солей(кальция хлорид безводный, железа нитрата нонагидрат, калия хлорид, магния сульфата гептагидрат, натрия хлорид, калия дигидрофосфат, натрия гидрофосфат безводный), витаминов (аскорбиновая кислота, D-биотин, эргокальциферол, кальция пантотенат, холина хлорид, фолиевая кислота, I-инозитол, менадион, никотиновая кислота, никотинамид, парааминобензойная кислота, пиридоксаля гидрохлорид, пиридоксина гидрохлорид, рибофлавин, тиамина гидрохлорид, ретинола ацетат, альфа-токоферола фосфат натрия) и других компонентов (аденина сульфат, трифосаденин динатрия, аденозина фосфат, холестерол, дезоксирибоза, декстроза, глутатион восстановленный, гуанина гидрохлорид, гипоксантин динатрия, рибоза, натрия ацетат, тимин, полисорбат 80, урацил, ксантин динатрия), растворенных в воде для инъекций.</p> | E22: 42367 | F22: 2 | G22: 1 | H22: https://grls.rosminzdrav.ru/InstrImg/2021/10/06/1474149/bd8cf367-32be-419a-a06f-cb35a0ecd9d1.pdf | I22: 45119
A23: 22 | B23: =VLOOKUP(A23,vaccines!A:B,2) -> Avaxim_160 | C23: На 1 дозу (0,5 мл): Активный компонент: • Вирус гепатита А¹·² инактивированный — 160 единиц антигена³. ¹ - штамм GBM, культивированный в культуре диплоидных клеток человека MRC-5; ² - инактивированный формальдегидом и адсорбированный на алюминия гидроксиде; ³ - содержание антигена выражено с использованием внутреннего референс-стандарта компании-производителя. Вспомогательные вещества: • Алюминия гидроксид (в пересчете на алюминий) — 0,3 мг, 2-феноксиэтанол — 2,5 мкл, формальдегид — 12,5 мкг, среда Хэнкс 199⁴ — до 0,5 мл, кислота хлористоводородная или натрия гидроксид для регулировки значения pH. • Неомицин (производственная примесь) — не более 5 мкг/мл. ⁴ - среда Хэнкс 199 (без фенолового красного) является смесью аминокислот (D,L-аланин, L-аргинина гидрохлорид, D,L-аспарагиновая кислота, L-цистеина гидрохлорида моногидрат, L-цистина дигидрохлорид, D,L-глутаминовой кислоты моногидрат, L-глутамин, глицин, L-гистидина гидрохлорида моногидрат, D,L-изолейцин, L-гидроксипролин, D,L-лейцин, L-лизина гидрохлорид, D,L-метионин, D,L-фенилаланин, L-пролин, D,L-серин, D,L-треонин, D,L-триптофан, L-тирозин динатрия, D,L-валин), минеральных солей(кальция хлорид безводный, железа нитрата нонагидрат, калия хлорид, магния сульфата гептагидрат, натрия хлорид, калия дигидрофосфат, натрия гидрофосфат безводный), витаминов (аскорбиновая кислота, D-биотин, эргокальциферол, кальция пантотенат, холина хлорид, фолиевая кислота, I-инозитол, менадион, никотиновая кислота, никотинамид, парааминобензойная кислота, пиридоксаля гидрохлорид, пиридоксина гидрохлорид, рибофлавин, тиамина гидрохлорид, ретинола ацетат, альфа-токоферола фосфат натрия) и других компонентов (аденина сульфат, трифосаденин динатрия, аденозина фосфат, холестерол, дезоксирибоза, декстроза, глутатион восстановленный, гуанина гидрохлорид, гипоксантин динатрия, рибоза, натрия ацетат, тимин, полисорбат 80, урацил, ксантин динатрия), растворенных в воде для инъекций. | D23: <p>На 1&nbsp;дозу (0,5&nbsp;мл):</p> <p><i>Активный компонент:</i> <ul><li>Вирус гепатита&nbsp;А¹<sup>,</sup>² инактивированный — 160&nbsp;единиц антигена³.</li></ul></p> <p>¹ - штамм GBM, культивированный в культуре диплоидных клеток человека MRC-5;<br> ² - инактивированный формальдегидом и адсорбированный на алюминия гидроксиде;<br> ³ - содержание антигена выражено с использованием внутреннего референс-стандарта компании-производителя.</p> <p><i>Вспомогательные вещества:</i> <ul><li>Алюминия гидроксид (в пересчете на алюминий) — 0,3&nbsp;мг, 2-феноксиэтанол — 2,5&nbsp;мкл, формальдегид — 12,5&nbsp;мкг, среда Хэнкс&nbsp;199⁴ — до 0,5&nbsp;мл, кислота хлористоводородная или натрия гидроксид для регулировки значения pH.</li> <li>Неомицин (производственная примесь) — не более 5&nbsp;мкг/мл.</li></ul></p> <p>⁴ - среда Хэнкс&nbsp;199 (без фенолового красного) является смесью аминокислот (D,L-аланин, L-аргинина гидрохлорид, D,L-аспарагиновая кислота, L-цистеина гидрохлорида моногидрат, L-цистина дигидрохлорид, D,L-глутаминовой кислоты моногидрат, L-глутамин, глицин, L-гистидина гидрохлорида моногидрат, D,L-изолейцин, L-гидроксипролин, D,L-лейцин, L-лизина гидрохлорид, D,L-метионин, D,L-фенилаланин, L-пролин, D,L-серин, D,L-треонин, D,L-триптофан, L-тирозин динатрия, D,L-валин), минеральных солей(кальция хлорид безводный, железа нитрата нонагидрат, калия хлорид, магния сульфата гептагидрат, натрия хлорид, калия дигидрофосфат, натрия гидрофосфат безводный), витаминов (аскорбиновая кислота, D-биотин, эргокальциферол, кальция пантотенат, холина хлорид, фолиевая кислота, I-инозитол, менадион, никотиновая кислота, никотинамид, парааминобензойная кислота, пиридоксаля гидрохлорид, пиридоксина гидрохлорид, рибофлавин, тиамина гидрохлорид, ретинола ацетат, альфа-токоферола фосфат натрия) и других компонентов (аденина сульфат, трифосаденин динатрия, аденозина фосфат, холестерол, дезоксирибоза, декстроза, глутатион восстановленный, гуанина гидрохлорид, гипоксантин динатрия, рибоза, натрия ацетат, тимин, полисорбат 80, урацил, ксантин динатрия), растворенных в воде для инъекций.</p> | E23: 42131 | F23: 1 | G23: 0 | H23: https://grls.rosminzdrav.ru/InstrImg/2021/10/06/1474147/01e6e663-0f1b-4047-bdc9-365d6ba31c8a.pdf | I23: 45119
A24: 23 | B24: =VLOOKUP(A24,vaccines!A:B,2) -> Regevac_0_5 | C24: 1 детская доза (0,5 мл) вакцины содержит: Действующее вещество: очищенный поверхностный антиген вируса гепатита В (HBsAg) — 10 мкг. Вспомогательные вещества: алюминия гидроксид — 0,25 мг. Компоненты буферного раствора: натрия хлорид; натрия гидрофосфат; натрия дигидрофосфата дигидрат; 2 М раствор натрия гидроксида до рН 6,95–7,05; вода для инъекций. Данный препарат содержит менее 1 ммоль (23 мг) натрия на дозу. | D24: <p>1&nbsp;детская доза (0,5&nbsp;мл) вакцины содержит:</p> <p><i>Действующее вещество:</i> очищенный поверхностный антиген вируса гепатита В (HBsAg) — 10&nbsp;мкг.</p> <p><i>Вспомогательные вещества:</i> алюминия гидроксид — 0,25&nbsp;мг.</p> <p><i>Компоненты буферного раствора:</i> натрия хлорид; натрия гидрофосфат; натрия дигидрофосфата дигидрат; 2&nbsp;М раствор натрия гидроксида до рН&nbsp;6,95–7,05; вода для инъекций.</p> <p>Данный препарат содержит менее 1&nbsp;ммоль (23&nbsp;мг) натрия на дозу.</p> | E24: 45216 | F24: 1 | G24: 0 | H24: https://grls.rosminzdrav.ru/InstrImg/2025/06/16/1518193/6df836e1-9750-4ca5-be05-590641b808ac.pdf | I24: =I23 -> 45119 | J24: 45988
A25: 24 | B25: =VLOOKUP(A25,vaccines!A:B,2) -> HepB_Combiotech_0_5 | C25: 1 доза для детей (0,5 мл) содержит: • Антиген вируса гепатита В поверхностный рекомбинантный (HBsAg) (серотип ау и/или ad)¹·² — 10 мкг ¹ Получен из дрожжевых клеток Saccharomyces cerevisiae (серотип ау) и/или Hansenula polymorpha (серотип ау и/или ad) по технологии рекомбинантной ДНК. ² Адсорбированный на алюминия гидроксиде (0,25 мг Al³⁺). Перечень вспомогательных веществ: • Натрия дигидрофосфат дигидрат; • Натрия хлорид; • Натрия гидроксид; • Вода для инъекций. | D25: <p>1&nbsp;доза для детей (0,5&nbsp;мл) содержит: <ul><li>Антиген вируса гепатита В поверхностный рекомбинантный (HBsAg) (серотип <i>ау</i> и/или <i>ad</i>)¹<sup>,</sup>² — 10&nbsp;мкг</li></ul> ¹&nbsp;Получен из дрожжевых клеток <i>Saccharomyces cerevisiae</i> (серотип <i>ау</i>) и/или <i>Hansenula polymorpha</i> (серотип <i>ау</i> и/или <i>ad</i>) по технологии рекомбинантной ДНК.<br> ²&nbsp;Адсорбированный на алюминия гидроксиде (0,25&nbsp;мг Al³⁺).<br><br> <i>Перечень вспомогательных веществ:</i> <ul><li>Натрия дигидрофосфат дигидрат;</li> <li>Натрия хлорид;</li> <li>Натрия гидроксид;</li> <li>Вода для инъекций.</li></ul></p> | E25: 46056 | F25: 1 | G25: 0 | H25: https://grls.rosminzdrav.ru/InstrImg/2026/03/04/1527238/fe2adafe-5094-4da2-bbba-1a640a0ceb4e.pdf | I25: =I24 -> 45119 | J25: 46130
A26: 25 | B26: =VLOOKUP(A26,vaccines!A:B,2) -> Euvax_B_0_5 | C26: Доза для детей (0,5 мл): Активный компонент: • Поверхностный антиген вируса гепатита В (HBsAg) очищенный — 10 мкг. Вспомогательные вещества: • Гель алюминия гидроксида (по алюминию) — 0,25 мг. • Калия дигидрофосфат (буферный агент) — q.s. • Натрия гидрофосфат (буферный агент) — q.s. • Натрия хлорид — 4,25 мг. • Вода для инъекций — до 0,5 мл. | D26: <p>Доза для детей (0,5&nbsp;мл):</p> <p><i>Активный компонент:</i> <ul><li>Поверхностный антиген вируса гепатита В (HBsAg) очищенный — 10&nbsp;мкг.</li></ul> <i>Вспомогательные вещества:</i> <ul><li>Гель алюминия гидроксида (по алюминию) — 0,25&nbsp;мг.</li> <li>Калия дигидрофосфат (буферный агент) — q.s.</li> <li>Натрия гидрофосфат (буферный агент) — q.s.</li> <li>Натрия хлорид — 4,25&nbsp;мг.</li> <li>Вода для инъекций — до 0,5&nbsp;мл.</li></ul></p> | E26: 42410 | F26: 2 | G26: 1 | H26: https://grls.rosminzdrav.ru/InstrImg/2019/8/6/1445331/%D0%9F_N011073[2016]_1.pdf | I26: 45120
A27: 26 | B27: =VLOOKUP(A27,vaccines!A:B,2) -> Euvax_B_1_0 | C27: Доза для взрослых (1,0 мл): Активный компонент: • Поверхностный антиген вируса гепатита В (HBsAg) очищенный — 20 мкг. Вспомогательные вещества: • Гель алюминия гидроксида (по алюминию) — 0,50 мг. • Калия дигидрофосфат (буферный агент) — q.s. • Натрия гидрофосфат (буферный агент) — q.s. • Натрия хлорид — 8,50 мг. • Вода для инъекций — до 1,0 мл. | D27: <p>Доза для взрослых (1,0&nbsp;мл):</p> <p><i>Активный компонент:</i> <ul><li>Поверхностный антиген вируса гепатита В (HBsAg) очищенный — 20&nbsp;мкг.</li></ul> <i>Вспомогательные вещества:</i> <ul><li>Гель алюминия гидроксида (по алюминию) — 0,50&nbsp;мг.</li> <li>Калия дигидрофосфат (буферный агент) — q.s.</li> <li>Натрия гидрофосфат (буферный агент) — q.s.</li> <li>Натрия хлорид — 8,50&nbsp;мг.</li> <li>Вода для инъекций — до 1,0&nbsp;мл.</li></ul></p> | E27: 42410 | F27: 2 | G27: 1 | H27: https://grls.rosminzdrav.ru/InstrImg/2019/8/6/1445331/%D0%9F_N011073[2016]_1.pdf | I27: 45120
A28: 27 | B28: =VLOOKUP(A28,vaccines!A:B,2) -> Cervarix | C28: 1 прививочная доза (0,5 мл) содержит: Действующие вещества: • L1 протеин вируса папилломы человека типа 16 (ВПЧ-16L1) — 20 мкг. • L1 протеин вируса папилломы человека типа 18 (ВПЧ-18L1) — 20 мкг. Адъювантная система AS04: • Алюминия гидроксид — 0,5 мг. • 3-О-дезацил-4’-монофосфориллипид А — 50 мкг. Перечень вспомогательных веществ: • Натрия хлорид — 4,4 мг. • Натрия дигидрофосфата дигидрат — 0,624 мг. • Вода для инъекций — q.s. до 0,5 мл. | D28: <p>1&nbsp;прививочная доза (0,5&nbsp;мл) содержит:</p> <p><i>Действующие вещества:</i> <ul><li>L1&nbsp;протеин вируса папилломы человека типа&nbsp;16 (ВПЧ-16L1) — 20&nbsp;мкг.</li> <li>L1&nbsp;протеин вируса папилломы человека типа&nbsp;18 (ВПЧ-18L1) — 20&nbsp;мкг.</li></ul> <i>Адъювантная система AS04:</i> <ul><li>Алюминия гидроксид — 0,5&nbsp;мг.</li> <li>3-О-дезацил-4’-монофосфориллипид&nbsp;А — 50&nbsp;мкг.</li></ul> <i>Перечень вспомогательных веществ:</i> <ul><li>Натрия хлорид — 4,4&nbsp;мг.</li> <li>Натрия дигидрофосфата дигидрат — 0,624&nbsp;мг.</li> <li>Вода для инъекций — q.s. до 0,5&nbsp;мл.</li></ul></p> | E28: 45513 | H28: https://lk.regmed.ru/Register/GetPDFfromDA?ID=1611660161 | I28: =I27 -> 45120 | J28: 45589
A29: 28 | B29: =VLOOKUP(A29,vaccines!A:B,2) -> Gardasil_4 | C29: Одна доза (0,5 мл) содержит Действующие вещества: рекомбинантные антигены — L1 белок вируса папилломы человека в следующих количествах: тип 6 — 20 мкг, тип 11 — 40 мкг, тип 16 — 40 мкг, тип 18 — 20 мкг. Перечень вспомогательных веществ: • Алюминий в виде алюминия гидроксифосфата сульфата аморфного. • Натрия хлорид. • L-гистидин. • Полисорбат-80. • Натрия борат. • Вода для инъекций. Консервантов и антибиотиков не содержит. | D29: <p>Одна доза (0,5&nbsp;мл) содержит </p> <p><i>Действующие вещества:</i> рекомбинантные антигены — L1&nbsp;белок вируса папилломы человека в следующих количествах: тип&nbsp;6 — 20&nbsp;мкг, тип&nbsp;11 — 40&nbsp;мкг, тип&nbsp;16 — 40&nbsp;мкг, тип&nbsp;18 — 20&nbsp;мкг.</p> <p><i>Перечень вспомогательных веществ:</i> <ul><li>Алюминий в виде алюминия гидроксифосфата сульфата аморфного.</li> <li>Натрия хлорид.</li> <li>L-гистидин.</li> <li>Полисорбат-80.</li> <li>Натрия борат.</li> <li>Вода для инъекций.</li></ul> Консервантов и антибиотиков не содержит.</p> | E29: 45386 | H29: https://lk.regmed.ru/Register/GetPDFfromDA?ID=1575625191 | I29: 45120 | J29: 45483
